Workbook
Name Broker_and_Agent_Management: 'Dropdown List'!$K$2:$K$22
Name Claims: 'Dropdown List'!$B$2:$B$22
Name Evaluation: 'Dropdown List'!$H$2:$H$22
Name Functions: 'Dropdown List'!$A$2:$A$22
Name Information_Gathering_and_Risk_Selection: 'Dropdown List'!$L$2:$L$22
Name Initiation: 'Dropdown List'!$F$2:$F$22
Name Investigation: 'Dropdown List'!$G$2:$G$22
Name Issuance: 'Dropdown List'!$O$2:$O$22
Name Legal_Support: 'Dropdown List'!$V$2:$V$22
Name Legal_Support_Services: 'Dropdown List'!$E$2:$E$22
Name Litigation_and_Resolution: 'Dropdown List'!$I$2:$I$22
Name Office_of_General_Counsel: 'Dropdown List'!$W$2:$W$22
Name Policy_Servicing: 'Dropdown List'!$P$2:$P$22
Name Premium_Audit: 'Dropdown List'!$Q$2:$Q$22
Name Pricing_and_Negotiation: 'Dropdown List'!$N$2:$N$22
Name Procurement: 'Dropdown List'!$X$2:$X$22
Name Risk_Assessment_and_Rating: 'Dropdown List'!$M$2:$M$22
Name Risk_Control: 'Dropdown List'!$R$2:$R$22
Name Sales: 'Dropdown List'!$S$2:$S$22
Name Sales_and_Customer_Support: 'Dropdown List'!$T$2:$T$22
Name Sales_and_Service: 'Dropdown List'!$D$2:$D$22
Name Service_and_Upsell: 'Dropdown List'!$U$2:$U$22
Name Slicer_Business_Lines: #N/A
Name Slicer_Client: #N/A
Name Slicer_Client_Geography: #N/A
Name Slicer_Country: #N/A
Name Slicer_EXL_Delivery_Location: #N/A
Name Slicer_Function__L1: #N/A
Name Slicer_LOB___Product_Type: #N/A
Name Slicer_Work_Type: #N/A
Name Subrogation_and_Compliance: 'Dropdown List'!$J$2:$J$22
Name Underwriting_and_UW_Support: 'Dropdown List'!$C$2:$C$22

Sheet 1. General Instructions
B1: General Instructions
B3: 1) | C3: Do not modify the 'Data Collection' sheet in any way.
B4: 2) | C4: Do not paste values in the dropdowns. If you are unable to find an option from the drop down menu please provide details using 'Insert Comment' function
B5: 3) | C5: Do not merge cells. In the event a data point applies to more than 1 process, please enter on separate row items and/ or add details using the 'Insert Comment' function
B6: 4) | C6: In the event additional details need to be shared and you do not see a provision for it, please add using 'Insert Comment' and highlight the cell
B7: 5) | C7: Please include details for processes we performed in the past but are no longer active/ ramped down. There is a provision to call out their status appropriately in the sheet
B8: 6) | C8: Please add rows as required depending on the number of processes. The template currently has provision to include details for 100 processes
B9: 7) | C9: When updating LOB details, please use the abbreviations provided below and be consistent. Also, if you use additional abbreviations please share them on email when sending the updated file
B10: 8) | C10: For cells that may need multiple data point please only use a 'comma' as a seperator
B12: Field Description and Input Instructions
B14: # | C14: Field Names | D14: Field Type | E14: Description
B15: GENERAL OVERVIEW
B16: 1 | C16: Client | D16: Drop Down | E16: Please select your client name from the drop down menu
B17: 2 | C17: Client Description | D17: Drop Down | E17: This is a formula driven cell. Once you selct the clinet name, the drop down menu will only provide the corresponding 'Client Description' to select. Please choose and move forward
B18: 3 | C18: Client Geography | D18: Drop Down | E18: Please select the location from the drop down menu. If a location needs to be added, please insert a comment providing details, and we will add. Do Not modify the sheet.
B19: 4 | C19: EXL Delivery Location | D19: Drop Down | E19: Please select the location from the drop down menu. If a location needs to be added, please insert a comment providing details, and we will add. Do Not modify the sheet.
B20: 5 | C20: EXL Process Manager | D20: Free Text | E20: Please state the Process Manager name
B21: 6 | C21: Relationship Tenure | D21: Free Text | E21: Please state the number of years (upto 2 decimal places) your process has been active with EXL.
B22: 7 | C22: Current Status | D22: Drop Down | E22: Please select the appropriate status from drop down menu
B23: 8 | C23: Function (L1) | D23: Drop Down | E23: Please select the appropriate function from the drop down menu
B24: 9 | C24: Function (L2) | D24: Drop Down | E24: This is a formula driven cell. Once you selct the Function (L1), the drop down menu will only provide corresponding options. Please select the most appropriate option and move forward
B25: 10 | C25: Process Name (L3) | D25: Drop Down | E25: This is a formula driven cell. Once you selct the Function (L2), the drop down menu will only provide corresponding options. Please select the most appropriate option and move forward
B26: 11 | C26: Task Name | D26: Free Text | E26: Please state the task name using comon industry key words such as FNOL, Endorsements, Vendor Payments etc. that best describes the task
B27: 12 | C27: Process Description/ High-level steps | D27: Free Text | E27: Please provide a description of the work performed. Use bullet points to detail the process, with not more than 10 bullet points
... B36: 21 | C36: Ramp Duration | D36: Free Text | E36: Please state the number of weeks required for live production to achieve steady state. Please use the below format while updating: 1) If ramp uses complete weeks then state the exact number of weeks. Example - 2 2) If ramp spills over to a portion of the following week state a range. Example - 3 to 4
B37: STAFFING & PRICING
B38: 22 | C38: Pricing Model | D38: Drop Down | E38: Please selct the appropriate pricing model from the drop down menu
B39: 23 | C39: Annual Rate | D39: Free Text | E39: Please provide details of the annual rate
B40: 24 | C40: Billable FTEs | D40: Free Text | E40: Please state the billable FTE count (upto 2 decimal places)
B41: 25 | C41: SME + QA + Trainer | D41: Free Text | E41: Please state the combined count of SME+QA+Trainer supporting the process. Do not include buffer staff. (upto 2 decimal places)
B42: 26 | C42: Supervisor | D42: Free Text | E42: Please state the supervisor FTE count supporting the process (upto 2 decimal places)
B43: 27 | C43: Roster HC | D43: Free Text | E43: Please state the buffer staff count supporting the process (upto 2 decimal places)
B44: PERFORMANCE MANAGEMENT
B45: 28 | C45: Work Allocation | D45: Drop Down | E45: Please select the appropriate work allocation method from the drop down menu
B46: 29 | C46: Average Monthly Volume | D46: Free Text | E46: Please state the combined average monthly volume across all LOBs serviced in the process
B47: 30 | C47: Avergae Monthly Volume by LOB | D47: Free Text | E47: Please state a breakdown of average monthly volume by LOB. If this data is not tracked/ available please enter "NA"
B48: 31 | C48: Peak Volume Months | D48: Free Text | E48: Please state details of peak volume months; use the format - MMM, Volume. Example - Jan, Feb, 6300 If there are no peak months please enter "NA"
B49: 32 | C49: Process AHT | D49: Free Text | E49: Please state the process AHT as agreed with yur client (in mins and upto 2 deciaml places)
B50: 33 | C50: Timeliness SLA | D50: Free Text | E50: Please state the timeliness SLA as agreed with your client
B51: 34 | C51: Quality SLA | D51: Free Text | E51: Please state the quality SLA as agreed with your client
B52: 35 | C52: Quality Methodology | D52: Drop Down | E52: Please select the appropriate methodology from the drop down menu
B53: 36 | C53: Additional Metrics - 1 | D53: Free Text | E53: Provide the details of any additional metrics captured in the process
B54: 37 | C54: Additional Metrics - 2 | D54: Free Text | E54: Provide the details of any additional metrics captured in the process
B55: VALUE ADDED SERVICES
B56: 38 | C56: Pain Points | D56: Free Text | E56: Please state top 3 pain points that exist today in the process. If there areny any, please state "NA"
B57: 39 | C57: Key Customer / Business Outcomes Impacted | D57: Free Text | E57: Please provide details of any customer/ business metrics impacted. If there aren't any please state "NA"
B58: 40 | C58: Implemented Digital Solutions (if any) | D58: Drop Down | E58: Please select the appropriate type of digital solution implemented in the process from the drop down menu
B59: 41 | C59: Summary of Implemented Solution | D59: Free Text | E59: Please provide the details of the implemented solution
B60: 42 | C60: Expected/ Derived Benefits | D60: Free Text | E60: Please provide details of the benefits yeilded from the digital solution
B61: 43 | C61: Planned/Ongoing Digital Solutions (if any) | D61: Drop Down | E61: Please select the appropriate type of digital solution planned to be implemented in the process from the drop down menu
B62: 44 | C62: Summary of Planned Solutions | D62: Free Text | E62: Please provide the details of the implemented solution
B63: 45 | C63: Expected Benefits | D63: Free Text | E63: Please provide details of the benefits expected from the digital solution
B64: 46 | C64: Any client led innovation / transformation | D64: Free Text | E64: Please provide details of any digital solutions implemented by the client. If there arent any, please state "NA"
B65: ADDITIONAL DETAILS
B66: 47 | C66: Suppliers | D66: Free Text | E66: Please provide details of teams that provide inputs for the process
B67: 48 | C67: Input Format | D67: Drop Down | E67: Please select the appropriate input format from the drop down menu
B68: 49 | C68: Standardization level of Inputs | D68: Drop Down | E68: Please select the appropriate option from the drop down menu
B69: 50 | C69: % split of Input types | D69: Free Text | E69: Please provide a breakdown of volume% split by each input type. Example - Emails : 70%, SharePoint : 30%
B70: 51 | C70: Output Format | D70: Drop Down | E70: Please select the appropriate output format from the drop down menu
B71: 52 | C71: Customers | D71: Free Text | E71: Please provide details of teams/roles that use the output from the process
B72: 53 | C72: Client Applications / Admin Systems | D72: Free Text | E72: Provide the names of clients applications/admin systems used to perform the activities in this process
A230: Westcor Land Title Insurance | C230: North America | D230: Pune, India | E230: Yusuf Bhavnagarwala | F230: 5 months | G230: Active | H230: Underwriting and UW Support | I230: Broker and Agent Management | J230: Payments Processing/Management | K230: Broker and Agent payment | L230: Receive remittance from Agents and update it in client system with Premium and retention details | M230: Personal & Commercial | N230: Property | O230: Property 100% | P230: All | Q230: Back Office | R230: L2 | S230: 1 week | T230: 5 Weeks | U230: 10 Weeks | V230: Transaction Based | W230: $0.55 - Year 1 $0.50 - Year 2 $0.40 - Year 3 $0.38 - Year 4+ | X230: TBP | Y230: 1 | Z230: 1 | AA230: 9 | AB230: Manual | AC230: 95000 | AD230: NA | AE230: Jul-Dec | AF230: To be finalized | AG230: To be baselined post ramp | AH230: 0.95 | AI230: DPO – Defect Per Opportunity | AL230: Legacy application resulting in 100% manual efforts in processing | AM230: Delay in processing/reconcilation | AQ230: Extraction Tool | AR230: > Implementing cloud native AI powered Remittance app to replace Company’s OTIS application, to automate the processing of Remittance reports from Agents in form of email, mail or web > Development of rating calculator in conjunction with the Remittance Application > Integrated system built using Low code/No code platform for Remittance processing > Extraction engine to extract details from structured and unstructured documents and integrate the output with Remittance Application > Standalone component to consume data feed from external API sources and prepare feed for Import Agent (Standalone utility) or directly feed into new Remittance database through API service layer. Segregate data and prepare data entities for storage in application database tables > Normalized data structure to eliminate data redundancy/ replication and provides real time data integration with eWestCor DB | AS230: 25% Productivity Benefit | AT230: NA | AU230: Brokers and Agents | AV230: Multiple | AW230: Semi-Structured | AX230: Not available | AY230: Instructions in Application | AZ230: UW, Agent, Broker | BA230: Citrix, OTIS, E-Westcor, Outlook, Shared Drive and MS Teams

Sheet Sheet1
A2: Sum of Total Staff | B2: Column Labels
A3: Row Labels | B3: Colombia | C3: India | D3: Philippines | E3: South Africa | F3: Grand Total
A4: Claims | B4: 13 | C4: 1855.4288 | D4: 3498.24 | E4: 477.98 | F4: 5844.6488
A5: Evaluation | C5: 102.41875 | D5: 178.77 | E5: 2.09 | F5: 283.27875
A6: Initiation | B6: 13 | C6: 761.42415 | D6: 3231.74 | E6: 446.44 | F6: 4452.6042
A7: Investigation | C7: 200.29463 | D7: 39.2 | E7: 19.59 | F7: 259.08463
A8: Litigation and Resolution | C8: 572.94639 | D8: 36.53 | E8: 6.18 | F8: 615.65639
A9: Subrogation and Compliance | C9: 218.34487 | D9: 12 | E9: 3.68 | F9: 234.02487
A10: Legal Support Services | C10: 31 | F10: 31
A11: Legal Support | C11: 19 | F11: 19
A12: Procurement | C12: 12 | F12: 12
A13: Sales and Service | B13: 20 | C13: 110 | D13: 345 | E13: 447 | F13: 922
A14: Sales and Customer Support | B14: 20 | C14: 110 | D14: 345 | E14: 65 | F14: 540
A15: Service and Upsell | E15: 382 | F15: 382
A16: Underwriting and UW Support | C16: 2147.3888 | D16: 6 | E16: 109 | F16: 2262.3888
A17: Broker and Agent Management | C17: 49.51 | F17: 49.51
A18: Information Gathering and Risk Selection | C18: 411.46 | E18: 0 | F18: 411.46
A19: Issuance | C19: 492.86374 | F19: 492.86374
A20: Policy Servicing | C20: 925.35498 | D20: 5 | E20: 109 | F20: 1039.355
A21: Premium Audit | C21: 29.93 | F21: 29.93
A22: Risk Assessment and Rating | C22: 238.27012 | F22: 238.27012
A23: Risk Control | D23: 1 | F23: 1
A24: Grand Total | B24: 33 | C24: 4143.8176 | D24: 3849.24 | E24: 1033.98 | F24: 9060.0376

Sheet 2. Data Collection
A1: Client | B1: Client Description | C1: Client Geography | D1: EXL Delivery Location | E1: Country | F1: EXL Process Manager | G1: Relationship Tenure (years) | H1: Current Status | I1: Function (L1) | J1: Function (L2) | K1: Process Name (L3) | L1: Task Name | M1: Process Description/ High-level steps | N1: Business Lines | O1: LOB / Product Type | P1: LOB Breakup | Q1: Market Type | R1: Work Type | S1: Complexity Level | T1: Pre-Process Training Duration (weeks) | U1: Process Training Duration (weeks) | V1: Ramp Duration (weeks) | W1: Pricing Model | X1: Pricing Currency | Y1: Annual Rate | Z1: Billable FTEs | AA1: SME + QA + Trainer | AB1: Supervisor | AC1: Roster HC (Only Buffer Resources) | AD1: Total Staff | AE1: Roster % | AF1: Average Monthly Volume | AG1: Avergae Monthly Volume by LOB | AH1: Peak Volume Months | AI1: Process AHT (Minutes) | AJ1: Timeliness SLA | AK1: Quality SLA | AL1: Quality Methodology | AM1: Additional Metrics - 1 | AN1: Additional Metrics - 2 | AO1: Pain Points | AP1: Key Customer / Business Outcomes Impacted | AQ1: Implemented Digital Solutions (if any) | AR1: Summary of Implemented Solution | AS1: Expected/ Derived Benefits | AT1: Planned/Ongoing Digital Solutions (if any) | AU1: Summary of Planned Solutions | AV1: Expected Benefits | AW1: Any client led innovation / transformation | AX1: Suppliers | AY1: Input Format | AZ1: Standardization level of Inputs | BA1: % split of Input types | BB1: Output Format | BC1: Customers | BD1: Client Applications / Admin Systems
A2: Free Text | B2: Free Text | C2: Drop Down | D2: Drop Down | E2: Autopopulated Field | F2: Free Text | G2: Free Text | H2: Drop Down | I2: Drop Down | J2: Drop Down | K2: Drop Down | L2: Free Text | M2: Free Text | N2: Drop Down | O2: Drop Down | P2: Free Text | Q2: Drop Down | R2: Drop Down | S2: Drop Down | T2: Free Text | U2: Free Text | V2: Free Text | W2: Drop Down | X2: Drop Down | Y2: Free Text | Z2: Free Text | AA2: Free Text | AB2: Free Text | AC2: Free Text | AD2: Free Text | AE2: Free Text | AF2: Free Text | AG2: Free Text | AH2: Free Text | AI2: Free Text | AJ2: Free Text | AK2: Free Text | AL2: Drop Down | AM2: Free Text | AN2: Free Text | AO2: Free Text | AP2: Free Text | AQ2: Free Text | AR2: Free Text | AS2: Free Text | AT2: Free Text | AU2: Free Text | AV2: Free Text | AW2: Free Text | AX2: Free Text | AY2: Free Text | AZ2: Drop Down | BA2: Free Text | BB2: Free Text | BC2: Free Text | BD2: Free Text
A3: Nationwide | B3: Fortune 500 & Large US Insurance carrier | C3: North America | D3: Manila, PHP | E3: =VLOOKUP(D3,'Dropdown List'!$F$26:$G$40,2,0) -> Philippines | F3: Chona Mae Catimbang | G3: 1 year | H3: Active | I3: Claims | J3: Initiation | K3: First Notice of Loss Calls | L3: PL FNOL Auto | M3: Receive first notice of loss calls for auto collisions, accidents and any type of loss related to automobile/vehicle Receive calls from policyholders on FNOL inquiries and existing claims Receive calls for large loss greater than 10,000 USD | N3: Personal | O3: Auto | P3: Auto | Q3: All | R3: Voice | S3: L3 | T3: 4 | U3: 6 | V3: 16 | W3: Transaction Based | X3: USD | Y3: 4372 | Z3: 30 | AA3: 10 | AB3: 4 | AC3: 30 | AD3: =SUM(Z3:AC3) -> 74 | AE3: =AC3/AD3 -> 0.40540541 | AI3: 574 | AK3: CSM 95% Handling 85% CSM 90% | AL3: DPU – Defect Per Unit | AO3: Quality methodology | AX3: Onshore clients | AY3: FNOL, Inquiry | AZ3: Unstructured | BB3: Multiple | BC3: Policyholders, agent, 3rd party | BD3: Claims Center
A4: Nationwide | B4: Fortune 500 & Large US Insurance carrier | C4: North America | D4: Cebu, PHP | E4: =VLOOKUP(D4,'Dropdown List'!$F$26:$G$40,2,0) -> Philippines | F4: Chona Mae Catimbang | G4: 1 year | H4: Active | I4: Claims | J4: Initiation | K4: First Notice of Loss Calls | L4: PL FNOL Auto | M4: Receive first notice of loss calls for auto collisions, accidents and any type of loss related to automobile/vehicle Receive calls from policyholders on FNOL inquiries and existing claims Receive calls for large loss greater than 10,000 USD | N4: Personal | O4: Auto | P4: Auto | Q4: All | R4: Voice | S4: L3 | T4: 4 | U4: 6 | V4: 16 | W4: Transaction Based | X4: USD | Y4: 4372 | Z4: 75 | AA4: 10 | AB4: 7 | AC4: 30 | AD4: =SUM(Z4:AC4) -> 122 | AE4: =AC4/AD4 -> 0.24590164 | AI4: 574 | AK4: CSM 95% Handling 85% CSM 90% | AL4: DPU – Defect Per Unit | AO4: Quality methodology | AX4: Onshore clients | AY4: FNOL, Inquiry | AZ4: Unstructured | BB4: Multiple | BC4: Policyholders, agent, 3rd party | BD4: Claims Center
A5: Nationwide | B5: Fortune 500 & Large US Insurance carrier | C5: North America | D5: Manila, PHP | E5: =VLOOKUP(D5,'Dropdown List'!$F$26:$G$40,2,0) -> Philippines | F5: Raymond Perez | G5: 1 year | H5: Active | I5: Claims | J5: Initiation | K5: First Notice of Loss Calls | L5: PL FNOL Property | M5: Receive first notice of loss calls for businessproperty loss - weather related, wind hail, hurricane, tornadoes etc. Receive calls from policyholders on FNOL incuiries and existing claims | N5: Personal | O5: Property | P5: Property | Q5: All | R5: Voice | S5: L3 | T5: 4 | U5: 6 | V5: 11 | W5: Transaction Based | X5: USD | Y5: 4372 | Z5: 30 | AA5: 5 | AB5: 2 | AC5: 3 | AD5: =SUM(Z5:AC5) -> 40 | AE5: =AC5/AD5 -> 0.075 | AI5: 574 | AK5: CSM 95% Handling 85% CSM 90% | AL5: DPU – Defect Per Unit | AO5: Quality methodology | AX5: Onshore clients | AY5: FNOL, Inquiry | AZ5: Unstructured | BB5: Multiple | BC5: Policyholders, agent, 3rd party | BD5: Claims Center
A6: Nationwide | B6: Fortune 500 & Large US Insurance carrier | C6: North America | D6: Cebu, PHP | E6: =VLOOKUP(D6,'Dropdown List'!$F$26:$G$40,2,0) -> Philippines | F6: Raymond Perez | G6: 1 year | H6: Active | I6: Claims | J6: Initiation | K6: First Notice of Loss Calls | L6: PL FNOL Property | M6: Receive first notice of loss calls for businessproperty loss - weather related, wind hail, hurricane, tornadoes etc. Receive calls from policyholders on FNOL incuiries and existing claims | N6: Personal | O6: Property | P6: Property | Q6: All | R6: Voice | S6: L3 | T6: 4 | U6: 6 | V6: 11 | W6: Transaction Based | X6: USD | Y6: 4372 | Z6: 25 | AA6: 5 | AB6: 2 | AC6: 3 | AD6: =SUM(Z6:AC6) -> 35 | AE6: =AC6/AD6 -> 0.085714286 | AI6: 574 | AK6: CSM 95% Handling 85% CSM 90% | AL6: DPU – Defect Per Unit | AO6: Quality methodology | AX6: Onshore clients | AY6: FNOL, Inquiry | AZ6: Unstructured | BB6: Multiple | BC6: Policyholders, agent, 3rd party | BD6: Claims Center
A7: Nationwide | B7: Fortune 500 & Large US Insurance carrier | C7: North America | D7: Manila, PHP | E7: =VLOOKUP(D7,'Dropdown List'!$F$26:$G$40,2,0) -> Philippines | F7: Raymond Perez | G7: 1 year | H7: Active | I7: Claims | J7: Initiation | K7: First Notice of Loss Calls | L7: Business inquiry calls | M7: Receive calls from policyholders on FNOL inquiries and existing claims | N7: Specialty | O7: Multi/ Combination | P7: Multiple | Q7: All | R7: Voice | S7: L3 | T7: 4 | U7: 6 | V7: 11 | W7: Transaction Based | X7: USD | Y7: 5247 | Z7: 30 | AA7: 3 | AB7: 1 | AC7: 3 | AD7: =SUM(Z7:AC7) -> 37 | AE7: =AC7/AD7 -> 0.081081081 | AI7: 380 | AK7: 0.95 | AL7: Weighted DPO – Weighted Defect Per Opportunity | AO7: Quality methodology | AX7: Onshore clients | AY7: FNOL, Inquiry | AZ7: Unstructured | BB7: Multiple | BC7: Policyholders, agent, 3rd party | BD7: Claims Center
A8: Nationwide | B8: Fortune 500 & Large US Insurance carrier | C8: US | D8: Manila, PHP | E8: =VLOOKUP(D8,'Dropdown List'!$F$26:$G$40,2,0) -> Philippines | F8: David De Vera | G8: 1 Year | H8: Active | I8: Claims | J8: Initiation | K8: First Notice of Loss Calls | L8: Business FNOL Inquiry calls | M8: Receive first notice of loss calls for business auto and property loss - weather related, wind hail, hurricane, tornadoes etc. Receive calls from policyholders on FNOL incuiries and existing claims | N8: Commercial | O8: Multi/ Combination | P8: Auto, Property | Q8: All | R8: Voice | S8: L3 | T8: 4 | U8: 6 | V8: 11 | W8: Transaction Based | X8: USD | Y8: 5247 | Z8: 30 | AA8: 2 | AB8: 1 | AC8: 3 | AD8: =SUM(Z8:AC8) -> 36 | AE8: =AC8/AD8 -> 0.083333333 | AK8: 0.9 | AL8: DPU – Defect Per Unit | AO8: Quality methodology | AX8: Onshore clients | AY8: FNOL, Inquiry | AZ8: Unstructured | BB8: Multiple | BC8: Policyholders, agent, 3rd party | BD8: Claims Center
A9: Nationwide | B9: Fortune 500 & Large US Insurance carrier | C9: US | D9: Manila, PHP | E9: =VLOOKUP(D9,'Dropdown List'!$F$26:$G$40,2,0) -> Philippines | F9: David De Vera | G9: 1 Year | H9: Active | I9: Claims | J9: Initiation | K9: First Notice of Loss Calls | L9: Business FNOL Inquiry calls | M9: Receive first notice of loss calls for business auto and property loss - weather related, wind hail, hurricane, tornadoes etc. Receive calls from policyholders on FNOL incuiries and existing claims | N9: Commercial | O9: Multi/ Combination | P9: Auto, Property | Q9: All | R9: Voice | S9: L3 | T9: 4 | U9: 6 | V9: 11 | W9: Transaction Based | X9: USD | Y9: 5247 | Z9: 25 | AA9: 2 | AB9: 1 | AC9: 3 | AD9: =SUM(Z9:AC9) -> 31 | AE9: =AC9/AD9 -> 0.096774194 | AK9: 0.95 | AL9: Weighted DPO – Weighted Defect Per Opportunity | AO9: Quality methodology | AX9: Onshore clients | AY9: FNOL, Inquiry | AZ9: Unstructured | BB9: Multiple | BC9: Policyholders, agent, 3rd party | BD9: Claims Center
A10: Nationwide | B10: Fortune 500 & Large US Insurance carrier | C10: US | D10: Manila, PHP | E10: =VLOOKUP(D10,'Dropdown List'!$F$26:$G$40,2,0) -> Philippines | F10: David De Vera | G10: 1 Year | H10: Inactive | I10: Claims | J10: Initiation | K10: First Notice of Loss Calls | L10: FNOL, Inquiry calls | M10: Receive first notice of loss calls for business auto and property loss - weather related, wind hail, hurricane, tornadoes etc. Receive calls from policyholders on FNOL incuiries and existing claims | N10: Personal | O10: Multi/ Combination | P10: Auto, Property | Q10: All | R10: Voice | S10: L3 | T10: 4 | U10: 6 | V10: 20 | W10: Transaction Based | X10: USD | Y10: 5247 | Z10: 19 | AA10: 1 | AB10: 2 | AC10: 2 | AD10: =SUM(Z10:AC10) -> 24 | AE10: =AC10/AD10 -> 0.083333333 | AK10: 0.95 | AL10: Weighted DPO – Weighted Defect Per Opportunity | AO10: Quality methodology | AX10: Onshore clients | AY10: FNOL, Inquiry | AZ10: Unstructured | BB10: Multiple | BC10: Policyholders, agent, 3rd party | BD10: Claims Center
A11: Nationwide | B11: Fortune 500 & Large US Insurance carrier | C11: US | D11: Manila, PHP | E11: =VLOOKUP(D11,'Dropdown List'!$F$26:$G$40,2,0) -> Philippines | F11: John Pin Onrade | G11: 1 Year | H11: Active | I11: Claims | J11: Initiation | K11: Data entry | L11: CPT-Imaging + DESK, PRN, URS, CLME | File Claimant Carrier FNOL | File Copy/File Request | General Admin + Box | General Admin + Document Uploads | West Virginia–Mass Mailing Task | General Admin + Imaging | General Admin + Policy Request | Genesys Call Recording / Review | General Admin + Litigation Solutions | General Admin + Child Liens | General Admin + Escheat | General Admin + PL Sales Inquiries | ID Admin / Ordering + ClaimCenter Changes | ID Admin / Ordering + Ordering System Access / IDs | ID Admin / Ordering + Call Center Equipment / Supplies (except New Hire) | ID Admin / Ordering + Call Center New Hire / Term / Transfer | ID Admin / Ordering + New Hire Equipment and Access | ID Admin / Ordering + Order Supplies / Equipment | ID Admin / Ordering + Surplus | ID Admin / Ordering + Terminations | Senior Admin + Manual Check Ordering / Maintenance | Senior Admin + TX DMV | M11: Forwarding to the right department. Sorting the queries that mailbox is receiving. Claimant carrier requests assist the adjuster with reporting FNOL to the claimant (other party in a claim). When a claim has already been filed with the Claimant Carrier, these requests assist in obtaining additional claim information. A File Copy request is received as an activity through Claim Center when an adjuster requests a complete copy of the claim file materials (Claim Center documents, notes, medical bills, records, etc) This task covers the process for uploading images into Claim Center when they are received from LITSPEC mailbox. Admin processers will be getting the box link and passwords to open and retrieve the documents. This task covers the process for uploading images into Claim Center when they are received from Complex, LSI and Claims Adjusters. These are mostly medical related documents - medical records and/or bills. This task is received as an activity through Claim Center in the form of a Policy Request. The imaging task consists of imaging the claim notes, documents, and emails into the claim file for adjusters. This is to ensure that a claim is properly handled with all the required documentation be attached to the claim. Claim notes and documentation can be received through email that provide information from estimators, vendors, and customers. Policy Request is received as an activity through Claim Center. The process often starts with the adjuster requesting policy documents such as certified declaration page, the policy jacket and/or endorsements. This task covers request for a Genesys call recording to be pulled and uploaded to Claim Center. Adjuster send requests to Litigation Solutions for documents pertaining to their claim file for medical records, employment records, surveillance, Xrays etc. LitSol will send these requests on to assist with uploading the documents to the claim files. To determine if any liens exist To review the check status to determine a resolution to the check Our sales partners will send an email to connect with claim's leader regarding an escalated claim issue. This request is being initiated by PL Claims Organizations to Everything Admin for assistance with ClaimCenter changes, access ordering, Call Center needed equipment and supplies, requesting new access for new hires, enabling or deactivating accesses for transfers and deactivating access requests for Call Centers, requesting new access, ordering supplies and equipment for new hires, assistance with retrieval of devices and assistance with Terminations This is the process for sending packs to field or CAT adjusters. Assistance in provided for Adding, Changing, or Deleting authorized users and Password Resets for TX DMV | N11: Personal | O11: Multi/ Combination | P11: Auto | Q11: All | R11: Blended | S11: L2 | T11: 2 | U11: 5 | V11: 6 | W11: FTE Based | X11: USD | Y11: 31927.5 | Z11: 28 | AA11: 3 | AB11: 2 | AC11: 13 | AD11: =SUM(Z11:AC11) -> 46 | AE11: =AC11/AD11 -> 0.2826087 | AK11: 0.9 | AL11: DPU – Defect Per Unit | AO11: Quality methodology | AX11: Onshore clients | AY11: Admin Voice + Foundational | AZ11: Unstructured | BB11: Multiple | BC11: Policyholders, agent, 3rd party | BD11: Outlook, Ariba, EA Sharepoint, MyTech, Service Now, IIQ, Agero, Mozart, DPA, ARMS, Knowledge Advance, EFileNet, Onboarding Guide Excel
A12: Nationwide | B12: Fortune 500 & Large US Insurance carrier | C12: US | D12: Manila, PHP | E12: =VLOOKUP(D12,'Dropdown List'!$F$26:$G$40,2,0) -> Philippines | F12: John Pin Onrade | G12: 1 Year | H12: Active | I12: Claims | J12: Initiation | K12: Claim Setup and assignment | L12: Mitchell – No Match (Previously known as General Admin + AIS No Match) | General Admin + Iron Mountain / GRM Requests | General Admin + NY DMV | General Admin + SIU Blue | PIP (Michigan Provider) | Mitchell Payments - Issue Payments (Previously known as General Admin + AIS Issue Payment) | General Admin + eSubro Hub | General Admin + Kentucky Arbitrations | General Admin + LitFax | General Admin + MD Supplements | General Admin + NICB Payments | General Admin + NWSOP | General Admin + Respondent Arbitrations | General Admin + SUB UM/Insure No Pay | Reporting + ARB Report | MD Fire and Theft Dispatching | SERO Dispatching | WCZASIGN Dispatching Assignment | SPECTOYS & SPECOYS Network Assignment | NECZ Dispatching | National Recovery/Subrogation Dispatching | ClaimCenter Proxy Assignments | MD Total Loss Dispatching | CCC1 Portal Bucket Assignments | M12: A Doc ID is considered a Claim No Match when the information provided on the bill or in the accompanying documentation does not match the same information in the Nationwide claim feed received by Mitchell or there are multiple dates of loss. Review request to see who the NY DMV search is to be run for. Requestor may be asking for a VIN search or a license plate search. This provides instructions for pulling a credit report from TransUnion. Claims Associates requests checks be written to PIP providers for services completed. Bills are assigned to Admins in Mitchell each day. Once all bills have been submitted, refer to Bill Assignment Tracker spreadsheet as Claim Number, MCCA, and Bill Number will be needed to issue each payment. Admin review all incoming demands and distributes accordingly in E-Subrogation Hub (ESH) and mark the Productivity Tracker Spreadsheet. Kentucky Arbitrations are received from the Kentucky Insurance Arbitration Association. Admins assign the arbitrations to specific adjusters who have been trained as independent arbitrators for KY PIP claims involving other insurance companies. Once a claim has gone into Litigation, Nationwide will be served through NWSOP. A request will be submitted via email to LITFAX@nationwide.comemail link from NWSOP to have the claim reassigned to a Litigation Adjuster. This outlines Material Damage (MD) Supplements and invoices received for additional repairs needed. The Nationwide Crime Bureau submits fees that are due for services related to Claims investigations. Suits/Complaints and other documents served upon Nationwide through its registered agent, CSC, are received via the LITFAX shared mailbox (LITFAX@nationwide.com). However, some suits/complaints may be forwarded to LITFAX from another source, such as an adjuster or director. In general, the documents are processed by uploading them to the claim and assigning a new adjuster or notifying an existing adjuster. Most sections of this KA apply to suit/complaint documents. This workflow applies to all states EXCEPT the following: AL, AR, IL, IN, KY, MI, MS, OH, TN, WV. For those states, LITFAX Assignments (PL) would be applicable. Processing new respondent arbitration files to be assigned for response to a National Recovery Associate. Assigning and completing of recovery tasks placed in recovery queues. Running report in the Arbitration Forums website to determine all unanswered respondent arbitration files due within 48 hours and notifying the handling associate. This covers the processes for assigning claims from ClaimCenter that cannot be automated and file assigning Fire & Theft claims to adjusters. This covers the processes for reassigning claims from requests received from parties requesting reconsideration of the claims decision on the BI coverage. This covers the processes for assigning claims from ClaimCenter that cannot be automated and file assigning CICS claims to adjusters in the Northeast claims area. This covers the processes for manually assigning claims to subrogation Claims Associates. This covers the processes for assigning claims from multiple Proxies within ClaimCenter. Each Proxy has specific handling procedures and assignment criteria. This overs the processes for assigning MD Total Loss claims from ClaimCenter that cannot be automated and assigning claims sent in via the TLWESTDISPATCH, SHAREDTLESTIMATE, and TLDISPATCHCCZ queues. Assigning Private Client MD claims that are not located in ClaimCenter for all other dispatch buckets D out of the CCC1 portal. | N12: Personal | O12: Multi/ Combination | P12: Auto | Q12: All | R12: Back Office | S12: L2 | T12: 2 | U12: 5 | V12: 6 | W12: FTE Based | X12: USD | Y12: 31927.5 | Z12: 16 | AA12: 3 | AB12: 2 | AC12: 3 | AD12: =SUM(Z12:AC12) -> 24 | AE12: =AC12/AD12 -> 0.125 | AK12: 0.9 | AL12: DPU – Defect Per Unit | AO12: Quality methodology | AX12: Onshore clients | AY12: Doc Mgmt | AZ12: Unstructured | BB12: Multiple | BC12: Policyholders, agent, 3rd party | BD12: Dimension 360, Claim center Iron Mountain Connect NY DMV site, DMV spreadsheet Claim Center, Transunion, CBR template Mitchell decision point, Claim Center Mitchell decision point, Claim Center Arbitration forums, productivity sharepoint
A13: Nationwide | B13: Fortune 500 & Large US Insurance carrier | C13: US | D13: Manila, PHP | E13: =VLOOKUP(D13,'Dropdown List'!$F$26:$G$40,2,0) -> Philippines | F13: John Pin Onrade | G13: 1 Year | H13: Active | I13: Claims | J13: Initiation | K13: Claim Setup and assignment | L13: CSP- Orphan mail | TOWRMB | Faxed FNOL Queue | Incoming phone call | Indexing | Mail Upload | Personal line FNOL's Recieved in enewloss email | PL request sent to CCCTECH | Private Client FNOL | Safelite Verification Request Route mails | RSA Towing | Tow Uncashed Checks | Voicemail | Arbiration Tasks | Check Copy Request | Child liens | Claimcenter Unarchived request | Claims Maintenance Services Request | Compex | CSU Pending | Detached claim | Documents on Disabled claim | Litigation images | Litigation Solution | PL Transfer/ Disable | Salvage EFT | Tow Glass Unidentified Mail | Wdclms |W9 Request | M13: Claim services processing receives claims mail documents through ClaimCenter in the Orphan Files. Items are routed from document solutions that are unidentified. Mail is routed as need to the appropriate claim or department. Invoices for Roadside Assistance are received in call center agent and has been set up already requesting to pay the policyholder or vendor. Claims are reviewed for coverage and paid in Claim Center. Auto FNOL(First notices of loss) can originate from AWD. All personal lines auto claims are filed and handled out of the ClaimCenter system. Claims Services processing completes call out to obtain additional information on First Notices of Loss(FNOLs), claim mail, or unidentifiable mail. Associates skilled to specific work types will take inbound calls from agents, members, or providers. AWD captures work electronically and allocates it based on importance, processor skill and processor availability. This page describes the process of identifying the type of work so AWD can allocate work appropriately. Personal Lines Property FNOLs(first notices of loss) originate in AWD. All personal lines property claim are filed and handled out of claim center with the exception of Harleysville. Agents, associates, and third paries send FNOLs and other requests to CCCCTECH All Private Client first notice of loss(FNOL) request received are filed and handled out of CBI(Private Client intake system). This can be located under Aplication in Claims gateway. Claims Serrvices completes coverage verification on Glass Only claims for Nationwide's glass partner, Safelite. Processor also reassign existing claims to Claims Associates for investigation on California car seat claims. Claims Services processing receives claims mail documents through AWD system, various email inboxes, and hard copy mail sent into the processing locations. Mail is routed as needed to the appropriate Claims Associate or Department. Invoices for Roadside Assistance are received in Claim Services via fax, email, or mail and paid to the policyholder or vendor. The claims are set up and paid in Claim Center once the invoice is reviewed and coverage is determined. Activity generates at 180 days to call out the payee to verify if check was received or not. Child Support Lien Network emails the CCCTECH inbox each day, requesting the status of claims. If Claim is archived in ClaimCenter submit request to unarchive | N13: Personal | O13: Multi/ Combination | P13: Auto | Q13: All | R13: Blended | S13: L2 | T13: 2 | U13: 5 | V13: 6 | W13: FTE Based | X13: USD | Y13: 31893.75 | Z13: 9 | AA13: 4 | AB13: 2 | AC13: 13 | AD13: =SUM(Z13:AC13) -> 28 | AE13: =AC13/AD13 -> 0.46428571 | AK13: 0.9 | AL13: DPU – Defect Per Unit | AO13: Quality methodology | AX13: Onshore clients | AY13: FNOL Processing | AZ13: Unstructured | BB13: Multiple | BC13: Policyholders, agent, 3rd party | BD13: Claim center, Gateway, ISO, AWD
A14: Nationwide | B14: Fortune 500 & Large US Insurance carrier | C14: US | D14: Manila, PHP | E14: =VLOOKUP(D14,'Dropdown List'!$F$26:$G$40,2,0) -> Philippines | F14: Cherree Anne Leones | G14: 1 Year | H14: Active | I14: Claims | J14: Initiation | K14: Claim Setup and assignment | L14: Certified Mail | Charge/Credit Coding Changes/ Check Copy Requests | File Copy | File Copy – IME | Hello Packet | Medical Records and Bills Request | Misc Letters (ORM Letters, Prior Medical Records Request, Record Only Letter, Reassignment Letter, Closing Notification, Contact Letter) | Payments/Invoices / Texas Board Fees / Sassupport | Proof of Delivery | Provider Phone Call | Returned checks/stop pay/reissue | TDI DWC Documents | Unmatched Mail Vendor Referral | W-9 Requests / Provider Contact. | M14: Certified Mail can be requested anytime a document needs to be sent certified, this typically occurs with a state form Requests are received from claims associates to make payment code changes on Workers' Compensation related claims. The Changes are caused from either a check being send on a wrong claim, the incorrect amount was paid, or a check was coded incorrectly. Workers' Compensation Claims associates will request various parts of the file to be printed. Documents are then returned to the adjuster or sent to another party, typically Trial Division and/or Outside Counsel, per the request via Box.com New Documents are sent to insured and injured works for new Workers' Compensation claims. Mail, email or fax letters to providers to request bills and/or records for the claim file Create and issue claim center letters for the requesting adjuster "1. Emails come from sassupport daily 2. Invoices must be paid by EOD unless the W9 is missing 3. If payment amount issued by Mitchell is $0.00, still mail EOR to provider without check and notate the claim 4. When issuing Private Client payments, follow up next business day to see if any transactions need to be reapproved" SendPro is a 3rd Party application with DocSolutions, used to obtain tracking numbers and signature cards for document bundles sent out of Claim Center. This process outlines the steps to obtain the necessary information, what to upload in Claim Center, and how to document the claim file. The Expedited Claim handling program is designed to increase claim handling efficiencies for low complexity minor medical claims. The Expedited Claim process allows the claims associate to efficiently move the claim through its life cycle by reducing non-value-added claim contacts and minimizing claim documentation requirements. This results in greater flexibility for the claims tam to apply appropriate amount of time, expertise, and resources to claims with greater severity and/or complexity. Handling payments and account information via email, EFT, digital payments and manual checks. Workers' Compensation team receives a request via email to upload attached documents in Claim Center and inform the adjuster on file for further processing. Requests are received via email to confirm whether the filed claim is within Nationwide's system or its assigned to a Third Party Administrator. Utilization of contracted vendors in making vendor referrals such as social media, surveillance and Medical canvassing, Field Case Management and others Contact providers to get the bills and/or records for the claim file. | N14: Commercial | O14: Multi/ Combination | P14: Commercial | Q14: All | R14: Blended | S14: L2 | T14: 2 | U14: 7 | V14: 4 | W14: FTE Based | X14: USD | Y14: 34115 | Z14: 7 | AA14: 2 | AB14: 1 | AC14: 3 | AD14: =SUM(Z14:AC14) -> 13 | AE14: =AC14/AD14 -> 0.23076923 | AK14: 0.9 | AL14: DPU – Defect Per Unit | AO14: Quality methodology | AX14: Onshore clients | AY14: Workers Compensation | AZ14: Unstructured | BB14: Multiple | BC14: Business, agents, providers | BD14: Claim Center, Genesys, Outlook Mailbox, Fax Link, ISO, Private Client
A15: Nationwide | B15: Fortune 500 & Large US Insurance carrier | C15: US | D15: Manila, PHP | E15: =VLOOKUP(D15,'Dropdown List'!$F$26:$G$40,2,0) -> Philippines | F15: Narissa Dela Rosa | G15: 1 Year | H15: Active | I15: Claims | J15: Initiation | K15: Data entry | L15: Dispatch+Assignments File Claimant Carrier FNOL File Copy/File Request General Admin+Imaging General Admin+Medical Requests ID Admin/Ordering+ClaimCenter Changes ID Admin/Ordering+New Hire Equipment and Access ID Admin/Ordering+Order Supplies/Equipment ID Admin/Ordering+Ordering System Access/IDs ID Admin/Ordering+Terminations General Admin+AIS No Match General Admin+Box General Admin+Child Liens General Admin+Document Uploads General Admin+Escheat General Admin+eSubro Hub General Admin+Inventory Content Lists General Admin+LitFax General Admin+Litigation Solutions General Admin+Medicare General Admin+NWSOP General Admin+Other - General Admin+Record Requests General Admin+Respondant Arbitrations General Admin+SIU Blue | M15: Supplier shall handle various administrative tasks for commercial lines of business, including the assignment of work, managing time-sensitive requests, coordinate data gathering and information, prepare reports, ensure coordination between administrative functions across relevant departments of the Customer, and file first notice of loss (FNOL) with applicable third party carriers. | N15: Commercial | O15: Multi/ Combination | P15: Commercial | Q15: All | R15: Blended | S15: L2 | T15: 2 | U15: 5 | V15: 6 | W15: FTE Based | X15: USD | Y15: 31910.625 | Z15: 8 | AA15: 2 | AB15: 1 | AC15: 3 | AD15: =SUM(Z15:AC15) -> 14 | AE15: =AC15/AD15 -> 0.21428571 | AK15: 0.9 | AL15: DPU – Defect Per Unit | AO15: Quality methodology | AX15: Onshore clients | AY15: Claims Admin | AZ15: Unstructured | BB15: Multiple | BC15: Policyholders, agent, 3rd party | BD15: Outlook, Ariba, EA Sharepoint, MyTech, Service Now, IIQ, Agero, Mozart, DPA, ARMS, Knowledge Advance, EFileNet, Onboarding Guide Excel
A16: Nationwide | B16: Fortune 500 & Large US Insurance carrier | C16: US | D16: Manila, PHP | E16: =VLOOKUP(D16,'Dropdown List'!$F$26:$G$40,2,0) -> Philippines | F16: Narissa Dela Rosa | G16: 1 Year | H16: Active | I16: Claims | J16: Initiation | K16: Claim Setup and assignment | L16: 1099 Correction Bnotice W9 Requests Reject Report - Taxport Tax Returned Mail CL requests sent to CCCCTECH Check copy requests Claims Maintenance Services Requests PL Transfer/Disable CL Transfer/disables NWAG email box AG FNOLs received in enewloss email Commercial Lines FNOLs received in enewloss email Faxed FNOL queue Harleysville CL Requests sent to FNOL Tow Claims/Tow Mail Detached Claims Safelite verification requests - Help Desk AGASSIST Allied Extra CLAIMTAX CSP - Orphan Mail Incoming Phone Call IRS Penalty List - 972CG Mail Upload MailPrep NWAG Claims Operation Queue Salvage EFT Special Project Tow Glass Unidentified Mail Voicemail W9 Entry - via email to associate Wdclms Code Cards for Allied purged policies Tax Levy and UCC Liens | M16: Supplier shall handle a combination of tasks for commercial lines of business such as handling claim resolution, managing intricate claims services functions, handling correspondence, conducting statistical reporting, handling small first_x0002_party claims, assisting with special projects across various business lines of the Customer | N16: Commercial | O16: Multi/ Combination | P16: Commercial | Q16: All | R16: Blended | S16: L2 | T16: 2 | U16: 7 | V16: 7 | W16: FTE Based | X16: USD | Y16: 32855.625 | Z16: 24 | AA16: 2 | AB16: 2 | AC16: 7 | AD16: =SUM(Z16:AC16) -> 35 | AE16: =AC16/AD16 -> 0.2 | AK16: 0.9 | AL16: DPU – Defect Per Unit | AO16: Quality methodology | AX16: Onshore clients | AY16: Claims Processing | AZ16: Unstructured | BB16: Multiple | BC16: Policyholders, agent, 3rd party | BD16: Outlook, Ariba, EA Sharepoint, MyTech, Service Now, IIQ, Agero, Mozart, DPA, ARMS, Knowledge Advance, EFileNet, Onboarding Guide Excel
A17: Nationwide | B17: Fortune 500 & Large US Insurance carrier | C17: US | D17: Manila, PHP | E17: =VLOOKUP(D17,'Dropdown List'!$F$26:$G$40,2,0) -> Philippines | F17: Narissa Dela Rosa | G17: 1 Year | H17: Active | I17: Claims | J17: Initiation | K17: Claim Setup and assignment | L17: Keying Processing: Agent/Foreign Wire Transfers Keying Processing: Multiple & Bulk Invoices – Emails Keying Processing: ODEI Invoices to Pay Keying Processing: Stale Dated/Stop Pays Keying Processing: Transfers/Recodes Keying Processing: Invoices – Emails / Omniview Vendor Processing: Link & Sync Vendor Processing: New Vendor Setup with W9 Vendor Processing: PIP New Vendor Setup Vendor Processing: Scheduler – ClaimCenter Vendor Processing: Scheduler – Omniview Vendor Processing: THF New Vendor Setup Vendor Processing: Vendor Updates Vendor Processing: W9 Repository | M17: Supplier shall provide check processing services which involves handling time sensitive requests, vendor processing tasks, claims invoice tasks, payment tasks and single invoices that come in via email or Omniview that need paid to be paid to third party vendors. | N17: Commercial | O17: Multi/ Combination | P17: Commercial | Q17: All | R17: Blended | S17: L2 | T17: 2 | U17: 5 | V17: 3 | W17: FTE Based | X17: USD | Y17: 34391.25 | Z17: 6 | AA17: 2 | AB17: 1 | AC17: 2 | AD17: =SUM(Z17:AC17) -> 11 | AE17: =AC17/AD17 -> 0.18181818 | AK17: 0.985 | AL17: Weighted DPO – Weighted Defect Per Opportunity | AO17: Quality methodology | AX17: Onshore clients | AY17: Claims Processing | AZ17: Unstructured | BB17: Multiple | BC17: Policyholders, agent, 3rd party | BD17: Claim center, Gateway, ISO, AWD
A18: Nationwide | B18: Fortune 500 & Large US Insurance carrier | C18: US | D18: Manila, PHP | E18: =VLOOKUP(D18,'Dropdown List'!$F$26:$G$40,2,0) -> Philippines | F18: Narissa Dela Rosa | G18: 1 Year | H18: Active | I18: Claims | J18: Initiation | K18: Data entry | L18: First Notice of Loss: ESS emails and eFaxes First-Notice-Of-Loss: ESS Special programs and Western Heritage: Emails & eFaxes First-Notice-Of-Loss: Incoming inquiry and FNOL Calls (Phones - CSR) NW E&S FNOL & Inquiry Calls (Previously in Todd Robertson's org) ClaimCenter Research | M18: Supplier shall handle back-office services include managing FNOL emails (essreportaloss@nationwide.com), eFaxes and emails for the ESS program business and small volume of Western Heritage business. Supplier will also manage FNOL emails (essreportaloss@nationwide.com) and faxes that are ingested into Omniview. | N18: Commercial | O18: Multi/ Combination | P18: Commercial | Q18: All | R18: Blended | S18: L2 | T18: 2 | U18: 14 | V18: 8 | W18: FTE Based | X18: USD | Y18: 32855.625 | Z18: 9 | AA18: 2 | AB18: 1 | AC18: 3 | AD18: =SUM(Z18:AC18) -> 15 | AE18: =AC18/AD18 -> 0.2 | AK18: 0.95 | AL18: Weighted DPO – Weighted Defect Per Opportunity | AO18: Quality methodology | AX18: Onshore clients | AY18: Claims Support: ESS New Loss Back Office | AZ18: Unstructured | BB18: Multiple | BC18: Policyholders, agent, 3rd party | BD18: Claim center, Gateway, ISO, AWD
A19: American Modern Insurance Group | B19: US National Specialty Carrier | C19: US | D19: Noida, India | E19: =VLOOKUP(D19,'Dropdown List'!$F$26:$G$40,2,0) -> India | F19: Souvick Paul | G19: 5 | H19: Active | I19: Underwriting and UW Support | J19: Broker and Agent Management | K19: New Agent Set-up | L19: Coordination Setup Modification Cancellations | M19: Coordination process involves reviewing and coordinating the requests received in Appian with respect to making changes to agency, licensed producer, Sub-producer, Direct employee and other entity details. Setup and Modifications process involve either working on the setup (appointing new agenies/agents) requests or changes to existing entities requests in Prism (Modern Link) based on the SOP guidelines as well as information available in Vertafore application. Cancels process involves managing termination request for entities such as sub/licensed producer, DE/Processor, products and states in Prism (Modern Link) based on the SOP guidelines as well as information available in Vertafore, Cognos reports and HUON application | N19: Specialty | O19: Multi/ Combination | P19: Auto, Home, Motor Cycle, Collector Vehicle, Watercraft, Manufactured/Mobile home | Q19: Small & Mid Size | R19: Back Office | S19: L3 | T19: 1 | U19: 8 | V19: 8 | W19: FTE Based | X19: USD | Y19: 29825.983 | Z19: 17 | AA19: 2 | AB19: 1 | AC19: 2 | AD19: =SUM(Z19:AC19) -> 22 | AE19: =AC19/AD19 -> 0.090909091 | AF19: 21000 | AG19: NA | AH19: Mar, Apr, May & Jun | AI19: 20 | AJ19: Same Day | AK19: 0.96 | AL19: DPO – Defect Per Opportunity | AM19: NA | AN19: NA | AO19: Agency feedbacks | AP19: Quality | AQ19: NA | AR19: NA | AS19: NA | AT19: NA | AU19: NA | AV19: NA | AW19: Appian for workflow management. Scout for sched aderence monitoring | AX19: Agencies & inhouse team | AY19: Multiple | AZ19: Semi-Structured | BA19: Emails: 10% Database: 90% | BB19: Emails | BC19: Agencies | BD19: Citrix Appian Modern Link AMSuite Filenet Outlook Vertafore DocuSign Cognos Adobe Pro Access Accessory Manager Blue Screens AMIG Shared Drive MS EXCEL MS Teams MS Word
A20: American Modern Insurance Group | B20: US National Specialty Carrier | C20: US | D20: Noida, India | E20: =VLOOKUP(D20,'Dropdown List'!$F$26:$G$40,2,0) -> India | F20: Souvick Paul | G20: 5 | H20: Active | I20: Underwriting and UW Support | J20: Policy Servicing | K20: Endorsements intake and setup | L20: Non Premium Endorsement, Premium Bearing Endorsement, AOR, Schedule Manufactured Home, Cancellation, AOR, Watercraft Processing, Motorcycle processing, Collector vehicle processing, EZPAY, e-Sign, New Business, DocuSign | M20: Cases are received in form of emails/ Modernlink/ Filenet/ Phonechat/ manual requests in Appian from agent/insured/ third parties in regards to their Insurance products with AMIG. Requests are in regards to updating policies/ billing or coverage inquiries which may or may not result in impacting the premiums. The general steps include verifying the requestor’s authenticity, taking appropriate actions which includes policy processing in Amsuite/ Modernlink, sending response to requestor on what all actions are completed basis the request or if there are any further requirements to complete the request and imaging the requests/ attachments in Amsuite/Filenet. Post all the steps memo is created which includes documenting all the necessary details pertaining to the case. | N20: Specialty | O20: Multi/ Combination | P20: Auto, Home, Motor Cycle, Collector Vehicle, Watercraft, Manufactured/Mobile home | Q20: Small & Mid Size | R20: Back Office | S20: L3 | T20: 1 | U20: 4 | V20: 6 | W20: FTE Based | X20: USD | Y20: 29825.983 | Z20: 27 | AA20: 2 | AB20: 1 | AC20: 3 | AD20: =SUM(Z20:AC20) -> 33 | AE20: =AC20/AD20 -> 0.090909091 | AF20: 25000 | AG20: NA | AH20: Mar, Apr, May & Jun | AI20: 9 | AJ20: 1 Day | AK20: 0.92 | AL20: DPO – Defect Per Opportunity | AM20: NA | AN20: NA | AO20: Customer feedbacks | AP20: Quality | AQ20: NA | AR20: NA | AS20: NA | AT20: NA | AU20: NA | AV20: NA | AW20: Appian for workflow management. Scout for sched aderence monitoring | AX20: Agent, Insured, Third Parties & inhouse team | AY20: Multiple | AZ20: Unstructured | BA20: Emails: 90% Images: 10% | BB20: Emails | BC20: Agents, Insureds & Third parties | BD20: Citrix Appian Modern Link AMSuite Filenet Outlook DocuSign Adobe Pro Access MAT Tool AMIG Shared Drive MS EXCEL MS Teams MS Word
A21: American Modern Insurance Group | B21: US National Specialty Carrier | C21: US | D21: Noida, India | E21: =VLOOKUP(D21,'Dropdown List'!$F$26:$G$40,2,0) -> India | F21: Souvick Paul | G21: 5 | H21: Active | I21: Underwriting and UW Support | J21: Policy Servicing | K21: Indexing | L21: Cordination to Underwriting | M21: This process includes reviewing and coordinating requests received in Appian. Requests/emails received in Appian must be reviewed and identified the request per the nature. After the selection of type, request to be coordinated to appropriate team (underwriting/Not assigned bucket/Customer Service, others) for Residential & Recreational LOB as outlined in the SOP. For Certified policy request task, we have to Certify the dec page and validate form numbers from the guidewire accordingly, 100% volume to be touched by EXL & worked upon as outlined in SOP. In the Commercial line section, we review the requests/emails (received in endorsement & NB requests mailboxes) and setup the task in the task manager and coordinate to appropriate underwriters. | N21: Specialty | O21: Multi/ Combination | P21: Auto, Home, Motor Cycle, Collector Vehicle, Watercraft, Manufactured/Mobile home | Q21: Small & Mid Size | R21: Back Office | S21: L3 | T21: 1 | U21: 2 | V21: 2 | W21: FTE Based | X21: USD | Y21: 29825.983 | Z21: 7 | AA21: 0 | AB21: 0.5 | AC21: 1 | AD21: =SUM(Z21:AC21) -> 8.5 | AE21: =AC21/AD21 -> 0.11764706 | AF21: 7000 | AG21: NA | AH21: Mar, Apr, May & Jun | AI21: 5 | AJ21: Same Day | AK21: 0.9 | AL21: DPO – Defect Per Opportunity | AM21: NA | AN21: NA | AO21: NA | AP21: NA | AQ21: NA | AR21: NA | AS21: NA | AT21: NA | AU21: NA | AV21: NA | AW21: Appian for workflow management. Scout for sched aderence monitoring | AX21: Agent, Insured & inhouse team | AY21: Multiple | AZ21: Unstructured | BA21: Emails: 98% Application on browser: 1% Mainframe: 1% | BB21: Emails | BC21: Underwriters | BD21: Citrix Appian Modern Link AMSuite Filenet Outlook Adobe Pro Access AMIG Shared Drive MS EXCEL MS Teams MS Word
A22: American Modern Insurance Group | B22: US National Specialty Carrier | C22: US | D22: Noida, India | E22: =VLOOKUP(D22,'Dropdown List'!$F$26:$G$40,2,0) -> India | F22: Souvick Paul | G22: 2.9 | H22: Active | I22: Claims | J22: Investigation | K22: Requesting Police report | L22: Claims FileNet, File Copy, Police/Fire Report, Recorded Statement, NSM, MBA Commercial, SerachTec deed search, ISO Deed Search & New Losses | M22: The claims transactions involve uploading emails, saving the documents for adjuster in file copy request, pull the Dec Page to certify for certify policy request, order the PR/FR reports through ISO in PR/FR task, submit the recorded statement on 3rd party website for transcription and new claims are being generated on the guidewire basis the loss details received on email for the task NSM, MBA commercial & New losses. | N22: Specialty | O22: Multi/ Combination | P22: Auto, Home, Motor Cycle, Collector Vehicle, Watercraft, Manufactured/Mobile home | Q22: Small & Mid Size | R22: Back Office | S22: L3 | T22: 1 | U22: 3 | V22: 3 | W22: FTE Based | X22: USD | Y22: 28113.85 | Z22: 4 | AA22: 0 | AB22: 0.5 | AC22: 1 | AD22: =SUM(Z22:AC22) -> 5.5 | AE22: =AC22/AD22 -> 0.18181818 | AF22: 12000 | AG22: NA | AH22: Mar & Oct | AI22: 3 | AJ22: Same Day | AK22: 0.9 | AL22: DPO – Defect Per Opportunity | AM22: NA | AN22: NA | AO22: NA | AP22: NA | AQ22: NA | AR22: NA | AS22: NA | AT22: NA | AU22: NA | AV22: NA | AW22: No | AX22: Adjuster & inhouse team | AY22: Multiple | AZ22: Unstructured | BA22: Emails: 80% Application on browser: 20% | BB22: Emails | BC22: Underwriters | BD22: Citrix Modern Link AMSuite Filenet Outlook Production tool Adobe Pro Access MS Access Tool ISO Guidewire Claims Center Infraware SerachTEc Fonefinder AMIGAddin.Amclaims tool AMIG Shared Drive MS EXCEL MS Teams MS Word
A23: RSA Insurance | B23: UK P&C client | C23: UK | D23: Pune, India | E23: =VLOOKUP(D23,'Dropdown List'!$F$26:$G$40,2,0) -> India | F23: Kanishka Singh | G23: 1 | H23: Active | I23: Underwriting and UW Support | J23: Broker and Agent Management | K23: Maintenance | L23: BRM Support Application Management Change/testing Coordination Data Monitoring Application Support Data Reporting | M23: Identify opportunities and manage trends: Use BRM to spot business opportunities and trends. Plan broker strategies: Utilize the application to support strategic planning for brokers. Allocate policy activities: Assign policy-related tasks requested by brokers and customers. Perform periodic policy services: Carry out regular services on policies. Manage broker relationships: Proactively manage broker interactions and relationships. Enable seamless workflow management: Handle leads, quotes, mid-term adjustments, and renewals efficiently. | N23: Commercial | O23: Multi/ Combination | P23: Auto,Property,Package | Q23: All | R23: Back Office | S23: L5 | T23: 1 weeks | U23: 4 weeks | V23: 2 weeks | W23: FTE Based | X23: GBP | Y23: 25059 | Z23: 2 | AA23: 0 | AB23: 1 | AC23: 0 | AD23: =SUM(Z23:AC23) -> 3 | AE23: =AC23/AD23 -> 0 | AF23: NA | AG23: NA | AH23: NA | AI23: NA | AJ23: NA | AK23: NA | AL23: Others | AM23: NA | AN23: NA | AO23: NA | AP23: NA | AQ23: NA | AR23: NA | AS23: NA | AT23: NA | AU23: NA | AV23: NA | AW23: NA | AX23: Internal departments Brokers Onshore Underwriters | AY23: Information, forms, policy details, customer requests, database entries, and broker strategies | AZ23: Unstructured | BA23: Emails: 60% Spreadsheets: 20% System-Generated Reports: 10% Broker Correspondence: 10% | BB23: Reports, strategic plans, task assignments, service records, Digital reports, dashboards, emails, notifications, and workflow updates | BC23: Onshore Underwriters Internal Teams | BD23: Broker Relationship Management (BRM) systems
A24: RSA Insurance | B24: UK P&C client | C24: UK | D24: Noida, India | E24: =VLOOKUP(D24,'Dropdown List'!$F$26:$G$40,2,0) -> India | F24: Kanishka Singh | G24: 1 | H24: Active | I24: Underwriting and UW Support | J24: Information Gathering and Risk Selection | K24: Broker Correspondence | L24: System-Generated Reports (HUB) Management Scanned Correspondence Handling (SRI) Policy Rekeying Report Management Diary Reminder Management Geo Score Generation and Provision Policy Actions and Leads Creation RNL Declarations Dispatch to Brokers New Policy Setup via Rekeying Motor Cover Notes Upload (SRI) | M24: Handle policy rekeying details: Process details from the shared mailbox and HUB broker platform. Manage diary reminders: Handle reminders from BRM. Manage scanned correspondence: Handle correspondence received from brokers, for PA, lead or Indexising. Process periodic spreadsheets: Manage spreadsheets from onshore stakeholders. Handle Motor cover note work: Process work received on the Motor cover note system. Create logs in BRM: Identify requests as new business or changes to existing customer details. Chase required information: Follow up with brokers for necessary information. Rekey policies: Update policies received from brokers. Correspond with brokers: Communicate regarding RNL declarations. Provide Geo scores: Send Geo scores to underwriters on SRI. Upload Motor cover notes: Upload Motor cover notes on SRI. | N24: Commercial | O24: Multi/ Combination | P24: Auto,Property,Package | Q24: All | R24: Back Office | S24: L3 | T24: 1 weeks | U24: 0 | V24: 4 weeks | W24: FTE Based | X24: GBP | Y24: 20183.24 | Z24: 28 | AA24: 2 | AB24: 1 | AC24: 2.5 | AD24: =SUM(Z24:AC24) -> 33.5 | AE24: =AC24/AD24 -> 0.074626866 | AF24: 29303 | AG24: NA | AH24: July, September, October | AI24: Maximum - 120 min, Minimum - 30 sec | AJ24: 0.95 | AK24: 0.95 | AL24: DPU and DPO | AM24: NA | AN24: NA | AO24: NA | AP24: NA | AQ24: NA | AR24: NA | AS24: NA | AT24: NA | AU24: NA | AV24: NA | AW24: NA | AX24: Onshore teams Brokers | AY24: Shared mailbox HUB broker platform BRM diary reminders Scanned correspondence Periodic spreadsheets Motor cover note system | AZ24: Unstructured | BA24: Emails: 60% Spreadsheets: 20% System-Generated Reports: 10% Broker Correspondence: 5% Policy Adjustment Requests: 3% Renewal Requests: 2% | BB24: Policy actions and leads Geo scores Notepad updates | BC24: Underwriters Brokers | BD24: IS2000: For managing policies and generating documents. Acturis: For making underwriting decisions and generating quotes. SRI & IS2000: For handling broker correspondence and policy changes. SRI - Document Management System: For storing and retrieving scanned documents and emails. BRM - Broker Relationship manager software application used to manage workflow across teams
A25: RSA Insurance | B25: UK P&C client | C25: UK | D25: Pune, India | E25: =VLOOKUP(D25,'Dropdown List'!$F$26:$G$40,2,0) -> India | F25: Kanishka Singh | G25: 1 | H25: Active | I25: Underwriting and UW Support | J25: Information Gathering and Risk Selection | K25: Broker Correspondence | L25: System-Generated Reports (HUB) Management Scanned Correspondence Handling (SRI) Policy Rekeying Report Management Diary Reminder Management Geo Score Generation and Provision Policy Actions and Leads Creation RNL Declarations Dispatch to Brokers New Policy Setup via Rekeying Motor Cover Notes Upload (SRI) | M25: Handle policy rekeying details: Process details from the shared mailbox and HUB broker platform. Manage diary reminders: Handle reminders from BRM. Manage scanned correspondence: Handle correspondence received from brokers, for PA, lead or Indexising. Process periodic spreadsheets: Manage spreadsheets from onshore stakeholders. Handle Motor cover note work: Process work received on the Motor cover note system. Create logs in BRM: Identify requests as new business or changes to existing customer details. Chase required information: Follow up with brokers for necessary information. Rekey policies: Update policies received from brokers. Correspond with brokers: Communicate regarding RNL declarations. Provide Geo scores: Send Geo scores to underwriters on SRI. Upload Motor cover notes: Upload Motor cover notes on SRI. | N25: Commercial | O25: Multi/ Combination | P25: Auto,Property,Package | Q25: All | R25: Back Office | S25: L3 | T25: 1 weeks | U25: 0 | V25: 4 weeks | W25: FTE Based | X25: GBP | Y25: 20183.24 | Z25: 28 | AA25: 2 | AB25: 1 | AC25: 2.5 | AD25: =SUM(Z25:AC25) -> 33.5 | AE25: =AC25/AD25 -> 0.074626866 | AF25: 29303 | AG25: NA | AH25: July, September, October | AI25: Maximum - 120 min, Minimum - 30 sec | AJ25: 0.95 | AK25: 0.95 | AL25: DPU and DPO | AM25: NA | AN25: NA | AO25: NA | AP25: NA | AQ25: NA | AR25: NA | AS25: NA | AT25: NA | AU25: NA | AV25: NA | AW25: NA | AX25: Onshore teams Brokers | AY25: Shared mailbox HUB broker platform BRM diary reminders Scanned correspondence Periodic spreadsheets Motor cover note system | AZ25: Unstructured | BA25: Emails: 60% Spreadsheets: 20% System-Generated Reports: 10% Broker Correspondence: 5% Policy Adjustment Requests: 3% Renewal Requests: 2% | BB25: Policy actions and leads Geo scores Notepad updates | BC25: Underwriters Brokers | BD25: IS2000: For managing policies and generating documents. Acturis: For making underwriting decisions and generating quotes. SRI & IS2000: For handling broker correspondence and policy changes. SRI - Document Management System: For storing and retrieving scanned documents and emails. BRM - Broker Relationship manager software application used to manage workflow across teams
A26: RSA Insurance | B26: UK P&C client | C26: UK | D26: Noida, India | E26: =VLOOKUP(D26,'Dropdown List'!$F$26:$G$40,2,0) -> India | F26: Kanishka Singh | G26: 1 | H26: Active | I26: Underwriting and UW Support | J26: Issuance | K26: New Business Issuance | L26: System-Generated Reports Management Scanned Correspondence Handling Policy Information Debiting on IS2000 Premium Matching with Underwriter’s Quote Policy Document and Certificate Issuance Broker Leads Management Quote Creation on System Quote Sharing with Onshore Underwriters | M26: Handle system-generated reports: Process reports generated by the system. Manage scanned correspondence: Handle correspondence received from underwriters and brokers. Process broker leads: Manage leads received from brokers. Debit policy information: Enter policy information on IS2000. Match premiums with quotes: Ensure premiums match the underwriter’s quote. Issue policy documents and certificates: Provide customers with policy documents and certificates. Create quotes: Generate quotes on the system based on lead presentations. Share quotes with underwriters: Send quotes to onshore underwriters for further correspondence. Issue motor certificates: Provide motor certificates to customers. | N26: Commercial | O26: Multi/ Combination | P26: Auto,Property,Package | Q26: All | R26: Back Office | S26: L3 | T26: 1 weeks | U26: 6 weeks | V26: 3 weeks | W26: FTE Based | X26: GBP | Y26: 20183.24 | Z26: 4.5 | AA26: 0.5 | AB26: 1 | AC26: 0.5 | AD26: =SUM(Z26:AC26) -> 6.5 | AE26: =AC26/AD26 -> 0.076923077 | AF26: 1563.5 | AG26: NA | AH26: July, September, October | AI26: Maximum - 120 min, Minimum - 30 sec | AJ26: 0.95 | AK26: 0.95 | AL26: DPU and DPO | AM26: NA | AN26: NA | AO26: NA | AP26: NA | AQ26: NA | AR26: NA | AS26: NA | AT26: NA | AU26: NA | AV26: NA | AW26: NA | AX26: Underwriters Brokers | AY26: System-generated reports Scanned correspondence Broker leads | AZ26: Unstructured | BA26: System-generated reports: 30% Scanned correspondence: 40% Broker leads: 30% | BB26: Policy documents and certificates Quotes Premium matches Policy debiting records | BC26: Underwriters Brokers | BD26: IS2000: For managing policies and generating documents. Acturis: For making underwriting decisions and generating quotes. SRI & IS2000: For handling broker correspondence and policy changes. SRI - Document Management System: For storing and retrieving scanned documents and emails. BRM - Broker Relationship manager software application used to manage workflow across teams
A27: RSA Insurance | B27: UK P&C client | C27: UK | D27: Pune, India | E27: =VLOOKUP(D27,'Dropdown List'!$F$26:$G$40,2,0) -> India | F27: Kanishka Singh | G27: 1 | H27: Active | I27: Underwriting and UW Support | J27: Issuance | K27: New Business Issuance | L27: System-Generated Reports Management Scanned Correspondence Handling Policy Information Debiting on IS2000 Premium Matching with Underwriter’s Quote Policy Document and Certificate Issuance Broker Leads Management Quote Creation on System Quote Sharing with Onshore Underwriters | M27: Handle system-generated reports: Process reports generated by the system. Manage scanned correspondence: Handle correspondence received from underwriters and brokers. Process broker leads: Manage leads received from brokers. Debit policy information: Enter policy information on IS2000. Match premiums with quotes: Ensure premiums match the underwriter’s quote. Issue policy documents and certificates: Provide customers with policy documents and certificates. Create quotes: Generate quotes on the system based on lead presentations. Share quotes with underwriters: Send quotes to onshore underwriters for further correspondence. Issue motor certificates: Provide motor certificates to customers. | N27: Commercial | O27: Multi/ Combination | P27: Auto,Property,Package | Q27: All | R27: Back Office | S27: L3 | T27: 1 weeks | U27: 6 weeks | V27: 3 weeks | W27: FTE Based | X27: GBP | Y27: 20183.24 | Z27: 4.5 | AA27: 0.5 | AB27: 1 | AC27: 0.5 | AD27: =SUM(Z27:AC27) -> 6.5 | AE27: =AC27/AD27 -> 0.076923077 | AF27: 1563.5 | AG27: NA | AH27: July, September, October | AI27: Maximum - 120 min, Minimum - 30 sec | AJ27: 0.95 | AK27: 0.95 | AL27: DPU and DPO | AM27: NA | AN27: NA | AO27: NA | AP27: NA | AQ27: NA | AR27: NA | AS27: NA | AT27: NA | AU27: NA | AV27: NA | AW27: NA | AX27: Underwriters Brokers | AY27: System-generated reports Scanned correspondence Broker leads | AZ27: Unstructured | BA27: System-generated reports: 30% Scanned correspondence: 40% Broker leads: 30% | BB27: Policy documents and certificates Quotes Premium matches Policy debiting records | BC27: Underwriters Brokers | BD27: IS2000: For managing policies and generating documents. Acturis: For making underwriting decisions and generating quotes. SRI & IS2000: For handling broker correspondence and policy changes. SRI - Document Management System: For storing and retrieving scanned documents and emails. BRM - Broker Relationship manager software application used to manage workflow across teams
A28: RSA Insurance | B28: UK P&C client | C28: UK | D28: Pune, India | E28: =VLOOKUP(D28,'Dropdown List'!$F$26:$G$40,2,0) -> India | F28: Kanishka Singh | G28: 1 | H28: Active | I28: Underwriting and UW Support | J28: Policy Servicing | K28: Correspondence with Brokers and UWs | L28: System-Generated Reports Management Scanned Correspondence Handling Policy Updates (Cover, Address, Name) Policy Actions (Cancellations, Renewals) Premium and Refund Calculations Referral Clearing Renewal Terms Issuance Terrorism Quotes Creation Geo Scores Provision Commercial Vehicle Administrative Work Agency Transfer Handling Payment Collection and Banking (CARD/BACS) Outstanding Direct Debit Chasing | M28: Handle system reports and broker correspondence: Update policies and perform actions like cancellations and renewals. Calculate premiums and refunds: Determine policy costs and process refunds. Clear referrals: Resolve referrals to ensure policy accuracy. Issue renewal terms: Provide renewal conditions to brokers. Create terrorism quotes: Generate quotes for terrorism coverage. Provide geo scores: Assess and provide geographical risk scores. Manage agency transfers: Handle the transfer of agency responsibilities. Issue payments: Process day-to-day premium-related payments. Chase outstanding premiums: Follow up on unpaid premiums. Administer commercial vehicle policies: Manage EDI transactions and issue No Claims Bonus certificates. | N28: Commercial | O28: Multi/ Combination | P28: Auto,Property,Package | Q28: All | R28: Back Office | S28: L3 | T28: 1 weeks | U28: 4 weeks | V28: 4 weeks | W28: FTE Based | X28: GBP | Y28: 20183.24 | Z28: 28 | AA28: 2 | AB28: 2 | AC28: 3 | AD28: =SUM(Z28:AC28) -> 35 | AE28: =AC28/AD28 -> 0.085714286 | AF28: 27938 | AG28: NA | AH28: July, September, October | AI28: Maximum - 120 min, Minimum - 30 sec | AJ28: 0.95 | AK28: 0.95 | AL28: DPU and DPO | AM28: NA | AN28: NA | AO28: NA | AP28: NA | AQ28: NA | AR28: NA | AS28: NA | AT28: NA | AU28: NA | AV28: NA | AW28: NA | AX28: Brokers Onshore teams | AY28: Shared mailbox Acturis broker platform Shared drive BRM SRI | AZ28: Unstructured | BA28: Shared mailbox: 25% Acturis broker platform: 25% Shared drive: 20% BRM: 15% SRI: 15% | BB28: Renewals Referrals Policy amendments Premium calculations Refunds Direct debit mandates Collected premiums Policy documents | BC28: Underwriters Brokers | BD28: IS2000: For managing policies and generating documents. Acturis: For making underwriting decisions and generating quotes. SRI & IS2000: For handling broker correspondence and policy changes. SRI - Document Management System: For storing and retrieving scanned documents and emails. BRM - Broker Relationship manager software application used to manage workflow across teams
A29: RSA Insurance | B29: UK P&C client | C29: UK | D29: Pune, India | E29: =VLOOKUP(D29,'Dropdown List'!$F$26:$G$40,2,0) -> India | F29: Kanishka Singh | G29: 1 | H29: Active | I29: Underwriting and UW Support | J29: Policy Servicing | K29: Correspondence with Brokers and UWs | L29: Setting Terms and Conditions Renewal Allocations and Premium Calculation Additional and Refund Premiums (AP/RP) Calculation Mid-Term Adjustments (MTAs) Management Referral Review and Authorization (PUA Level) Reviewing and Clearing Referrals Preparing Renewals Reviewing Premium Terms Issuing Policies Managing Claims Queries eTrade Migration (Rekey) Management | M29: Review referrals and policy details: Assess referrals from brokers, claims department, or system triggers at various stages. Gather necessary information: Collect data from Geo reports, survey reports, and Google, and communicate with brokers for additional or missing information. Apply terms and conditions: Make required changes based on risk information and PUA authority level. Refer complex cases: Escalate cases above PUA authority level to the appropriate PUA with full review and recommendations. Manage diaries: Schedule future actions on agreed cover. Update files: Ensure all required changes are made and files are updated. Send decisions to brokers: Communicate agreed decisions and confirmations to brokers via email. Review internal referrals: Handle premium or commission queries from accounts and cover queries from claims. Issue renewals: Process renewals as per referral guidance. Clear referrals: Ensure all conditions are met according to underwriting appetite. Amend policies and issue documents: Update policies or create new quotes and send documents/emails to brokers. Adjust premiums and provide refunds: Modify premiums or issue refunds based on changes in cover or conditions. | N29: Commercial | O29: Multi/ Combination | P29: Auto,Property,Package | Q29: All | R29: Back Office | S29: L4 - L7 | T29: 1 weeks | U29: 12 weeks | V29: 8 weeks | W29: FTE Based | X29: GBP | Y29: L4 - £22803 L5 - £25059 L6 - £27994 L7 - £30043 | Z29: 104 | AA29: 0 | AB29: 5 | AC29: 25 | AD29: =SUM(Z29:AC29) -> 134 | AE29: =AC29/AD29 -> 0.18656716 | AF29: 25318 | AG29: NA | AH29: July, September, October | AI29: MTA - 30 min, Renewals - 60 min | AJ29: 0.95 | AK29: NA | AL29: Weighted DPO – Weighted Defect Per Opportunity | AM29: NA | AN29: NA | AO29: NA | AP29: NA | AQ29: NA | AR29: NA | AS29: NA | AT29: NA | AU29: NA | AV29: NA | AW29: NA | AX29: Onshore teams Brokers | AY29: Acturis Power Place SRI Emails | AZ29: Unstructured | BA29: Emails: 60% Spreadsheets: 20% System-Generated Reports: 10% Broker Correspondence: 5% Policy Adjustment Requests: 3% Renewal Requests: 2% | BB29: Renewals Referrals Policy amendments Premium adjustments Refunds | BC29: Underwriters Brokers | BD29: IS2000: Manages policies, generates documents, calculates premiums, issues refunds, and manages direct debits. Acturis: Makes underwriting decisions and generates quotes. SRI: Stores and retrieves scanned documents and emails. Handles broker correspondence and policy changes. BRM: Manages workflow across teams.
A30: RSA Insurance | B30: UK P&C client | C30: UK | D30: Noida, India | E30: =VLOOKUP(D30,'Dropdown List'!$F$26:$G$40,2,0) -> India | F30: Kanishka Singh | G30: 1 | H30: Active | I30: Underwriting and UW Support | J30: Policy Servicing | K30: Premium Billing and Collections | L30: Timely Negotiations and Collections Accurate Account Reconciliations Investigation of Unpaid Premiums | M30: Manage system reports and broker correspondence: Handle incoming documents and communications from brokers. Negotiate and collect premiums: Facilitate timely negotiations and collections of commercial policy premiums. Reconcile accounts: Perform thorough and accurate account reconciliations to minimize debt. Investigate unpaid premiums: Conduct detailed investigations to resolve unpaid premiums. Chase collections: Actively pursue collections on the allocated portfolio. Send statements: Inform brokers of overdue or due amounts. Allocate payments: Apply received payments to various agencies and perform reconciliation. Follow up on payments: Follow up with brokers and underwriters for unresolved queries. Issue refunds: Process refunds to brokers if they are due. Clear premiums: Reconcile payments to clear outstanding/due premiums from accounts. | N30: Commercial | O30: Multi/ Combination | P30: Auto,Property,Package | Q30: All | R30: Blended | S30: L2 | T30: 1 weeks | U30: 4 weeks | V30: 4 weeks | W30: FTE Based | X30: GBP | Y30: Assistant Accountant - £28019.6 Broker Rec Manager - £41475.1 | Z30: 3 | AA30: 0 | AB30: 1 | AC30: 1 | AD30: =SUM(Z30:AC30) -> 5 | AE30: =AC30/AD30 -> 0.2 | AF30: NA | AG30: NA | AH30: July, September, October | AI30: NA | AJ30: 0.95 | AK30: NA | AL30: Others | AM30: NA | AN30: NA | AO30: NA | AP30: NA | AQ30: NA | AR30: NA | AS30: NA | AT30: NA | AU30: NA | AV30: NA | AW30: NA | AX30: Onshore teams Brokers | AY30: Files from onshore Emails from brokers | AZ30: Unstructured | BA30: Files from onshore: 60% Emails from brokers: 40% | BB30: Cleared premiums Statements Payment allocations Follow-up records Refunds | BC30: Underwriters Brokers | BD30: IS2000: For managing policies and generating documents. Acturis: For making underwriting decisions and generating quotes. SRI & IS2000: For handling broker correspondence and policy changes. SRI - Document Management System: For storing and retrieving scanned documents and emails. BRM - Broker Relationship manager software application used to manage workflow across teams
A31: Kemper | B31: Regional US P&C Carrier | C31: US | D31: Noida, India | E31: =VLOOKUP(D31,'Dropdown List'!$F$26:$G$40,2,0) -> India | F31: Gaurav Agarwal | G31: 10 | H31: Active | I31: Claims | J31: Initiation | K31: After Hours Support | L31: Claim File Copies | M31: Claim file copy requests. | N31: Personal | O31: Multi/ Combination | P31: Auto/Property | Q31: Mid Size | R31: Back Office | S31: L2 | T31: 1 | U31: 2 | V31: 3 | W31: FTE Based | X31: USD | Y31: 24417.299 | Z31: 2 | AA31: 0.1 | AB31: 0.04 | AC31: 1.1 | AD31: =SUM(Z31:AC31) -> 3.24 | AE31: =AC31/AD31 -> 0.33950617 | AF31: 428 | AG31: NA | AH31: NA | AI31: 17.28 | AJ31: 0.95 | AK31: 0.95 | AL31: DPO – Defect Per Opportunity | AM31: NA | AN31: NA | AO31: NA | AP31: NA | AQ31: NA | AR31: NA | AS31: NA | AT31: NA | AU31: NA | AV31: NA | AW31: NA | AX31: Claim Adjuster | AY31: Instructions in Application/Emails | AZ31: Semi-Structured | BA31: 1 | BB31: Access to claim related documents | BC31: Attorney/Law firms, Claim adjusters, Government agencies etc | BD31: Claim Center, P8, MS office, Medflow, Infinty Policy System, Foxit Phantom
A32: Kemper | B32: Regional US P&C Carrier | C32: US | D32: Noida, India | E32: =VLOOKUP(D32,'Dropdown List'!$F$26:$G$40,2,0) -> India | F32: Gaurav Agarwal | G32: 10 | H32: Active | I32: Claims | J32: Initiation | K32: After Hours Support | L32: IA Supplement Messages | M32: Send emails/voice mail messages received from repair facilities to regional dispatch mailboxes. | N32: Personal | O32: Multi/ Combination | P32: Auto/Property | Q32: Mid Size | R32: Back Office | S32: L1 | T32: 1 | U32: 1 | V32: 2 | W32: FTE Based | X32: USD | Y32: 20576.695 | Z32: 6 | AA32: 0.1 | AB32: 0.04 | AC32: 1.1 | AD32: =SUM(Z32:AC32) -> 7.24 | AE32: =AC32/AD32 -> 0.1519337 | AF32: 2502 | AG32: NA | AH32: NA | AI32: 4.52 | AJ32: 0.95 | AK32: 0.95 | AL32: DPO – Defect Per Opportunity | AM32: NA | AN32: NA | AO32: NA | AP32: NA | AQ32: NA | AR32: NA | AS32: NA | AT32: NA | AU32: NA | AV32: NA | AW32: NA | AX32: Body Shops | AY32: Emails | AZ32: Unstructured | BA32: 1 | BB32: Documents uploaded to CCC Portal and assignment to damage appraiser for vehicle inspection | BC32: Appraiser, Claim Adjuster | BD32: Claim Center, CCC portal, MS office
A33: Kemper | B33: Regional US P&C Carrier | C33: US | D33: Noida, India | E33: =VLOOKUP(D33,'Dropdown List'!$F$26:$G$40,2,0) -> India | F33: Gaurav Agarwal | G33: 10 | H33: Active | I33: Claims | J33: Initiation | K33: After Hours Support | L33: Matter Setups & Closures | M33: Setup Matter on claim files for legal expenses to be paid and close Matters post payments | N33: Personal | O33: Multi/ Combination | P33: Auto/Property | Q33: Mid Size | R33: Back Office | S33: L2 | T33: 1 | U33: 2 | V33: 3 | W33: FTE Based | X33: USD | Y33: 24417.299 | Z33: 2 | AA33: 0.1 | AB33: 0.04 | AC33: 1.1 | AD33: =SUM(Z33:AC33) -> 3.24 | AE33: =AC33/AD33 -> 0.33950617 | AF33: 670 | AG33: NA | AH33: NA | AI33: 14.6 | AJ33: 0.95 | AK33: 0.95 | AL33: DPO – Defect Per Opportunity | AM33: NA | AN33: NA | AO33: NA | AP33: NA | AQ33: NA | AR33: NA | AS33: NA | AT33: NA | AU33: NA | AV33: NA | AW33: NA | AX33: Claim Adjuster | AY33: Instructions in Application/Emails | AZ33: Semi-Structured | BA33: 1 | BB33: Matter created for law firm and claim adjuster | BC33: Claim Adjuster/Law firm | BD33: Claim Center & Bottomline Legal Exchange, MS office
A34: Kemper | B34: Regional US P&C Carrier | C34: US | D34: Noida, India | E34: =VLOOKUP(D34,'Dropdown List'!$F$26:$G$40,2,0) -> India | F34: Gaurav Agarwal | G34: 10 | H34: Active | I34: Claims | J34: Evaluation | K34: Quality Management | L34: QA Support | M34: QA Support | N34: Personal | O34: Multi/ Combination | P34: Auto/Property | Q34: Mid Size | R34: Back Office | S34: L4 | T34: NA | U34: NA | V34: NA | W34: FTE Based | X34: USD | Y34: 33328.059 | Z34: 3 | AA34: 0.1 | AB34: 0.04 | AC34: 1.1 | AD34: =SUM(Z34:AC34) -> 4.24 | AE34: =AC34/AD34 -> 0.25943396 | AF34: NA | AG34: NA | AH34: NA | AI34: NA | AJ34: 0.95 | AK34: 0.95 | AL34: DPO – Defect Per Opportunity | AM34: NA | AN34: NA | AO34: NA | AP34: NA | AQ34: NA | AR34: NA | AS34: NA | AT34: NA | AU34: NA | AV34: NA | AW34: NA | AX34: NA | AY34: Multiple | AZ34: Semi-Structured | BA34: NA | BB34: NA | BC34: NA | BD34: All Client Applications / Admin Systems
A35: Kemper | B35: Regional US P&C Carrier | C35: US | D35: Noida, India | E35: =VLOOKUP(D35,'Dropdown List'!$F$26:$G$40,2,0) -> India | F35: Gaurav Agarwal | G35: 10 | H35: Active | I35: Claims | J35: Subrogation and Compliance | K35: Salvage Settlement | L35: Salvage Deficit Payments | M35: Salvage deficit payments processed for invoices received via email from vendor. | N35: Personal | O35: Multi/ Combination | P35: Auto/Property | Q35: Mid Size | R35: Back Office | S35: L2 | T35: 1 | U35: 2 | V35: 3 | W35: FTE Based | X35: USD | Y35: 24417.299 | Z35: 2 | AA35: 0.1 | AB35: 0.04 | AC35: 1.1 | AD35: =SUM(Z35:AC35) -> 3.24 | AE35: =AC35/AD35 -> 0.33950617 | AF35: 1088 | AG35: NA | AH35: NA | AI35: 5.86 | AJ35: 0.95 | AK35: 0.95 | AL35: DPO – Defect Per Opportunity | AM35: NA | AN35: NA | AO35: NA | AP35: NA | AQ35: NA | AR35: NA | AS35: NA | AT35: NA | AU35: NA | AV35: NA | AW35: NA | AX35: Kemper | AY35: Emails | AZ35: Unstructured | BA35: 1 | BB35: Payment/EFT issued to salvage vendor | BC35: Vendor | BD35: Claim Center
A36: Kemper | B36: Regional US P&C Carrier | C36: US | D36: Noida, India | E36: =VLOOKUP(D36,'Dropdown List'!$F$26:$G$40,2,0) -> India | F36: Gaurav Agarwal | G36: 10 | H36: Active | I36: Claims | J36: Initiation | K36: After Hours Support | L36: Eschest Checks | M36: Processing of returned escheat letters from customers. Confirm if money owed and reissue check as needed | N36: Personal | O36: Multi/ Combination | P36: Auto/Property | Q36: Mid Size | R36: Back Office | S36: L2 | T36: 1 | U36: 2 | V36: 3 | W36: FTE Based | X36: USD | Y36: 24417.299 | Z36: 1 | AA36: 0.1 | AB36: 0.04 | AC36: 1.1 | AD36: =SUM(Z36:AC36) -> 2.24 | AE36: =AC36/AD36 -> 0.49107143 | AF36: 312 | AG36: NA | AH36: NA | AI36: 8.67 | AJ36: 0.95 | AK36: 0.95 | AL36: DPO – Defect Per Opportunity | AM36: NA | AN36: NA | AO36: NA | AP36: NA | AQ36: NA | AR36: NA | AS36: NA | AT36: NA | AU36: NA | AV36: NA | AW36: NA | AX36: Kemper | AY36: Emails | AZ36: Unstructured | BA36: 1 | BB36: Uncashed payment forwarded to escheatment team | BC36: Onshore Escheatment Team | BD36: Claim Center, Nintex Application
A37: Kemper | B37: Regional US P&C Carrier | C37: US | D37: Noida, India | E37: =VLOOKUP(D37,'Dropdown List'!$F$26:$G$40,2,0) -> India | F37: Gaurav Agarwal | G37: 10 | H37: Active | I37: Claims | J37: Initiation | K37: Adjuster Onboarding/Off-boarding | L37: KSG Claims System Access Request | M37: Submitting system access request for new hires and/or existing employees. | N37: Personal | O37: Multi/ Combination | P37: Auto/Property | Q37: Mid Size | R37: Back Office | S37: L2 | T37: 1 | U37: 2 | V37: 3 | W37: FTE Based | X37: USD | Y37: 24417.299 | Z37: 1 | AA37: 0.1 | AB37: 0.04 | AC37: 1.1 | AD37: =SUM(Z37:AC37) -> 2.24 | AE37: =AC37/AD37 -> 0.49107143 | AF37: 2567 | AG37: NA | AH37: NA | AI37: 6 | AJ37: 0.95 | AK37: 0.95 | AL37: DPO – Defect Per Opportunity | AM37: NA | AN37: NA | AO37: NA | AP37: NA | AQ37: NA | AR37: NA | AS37: NA | AT37: NA | AU37: NA | AV37: NA | AW37: NA | AX37: Kemper | AY37: Emails | AZ37: Semi-Structured | BA37: 1 | BB37: Multiple applications access, login Id and password created/deleted/reset for existing employees | BC37: Onshore Employee | BD37: Claim Center, Multiple applications whose access is required
A38: Kemper | B38: Regional US P&C Carrier | C38: US | D38: Noida, India | E38: =VLOOKUP(D38,'Dropdown List'!$F$26:$G$40,2,0) -> India | F38: Gaurav Agarwal | G38: 10 | H38: Active | I38: Claims | J38: Initiation | K38: Indexing | L38: Unidentified Mail Queues | M38: Research unidentified documents received in Indexing systems so as to match them to the correct claim files. | N38: Personal | O38: Multi/ Combination | P38: Auto/Property | Q38: Mid Size | R38: Back Office | S38: L3 | T38: 1 | U38: 4 | V38: 4 | W38: FTE Based | X38: USD | Y38: 29414.285 | Z38: 8.4 | AA38: 0.1 | AB38: 0.04 | AC38: 1.1 | AD38: =SUM(Z38:AC38) -> 9.64 | AE38: =AC38/AD38 -> 0.11410788 | AF38: 14140 | AG38: NA | AH38: NA | AI38: 4.78 | AJ38: 0.95 | AK38: 0.95 | AL38: DPO – Defect Per Opportunity | AM38: NA | AN38: NA | AO38: NA | AP38: NA | AQ38: NA | AR38: NA | AS38: NA | AT38: NA | AU38: NA | AV38: NA | AW38: NA | AX38: Kemper | AY38: Images | AZ38: Structured | BA38: 1 | BB38: Document indexed with correct claim | BC38: Claim Adjuster | BD38: Claim Center, D360, Claims Historical Repository
A39: Kemper | B39: Regional US P&C Carrier | C39: US | D39: Noida, India | E39: =VLOOKUP(D39,'Dropdown List'!$F$26:$G$40,2,0) -> India | F39: Gaurav Agarwal | G39: 10 | H39: Active | I39: Claims | J39: Litigation and Resolution | K39: Bill Payment (Medical Legal, Non Medical, Vendor) | L39: Vendor Payments and Legal Bill Invoice Payments | M39: Issue payments to various vendors in claims systems. Invoices are emailed. | N39: Personal | O39: Multi/ Combination | P39: Auto/Property | Q39: Mid Size | R39: Back Office | S39: L2 | T39: 1 | U39: 2 | V39: 3 | W39: FTE Based | X39: USD | Y39: 24417.299 | Z39: 8.5 | AA39: 0.1 | AB39: 0.04 | AC39: 1.1 | AD39: =SUM(Z39:AC39) -> 9.74 | AE39: =AC39/AD39 -> 0.11293634 | AF39: 6360 | AG39: NA | AH39: NA | AI39: 6 | AJ39: 0.95 | AK39: 0.95 | AL39: DPO – Defect Per Opportunity | AM39: NA | AN39: NA | AO39: NA | AP39: NA | AQ39: NA | AR39: NA | AS39: NA | AT39: NA | AU39: NA | AV39: NA | AW39: NA | AX39: Vendor | AY39: Emails | AZ39: Semi-Structured | BA39: 1 | BB39: Payment issued to vendor | BC39: Vendor | BD39: Claim Center, Bottemline Legal Exchange
A40: Kemper | B40: Regional US P&C Carrier | C40: US | D40: Noida, India | E40: =VLOOKUP(D40,'Dropdown List'!$F$26:$G$40,2,0) -> India | F40: Gaurav Agarwal | G40: 10 | H40: Active | I40: Claims | J40: Subrogation and Compliance | K40: Initiate Recovery Collection & processing | L40: Subro Recovery payments | M40: Payments issuance in Kemper Claims Center (KCC) of demands with completed PD reviews | N40: Personal | O40: Multi/ Combination | P40: Auto/Property | Q40: Mid Size | R40: Back Office | S40: L2 | T40: 1 | U40: 2 | V40: 3 | W40: FTE Based | X40: USD | Y40: 24417.299 | Z40: 5 | AA40: 0.1 | AB40: 0.04 | AC40: 1.1 | AD40: =SUM(Z40:AC40) -> 6.24 | AE40: =AC40/AD40 -> 0.17628205 | AF40: 2914 | AG40: NA | AH40: NA | AI40: 10.43 | AJ40: 0.95 | AK40: 0.95 | AL40: DPO – Defect Per Opportunity | AM40: NA | AN40: NA | AO40: NA | AP40: NA | AQ40: NA | AR40: NA | AS40: NA | AT40: NA | AU40: NA | AV40: NA | AW40: NA | AX40: Kemper | AY40: Emails | AZ40: Unstructured | BA40: 1 | BB40: Recovered amount posted in claims system | BC40: Claim Adjuster | BD40: Claim Center
A41: Kemper | B41: Regional US P&C Carrier | C41: US | D41: Noida, India | E41: =VLOOKUP(D41,'Dropdown List'!$F$26:$G$40,2,0) -> India | F41: Gaurav Agarwal | G41: 10 | H41: Active | I41: Claims | J41: Subrogation and Compliance | K41: Initiate Recovery Collection & processing | L41: Recovery Compliance Letters | M41: Completion of NY/TX compliance letters | N41: Personal | O41: Multi/ Combination | P41: Auto/Property | Q41: Mid Size | R41: Back Office | S41: L2 | T41: 1 | U41: 2 | V41: 3 | W41: FTE Based | X41: USD | Y41: 24417.299 | Z41: 1 | AA41: 0.1 | AB41: 0.04 | AC41: 1.1 | AD41: =SUM(Z41:AC41) -> 2.24 | AE41: =AC41/AD41 -> 0.49107143 | AF41: 766 | AG41: NA | AH41: NA | AI41: 4.84 | AJ41: 0.95 | AK41: 0.95 | AL41: DPO – Defect Per Opportunity | AM41: NA | AN41: NA | AO41: NA | AP41: NA | AQ41: NA | AR41: NA | AS41: NA | AT41: NA | AU41: NA | AV41: NA | AW41: NA | AX41: Kemper | AY41: Emails | AZ41: Unstructured | BA41: 1 | BB41: Acknowledgement letter sent to insured | BC41: Insured | BD41: Claim Center
A42: Kemper | B42: Regional US P&C Carrier | C42: US | D42: Noida, India | E42: =VLOOKUP(D42,'Dropdown List'!$F$26:$G$40,2,0) -> India | F42: Gaurav Agarwal | G42: 10 | H42: Active | I42: Claims | J42: Litigation and Resolution | K42: Bill Payment (Medical Legal, Non Medical, Vendor) | L42: AACC Vendor Payments | M42: Issue payments to various vendors in claims systems. Invoices are emailed. | N42: Personal | O42: Multi/ Combination | P42: Auto/Property | Q42: Mid Size | R42: Back Office | S42: L2 | T42: 1 | U42: 2 | V42: 3 | W42: FTE Based | X42: USD | Y42: 24417.299 | Z42: 1 | AA42: 0.1 | AB42: 0.04 | AC42: 1.1 | AD42: =SUM(Z42:AC42) -> 2.24 | AE42: =AC42/AD42 -> 0.49107143 | AF42: 106 | AG42: NA | AH42: NA | AI42: 8 | AJ42: 0.95 | AK42: 0.95 | AL42: DPO – Defect Per Opportunity | AM42: NA | AN42: NA | AO42: NA | AP42: NA | AQ42: NA | AR42: NA | AS42: NA | AT42: NA | AU42: NA | AV42: NA | AW42: NA | AX42: Vendor | AY42: Emails | AZ42: Unstructured | BA42: 1 | BB42: Payment issued to vendor | BC42: Vendor | BD42: American Access Claims Center, CCC Portal
A43: Kemper | B43: Regional US P&C Carrier | C43: US | D43: Noida, India | E43: =VLOOKUP(D43,'Dropdown List'!$F$26:$G$40,2,0) -> India | F43: Gaurav Agarwal | G43: 10 | H43: Active | I43: Claims | J43: Initiation | K43: Claim Setup and assignment | L43: FNOL Claim Setup | M43: Reviews the FNOL document, set up a claim with available information and assign it to the claims adjuster | N43: Personal | O43: Multi/ Combination | P43: Auto/Property | Q43: Mid Size | R43: Back Office | S43: L3 | T43: 1 | U43: 4 | V43: 3 | W43: FTE Based | X43: USD | Y43: 29414.285 | Z43: 5 | AA43: 0.1 | AB43: 0.04 | AC43: 1.1 | AD43: =SUM(Z43:AC43) -> 6.24 | AE43: =AC43/AD43 -> 0.17628205 | AF43: 779 | AG43: NA | AH43: NA | AI43: 15 | AJ43: 0.95 | AK43: 0.95 | AL43: DPO – Defect Per Opportunity | AM43: NA | AN43: NA | AO43: NA | AP43: NA | AQ43: NA | AR43: NA | AS43: NA | AT43: NA | AU43: NA | AV43: NA | AW43: NA | AX43: Kemper | AY43: Images | AZ43: Semi-Structured | BA43: 1 | BB43: Claim generated for a loss | BC43: Claim Adjuster | BD43: Claim Center
A44: Kemper | B44: Regional US P&C Carrier | C44: US | D44: Noida, India | E44: =VLOOKUP(D44,'Dropdown List'!$F$26:$G$40,2,0) -> India | F44: Gaurav Agarwal | G44: 10 | H44: Active | I44: Claims | J44: Initiation | K44: Indexing | L44: AACC Mail Processing | M44: Reviews the misrouted documents and index those to the correct claim file | N44: Personal | O44: Multi/ Combination | P44: Auto/Property | Q44: Mid Size | R44: Back Office | S44: L3 | T44: 1 | U44: 4 | V44: 3 | W44: FTE Based | X44: USD | Y44: 29414.285 | Z44: 3 | AA44: 0.1 | AB44: 0.04 | AC44: 1.1 | AD44: =SUM(Z44:AC44) -> 4.24 | AE44: =AC44/AD44 -> 0.25943396 | AF44: 6169 | AG44: NA | AH44: NA | AI44: 3.5 | AJ44: 0.95 | AK44: 0.95 | AL44: DPO – Defect Per Opportunity | AM44: NA | AN44: NA | AO44: NA | AP44: NA | AQ44: NA | AR44: NA | AS44: NA | AT44: NA | AU44: NA | AV44: NA | AW44: NA | AX44: Kemper | AY44: Images | AZ44: Structured | BA44: 1 | BB44: Document indexed with correct claim | BC44: Claim Adjuster | BD44: Image Right and AA Claims Center, Lexis Nexis
A45: Kemper | B45: Regional US P&C Carrier | C45: US | D45: Noida, India | E45: =VLOOKUP(D45,'Dropdown List'!$F$26:$G$40,2,0) -> India | F45: Gaurav Agarwal | G45: 10 | H45: Active | I45: Claims | J45: Investigation | K45: Requesting Police report | L45: AACC Ordering Police Report | M45: Draft requests to oder police report from an application basis adjuster's request | N45: Personal | O45: Multi/ Combination | P45: Auto/Property | Q45: Mid Size | R45: Back Office | S45: L3 | T45: 1 | U45: 2 | V45: 3 | W45: FTE Based | X45: USD | Y45: 29414.285 | Z45: 1 | AA45: 0.1 | AB45: 0.04 | AC45: 1.1 | AD45: =SUM(Z45:AC45) -> 2.24 | AE45: =AC45/AD45 -> 0.49107143 | AF45: 1149 | AG45: NA | AH45: NA | AI45: 9 | AJ45: 0.95 | AK45: 0.95 | AL45: DPO – Defect Per Opportunity | AM45: NA | AN45: NA | AO45: NA | AP45: NA | AQ45: NA | AR45: NA | AS45: NA | AT45: NA | AU45: NA | AV45: NA | AW45: NA | AX45: Kemper | AY45: Emails | AZ45: Structured | BA45: 1 | BB45: Police report ordered for further investigation | BC45: Claim Adjuster | BD45: AA Claims Center, Lexis Nexis
A46: Kemper | B46: Regional US P&C Carrier | C46: US | D46: Cape Town, South Africa | E46: =VLOOKUP(D46,'Dropdown List'!$F$26:$G$40,2,0) -> South Africa | F46: Faeekah Cornelius | G46: 4 | H46: Active | I46: Claims | J46: Initiation | K46: After Hours Support | L46: TL Assignments | M46: Assignment of claims and exposures to the total loss adjuster per the daily log sheet | N46: Personal | O46: Multi/ Combination | P46: Auto/Property | Q46: Mid Size | R46: Back Office | S46: L1 | T46: 1 | U46: 2 | V46: 2 | W46: FTE Based | X46: USD | Y46: 28463.005 | Z46: 1.5 | AA46: 0.09 | AB46: 0.06 | AC46: 1.09 | AD46: =SUM(Z46:AC46) -> 2.74 | AE46: =AC46/AD46 -> 0.39781022 | AF46: 5724 | AG46: NA | AH46: NA | AI46: 3 | AJ46: 0.95 | AK46: 0.95 | AL46: DPO – Defect Per Opportunity | AM46: NA | AN46: NA | AO46: NA | AP46: NA | AQ46: NA | AR46: NA | AS46: NA | AT46: NA | AU46: NA | AV46: NA | AW46: NA | AX46: Claim Adjuster | AY46: Instructions in Application | AZ46: Structured | BA46: 1 | BB46: Instructions in Application | BC46: Claim Adjuster | BD46: Claim Center, P8, MS office
... A50: Kemper | B50: Regional US P&C Carrier | C50: US | D50: Cape Town, South Africa | E50: =VLOOKUP(D50,'Dropdown List'!$F$26:$G$40,2,0) -> South Africa | F50: Faeekah Cornelius | G50: 4 | H50: Active | I50: Claims | J50: Initiation | K50: After Hours Support | L50: Return Check | M50: Review of outstanding checks to verify funds owed, and void & reissue checks as needed. | N50: Personal | O50: Multi/ Combination | P50: Auto/Property | Q50: Mid Size | R50: Back Office | S50: L1 | T50: 1 | U50: 2 | V50: 2 | W50: FTE Based | X50: USD | Y50: 28463.005 | Z50: 1 | AA50: 0.09 | AB50: 0.06 | AC50: 1.09 | AD50: =SUM(Z50:AC50) -> 2.24 | AE50: =AC50/AD50 -> 0.48660714 | AF50: 1010 | AG50: NA | AH50: NA | AI50: 4.59 | AJ50: 0.95 | AK50: 0.95 | AL50: DPO – Defect Per Opportunity | AM50: NA | AN50: NA | AO50: NA | AP50: NA | AQ50: NA | AR50: NA | AS50: NA | AT50: NA | AU50: NA | AV50: NA | AW50: NA | AX50: Claim Adjuster | AY50: Emails | AZ50: Semi-Structured | BA50: 1 | BB50: Checks voided | BC50: Claim Adjuster | BD50: Claim Center
A51: Kemper | B51: Regional US P&C Carrier | C51: US | D51: Cape Town, South Africa | E51: =VLOOKUP(D51,'Dropdown List'!$F$26:$G$40,2,0) -> South Africa | F51: Faeekah Cornelius | G51: 4 | H51: Active | I51: Claims | J51: Initiation | K51: After Hours Support | L51: Transcription Request - Send | M51: Locating recorded statements, identify wether recordings match, sending them to sysman folder to be transcribed. | N51: Personal | O51: Multi/ Combination | P51: Auto/Property | Q51: Mid Size | R51: Voice | S51: L2 | T51: 1 | U51: 2 | V51: 2 | W51: FTE Based | X51: USD | Y51: 30143.822 | Z51: 1.5 | AA51: 0.09 | AB51: 0.06 | AC51: 1.09 | AD51: =SUM(Z51:AC51) -> 2.74 | AE51: =AC51/AD51 -> 0.39781022 | AF51: 231 | AG51: NA | AH51: NA | AI51: 4.27 | AJ51: 0.95 | AK51: 0.95 | AL51: DPO – Defect Per Opportunity | AM51: NA | AN51: NA | AO51: NA | AP51: NA | AQ51: NA | AR51: NA | AS51: NA | AT51: NA | AU51: NA | AV51: NA | AW51: NA | AX51: Claim Adjuster | AY51: Instructions in Application | AZ51: Structured | BA51: NA | BB51: Documents and recordings uploaded to transcription | BC51: Claim Adjuster | BD51: Claim Center, P8, NICE, MSTEAMS, INFINITY
A52: Kemper | B52: Regional US P&C Carrier | C52: US | D52: Cape Town, South Africa | E52: =VLOOKUP(D52,'Dropdown List'!$F$26:$G$40,2,0) -> South Africa | F52: Faeekah Cornelius | G52: 4 | H52: Active | I52: Claims | J52: Initiation | K52: After Hours Support | L52: Transcription Request - Receive | M52: Locating transcribed statements in the sysman folder and uploading document to correct claim. | N52: Personal | O52: Multi/ Combination | P52: Auto/Property | Q52: Mid Size | R52: Voice | S52: L1 | T52: 1 | U52: 3 | V52: 3 | W52: FTE Based | X52: USD | Y52: 28463.005 | Z52: 0.5 | AA52: 0.09 | AB52: 0.06 | AC52: 1.09 | AD52: =SUM(Z52:AC52) -> 1.74 | AE52: =AC52/AD52 -> 0.62643678 | AF52: 227 | AG52: NA | AH52: NA | AI52: 4.27 | AJ52: 0.95 | AK52: 0.95 | AL52: DPO – Defect Per Opportunity | AM52: NA | AN52: NA | AO52: NA | AP52: NA | AQ52: NA | AR52: NA | AS52: NA | AT52: NA | AU52: NA | AV52: NA | AW52: NA | AX52: Claim Adjuster | AY52: Instructions in Application | AZ52: Structured | BA52: 1 | BB52: Transcriptibed documents and recording uploaded | BC52: Claim Adjuster | BD52: Claim Center, P8, NICE, MSTEAMS, INFINITY
A53: Kemper | B53: Regional US P&C Carrier | C53: US | D53: Cape Town, South Africa | E53: =VLOOKUP(D53,'Dropdown List'!$F$26:$G$40,2,0) -> South Africa | F53: Faeekah Cornelius | G53: 4 | H53: Active | I53: Claims | J53: Initiation | K53: After Hours Support | L53: Claim File Copies - KCC/ICS | M53: Claim file copy requests. | N53: Personal | O53: Multi/ Combination | P53: Auto/Property | Q53: Mid Size | R53: Back Office | S53: L2 | T53: 1 | U53: 2 | V53: 2 | W53: FTE Based | X53: USD | Y53: 30143.822 | Z53: 6.75 | AA53: 0.09 | AB53: 0.06 | AC53: 1.09 | AD53: =SUM(Z53:AC53) -> 7.99 | AE53: =AC53/AD53 -> 0.13642053 | AF53: 3507 | AG53: NA | AH53: NA | AI53: 7.58 | AJ53: 0.95 | AK53: 0.95 | AL53: DPO – Defect Per Opportunity | AM53: NA | AN53: NA | AO53: NA | AP53: NA | AQ53: NA | AR53: NA | AS53: NA | AT53: NA | AU53: NA | AV53: NA | AW53: NA | AX53: Claim Adjuster | AY53: Instructions in Application | AZ53: Semi-Structured | BA53: 1 | BB53: Access to claim related documents | BC53: Attorney/Law firms, Claim adjusters, Government agencies etc | BD53: Claim Center, P8, MS office, Medflow, Infinty Policy System, Foxit Phantom
A54: Kemper | B54: Regional US P&C Carrier | C54: US | D54: Cape Town, South Africa | E54: =VLOOKUP(D54,'Dropdown List'!$F$26:$G$40,2,0) -> South Africa | F54: Faeekah Cornelius | G54: 4 | H54: Active | I54: Claims | J54: Initiation | K54: After Hours Support | L54: Letter Print File | M54: Assignment of requested letters and check. | N54: Personal | O54: Multi/ Combination | P54: Auto/Property | Q54: Mid Size | R54: Back Office | S54: L1 | T54: 1 | U54: 2 | V54: 2 | W54: FTE Based | X54: USD | Y54: 28463.005 | Z54: 0.25 | AA54: 0.09 | AB54: 0.06 | AC54: 1.09 | AD54: =SUM(Z54:AC54) -> 1.49 | AE54: =AC54/AD54 -> 0.73154362 | AF54: 105 | AG54: NA | AH54: NA | AI54: 4.15 | AJ54: 0.95 | AK54: 0.95 | AL54: DPO – Defect Per Opportunity | AM54: NA | AN54: NA | AO54: NA | AP54: NA | AQ54: NA | AR54: NA | AS54: NA | AT54: NA | AU54: NA | AV54: NA | AW54: NA | AX54: Claim Adjuster | AY54: Emails | AZ54: Semi-Structured | BA54: 1 | BB54: Letters and Checks reissued | BC54: Claim Adjuster | BD54: Claim Center
A55: Kemper | B55: Regional US P&C Carrier | C55: US | D55: Cape Town, South Africa | E55: =VLOOKUP(D55,'Dropdown List'!$F$26:$G$40,2,0) -> South Africa | F55: Faeekah Cornelius | G55: 4 | H55: Active | I55: Claims | J55: Initiation | K55: Claim Setup and assignment | L55: Arbitration Assignments | M55: Assigning Claims to adjusters in order to litigate arbitration process | N55: Personal | O55: Multi/ Combination | P55: Auto/Property | Q55: Mid Size | R55: Back Office | S55: L1 | T55: 1 | U55: 2 | V55: 2 | W55: FTE Based | X55: USD | Y55: 28463.005 | Z55: 1 | AA55: 0.09 | AB55: 0.06 | AC55: 1.09 | AD55: =SUM(Z55:AC55) -> 2.24 | AE55: =AC55/AD55 -> 0.48660714 | AF55: 2255 | AG55: NA | AH55: NA | AI55: 5 | AJ55: 0.95 | AK55: 0.95 | AL55: DPO – Defect Per Opportunity | AM55: NA | AN55: NA | AO55: NA | AP55: NA | AQ55: NA | AR55: NA | AS55: NA | AT55: NA | AU55: NA | AV55: NA | AW55: NA | AX55: Claim Adjuster | AY55: Instructions in Application | AZ55: Structured | BA55: 1 | BB55: claims assigned to Abitration adjusters | BC55: Claim Adjuster | BD55: Claim Center, Arb Forum
A56: Kemper | B56: Regional US P&C Carrier | C56: US | D56: Cape Town, South Africa | E56: =VLOOKUP(D56,'Dropdown List'!$F$26:$G$40,2,0) -> South Africa | F56: Faeekah Cornelius | G56: 4 | H56: Active | I56: Claims | J56: Initiation | K56: Claim Setup and assignment | L56: Salvage Assignments | M56: Assignment of requests added to Salvage Assignment Queue. | N56: Personal | O56: Multi/ Combination | P56: Auto/Property | Q56: Mid Size | R56: Back Office | S56: L1 | T56: 1 | U56: 2 | V56: 2 | W56: FTE Based | X56: USD | Y56: 28463.005 | Z56: 2 | AA56: 0.09 | AB56: 0.06 | AC56: 1.09 | AD56: =SUM(Z56:AC56) -> 3.24 | AE56: =AC56/AD56 -> 0.33641975 | AF56: 3471 | AG56: NA | AH56: NA | AI56: 4.84 | AJ56: 0.95 | AK56: 0.95 | AL56: DPO – Defect Per Opportunity | AM56: NA | AN56: NA | AO56: NA | AP56: NA | AQ56: NA | AR56: NA | AS56: NA | AT56: NA | AU56: NA | AV56: NA | AW56: NA | AX56: Claim Adjuster | AY56: Instructions in Application | AZ56: Structured | BA56: 1 | BB56: damaged vehicles assigned to the Salvage department | BC56: Claim Adjuster | BD56: Claim Center, CSA Today
A57: Kemper | B57: Regional US P&C Carrier | C57: US | D57: Cape Town, South Africa | E57: =VLOOKUP(D57,'Dropdown List'!$F$26:$G$40,2,0) -> South Africa | F57: Faeekah Cornelius | G57: 4 | H57: Active | I57: Claims | J57: Initiation | K57: Claim Setup and assignment | L57: PIP Assignments | M57: Assignment and reassignment of claims and exposures to suitable adjusters according to live spreadsheet. | N57: Personal | O57: Multi/ Combination | P57: Auto/Property | Q57: Mid Size | R57: Back Office | S57: L1 | T57: 1 | U57: 2 | V57: 2 | W57: FTE Based | X57: USD | Y57: 28463.005 | Z57: 1.5 | AA57: 0.09 | AB57: 0.06 | AC57: 1.09 | AD57: =SUM(Z57:AC57) -> 2.74 | AE57: =AC57/AD57 -> 0.39781022 | AF57: 1723 | AG57: NA | AH57: NA | AI57: 5.98 | AJ57: 0.95 | AK57: 0.95 | AL57: DPO – Defect Per Opportunity | AM57: NA | AN57: NA | AO57: NA | AP57: NA | AQ57: NA | AR57: NA | AS57: NA | AT57: NA | AU57: NA | AV57: NA | AW57: NA | AX57: Claim Adjuster | AY57: Instructions in Application | AZ57: Structured | BA57: 1 | BB57: exposures assigned to adjusters for further handling | BC57: Claim Adjuster | BD57: Claim Center
A58: Kemper | B58: Regional US P&C Carrier | C58: US | D58: Cape Town, South Africa | E58: =VLOOKUP(D58,'Dropdown List'!$F$26:$G$40,2,0) -> South Africa | F58: Faeekah Cornelius | G58: 4 | H58: Active | I58: Claims | J58: Initiation | K58: After Hours Support | L58: Property Document Import Mailbox | M58: Uploads of Property documents. | N58: Personal | O58: Multi/ Combination | P58: Auto/Property | Q58: Mid Size | R58: Back Office | S58: L2 | T58: 1 | U58: 2 | V58: 2 | W58: FTE Based | X58: USD | Y58: 30143.822 | Z58: 1 | AA58: 0.09 | AB58: 0.06 | AC58: 1.09 | AD58: =SUM(Z58:AC58) -> 2.24 | AE58: =AC58/AD58 -> 0.48660714 | AF58: 1509 | AG58: NA | AH58: NA | AI58: 6.31 | AJ58: 0.95 | AK58: 0.95 | AL58: DPO – Defect Per Opportunity | AM58: NA | AN58: NA | AO58: NA | AP58: NA | AQ58: NA | AR58: NA | AS58: NA | AT58: NA | AU58: NA | AV58: NA | AW58: NA | AX58: Claim Adjuster | AY58: Instructions in Application | AZ58: Semi-Structured | BA58: 1 | BB58: Access to claim related documents | BC58: Claim Adjuster | BD58: Claim Center, D360,MS Office
A59: Kemper | B59: Regional US P&C Carrier | C59: US | D59: Cape Town, South Africa | E59: =VLOOKUP(D59,'Dropdown List'!$F$26:$G$40,2,0) -> South Africa | F59: Faeekah Cornelius | G59: 4 | H59: Active | I59: Claims | J59: Initiation | K59: Indexing | L59: Misrouted Documents Queue | M59: Routing/sending documents from incorrect claim file to the approriate claim file. | N59: Personal | O59: Multi/ Combination | P59: Auto/Property | Q59: Mid Size | R59: Back Office | S59: L2 | T59: 1 | U59: 2 | V59: 2 | W59: FTE Based | X59: USD | Y59: 30143.822 | Z59: 0.5 | AA59: 0.09 | AB59: 0.06 | AC59: 1.09 | AD59: =SUM(Z59:AC59) -> 1.74 | AE59: =AC59/AD59 -> 0.62643678 | AF59: 354 | AG59: NA | AH59: NA | AI59: 5.04 | AJ59: 0.95 | AK59: 0.95 | AL59: DPO – Defect Per Opportunity | AM59: NA | AN59: NA | AO59: NA | AP59: NA | AQ59: NA | AR59: NA | AS59: NA | AT59: NA | AU59: NA | AV59: NA | AW59: NA | AX59: Claim Adjuster | AY59: Images | AZ59: Structured | BA59: 1 | BB59: documents routed to the correct claim | BC59: Claim Adjuster | BD59: Claim Center,D360
A60: Kemper | B60: Regional US P&C Carrier | C60: US | D60: Cape Town, South Africa | E60: =VLOOKUP(D60,'Dropdown List'!$F$26:$G$40,2,0) -> South Africa | F60: Faeekah Cornelius | G60: 4 | H60: Active | I60: Claims | J60: Initiation | K60: Indexing | L60: New Document Queue | M60: Reasigning an activity to a new adjuster due to to the the previous adjusters absence. | N60: Personal | O60: Multi/ Combination | P60: Auto/Property | Q60: Mid Size | R60: Back Office | S60: L2 | T60: 1 | U60: 2 | V60: 2 | W60: FTE Based | X60: USD | Y60: 30143.822 | Z60: 0.5 | AA60: 0.09 | AB60: 0.06 | AC60: 1.09 | AD60: =SUM(Z60:AC60) -> 1.74 | AE60: =AC60/AD60 -> 0.62643678 | AF60: 731 | AG60: NA | AH60: NA | AI60: 5.04 | AJ60: 0.95 | AK60: 0.95 | AL60: DPO – Defect Per Opportunity | AM60: NA | AN60: NA | AO60: NA | AP60: NA | AQ60: NA | AR60: NA | AS60: NA | AT60: NA | AU60: NA | AV60: NA | AW60: NA | AX60: Claim Adjuster | AY60: Images | AZ60: Structured | BA60: 1 | BB60: claim assigned to alternate adjuster | BC60: Claim Adjuster | BD60: Claim Center
A61: Kemper | B61: Regional US P&C Carrier | C61: US | D61: Cape Town, South Africa | E61: =VLOOKUP(D61,'Dropdown List'!$F$26:$G$40,2,0) -> South Africa | F61: Faeekah Cornelius | G61: 4 | H61: Active | I61: Claims | J61: Initiation | K61: Claim Setup and assignment | L61: CCO Requests | M61: Policy update requests. | N61: Personal | O61: Multi/ Combination | P61: Auto/Property | Q61: Mid Size | R61: Back Office | S61: L2 | T61: 1 | U61: 2 | V61: 2 | W61: FTE Based | X61: USD | Y61: 30143.822 | Z61: 1 | AA61: 0.09 | AB61: 0.06 | AC61: 1.09 | AD61: =SUM(Z61:AC61) -> 2.24 | AE61: =AC61/AD61 -> 0.48660714 | AF61: 246 | AG61: NA | AH61: NA | AI61: 5.18 | AJ61: 0.95 | AK61: 0.95 | AL61: DPO – Defect Per Opportunity | AM61: NA | AN61: NA | AO61: NA | AP61: NA | AQ61: NA | AR61: NA | AS61: NA | AT61: NA | AU61: NA | AV61: NA | AW61: NA | AX61: Claim Adjuster | AY61: Instructions in Application | AZ61: Structured | BA61: 1 | BB61: claim updates | BC61: Claim Adjuster | BD61: Claim Center
A62: Kemper | B62: Regional US P&C Carrier | C62: US | D62: Cape Town, South Africa | E62: =VLOOKUP(D62,'Dropdown List'!$F$26:$G$40,2,0) -> South Africa | F62: Faeekah Cornelius | G62: 4 | H62: Active | I62: Claims | J62: Evaluation | K62: Quality Management | L62: QA Support | M62: QA Support | N62: Personal | O62: Multi/ Combination | P62: Auto/Property | Q62: Mid Size | R62: Back Office | S62: L4 | T62: NA | U62: NA | V62: NA | W62: FTE Based | X62: USD | Y62: 32906.961 | Z62: 1 | AA62: 0.09 | AB62: 0.06 | AC62: 1.09 | AD62: =SUM(Z62:AC62) -> 2.24 | AE62: =AC62/AD62 -> 0.48660714 | AF62: N/A | AG62: NA | AH62: NA | AI62: NA | AJ62: 0.95 | AK62: 0.95 | AL62: DPO – Defect Per Opportunity | AM62: NA | AN62: NA | AO62: NA | AP62: NA | AQ62: NA | AR62: NA | AS62: NA | AT62: NA | AU62: NA | AV62: NA | AW62: NA | AX62: Claim Adjuster | AY62: Multiple | AZ62: Semi-Structured | BA62: 1 | BB62: NA | BC62: NA | BD62: Claim Center, P8, NICE, MSTEAMS, INFINITY
A63: Kemper | B63: Regional US P&C Carrier | C63: US | D63: Cape Town, South Africa | E63: =VLOOKUP(D63,'Dropdown List'!$F$26:$G$40,2,0) -> South Africa | F63: Faeekah Cornelius | G63: 4 | H63: Active | I63: Claims | J63: Initiation | K63: After Hours Support | L63: KPC Claims DD E-mail Return Mailbox | M63: Downloading emails and audio/video files from KPC mailbox and upload them in D360 | N63: Personal | O63: Multi/ Combination | P63: Auto/Property | Q63: Mid Size | R63: Back Office | S63: L2 | T63: 1 | U63: 2 | V63: 2 | W63: FTE Based | X63: USD | Y63: 30143.822 | Z63: 0.5 | AA63: 0.09 | AB63: 0.06 | AC63: 1.09 | AD63: =SUM(Z63:AC63) -> 1.74 | AE63: =AC63/AD63 -> 0.62643678 | AF63: 1345 | AG63: NA | AH63: NA | AI63: 4.59 | AJ63: 0.95 | AK63: 0.95 | AL63: DPO – Defect Per Opportunity | AM63: NA | AN63: NA | AO63: NA | AP63: NA | AQ63: NA | AR63: NA | AS63: NA | AT63: NA | AU63: NA | AV63: NA | AW63: NA | AX63: Claim Adjuster | AY63: Images | AZ63: Structured | BA63: 1 | BB63: Access to claim related documents and multimedia | BC63: Claim Adjuster | BD63: D360,Claim Center
A64: Kemper | B64: Regional US P&C Carrier | C64: US | D64: Cape Town, South Africa | E64: =VLOOKUP(D64,'Dropdown List'!$F$26:$G$40,2,0) -> South Africa | F64: Faeekah Cornelius | G64: 4 | H64: Active | I64: Claims | J64: Subrogation and Compliance | K64: Info Gathering & Analysis | L64: Subro Arb Act Tracker | M64: Collating a spreadsheet for all the activites assigned to adjusters/groups on previous day and upload on OneDrive for the managers to access and retrieve data for their respective teams | N64: Personal | O64: Multi/ Combination | P64: Auto/Property | Q64: Mid Size | R64: Back Office | S64: L2 | T64: 1 | U64: 2 | V64: 2 | W64: FTE Based | X64: USD | Y64: 30143.822 | Z64: 0.5 | AA64: 0.09 | AB64: 0.06 | AC64: 1.09 | AD64: =SUM(Z64:AC64) -> 1.74 | AE64: =AC64/AD64 -> 0.62643678 | AF64: 3126 | AG64: NA | AH64: NA | AI64: 4.49 | AJ64: 0.95 | AK64: 0.95 | AL64: DPO – Defect Per Opportunity | AM64: NA | AN64: NA | AO64: NA | AP64: NA | AQ64: NA | AR64: NA | AS64: NA | AT64: NA | AU64: NA | AV64: NA | AW64: NA | AX64: Claim Adjuster | AY64: Instructions in Application | AZ64: Structured | BA64: 1 | BB64: uploaded for managers veiw | BC64: Claim Adjuster | BD64: Claim Center KCC
A65: Kemper | B65: Regional US P&C Carrier | C65: US | D65: Cape Town, South Africa | E65: =VLOOKUP(D65,'Dropdown List'!$F$26:$G$40,2,0) -> South Africa | F65: Faeekah Cornelius | G65: 4 | H65: Active | I65: Claims | J65: Litigation and Resolution | K65: Bill Payment (Medical Legal, Non Medical, Vendor) | L65: AACC Vendor Payments | M65: Issue payments to various vendors in claims systems. Invoices are emailed. | N65: Personal | O65: Multi/ Combination | P65: Auto/Property | Q65: Mid Size | R65: Back Office | S65: L2 | T65: 1 | U65: 3 | V65: 3 | W65: FTE Based | X65: USD | Y65: 30143.822 | Z65: 2 | AA65: 0.09 | AB65: 0.06 | AC65: 1.09 | AD65: =SUM(Z65:AC65) -> 3.24 | AE65: =AC65/AD65 -> 0.33641975 | AF65: 1 | AG65: NA | AH65: NA | AI65: 15.15 | AJ65: 0.95 | AK65: 0.95 | AL65: DPO – Defect Per Opportunity | AM65: NA | AN65: NA | AO65: NA | AP65: NA | AQ65: NA | AR65: NA | AS65: NA | AT65: NA | AU65: NA | AV65: NA | AW65: NA | AX65: Vendor | AY65: Instructions in Application | AZ65: Structured | BA65: 1 | BB65: Payment issued to vendor | BC65: Claim Adjuster | BD65: American Access Claims Center, CCC Portal
A66: Kemper | B66: Regional US P&C Carrier | C66: US | D66: Cape Town, South Africa | E66: =VLOOKUP(D66,'Dropdown List'!$F$26:$G$40,2,0) -> South Africa | F66: Faeekah Cornelius | G66: 4 | H66: Active | I66: Claims | J66: Investigation | K66: Requesting Police report | L66: AACC Ordering Police Report | M66: Draft requests to oder police report from an application basis adjuster's request | N66: Personal | O66: Multi/ Combination | P66: Auto/Property | Q66: Mid Size | R66: Back Office | S66: L2 | T66: 1 | U66: 2 | V66: 2 | W66: FTE Based | X66: USD | Y66: 30143.822 | Z66: 0.5 | AA66: 0.09 | AB66: 0.06 | AC66: 1.09 | AD66: =SUM(Z66:AC66) -> 1.74 | AE66: =AC66/AD66 -> 0.62643678 | AF66: 1240 | AG66: NA | AH66: NA | AI66: 2.3 | AJ66: 0.95 | AK66: 0.95 | AL66: DPO – Defect Per Opportunity | AM66: NA | AN66: NA | AO66: NA | AP66: NA | AQ66: NA | AR66: NA | AS66: NA | AT66: NA | AU66: NA | AV66: NA | AW66: NA | AX66: Claim Adjuster | AY66: Instructions in Application | AZ66: Structured | BA66: 1 | BB66: Police report ordered for further investigation | BC66: Claim Adjuster | BD66: Lexis Nexis, AACC Portal, Image Right
A67: Kemper | B67: Regional US P&C Carrier | C67: US | D67: Cape Town, South Africa | E67: =VLOOKUP(D67,'Dropdown List'!$F$26:$G$40,2,0) -> South Africa | F67: Faeekah Cornelius | G67: 4 | H67: Active | I67: Claims | J67: Initiation | K67: Indexing | L67: AACC Mail Processing | M67: Reviews the misrouted documents and index those to the correct claim file | N67: Personal | O67: Multi/ Combination | P67: Auto/Property | Q67: Mid Size | R67: Back Office | S67: L2 | T67: 1 | U67: 3 | V67: 3 | W67: FTE Based | X67: USD | Y67: 30143.822 | Z67: 2.5 | AA67: 0.09 | AB67: 0.06 | AC67: 1.09 | AD67: =SUM(Z67:AC67) -> 3.74 | AE67: =AC67/AD67 -> 0.29144385 | AF67: 6167 | AG67: NA | AH67: NA | AI67: 1.57 | AJ67: 0.95 | AK67: 0.95 | AL67: DPO – Defect Per Opportunity | AM67: NA | AN67: NA | AO67: NA | AP67: NA | AQ67: NA | AR67: NA | AS67: NA | AT67: NA | AU67: NA | AV67: NA | AW67: NA | AX67: Claim Adjuster | AY67: Instructions in Application | AZ67: Structured | BA67: 1 | BB67: Document indexed with correct claim | BC67: Claim Adjuster | BD67: Lexis Nexis, AACC Portal, Image Right, Kemper Auto
A68: Assurant Solutions | B68: Large US Multi-line Specialty Carrier | C68: US | D68: Alabang, PHP | E68: =VLOOKUP(D68,'Dropdown List'!$F$26:$G$40,2,0) -> Philippines | F68: Mark Redondo | G68: 5 | H68: Active | I68: Claims | J68: Initiation | K68: Customer Service Call Centre - Repair/ Replacement/ SOS help/ General Inquiry | L68: Renters | M68: The renters insurance receives calls from insured regarding insurance coverage and other relevant information of renters. Associates address concerns and queries by not only checking insured’s insurance policy and coverage but they also provide payment processing, cancelation requests and update on profile information. | N68: Personal | O68: Property | P68: Property, Auto | Q68: All | R68: Voice | S68: L3 | T68: 2 | U68: 5 | V68: 6 | W68: FTE Based | X68: USD | Y68: 30000 | Z68: 35 | AA68: 3 | AB68: 2 | AC68: 5 | AD68: =SUM(Z68:AC68) -> 45 | AE68: =AC68/AD68 -> 0.11111111 | AF68: 34000 | AG68: 34000 | AH68: May - Oct | AI68: 360 secs | AJ68: shared queue with onshore | AK68: 0.95 | AL68: DPO – Defect Per Opportunity | AM68: NA | AN68: NA | AO68: NA | AP68: NA | AQ68: NA | AR68: NA | AS68: NA | AT68: Al Coach | AU68: NA | AV68: NA | AW68: NA | AX68: Insured, Property Management, Agents | AY68: Others | AZ68: Unstructured | BA68: NA | BB68: Others | BC68: Insured | BD68: PMS, AIC, Collab network, Exceed, Policy Prefix, CRM, Outlook, MS Office
A69: Assurant Solutions | B69: Large US Multi-line Specialty Carrier | C69: US | D69: Alabang, PHP | E69: =VLOOKUP(D69,'Dropdown List'!$F$26:$G$40,2,0) -> Philippines | F69: Mark Redondo | G69: 4 | H69: Active | I69: Claims | J69: Initiation | K69: First Notice of Loss Calls | L69: FNOL | M69: Files FNOL for property and auto claims Receives calls checking status of claim/payment | N69: Personal | O69: Auto & Property | P69: Property, Auto | Q69: All | R69: Voice | S69: L3 | T69: 2 | U69: 2 | V69: 12 | W69: FTE Based | X69: USD | Y69: 29786.16 | Z69: 52 | AA69: 4 | AB69: 4 | AC69: 8 | AD69: =SUM(Z69:AC69) -> 68 | AE69: =AC69/AD69 -> 0.11764706 | AF69: 46000 | AG69: 46000 | AH69: Aug - Nov | AI69: 378 secs | AJ69: 0.8 | AK69: 0.9 | AL69: DPO – Defect Per Opportunity | AM69: SL - 80% | AN69: NA | AO69: NA | AP69: NA | AQ69: Nervehub - Gameboards | AR69: Gameboard is a comprehensive visualization of operational performance across process, people and transformation | AS69: Higher performance rates given that the agents have access to view their performance scores | AT69: Al Coach | AU69: Generate actionable insights, AL/ML based Cognitive Nudges to drive behavior change and Personalise coaching regime unquely for each employee | AV69: Achieve target behavior to drive performance of each employee | AW69: NA | AX69: Insured | AY69: Others | AZ69: Unstructured | BA69: NA | BB69: Multiple | BC69: Insured | BD69: ICE Claims System, Outlook, KwikWork, Guidewire, MS Office, PLNAR
A70: CNA | B70: Top-10 US Commercial & Specialty Carrier | C70: US | D70: Noida, India | E70: =VLOOKUP(D70,'Dropdown List'!$F$26:$G$40,2,0) -> India | F70: Arpan Pandey, Varunjesh | G70: 6 | H70: Active | I70: Claims | J70: Litigation and Resolution | K70: Send Closing Documents | L70: File Closure | M70: Closing the file and sending closure letter | N70: Commercial | O70: Multi/ Combination | P70: Auto, Property, GL, Specialty lines, WC | Q70: Mid Size | R70: Back Office | S70: L1 | T70: 1 | U70: 2 | V70: 3 | W70: Transaction Based | X70: USD | Y70: 0.65854268 | Z70: 3.49 | AA70: 0 | AB70: 0.083333333 | AC70: 4 | AD70: =SUM(Z70:AC70) -> 7.5733333 | AE70: =AC70/AD70 -> 0.52816901 | AF70: 7324 | AG70: NA | AH70: NA | AI70: 5.2760911 | AJ70: 1 | AK70: 0.97 | AL70: DPU – Defect Per Unit | AM70: NA | AN70: NA | AO70: NA | AP70: NA | AQ70: NA | AR70: NA | AS70: NA | AT70: NA | AU70: NA | AV70: NA | AW70: NA | AX70: Claim Adjuster | AY70: ClaimCenter | AZ70: Semi-Structured | BA70: 100 | BB70: ClaimCenter | BC70: Claim Adjuster | BD70: ClaimCenter/ACT/T360/Coventry
A71: CNA | B71: Top-10 US Commercial & Specialty Carrier | C71: US | D71: Noida, India | E71: =VLOOKUP(D71,'Dropdown List'!$F$26:$G$40,2,0) -> India | F71: Arpan Pandey, Varunjesh | G71: 6 | H71: Active | I71: Claims | J71: Evaluation | K71: Case Management of File | L71: File Reloads | M71: Team works on the Claims for which the payment history is closed in ACT. Once the claim gets reload then the payment history opens/active in ACT. | N71: Commercial | O71: Multi/ Combination | P71: Auto, Property, GL, Specialty lines, WC | Q71: Mid Size | R71: Back Office | S71: L1 | T71: 1 | U71: 2 | V71: 2 | W71: Transaction Based | X71: USD | Y71: 1.08676 | Z71: 0.26 | AA71: 0 | AB71: 0.083333333 | AC71: 1 | AD71: =SUM(Z71:AC71) -> 1.3433333 | AE71: =AC71/AD71 -> 0.74441687 | AF71: 527 | AG71: NA | AH71: NA | AI71: 5.2 | AJ71: 0.98 | AK71: 0.97 | AL71: DPU – Defect Per Unit | AM71: NA | AN71: NA | AO71: NA | AP71: NA | AQ71: NA | AR71: NA | AS71: NA | AT71: NA | AU71: NA | AV71: NA | AW71: NA | AX71: Claim Adjuster | AY71: Email | AZ71: Semi-Structured | BA71: 100 | BB71: Email | BC71: Claim Adjuster | BD71: ClaimCenter/ACT/MS Outlook
A72: CNA | B72: Top-10 US Commercial & Specialty Carrier | C72: US | D72: Noida, India | E72: =VLOOKUP(D72,'Dropdown List'!$F$26:$G$40,2,0) -> India | F72: Arpan Pandey, Varunjesh | G72: 6 | H72: Active | I72: Claims | J72: Investigation | K72: Claim Coding | L72: ICD 9/10 Coding | M72: This is the process of updating and entering the ICD Event Code and the ICD Diagnosis Code in ClaimCenter for Specialty, Auto General Liability and General Liability claims. | N72: Commercial | O72: Multi/ Combination | P72: Auto, Property, GL, Specialty lines, WC | Q72: Mid Size | R72: Back Office | S72: L2 | T72: 1 | U72: 2 | V72: 3 | W72: Transaction Based | X72: USD | Y72: 3.4890596 | Z72: 1.15 | AA72: 0 | AB72: 0.083333333 | AC72: 1 | AD72: =SUM(Z72:AC72) -> 2.2333333 | AE72: =AC72/AD72 -> 0.44776119 | AF72: 276 | AG72: NA | AH72: NA | AI72: 20 | AJ72: 1 | AK72: 0.97 | AL72: DPU – Defect Per Unit | AM72: NA | AN72: NA | AO72: NA | AP72: NA | AQ72: NA | AR72: NA | AS72: NA | AT72: NA | AU72: NA | AV72: NA | AW72: NA | AX72: Claim Adjuster | AY72: ClaimCenter | AZ72: Semi-Structured | BA72: 100 | BB72: ClaimCenter | BC72: Claim Adjuster | BD72: ClaimCenter
A73: CNA | B73: Top-10 US Commercial & Specialty Carrier | C73: US | D73: Noida, India | E73: =VLOOKUP(D73,'Dropdown List'!$F$26:$G$40,2,0) -> India | F73: Arpan Pandey, Varunjesh | G73: 6 | H73: Active | I73: Claims | J73: Initiation | K73: Initial Acknowledgement Letters | L73: Letters & Forms - 21 Day Follow Ups | M73: The activity 21 Days follow up on JFE/Wage Statement/Resource Card is created and assigned to the Letters and Forms – Service Operations queue. This process is a follow up to the initial Send Service Center Acknowledgement Letter and applicable documents activity to see if documents were received. | N73: Commercial | O73: Multi/ Combination | P73: Single LOB - WC | Q73: Mid Size | R73: Back Office | S73: L2 | T73: 1 | U73: 2 | V73: 3 | W73: Transaction Based | X73: USD | Y73: 0.9977439 | Z73: 0.2 | AA73: 0 | AB73: 0.083333333 | AC73: 0.5 | AD73: =SUM(Z73:AC73) -> 0.78333333 | AE73: =AC73/AD73 -> 0.63829787 | AF73: 617 | AG73: NA | AH73: NA | AI73: 5.67 | AJ73: 0.98 | AK73: 0.97 | AL73: DPU – Defect Per Unit | AM73: NA | AN73: NA | AO73: NA | AP73: NA | AQ73: NA | AR73: NA | AS73: NA | AT73: NA | AU73: NA | AV73: NA | AW73: NA | AX73: Claim Adjuster | AY73: ClaimCenter | AZ73: Semi-Structured | BA73: 100 | BB73: ClaimCenter | BC73: Claim Adjuster | BD73: ClaimCenter
A74: CNA | B74: Top-10 US Commercial & Specialty Carrier | C74: US | D74: Noida, India | E74: =VLOOKUP(D74,'Dropdown List'!$F$26:$G$40,2,0) -> India | F74: Arpan Pandey, Varunjesh | G74: 6 | H74: Active | I74: Claims | J74: Investigation | K74: Coverage Verification | L74: CA Independent Medical Review | M74: Team review the medical documents to ensure that documents belong to the policy holder (injured worker). | N74: Commercial | O74: Multi/ Combination | P74: Single LOB - WC | Q74: Mid Size | R74: Back Office | S74: L3 | T74: 1 | U74: 2 | V74: 3 | W74: Transaction Based | X74: USD | Y74: 2.2709174 | Z74: 0.24 | AA74: 0 | AB74: 0.083333333 | AC74: 0.5 | AD74: =SUM(Z74:AC74) -> 0.82333333 | AE74: =AC74/AD74 -> 0.60728745 | AF74: 40 | AG74: NA | AH74: NA | AI74: 20.680915 | AJ74: 0.97 | AK74: 0.97 | AL74: DPU – Defect Per Unit | AM74: NA | AN74: NA | AO74: NA | AP74: NA | AQ74: NA | AR74: NA | AS74: NA | AT74: NA | AU74: NA | AV74: NA | AW74: NA | AX74: Claim Adjuster | AY74: ClaimCenter | AZ74: Semi-Structured | BA74: 100 | BB74: ClaimCenter | BC74: Claim Adjuster | BD74: ClaimCenter
A75: CNA | B75: Top-10 US Commercial & Specialty Carrier | C75: US | D75: Noida, India | E75: =VLOOKUP(D75,'Dropdown List'!$F$26:$G$40,2,0) -> India | F75: Arpan Pandey, Varunjesh | G75: 6 | H75: Active | I75: Claims | J75: Investigation | K75: Coverage Verification | L75: CA Independent Medical Reviews Download | M75: Team review the medical documents to ensure that documents belong to the policy holder (injured worker). | N75: Commercial | O75: Multi/ Combination | P75: Single LOB - WC | Q75: Mid Size | R75: Back Office | S75: L3 | T75: 1 | U75: 2 | V75: 3 | W75: Transaction Based | X75: USD | Y75: 2.2709174 | Z75: 0.07 | AA75: 0 | AB75: 0.083333333 | AC75: 0.5 | AD75: =SUM(Z75:AC75) -> 0.65333333 | AE75: =AC75/AD75 -> 0.76530612 | AF75: 38 | AG75: NA | AH75: NA | AI75: 20.680915 | AJ75: 0.97 | AK75: 0.97 | AL75: DPU – Defect Per Unit | AM75: NA | AN75: NA | AO75: NA | AP75: NA | AQ75: NA | AR75: NA | AS75: NA | AT75: NA | AU75: NA | AV75: NA | AW75: NA | AX75: Claim Adjuster | AY75: Maximus | AZ75: Semi-Structured | BA75: 100 | BB75: Maximus | BC75: Claim Adjuster | BD75: Maximus/ClaimCenter
A76: CNA | B76: Top-10 US Commercial & Specialty Carrier | C76: US | D76: Noida, India | E76: =VLOOKUP(D76,'Dropdown List'!$F$26:$G$40,2,0) -> India | F76: Arpan Pandey, Varunjesh | G76: 6 | H76: Active | I76: Claims | J76: Initiation | K76: Data entry | L76: CM Admin Fee Prep (Excel Log) | M76: Transfer documents and notes from old claim to re-keyed claim. | N76: Personal | O76: Multi/ Combination | P76: Auto/Property | Q76: Mid Size | R76: Back Office | S76: L1 | T76: 1 | U76: 2 | V76: 2 | W76: Transaction Based | X76: USD | Y76: 0.43308703 | Z76: 0 | AA76: 0 | AB76: 0.083333333 | AC76: 0.1 | AD76: =SUM(Z76:AC76) -> 0.18333333 | AE76: =AC76/AD76 -> 0.54545455 | AF76: 4 | AG76: NA | AH76: NA | AI76: 3.9440608 | AJ76: 0.97 | AK76: 0.97 | AL76: DPU – Defect Per Unit | AM76: NA | AN76: NA | AO76: NA | AP76: NA | AQ76: NA | AR76: NA | AS76: NA | AT76: NA | AU76: NA | AV76: NA | AW76: NA | AX76: Claim Adjuster | AY76: Email | AZ76: Semi-Structured | BA76: 100 | BB76: Email | BC76: Claim Adjuster | BD76: MS Outlook
A77: CNA | B77: Top-10 US Commercial & Specialty Carrier | C77: US | D77: Noida, India | E77: =VLOOKUP(D77,'Dropdown List'!$F$26:$G$40,2,0) -> India | F77: Arpan Pandey, Varunjesh | G77: 6 | H77: Active | I77: Claims | J77: Subrogation and Compliance | K77: Salvage Settlement | L77: CM Admin Fee Entry (Pyramid Data Entry) | M77: Salvage deficit payments processed for invoices received via email from vendor. | N77: Personal | O77: Multi/ Combination | P77: Auto/Property | Q77: Mid Size | R77: Back Office | S77: L2 | T77: 1 | U77: 2 | V77: 3 | W77: Transaction Based | X77: USD | Y77: 0.43308703 | Z77: 0.13 | AA77: 0 | AB77: 0.083333333 | AC77: 0.9 | AD77: =SUM(Z77:AC77) -> 1.1133333 | AE77: =AC77/AD77 -> 0.80838323 | AF77: 422 | AG77: NA | AH77: NA | AI77: 3.9440608 | AJ77: 0.97 | AK77: 0.97 | AL77: DPU – Defect Per Unit | AM77: NA | AN77: NA | AO77: NA | AP77: NA | AQ77: NA | AR77: NA | AS77: NA | AT77: NA | AU77: NA | AV77: NA | AW77: NA | AX77: Claim Adjuster | AY77: ClaimCenter | AZ77: Semi-Structured | BA77: 100 | BB77: ClaimCenter | BC77: Claim Adjuster | BD77: ClaimCenter
A78: CNA | B78: Top-10 US Commercial & Specialty Carrier | C78: US | D78: Noida, India | E78: =VLOOKUP(D78,'Dropdown List'!$F$26:$G$40,2,0) -> India | F78: Arpan Pandey, Varunjesh | G78: 6 | H78: Active | I78: Claims | J78: Subrogation and Compliance | K78: Initiate Recovery Collection & processing | L78: Impairment | M78: Subro recovery payments to be posted and daily check deposits to be processed. | N78: Personal | O78: Multi/ Combination | P78: Auto/Property | Q78: Mid Size | R78: Back Office | S78: L2 | T78: 1 | U78: 1 | V78: 2 | W78: Transaction Based | X78: USD | Y78: 0.91206818 | Z78: 0.05 | AA78: 0 | AB78: 0.083333333 | AC78: 0.5 | AD78: =SUM(Z78:AC78) -> 0.63333333 | AE78: =AC78/AD78 -> 0.78947368 | AF78: 42 | AG78: NA | AH78: NA | AI78: 4 | AJ78: 1 | AK78: NA | AL78: DPU – Defect Per Unit | AM78: NA | AN78: NA | AO78: NA | AP78: NA | AQ78: NA | AR78: NA | AS78: NA | AT78: NA | AU78: NA | AV78: NA | AW78: NA | AX78: Claim Adjuster | AY78: ECE | AZ78: Semi-Structured | BA78: 100 | BB78: Email | BC78: Claim Adjuster | BD78: ECE/MS Outlook
A79: CNA | B79: Top-10 US Commercial & Specialty Carrier | C79: US | D79: Noida, India | E79: =VLOOKUP(D79,'Dropdown List'!$F$26:$G$40,2,0) -> India | F79: Arpan Pandey, Varunjesh | G79: 6 | H79: Active | I79: Claims | J79: Initiation | K79: Initial Acknowledgement Letters | L79: Acknowledgement Letters – Workers & Non-Worker Compensation, Claim Reporting | M79: Team sends the acknowledgement letters/documents to the required parties that their claim has been received and share the adjuster details with main contact/claimant | N79: Commercial | O79: Multi/ Combination | P79: Auto, Property, GL, Specialty lines, WC | Q79: Mid Size | R79: Back Office | S79: L1 | T79: 1 | U79: 2 | V79: 3 | W79: Transaction Based | X79: USD | Y79: 1.9127252 | Z79: 6.51 | AA79: 0.6 | AB79: 0.083333333 | AC79: 7 | AD79: =SUM(Z79:AC79) -> 14.193333 | AE79: =AC79/AD79 -> 0.49318929 | AF79: 8236 | AG79: NA | AH79: NA | AI79: 10.426132 | AJ79: 1 | AK79: 0.97 | AL79: DPU – Defect Per Unit | AM79: NA | AN79: NA | AO79: NA | AP79: NA | AQ79: BOT | AR79: 4 BOTs are placed in AckLetter for end to end processing of NWC claims (Non SCHI) | AS79: By implementing BOT there was 3 FTE deduction | AT79: NA | AU79: NA | AV79: NA | AW79: NA | AX79: Claim Adjuster | AY79: ClaimCenter | AZ79: Semi-Structured | BA79: 100 | BB79: ClaimCenter | BC79: Claim Adjuster | BD79: ClaimCenter
A80: CNA | B80: Top-10 US Commercial & Specialty Carrier | C80: US | D80: Pune, India | E80: =VLOOKUP(D80,'Dropdown List'!$F$26:$G$40,2,0) -> India | F80: Arpan Pandey, Varunjesh | G80: 6 | H80: Active | I80: Claims | J80: Initiation | K80: Claim Setup and assignment | L80: * Commercial Auto (includes SnapSheet Full Time Employee) * Commercial Property * Commercial General Liability * Commercial Workers Compensation | M80: All high severity claims to set up and assigned to adjustor on priority | N80: Commercial | O80: Multi/ Combination | P80: Auto/Property/GL/WC | Q80: Mid Size & Large | R80: Back Office | S80: L3 | T80: 1 | U80: 4 | V80: 4 | W80: Transaction Based | X80: USD | Y80: 6.845607 | Z80: 1 | AA80: 0.029815146 | AB80: 0.029815146 | AC80: 1.222421 | AD80: =SUM(Z80:AC80) -> 2.2820513 | AE80: =AC80/AD80 -> 0.53566762 | AF80: 45 | AG80: NA | AH80: NA | AI80: 35.03 | AJ80: 0.95 | AK80: 0.97 | AL80: DPU – Defect Per Unit | AM80: NA | AN80: NA | AO80: NA | AP80: NA | AQ80: NA | AR80: NA | AS80: NA | AT80: NA | AU80: NA | AV80: NA | AW80: NA | AX80: Insureds / Agents | AY80: Emails | AZ80: Semi-Structured | BA80: 100 | BB80: Claim number in Application | BC80: Insureds / Agents | BD80: Claim center, ECE, MS Office, PDF, ECF, EPC
A81: CNA | B81: Top-10 US Commercial & Specialty Carrier | C81: US | D81: Pune, India | E81: =VLOOKUP(D81,'Dropdown List'!$F$26:$G$40,2,0) -> India | F81: Arpan Pandey, Varunjesh | G81: 6 | H81: Active | I81: Claims | J81: Initiation | K81: Indexing | L81: Commercial Work Distribution & Sorting | M81: Review loss information and claims document to assess LOB and transfer claim to respective queue | N81: Commercial | O81: Multi/ Combination | P81: Auto/Property/GL/WC/Specialty HP | Q81: Mid Size & Large | R81: Back Office | S81: L2 | T81: 1 | U81: 2 | V81: 2 | W81: Transaction Based | X81: USD | Y81: 1.4447541 | Z81: 1 | AA81: 0.029815146 | AB81: 0.029815146 | AC81: 1.222421 | AD81: =SUM(Z81:AC81) -> 2.2820513 | AE81: =AC81/AD81 -> 0.53566762 | AF81: 5300 | AG81: NA | AH81: NA | AI81: 4 | AJ81: 1 | AK81: 0.97 | AL81: DPU – Defect Per Unit | AM81: NA | AN81: NA | AO81: NA | AP81: NA | AQ81: NA | AR81: NA | AS81: NA | AT81: NA | AU81: NA | AV81: NA | AW81: NA | AX81: Insureds / Agents | AY81: Emails | AZ81: Semi-Structured | BA81: 100 | BB81: Instructions in Application | BC81: Insureds / Agents | BD81: Claim center, ECE, MS Office, PDF, ECF, EPC
A82: CNA | B82: Top-10 US Commercial & Specialty Carrier | C82: US | D82: Pune, India | E82: =VLOOKUP(D82,'Dropdown List'!$F$26:$G$40,2,0) -> India | F82: Arpan Pandey, Varunjesh | G82: 6 | H82: Active | I82: Claims | J82: Initiation | K82: Claim Setup and assignment | L82: Specialty - HealthPro | M82: Based on the loss information and documents set up a claim and assigned to adjuster | N82: Commercial | O82: Multi/ Combination | P82: Auto/Property/GL/WC/Specialty HP/DBA/TPA Oversight/Crawford/WC Tier 3 | Q82: Mid Size & Large | R82: Back Office | S82: L3 | T82: 1 | U82: 4 | V82: 4 | W82: Transaction Based | X82: USD | Y82: 13.748152 | Z82: 0 | AA82: 0.029815146 | AB82: 0.029815146 | AC82: 1.222421 | AD82: =SUM(Z82:AC82) -> 1.2820513 | AE82: =AC82/AD82 -> 0.95348837 | AF82: 7700 | AG82: NA | AH82: NA | AI82: 44.33 | AJ82: 0.95 | AK82: 0.97 | AL82: DPU – Defect Per Unit | AM82: NA | AN82: NA | AO82: NA | AP82: NA | AQ82: NA | AR82: NA | AS82: NA | AT82: NA | AU82: NA | AV82: NA | AW82: NA | AX82: Insureds / Agents | AY82: Emails | AZ82: Semi-Structured | BA82: 100 | BB82: Claim number in Application | BC82: Insureds / Agents | BD82: Claim center, ECE, MS Office, PDF, ECF, EPC
A83: CNA | B83: Top-10 US Commercial & Specialty Carrier | C83: US | D83: Pune, India | E83: =VLOOKUP(D83,'Dropdown List'!$F$26:$G$40,2,0) -> India | F83: Arpan Pandey, Varunjesh | G83: 6 | H83: Active | I83: Claims | J83: Initiation | K83: Indexing | L83: Risktech and Specialty Policy Attachment | M83: Request and attach policy document to the claim | N83: Commercial | O83: Multi/ Combination | P83: Auto/Property/GL/WC/Specialty HP/DBA/TPA Oversight/Crawford/WC Tier 3 | Q83: Mid Size & Large | R83: Back Office | S83: L2 | T83: 1 | U83: 1 | V83: 2 | W83: Transaction Based | X83: USD | Y83: 4.2259057 | Z83: 0.5 | AA83: 0.029815146 | AB83: 0.029815146 | AC83: 1.222421 | AD83: =SUM(Z83:AC83) -> 1.7820513 | AE83: =AC83/AD83 -> 0.68596286 | AF83: 970 | AG83: NA | AH83: NA | AI83: 11.7 | AJ83: 1 | AK83: 0.97 | AL83: DPU – Defect Per Unit | AM83: NA | AN83: NA | AO83: NA | AP83: NA | AQ83: NA | AR83: NA | AS83: NA | AT83: NA | AU83: NA | AV83: NA | AW83: NA | AX83: Claim Adjuster | AY83: Emails | AZ83: Semi-Structured | BA83: 100 | BB83: Instructions in Application | BC83: Claim Adjuster | BD83: Claim Center, ECE, MS Office
A84: CNA | B84: Top-10 US Commercial & Specialty Carrier | C84: US | D84: Pune, India | E84: =VLOOKUP(D84,'Dropdown List'!$F$26:$G$40,2,0) -> India | F84: Arpan Pandey, Varunjesh | G84: 6 | H84: Active | I84: Claims | J84: Evaluation | K84: Packet Prep, chronology summary | L84: MOX Claim Set up | M84: Audit all the fields and create medical summary for claim professionals | N84: Commercial | O84: Multi/ Combination | P84: WC | Q84: Mid Size & Large | R84: Back Office | S84: L3 | T84: 1 | U84: 4 | V84: 4 | W84: Transaction Based | X84: USD | Y84: 3.1836896 | Z84: 2 | AA84: 0.029815146 | AB84: 0.029815146 | AC84: 1.222421 | AD84: =SUM(Z84:AC84) -> 3.2820513 | AE84: =AC84/AD84 -> 0.3724564 | AF84: 1100 | AG84: NA | AH84: NA | AI84: 15.22 | AJ84: 1 | AK84: 0.97 | AL84: DPU – Defect Per Unit | AM84: NA | AN84: NA | AO84: NA | AP84: NA | AQ84: NA | AR84: NA | AS84: NA | AT84: NA | AU84: NA | AV84: NA | AW84: NA | AX84: Claim Adjuster | AY84: Claim Center Activities | AZ84: Structured | BA84: 100 | BB84: Instructions in Application | BC84: Claim Adjuster | BD84: Claim center, ECE, MS Office, PDF, ECF, EPC
A85: CNA | B85: Top-10 US Commercial & Specialty Carrier | C85: US | D85: Noida, India | E85: =VLOOKUP(D85,'Dropdown List'!$F$26:$G$40,2,0) -> India | F85: Arpan Pandey, Varunjesh | G85: 6 | H85: Active | I85: Claims | J85: Litigation and Resolution | K85: Bill Payment (Medical Legal, Non Medical, Vendor) | L85: Payment Transfer | M85: purpose of this task is to assist claim field operations with the processes of making a payment transfer through claim center | N85: Commercial | O85: Multi/ Combination | P85: Auto, Property, GL, Specialty lines, WC | Q85: Mid Size | R85: Back Office | S85: L2 | T85: 1 | U85: 3 | V85: 3 | W85: Transaction Based | X85: USD | Y85: 0.83822906 | Z85: 1 | AA85: 0.029815146 | AB85: 0.029815146 | AC85: 1.222421 | AD85: =SUM(Z85:AC85) -> 2.2820513 | AE85: =AC85/AD85 -> 0.53566762 | AF85: 800 | AG85: NA | AH85: NA | AI85: 5.55 | AJ85: 0.98 | AK85: 0.98 | AL85: DPO – Defect Per Opportunity | AM85: NA | AN85: NA | AO85: NA | AP85: NA | AQ85: NA | AR85: NA | AS85: NA | AT85: NA | AU85: NA | AV85: NA | AW85: NA | AY85: Instructions in Application | AZ85: Structured | BA85: 100 | BB85: Multiple | BD85: Claim Center & ACT
A86: CNA | B86: Top-10 US Commercial & Specialty Carrier | C86: US | D86: Noida, India | E86: =VLOOKUP(D86,'Dropdown List'!$F$26:$G$40,2,0) -> India | F86: Arpan Pandey, Varunjesh | G86: 6 | H86: Active | I86: Claims | J86: Litigation and Resolution | K86: Bill Payment (Medical Legal, Non Medical, Vendor) | L86: Legal Bill Payment | M86: In this task we make payments to Law firms, Vendors & Insureds for any legal expense/cost involved | N86: Commercial | O86: Multi/ Combination | P86: Auto, Property, GL, Specialty lines, WC | Q86: Mid Size | R86: Back Office | S86: L1 | T86: 1 | U86: 4 | V86: 4 | W86: Transaction Based | X86: USD | Y86: 1.033273 | Z86: 7 | AA86: 0.029815146 | AB86: 0.029815146 | AC86: 1.222421 | AD86: =SUM(Z86:AC86) -> 8.2820513 | AE86: =AC86/AD86 -> 0.14759882 | AF86: 9000 | AG86: NA | AH86: NA | AI86: 5.0207629 | AJ86: 0.98 | AK86: 0.98 | AL86: DPO – Defect Per Opportunity | AM86: NA | AN86: NA | AO86: NA | AP86: NA | AQ86: NA | AR86: NA | AS86: NA | AT86: NA | AU86: NA | AV86: NA | AW86: NA | AY86: Multiple | AZ86: Structured | BA86: 100 | BB86: Multiple | BD86: Claim Center, Mobius, TeamConnect, T360 & ACT
A87: CNA | B87: Top-10 US Commercial & Specialty Carrier | C87: US | D87: Noida, India | E87: =VLOOKUP(D87,'Dropdown List'!$F$26:$G$40,2,0) -> India | F87: Arpan Pandey, Varunjesh | G87: 6 | H87: Active | I87: Claims | J87: Initiation | K87: Claim Setup and assignment | L87: Reassign File Handler | M87: Purpose of this task is to assign the claims/matters to the correct claim professional | N87: Commercial | O87: Multi/ Combination | P87: Auto, Property, GL, Specialty lines, WC | Q87: Mid Size | R87: Back Office | S87: L2 | T87: 1 | U87: 3 | V87: 3 | W87: Transaction Based | X87: USD | Y87: 0.35 | Z87: 4 | AA87: 0.029815146 | AB87: 0.029815146 | AC87: 1.222421 | AD87: =SUM(Z87:AC87) -> 5.2820513 | AE87: =AC87/AD87 -> 0.23142922 | AF87: 900 | AG87: NA | AH87: NA | AI87: 1.6 | AJ87: 0.98 | AK87: 0.98 | AL87: DPO – Defect Per Opportunity | AM87: NA | AN87: NA | AO87: NA | AP87: NA | AQ87: NA | AR87: NA | AS87: NA | AT87: NA | AU87: NA | AV87: NA | AW87: NA | AY87: ClaimCenter | AZ87: Structured | BA87: 100 | BB87: ClaimCenter | BD87: Claim Center, TeamConnect & T360
A88: CNA | B88: Top-10 US Commercial & Specialty Carrier | C88: US | D88: Noida, India | E88: =VLOOKUP(D88,'Dropdown List'!$F$26:$G$40,2,0) -> India | F88: Arpan Pandey, Varunjesh | G88: 6 | H88: Active | I88: Claims | J88: Litigation and Resolution | K88: Bill Payment (Medical Legal, Non Medical, Vendor) | L88: Request for Reconsideration (RFR) Payments | M88: In this task when a law firm disputes the amount that was paid on an original invoice, they would submit a letter to RFR concerning the adjusted amount, a response letter is sent to the firm with a blind copy to the RFR mailbox for claims operations to process the payment | N88: Commercial | O88: Multi/ Combination | P88: Auto, Property, GL, Specialty lines, WC | Q88: Mid Size | R88: Back Office | S88: L2 | T88: 1 | U88: 4 | V88: 4 | W88: Transaction Based | X88: USD | Y88: 1.4266063 | Z88: 2 | AA88: 0.029815146 | AB88: 0.029815146 | AC88: 1.222421 | AD88: =SUM(Z88:AC88) -> 3.2820513 | AE88: =AC88/AD88 -> 0.3724564 | AF88: 500 | AG88: NA | AH88: NA | AI88: 6.07 | AJ88: 0.98 | AK88: 0.98 | AL88: DPO – Defect Per Opportunity | AM88: NA | AN88: NA | AO88: NA | AP88: NA | AQ88: NA | AR88: NA | AS88: NA | AT88: NA | AU88: NA | AV88: NA | AW88: NA | AY88: Emails | AZ88: Structured | BA88: 100 | BB88: Folder | BD88: Claim Center, TeamConnect, T360 & ACT
A89: CNA | B89: Top-10 US Commercial & Specialty Carrier | C89: US | D89: Noida, India | E89: =VLOOKUP(D89,'Dropdown List'!$F$26:$G$40,2,0) -> India | F89: Arpan Pandey, Varunjesh | G89: 6 | H89: Active | I89: Claims | J89: Litigation and Resolution | K89: Bill Payment (Medical Legal, Non Medical, Vendor) | L89: Medical Bills Pending List | M89: In this task we receive request to pay all the bills related to Medical on claim center | N89: Commercial | O89: Multi/ Combination | P89: Auto, Property, GL, Specialty lines, WC | Q89: Mid Size | R89: Back Office | S89: L2 | T89: 1 | U89: 4 | V89: 4 | W89: Transaction Based | X89: USD | Y89: 1.9436602 | Z89: 5 | AA89: 0.029815146 | AB89: 0.029815146 | AC89: 1.222421 | AD89: =SUM(Z89:AC89) -> 6.2820513 | AE89: =AC89/AD89 -> 0.19458946 | AF89: 4000 | AG89: NA | AH89: NA | AI89: 12.4 | AJ89: 0.98 | AK89: 0.98 | AL89: DPO – Defect Per Opportunity | AM89: NA | AN89: NA | AO89: NA | AP89: NA | AQ89: NA | AR89: NA | AS89: NA | AT89: NA | AU89: NA | AV89: NA | AW89: NA | AY89: ClaimCenter | AZ89: Structured | BA89: 100 | BB89: ClaimCenter | BD89: Claim Center,Conduent & ACT
A90: CNA | B90: Top-10 US Commercial & Specialty Carrier | C90: US | D90: Noida, India | E90: =VLOOKUP(D90,'Dropdown List'!$F$26:$G$40,2,0) -> India | F90: Arpan Pandey, Varunjesh | G90: 6 | H90: Active | I90: Claims | J90: Litigation and Resolution | K90: Bill Payment (Medical Legal, Non Medical, Vendor) | L90: Vehicle Registration Monthly Inquiry | M90: This process describes the steps to review the vehicle registration monthly inquiry report and to identify the invoice and amounts for payment | N90: Commercial | O90: Multi/ Combination | P90: Auto, Property, GL, Specialty lines, WC | Q90: Mid Size | R90: Back Office | S90: L4 | T90: NA | U90: NA | V90: NA | W90: Transaction Based | X90: USD | Y90: 1.1076664 | Z90: 1 | AA90: 0.029815146 | AB90: 0.029815146 | AC90: 1.222421 | AD90: =SUM(Z90:AC90) -> 2.2820513 | AE90: =AC90/AD90 -> 0.53566762 | AF90: 21 | AG90: NA | AH90: NA | AI90: 4.09 | AJ90: 0.98 | AK90: 0.98 | AL90: DPO – Defect Per Opportunity | AM90: NA | AN90: NA | AO90: NA | AP90: NA | AQ90: NA | AR90: NA | AS90: NA | AT90: NA | AU90: NA | AV90: NA | AW90: NA | AY90: Emails | AZ90: Structured | BA90: 100 | BB90: Emails | BD90: Claim Center & ACT
A91: CNA | B91: Top-10 US Commercial & Specialty Carrier | C91: US | D91: Noida, India | E91: =VLOOKUP(D91,'Dropdown List'!$F$26:$G$40,2,0) -> India | F91: Arpan Pandey, Varunjesh | G91: 6 | H91: Active | I91: Claims | J91: Subrogation and Compliance | K91: Salvage Settlement | L91: Close Recovery Indicator | M91: In this task we need to close recovery portion in claimcenter and in ACT post recovery | N91: Commercial | O91: Multi/ Combination | P91: Auto, Property, GL, Specialty lines, WC | Q91: Mid Size | R91: Back Office | S91: L2 | T91: 1 | U91: 2 | V91: 3 | W91: Transaction Based | X91: USD | Y91: 0.20710196 | Z91: 2 | AA91: 0.029815146 | AB91: 0.029815146 | AC91: 1.222421 | AD91: =SUM(Z91:AC91) -> 3.2820513 | AE91: =AC91/AD91 -> 0.3724564 | AF91: 1250 | AG91: NA | AH91: NA | AI91: 1.08 | AJ91: 0.97 | AK91: 0.97 | AL91: DPO – Defect Per Opportunity | AM91: NA | AN91: NA | AO91: NA | AP91: NA | AQ91: NA | AR91: NA | AS91: NA | AT91: NA | AU91: NA | AV91: NA | AW91: NA | AY91: ClaimCenter | AZ91: Structured | BA91: 100 | BB91: ClaimCenter | BD91: Claim Center & ACT
A92: CNA | B92: Top-10 US Commercial & Specialty Carrier | C92: US | D92: Noida, India | E92: =VLOOKUP(D92,'Dropdown List'!$F$26:$G$40,2,0) -> India | F92: Arpan Pandey, Varunjesh | G92: 6 | H92: Active | I92: Claims | J92: Litigation and Resolution | K92: Non Medical Bill Review & Approval | L92: Wage Calculation | M92: In this task team uses the wage calculator is used to eliminate the manual steps involved in validation and sanity checks | N92: Commercial | O92: Multi/ Combination | P92: Auto, Property, GL, Specialty lines, WC | Q92: Mid Size | R92: Back Office | S92: L3 | T92: 1 | U92: 4 | V92: 4 | W92: Transaction Based | X92: USD | Y92: 6.4886324 | Z92: 1 | AA92: 0.029815146 | AB92: 0.029815146 | AC92: 1.222421 | AD92: =SUM(Z92:AC92) -> 2.2820513 | AE92: =AC92/AD92 -> 0.53566762 | AF92: 430 | AG92: NA | AH92: NA | AI92: 30.02 | AJ92: 0.97 | AK92: 0.97 | AL92: DPO – Defect Per Opportunity | AM92: NA | AN92: NA | AO92: NA | AP92: NA | AQ92: NA | AR92: NA | AS92: NA | AT92: NA | AU92: NA | AV92: NA | AW92: NA | AY92: ClaimCenter | AZ92: Structured | BA92: 100 | BB92: ClaimCenter | BD92: Claim Center & ACT
A93: CNA | B93: Top-10 US Commercial & Specialty Carrier | C93: US | D93: Noida, India | E93: =VLOOKUP(D93,'Dropdown List'!$F$26:$G$40,2,0) -> India | F93: Arpan Pandey, Varunjesh | G93: 6 | H93: Active | I93: Claims | J93: Investigation | K93: Coverage Verification | L93: Deductible Tracking | M93: In this task team reviews the DT every 30 days until it's exausted | N93: Commercial | O93: Multi/ Combination | P93: Auto, Property, GL, Specialty lines, WC | Q93: Mid Size | R93: Back Office | S93: L2 | T93: 1 | U93: 2 | V93: 3 | W93: Transaction Based | X93: USD | Y93: 2.54 | Z93: 3 | AA93: 0.029815146 | AB93: 0.029815146 | AC93: 1.222421 | AD93: =SUM(Z93:AC93) -> 4.2820513 | AE93: =AC93/AD93 -> 0.28547556 | AF93: 2500 | AG93: NA | AH93: NA | AI93: 11.25 | AJ93: 0.97 | AK93: 0.97 | AL93: DPO – Defect Per Opportunity | AM93: NA | AN93: NA | AO93: NA | AP93: NA | AQ93: NA | AR93: NA | AS93: NA | AT93: NA | AU93: NA | AV93: NA | AW93: NA | AY93: ClaimCenter | AZ93: Unstructured | BA93: 100 | BB93: ClaimCenter | BD93: Claim Center, TeamConnect, T360 & ACT
A94: CNA | B94: Top-10 US Commercial & Specialty Carrier | C94: US | D94: Noida, India | E94: =VLOOKUP(D94,'Dropdown List'!$F$26:$G$40,2,0) -> India | F94: Arpan Pandey, Varunjesh | G94: 6 | H94: Active | I94: Claims | J94: Subrogation and Compliance | K94: Initiate Recovery Collection & processing | L94: Second Injury Fund | M94: Second Injury Fund is the dedicated fund for the purpose of reimbursing compensation payment made by th emmployers, insures or CP to their employees | N94: Commercial | O94: Multi/ Combination | P94: Auto, Property, GL, Specialty lines, WC | Q94: Mid Size | R94: Back Office | S94: L2 | T94: 1 | U94: 4 | V94: 4 | W94: Transaction Based | X94: USD | Y94: 15.834927 | Z94: 2 | AA94: 0.029815146 | AB94: 0.029815146 | AC94: 1.222421 | AD94: =SUM(Z94:AC94) -> 3.2820513 | AE94: =AC94/AD94 -> 0.3724564 | AF94: 250 | AG94: NA | AH94: NA | AI94: 72.27 | AJ94: 0.97 | AK94: 0.97 | AL94: DPO – Defect Per Opportunity | AM94: NA | AN94: NA | AO94: NA | AP94: NA | AQ94: NA | AR94: NA | AS94: NA | AT94: NA | AU94: NA | AV94: NA | AW94: NA | AY94: ClaimCenter | AZ94: Structured | BA94: 100 | BB94: ClaimCenter | BD94: Claim Center & ACT
A95: CNA | B95: Top-10 US Commercial & Specialty Carrier | C95: US | D95: Noida, India | E95: =VLOOKUP(D95,'Dropdown List'!$F$26:$G$40,2,0) -> India | F95: Arpan Pandey, Varunjesh | G95: 6 | H95: Active | I95: Claims | J95: Litigation and Resolution | K95: Duplicate Payment | L95: Duplicate Payment | M95: Identify Duplicate payments and initate recovery for the payments | N95: Commercial | O95: Multi/ Combination | P95: Auto, Property, GL, Specialty lines, WC | Q95: Mid Size | R95: Back Office | S95: L1 | T95: 1 | U95: 3 | V95: 3 | W95: Transaction Based | X95: USD | Y95: 0.65228617 | Z95: 1 | AA95: 0.029815146 | AB95: 0.029815146 | AC95: 1.222421 | AD95: =SUM(Z95:AC95) -> 2.2820513 | AE95: =AC95/AD95 -> 0.53566762 | AF95: 724 | AG95: NA | AH95: Nov-Dec | AI95: 3.47 | AJ95: 0.98 | AK95: 0.98 | AL95: DPU – Defect Per Unit | AM95: NA | AN95: NA | AO95: NA | AP95: NA | AQ95: NA | AR95: NA | AS95: NA | AT95: NA | AU95: NA | AV95: NA | AW95: NA | AX95: Claim Adjuster | AY95: Instructions in Application | AZ95: Semi-Structured | BA95: 100 | BB95: Multiple | BC95: Claim Adjuster | BD95: Claim Center, ACT, MS outlook, CRS, Teamconnect
A96: CNA | B96: Top-10 US Commercial & Specialty Carrier | C96: US | D96: Noida, India | E96: =VLOOKUP(D96,'Dropdown List'!$F$26:$G$40,2,0) -> India | F96: Arpan Pandey, Varunjesh | G96: 6 | H96: Active | I96: Claims | J96: Litigation and Resolution | K96: Stop Payment | L96: Stop Payment | M96: Stop incorrect payments | N96: Commercial | O96: Multi/ Combination | P96: Auto, Property, GL, Specialty lines, WC | Q96: Mid Size | R96: Back Office | S96: L2 | T96: 1 | U96: 3 | V96: 3 | W96: Transaction Based | X96: USD | Y96: 0.30012783 | Z96: 1 | AA96: 0.029815146 | AB96: 0.029815146 | AC96: 1.222421 | AD96: =SUM(Z96:AC96) -> 2.2820513 | AE96: =AC96/AD96 -> 0.53566762 | AF96: 421 | AG96: NA | AH96: Nov-Dec | AI96: 1.41 | AJ96: 0.98 | AK96: 0.98 | AL96: DPU – Defect Per Unit | AM96: NA | AN96: NA | AO96: NA | AP96: NA | AQ96: NA | AR96: NA | AS96: NA | AT96: NA | AU96: NA | AV96: NA | AW96: NA | AX96: Claim Adjuster | AY96: Instructions in Application | AZ96: Semi-Structured | BA96: 100 | BB96: Multiple | BC96: Claim Adjuster | BD96: Claim Center, ACT, MS outlook,
A97: CNA | B97: Top-10 US Commercial & Specialty Carrier | C97: US | D97: Noida, India | E97: =VLOOKUP(D97,'Dropdown List'!$F$26:$G$40,2,0) -> India | F97: Arpan Pandey, Varunjesh | G97: 6 | H97: Active | I97: Claims | J97: Litigation and Resolution | K97: Bill Payment (Medical Legal, Non Medical, Vendor) | L97: Manager Entry in ACT AZ and Check Release | M97: Add AZ authority and release payment checks | N97: Commercial | O97: Multi/ Combination | P97: Auto, Property, GL, Specialty lines, WC | Q97: Mid Size | R97: Back Office | S97: L2 | T97: 1 | U97: 3 | V97: 3 | W97: Transaction Based | X97: USD | Y97: 0.58512649 | Z97: 2 | AA97: 0.029815146 | AB97: 0.029815146 | AC97: 1.222421 | AD97: =SUM(Z97:AC97) -> 3.2820513 | AE97: =AC97/AD97 -> 0.3724564 | AF97: 6883 | AG97: NA | AH97: Nov-Dec | AI97: 2.59 | AJ97: 0.98 | AK97: 0.98 | AL97: DPU – Defect Per Unit | AM97: NA | AN97: NA | AO97: NA | AP97: NA | AQ97: NA | AR97: NA | AS97: NA | AT97: NA | AU97: NA | AV97: NA | AW97: NA | AX97: Claim Adjuster | AY97: Instructions in Application | AZ97: Semi-Structured | BA97: 100 | BB97: Multiple | BC97: Claim Adjuster | BD97: Claim Center, ACT, MS outlook,CRT DocumentMobius
A98: CNA | B98: Top-10 US Commercial & Specialty Carrier | C98: US | D98: Noida, India | E98: =VLOOKUP(D98,'Dropdown List'!$F$26:$G$40,2,0) -> India | F98: Arpan Pandey, Varunjesh | G98: 6 | H98: Active | I98: Claims | J98: Litigation and Resolution | K98: Bill Payment (Medical Legal, Non Medical, Vendor) | L98: Bill Payment - Non Workers Compensation, Bulk, Workers Compensation, Central Bill Pay Processing Unit | M98: Paid Vendor invoices, Insured, Claimants, Injured workers | N98: Commercial | O98: Multi/ Combination | P98: Auto, Property, GL, Specialty lines, WC | Q98: Mid Size | R98: Back Office | S98: L2 | T98: 1 | U98: 3 | V98: 3 | W98: Transaction Based | X98: USD | Y98: 1.3047728 | Z98: 7.5 | AA98: 0.029815146 | AB98: 0.029815146 | AC98: 1.222421 | AD98: =SUM(Z98:AC98) -> 8.7820513 | AE98: =AC98/AD98 -> 0.13919538 | AF98: 11295 | AG98: NA | AH98: Nov-Dec | AI98: 6.9499388 | AJ98: 0.98 | AK98: 0.98 | AL98: DPU – Defect Per Unit | AM98: NA | AN98: NA | AO98: NA | AP98: NA | AQ98: NA | AR98: NA | AS98: NA | AT98: NA | AU98: NA | AV98: NA | AW98: NA | AX98: Claim Adjuster | AY98: Multiple | AZ98: Semi-Structured | BA98: 100 | BB98: Multiple | BC98: Claim Adjuster | BD98: Claim Center, ACT, MS outlook,
A99: CNA | B99: Top-10 US Commercial & Specialty Carrier | C99: US | D99: Noida, India | E99: =VLOOKUP(D99,'Dropdown List'!$F$26:$G$40,2,0) -> India | F99: Arpan Pandey, Varunjesh | G99: 6 | H99: Active | I99: Claims | J99: Litigation and Resolution | K99: Bill Payment (Medical Legal, Non Medical, Vendor) | L99: Bill Payment - Wilber Invoices, PIP Bills, Mitchell Bills, Glass (Geber) Invoices | M99: Paid vendor invoices | N99: Commercial | O99: Multi/ Combination | P99: Auto, Property, GL, Specialty lines, WC | Q99: Mid Size | R99: Back Office | S99: L4 | T99: 1 | U99: 3 | V99: 3 | W99: Transaction Based | X99: USD | Y99: 1.65 | Z99: 1.5 | AA99: 0.029815146 | AB99: 0.029815146 | AC99: 1.222421 | AD99: =SUM(Z99:AC99) -> 2.7820513 | AE99: =AC99/AD99 -> 0.43939556 | AF99: 577 | AG99: NA | AH99: Nov-Dec | AI99: 8 | AJ99: 0.98 | AK99: 0.98 | AL99: DPU – Defect Per Unit | AM99: NA | AN99: NA | AO99: NA | AP99: NA | AQ99: NA | AR99: NA | AS99: NA | AT99: NA | AU99: NA | AV99: NA | AW99: NA | AX99: Claim Adjuster | AY99: Multiple | AZ99: Semi-Structured | BA99: 100 | BB99: Multiple | BC99: Claim Adjuster | BD99: Claim Center, ACT, MS outlook, Michell Decision Point
A100: CNA | B100: Top-10 US Commercial & Specialty Carrier | C100: US | D100: Noida, India | E100: =VLOOKUP(D100,'Dropdown List'!$F$26:$G$40,2,0) -> India | F100: Arpan Pandey, Varunjesh | G100: 6 | H100: Active | I100: Claims | J100: Subrogation and Compliance | K100: Initiate Recovery Collection & processing | L100: Recovery Vendor Bills Arbitration | M100: Paid Recovery arbitration bills to vendor | N100: Commercial | O100: Multi/ Combination | P100: Auto, Property, GL, Specialty lines, WC | Q100: Mid Size | R100: Back Office | S100: L2 | T100: 1 | U100: 3 | V100: 3 | W100: Transaction Based | X100: USD | Y100: 1.4393692 | Z100: 0.25 | AA100: 0.029815146 | AB100: 0.029815146 | AC100: 1.222421 | AD100: =SUM(Z100:AC100) -> 1.5320513 | AE100: =AC100/AD100 -> 0.79789822 | AF100: 138 | AG100: NA | AH100: Nov-Dec | AI100: 5.5 | AJ100: 0.98 | AK100: 0.98 | AL100: DPU – Defect Per Unit | AM100: NA | AN100: NA | AO100: NA | AP100: NA | AQ100: NA | AR100: NA | AS100: NA | AT100: NA | AU100: NA | AV100: NA | AW100: NA | AX100: Claim Adjuster | AY100: Multiple | AZ100: Semi-Structured | BA100: 100 | BB100: Multiple | BC100: Claim Adjuster | BD100: Claim Center, ACT, MS outlook,
A101: CNA | B101: Top-10 US Commercial & Specialty Carrier | C101: US | D101: Noida, India | E101: =VLOOKUP(D101,'Dropdown List'!$F$26:$G$40,2,0) -> India | F101: Arpan Pandey, Varunjesh | G101: 6 | H101: Active | I101: Claims | J101: Subrogation and Compliance | K101: Initiate Recovery Collection & processing | L101: SIU/Subrogation Bills Assign Pay | M101: Paid SIU/Subrogation bills | N101: Commercial | O101: Multi/ Combination | P101: Auto, Property, GL, Specialty lines, WC | Q101: Mid Size | R101: Back Office | S101: L2 | T101: 1 | U101: 3 | V101: 3 | W101: Transaction Based | X101: USD | Y101: 1.3043522 | Z101: 0.25 | AA101: 0.029815146 | AB101: 0.029815146 | AC101: 1.222421 | AD101: =SUM(Z101:AC101) -> 1.5320513 | AE101: =AC101/AD101 -> 0.79789822 | AF101: 79 | AG101: NA | AH101: Nov-Dec | AI101: 7.03 | AJ101: 0.98 | AK101: 0.98 | AL101: DPU – Defect Per Unit | AM101: NA | AN101: NA | AO101: NA | AP101: NA | AQ101: NA | AR101: NA | AS101: NA | AT101: NA | AU101: NA | AV101: NA | AW101: NA | AX101: Claim Adjuster | AY101: Multiple | AZ101: Semi-Structured | BA101: 100 | BB101: Multiple | BC101: Claim Adjuster | BD101: Claim Center, ACT, MS outlook,
A102: CNA | B102: Top-10 US Commercial & Specialty Carrier | C102: US | D102: Noida, India | E102: =VLOOKUP(D102,'Dropdown List'!$F$26:$G$40,2,0) -> India | F102: Arpan Pandey, Varunjesh | G102: 6 | H102: Active | I102: Claims | J102: Litigation and Resolution | K102: Indexing & Scanning Non Medical bills | L102: Crawford Cunningham Bill Payment | M102: Indexing - This is a process of indexing for vendor Crawford Cunnigham Bills | N102: Commercial | O102: Multi/ Combination | P102: Auto, Property, GL, Specialty lines, WC | Q102: Mid Size | R102: Back Office | S102: L1 | T102: 1 | U102: 3 | V102: 3 | W102: Transaction Based | X102: USD | Y102: 1.3425167 | Z102: 0.25 | AA102: 0.029815146 | AB102: 0.029815146 | AC102: 1.222421 | AD102: =SUM(Z102:AC102) -> 1.5320513 | AE102: =AC102/AD102 -> 0.79789822 | AF102: 44 | AG102: NA | AH102: Nov-Dec | AI102: 5.5 | AJ102: 0.98 | AK102: 0.98 | AL102: DPU – Defect Per Unit | AM102: NA | AN102: NA | AO102: NA | AP102: NA | AQ102: NA | AR102: NA | AS102: NA | AT102: NA | AU102: NA | AV102: NA | AW102: NA | AX102: Claim Adjuster | AY102: Multiple | AZ102: Semi-Structured | BA102: 100 | BB102: Multiple | BC102: Claim Adjuster | BD102: Claim Center, ACT, MS outlook,
A103: CNA | B103: Top-10 US Commercial & Specialty Carrier | C103: US | D103: Noida, India | E103: =VLOOKUP(D103,'Dropdown List'!$F$26:$G$40,2,0) -> India | F103: Arpan Pandey, Varunjesh | G103: 6 | H103: Active | I103: Claims | J103: Litigation and Resolution | K103: Indexing & Scanning Non Medical bills | L103: Scheduled Payments Nearing Completion Report and Activity | M103: Create activity to claim professional for notify scheduled payment nearing complition | N103: Commercial | O103: Multi/ Combination | P103: Auto, Property, GL, Specialty lines, WC | Q103: Mid Size | R103: Back Office | S103: L3 | T103: 1 | U103: 3 | V103: 3 | W103: Transaction Based | X103: USD | Y103: 0.16550358 | Z103: 1 | AA103: 0.029815146 | AB103: 0.029815146 | AC103: 1.222421 | AD103: =SUM(Z103:AC103) -> 2.2820513 | AE103: =AC103/AD103 -> 0.53566762 | AF103: 1200 | AG103: NA | AH103: Nov-Dec | AI103: 3.0141718 | AJ103: 0.98 | AK103: 0.98 | AL103: DPU – Defect Per Unit | AM103: NA | AN103: NA | AO103: NA | AP103: NA | AQ103: NA | AR103: NA | AS103: NA | AT103: NA | AU103: NA | AV103: NA | AW103: NA | AX103: Claim Adjuster | AY103: Multiple | AZ103: Semi-Structured | BA103: 100 | BB103: Multiple | BC103: Claim Adjuster | BD103: Claim Center, ACT, MS outlook,
...

Sheet Pivot Table
A10: Current Status | B10: Active
A12: Sum of Total Staff | B12: Column Labels
A13: Row Labels | B13: Commercial & Specialty | C13: Personal | D13: Specialty | E13: Commercial | F13: London Market | G13: Grand Total
A14: Claims | B14: 6 | C14: 2682.2129 | D14: 104.07 | E14: 2028.9779 | F14: 15 | G14: 4836.2609
A15: Evaluation | B15: 6 | C15: 19.45 | E15: 416.71875 | G15: 442.16875
A16: Initiation | C16: 2207.6133 | D16: 51 | E16: 541.79002 | G16: 2800.4034
A17: Investigation | C17: 87.864545 | D17: 53.07 | E17: 522.21468 | F17: 15 | G17: 678.14923
A18: Litigation and Resolution | C18: 143.3384 | E18: 506.72629 | G18: 650.06469
A19: Subrogation and Compliance | C19: 223.94667 | E19: 41.528205 | G19: 265.47487
A20: Legal Support Services | B20: 59 | C20: 44 | D20: 2 | E20: 63.5 | G20: 168.5
A21: Legal Support | B21: 59 | C21: 44 | D21: 2 | E21: 45.5 | G21: 150.5
A22: Procurement | E22: 18 | G22: 18
A23: Sales and Service | C23: 1293.8 | G23: 1293.8
A24: Sales and Customer Support | C24: 878.8 | G24: 878.8
A25: Service and Upsell | C25: 415 | G25: 415
A26: Underwriting and UW Support | B26: 274.26473 | C26: 546.91366 | D26: 131 | E26: 1322.41 | F26: 163 | G26: 2437.5884
A27: Broker and Agent Management | C27: 5 | D27: 22 | E27: 30.51 | G27: 57.51
A28: Information Gathering and Risk Selection | B28: 34 | E28: 212.46 | F28: 163 | G28: 409.46
A29: Issuance | B29: 110.59183 | C29: 42.41673 | D29: 17.5 | E29: 259.56 | G29: 430.06856
A30: Policy Servicing | B30: 87.610736 | C30: 476.91693 | D30: 91.5 | E30: 589.67 | G30: 1245.6977
A31: Premium Audit | E31: 29.93 | G31: 29.93
A32: Risk Assessment and Rating | B32: 42.062172 | C32: 0.08 | E32: 199.28 | G32: 241.42217
A33: Risk Control | E33: 1 | G33: 1
A34: Pricing and Negotiation | C34: 22.5 | G34: 22.5
A35: Grand Total | B35: 339.26473 | C35: 4566.9266 | D35: 237.07 | E35: 3414.8879 | F35: 178 | G35: 8736.1493

Sheet P&C Transactional Data
A1: Current Status | B1: Active
A3: Row Labels | B3: Sum of Total Staff | C3: Sum of Average Monthly Volume
A4: AIG | B4: 4 | C4: 0
A5: Claims | B5: 4 | C5: 0
A6: Subrogation and Compliance | B6: 4 | C6: 0
A7: Allstate | B7: 513 | C7: 192246.29
A8: Claims | B8: 349 | C8: 161046.29
A9: Initiation | B9: 349 | C9: 161046.29
A10: Underwriting and UW Support | B10: 164 | C10: 31200
A11: Policy Servicing | B11: 164 | C11: 31200
A12: American Modern Insurance Group | B12: 92 | C12: 74500
A13: Claims | B13: 11.5 | C13: 14500
A14: Initiation | B14: 6 | C14: 2500
A15: Investigation | B15: 5.5 | C15: 12000
... A144: Evaluation | B144: 3.47 | C144: 1529.1667
A145: Initiation | B145: 581
A146: Investigation | B146: 81.904545 | C146: 40069.5
A147: Litigation and Resolution | B147: 27.63 | C147: 1791.6667
A148: Subrogation and Compliance | B148: 17 | C148: 6282.3333
A149: Legal Support Services | B149: 12 | C149: 1960
A150: Legal Support | B150: 12 | C150: 1960
A151: QBE Holding | B151: 7 | C151: 0
A152: Claims | B152: 7 | C152: 0
A153: Subrogation and Compliance | B153: 7 | C153: 0
A154: RSA Insurance | B154: 257 | C154: 114989
A155: Underwriting and UW Support | B155: 257 | C155: 114989
A156: Broker and Agent Management | B156: 3 | C156: 0
A157: Information Gathering and Risk Selection | B157: 67 | C157: 58606
... A188: Grand Total | B188: 8736.1493 | C188: 5344361.2

Sheet Claims Data
B2: Client Name | C2: Pseudo Name | D2: Relationship Since | E2: Claim FTEs | F2: India | G2: Philippines | H2: South Africa | I2: US | J2: UK | K2: Colombia | L2: Total
B3: Allstate | E3: 349 | G3: 186 | H3: 163 | L3: =SUM(F3:K3) -> 349
B4: AMIG | E4: 12 | F4: 6 | G4: 6 | L4: =SUM(F4:K4) -> 12
B5: Assurant | E5: 113 | G5: 113 | L5: =SUM(F5:K5) -> 113
B6: Guard | E6: 21 | H6: 21 | L6: =SUM(F6:K6) -> 21
B7: CNA | E7: 231 | F7: 197 | G7: 34 | L7: =SUM(F7:K7) -> 231
B8: Convex | E8: 15 | F8: 15 | L8: =SUM(F8:K8) -> 15
B9: DLG | E9: 745 | F9: 641 | H9: 104 | L9: =SUM(F9:K9) -> 745
B10: Everest | E10: 33 | F10: 19 | H10: 14 | L10: =SUM(F10:K10) -> 33
B11: Farmers | E11: 16 | F11: 11 | I11: 5 | L11: =SUM(F11:K11) -> 16
B12: Hanover | E12: 78 | F12: 61 | H12: 17 | L12: =SUM(F12:K12) -> 78
B13: Hartford | E13: 849 | F13: 583 | G13: 266 | L13: =SUM(F13:K13) -> 849
B14: Hollard | E14: 353 | G14: 144 | H14: 209 | L14: =SUM(F14:K14) -> 353
B15: IAG | E15: 119 | F15: 33 | G15: 86 | L15: =SUM(F15:K15) -> 119
B16: Kemper | E16: 130 | F16: 69 | H16: 61 | L16: =SUM(F16:K16) -> 130
B17: Liberty Mutual | E17: 535 | F17: 489 | G17: 47 | L17: =SUM(F17:K17) -> 536
B18: MAPFRE | E18: 150 | F18: 50 | H18: 77 | K18: 23 | L18: =SUM(F18:K18) -> 150
B19: Nationwide | E19: 711 | F19: 130 | G19: 561 | K19: 20 | L19: =SUM(F19:K19) -> 711
B20: QBE | E20: 7 | F20: 5 | I20: 2 | L20: =SUM(F20:K20) -> 7
B21: USAA | E21: 40 | I21: 40 | L21: =SUM(F21:K21) -> 40
B22: ZAUS | E22: 57 | F22: 23 | G22: 34 | L22: =SUM(F22:K22) -> 57
B23: ZNA | E23: 268 | F23: 73 | G23: 195 | L23: =SUM(F23:K23) -> 268
B24: Total FTEs | E24: =SUM(E3:E23) -> 4832 | F24: =SUM(F3:F23) -> 2405 | G24: =SUM(G3:G23) -> 1672 | H24: =SUM(H3:H23) -> 666 | I24: =SUM(I3:I23) -> 47 | J24: =SUM(J3:J23) -> 0 | K24: =SUM(K3:K23) -> 43 | L24: =SUM(F24:K24) -> 4833
B26: Client Name | C26: Initiate | D26: Investigate | E26: Evaluation | F26: Litigation & Resolution | G26: Subrogation and Compliance | H26: Total
B27: Allstate | C27: 349 | H27: =SUM(C27:G27) -> 349
B28: AMIG | C28: 6 | D28: 6 | H28: =SUM(C28:G28) -> 12
B29: Assurant | C29: 113 | H29: =SUM(C29:G29) -> 113
B30: Guard | D30: 21 | H30: =SUM(C30:G30) -> 21
B31: CNA | C31: 62 | D31: 8 | E31: 33 | F31: 115 | G31: 13 | H31: =SUM(C31:G31) -> 231
B32: Convex | D32: 15 | H32: =SUM(C32:G32) -> 15
B33: DLG | C33: 628 | D33: 13 | F33: 96 | G33: 8 | H33: =SUM(C33:G33) -> 745
B34: Everest | C34: 29 | F34: 4 | H34: =SUM(C34:G34) -> 33
B35: Farmers | G35: 16 | H35: =SUM(C35:G35) -> 16
B36: Hanover | C36: 78 | H36: =SUM(C36:G36) -> 78
B37: Hartford | C37: 67 | D37: 414 | E37: 210 | F37: 134 | G37: 24 | H37: =SUM(C37:G37) -> 849
B38: Hollard | C38: 353 | H38: =SUM(C38:G38) -> 353
B39: IAG | C39: 119 | H39: =SUM(C39:G39) -> 119
B40: Kemper | C40: 85 | D40: 4 | E40: 6 | F40: 18 | G40: 16 | H40: =SUM(C40:G40) -> 129
B41: Liberty Mutual | C41: 124 | D41: 102 | E41: 8 | F41: 243 | G41: 58 | H41: =SUM(C41:G41) -> 535
B42: MAPFRE | C42: 100 | G42: 50 | H42: =SUM(C42:G42) -> 150
B43: Nationwide | C43: 581 | D43: 82 | E43: 3 | F43: 28 | G43: 17 | H43: =SUM(C43:G43) -> 711
B44: QBE | G44: 7 | H44: =SUM(C44:G44) -> 7
B45: USAA | G45: 40 | H45: =SUM(C45:G45) -> 40
B46: ZAUS | C46: 45 | G46: 12 | H46: =SUM(C46:G46) -> 57
B47: ZNA | C47: 60 | D47: 14 | E47: 182 | F47: 12 | H47: =SUM(C47:G47) -> 268
B48: Total | C48: =SUM(C27:C47) -> 2799 | D48: =SUM(D27:D47) -> 679 | E48: =SUM(E27:E47) -> 442 | F48: =SUM(F27:F47) -> 650 | G48: =SUM(G27:G47) -> 261 | H48: =SUM(C48:G48) -> 4831

Sheet Sheet2
C3: Missing Data
C4: Nationwide (Colombia)
C5: Hollard (Philippines)
C6: AMIG (Philippines)
C7: AA Insurance (India)

Sheet Dropdown List
A1: Functions | B1: Claims | C1: Underwriting and UW Support | D1: Sales and Service | E1: Legal Support Services | F1: Initiation | G1: Investigation | H1: Evaluation | I1: Litigation and Resolution | J1: Subrogation and Compliance | K1: Broker and Agent Management | L1: Information Gathering and Risk Selection | M1: Risk Assessment and Rating | N1: Pricing and Negotiation | O1: Issuance | P1: Policy Servicing | Q1: Premium Audit | R1: Risk Control | S1: Sales | T1: Sales and Customer Support | U1: Service and Upsell | V1: Legal Support | W1: Office of General Counsel | X1: Procurement
A2: Claims | B2: Initiation | C2: Broker and Agent Management | D2: Sales | E2: Legal Support | F2: Indexing | G2: Coverage Verification | H2: Complete referral to Providers | I2: Indexing & Scanning Non Medical bills | J2: Triage/ Demand Issuance | K2: Account Reconciliation | L2: Add Product | M2: Assess Conditional / Non Renewal Notice | N2: Prep Pricing | O2: Confirming Declaration of Policy details | P2: Auto ID Cards | Q2: Audit Scheduling | R2: Phone Surveys | S2: Quotes | T2: Quotes | U2: MTA Processing and Issuance | V2: Paralegal & Legal Secretary Services | W2: E2E Contracting Services | X2: E2E Contracting Services
A3: Underwriting and UW Support | B3: Investigation | C3: Information Gathering and Risk Selection | D3: Sales and Customer Support | E3: Office of General Counsel | F3: Data entry | G3: Loss/ Damage verification | H3: IME Scheduling | I3: Non Medical Bill Review & Approval | J3: Info Gathering & Analysis | K3: Agency Bill Operations | L3: Additional System Setup | M3: Assess DMV Report | N3: Debit/ credit application | O3: Finalize Issuance of policies | P3: Book of Profits | Q3: Clerical Support | R3: Express Surveys | S3: New Business Processing and Issuance | T3: New Business Processing and Issuance | U3: Renewal Processing and Issuance | V3: E-Discovery Document Review | W3: Abstraction & Summarization | X3: Abstraction & Summarization
A4: Sales and Service | B4: Evaluation | C4: Risk Assessment and Rating | D4: Service and Upsell | E4: Procurement | F4: Policy verification | G4: Claim Coding | H4: Case Management of File | I4: Wage Statement | J4: Salvage Settlement | K4: Collections | L4: Loss Runs | M4: Prepare Written Quote/ Proposal | N4: Applying fees and charges for any unusual expenses | O4: Issuing Certificate of Insurance | P4: Cancel and Rewrite | Q4: Field Audit | R4: UW Surveys | S4: Cross Sell | T4: Webchat - Query resolution, General Inquiry | U4: Complaint Management | V4: Redactions & Privilege Review | W4: Legal Research | X4: Supplier Monitoring
A5: Legal Support Services | B5: Litigation and Resolution | C5: Pricing and Negotiation | F5: Claim Setup and assignment | G5: Triaging for SIU, Subro | H5: NCM support tasks, Med Tasks | I5: Mileage Calculation | J5: Negotiation/ Arbitration/ Resolution | K5: Debt Management | L5: Assess Renewal | M5: Re-Rating | N5: Update pricing template | O5: New Business Issuance | P5: Cancellation notice | Q5: Internet Audit | R5: Consultative Risk Assessments | T5: MTA Processing | U5: Cancellations/ Reinstatements | V5: Redactions & Subpoena Review | W5: Compliance Services | X5: Contractors' & Service Providers' Performance (SLAs)
B6: Subrogation and Compliance | C6: Issuance | F6: Determining nature/severity of claim | G6: Stat Coding | H6: Packet Prep, chronology summary | I6: Validate Lien/ 3rd Party holder info | J6: Initiate Recovery Collection & processing | K6: Direct Bill | L6: Error Correction | M6: New Business Quotes/ Rating | N6: Fraud Management | O6: Renewal Issuance | P6: Certificates (COI, AI, Renewal) | Q6: Phone Audit | R6: Account Service and Coordination | T6: Renewal Prep and Processing | U6: Query resolution | V6: Summarization & Chronology of Documents | W6: External Counsel Management | X6: Contract Deliverables & Obligation Management
C7: Policy Servicing | F7: Send Initial Notification | G7: Gathering relevant reports | H7: Utilization Review | I7: Stop Payment | J7: Litigation Management | K7: Maintenance | L7: New Business setup | M7: Renewal Quotes/ Rating | N7: Actuarial Support | O7: Endorsements Issuance | P7: Endorsements intake and setup | Q7: Premium Audit Endorsements | T7: Complaint Management | U7: General Inquiry | W7: Legal Admin Support | X7: Contract Compliance
C8: Premium Audit | F8: First Notice of Loss Calls | G8: Requesting MVRs | H8: Determine assignment | I8: Duplicate Payment | J8: Adjuster License Management | K8: Marketing Analytics | L8: Broker Correspondence | M8: Endorsements Quotes/ Rating | O8: Printing, Scanning and Mailroom operations | P8: DMV and MVR | Q8: Mail Audits | T8: Cancellations/ Reinstatements | U8: Customer Assurance | W8: Litigation Support
C9: Risk Control | F9: After Hours Support | G9: Fraud detection | H9: Document clinical info | I9: Medical Bill Entry & Review | J9: Field Quality Management | K9: New Agent Set-up | L9: Clearance and Registration | M9: Manual coding of policies | P9: Indexing | Q9: Estimated Audits | T9: General Inquiry | U9: Premium Collections
F10: Customer Service Call Centre - Repair/ Replacement/ SOS help/ General Inquiry | G10: Scheduling for field investigation | H10: Medical Record Summarization | I10: Medical Bill Review and Repricing | J10: Fraud Handling | K10: Outreach | L10: Service Requests - Police Reports | M10: Analyze Exposure | P10: Mailroom Ops and Scanning | Q10: Quality Review and Premium billing | T10: Query Resolution | U10: Correspondence
F11: Full Service Mailroom & Scanning | G11: Evidence gathering | H11: Quality Management | I11: Medical Bill Coding | J11: Communicate Claim Disposition | K11: PA&L License Appointment Request | L11: Service Requests - DMV/ MVR | M11: Review Loss History | P11: Non Renewals/Renewal notice | Q11: Cancellation | U11: Upsell
F12: Initial Acknowledgement Letters | G12: Witness statements | H12: Peer Review & support | I12: State Guideline Research & Review | J12: Platform Provider | K12: Payments Processing/Management | L12: Service Request - OFAC / OFAC Clearance | M12: Assess and summarize financials | P12: Non-discretionary price modifications | U12: Premium Administration
F13: Provider Help Lines | G13: Requesting Police report | H13: Identify claims for closing | I13: Legal Document Review | K13: Renewals | L13: D&B Scores | M13: Prepare underwriter (UW) risk evaluation sheet | P13: OFAC Verification
F14: Loss Reserve | G14: Document Management | H14: Send packets for final submission | I14: Legal File Opening | K14: Surety | L14: Equipment Valuation | M14: Bordereaux Management | P14: Process Premium Refund
F15: State Form Filing | G15: State Form and Filing | H15: Reconsideration Reviews | I15: Legal Referral | K15: Transfers | L15: Location Data Cleansing | M15: SOV standardization | P15: Filing Services
F16: Legal Case creation | G16: State Reporting Corrections | H16: State Guideline Research & Review, ODG Benchmarks | I16: Legal Research & Analysis | K16: Unpaid items and written premiums | L16: Renewal Prep | M16: CAT modeling | P16: Loss run retrieval
F17: Adjuster License Management (addition/renewal/removal) | G17: External Distribution | H17: Assign expense codes | I17: Contract Management | K17: Verification of Agent/Agency license (P&AL initial & secondary) | L17: WC Filings/ CRITS | M17: Record Keeping | P17: Cancellation & Reinstatement
F18: Adjuster Onboarding/Off-boarding | G18: Inquiry calls from providers (medical bill review; bill intake; medical billing form and payment) | I18: Subpoena Reviews | L18: Rate - Per Expiring | M18: Renewal Rating | P18: Premium Billing and Collections
I19: Bill Payment (Medical Legal, Non Medical, Vendor) | L19: Validate and Update Policy info (Limits, Exposure State, Exposure, FEIN, Address, Name Insured, Employers Liability etc.) | M19: Property estimates | P19: Correspondence with Brokers and UWs
I20: Send Closing Documents | L20: Experience Mods | M20: Loss History Summary | P20: Customer service
L21: Service Requests - Survey records | P21: Quality Audit
L22: Request Missing Information from Broker
A25: Business Lines | B25: Market Type | C25: Pricing Model | D25: LOB | E25: Pricing Currency | F25: Delivery Location (City) | G25: Delivery Location (Country)
A26: Personal | B26: Small | C26: FTE Based | D26: Accident & Health | E26: USD | F26: Bogota, COL | G26: Colombia
A27: Commercial | B27: Mid Size | C27: Transaction Based | D27: ALL LOB | E27: GBP | F27: Chennai, India | G27: India
A28: Specialty | B28: Large | C28: Outcome Based | D28: Auto | E28: USD/GBP | F28: Hyderabad, India | G28: India
A29: Commercial & Specialty | B29: Specialized | C29: Project Based | D29: Auto & Property | E29: AUD | F29: Noida, India | G29: India
A30: London Market | B30: Direct Market | C30: Others | D30: Auto, Domestic Casualty | F30: Pune, India | G30: India
B31: Small & Mid Size | D31: Auto, WC & Property | F31: Alabang, PHP | G31: Philippines
B32: Mid Size & Large | D32: General Liability | F32: Cebu, PHP | G32: Philippines
B33: Small, Mid Size & Large | D33: GL | F33: Manila, PHP | G33: Philippines
B34: All | D34: Motor | F34: Pasay, PHP | G34: Philippines
D35: Motor, Property & Liability | F35: George, South Africa | G35: South Africa
D36: Multi/ Combination | F36: Cape Town, South Africa | G36: South Africa
D37: Package | F37: US Onshore | G37: US
D38: Property
D39: Property & Casualty
D40: Small Business
D41: Specialty
D42: UMB
D43: WC
A48: Client Geography | B48: Quality Methodology | C48: Input/ Output Formats | D48: Standardization of Tools | E48: Delivery Location Country
A49: US | B49: DPU – Defect Per Unit | C49: Images | D49: Structured | E49: India
A50: UK | B50: DPO – Defect Per Opportunity | C50: Acord | D50: Unstructured | E50: Philippines
A51: Australia | B51: Fatal DPU – Fatal Defect Per Unit | C51: PDFs | D51: Semi-Structured | E51: South Africa
A52: Global | B52: Weighted DPU – Weighted Defect Per Unit | C52: Editable PDFs | E52: Colombia
A53: Latam | B53: Weighted DPO – Weighted Defect Per Opportunity | C53: Emails | E53: North America
A54: Europe | B54: DPU and DPO | C54: Word | E54: UK
A55: Canada | B55: Others | C55: Excel | E55: Europe
C56: PPT
C57: Instructions in Application
C58: Multiple
C59: Others
