Workbook
Name Audit_ATC: 'Reference Tab - Do not Delete'!$I$21:$I$27
Name BIE: 'Reference Tab - Do not Delete'!$G$21:$G$27
Name DT_WC: 'Reference Tab - Do not Delete'!$D$21:$D$27
Name E_E2E: 'Reference Tab - Do not Delete'!$F$21:$F$27
Name Fin_Auto: 'Reference Tab - Do not Delete'!$K$21:$K$27
Name FNOL: 'Reference Tab - Do not Delete'!$B$21:$B$27
Name Food: 'Reference Tab - Do not Delete'!$A$21:$A$31
Name Int_Col: 'Reference Tab - Do not Delete'!$H$21:$H$27
Name Life_Cycle: 'Reference Tab - Do not Delete'!$C$35:$C$42
Name NB_PaaS: 'Reference Tab - Do not Delete'!$E$21:$E$27
Name PaaS: 'Reference Tab - Do not Delete'!$C$21:$C$27
Name PRA: 'Reference Tab - Do not Delete'!$J$21:$J$27
Name Sign_Off___Next_Steps: 'Reference Tab - Do not Delete'!$B$35:$B$40
Name TrRFF: 'Reference Tab - Do not Delete'!$L$21:$L$27
Name VOC_Source: 'Reference Tab - Do not Delete'!$A$35:$A$40

Sheet Sheet3
A1: Client | B1: Geography | C1: Strategic/Named | D1: Client Exec | E1: CEO | F1: CFO | G1: CRO | H1: CCO | I1: COO | J1: CIO/CTO | K1: CUO | L1: GWP | M1: Growth % | N1: Combined Ratio (2019) | O1: Do they outsource today | P1: Competitors | Q1: Renewal Date
A2: Swiss Re | B2: US | C2: Named | D2: Mohit | E2: J.Eric Smith | F2: Brian Rosenblum | G2: Stefanie Stratos | H2: Thomas Hyatte | I2: Rich Agar | J2: Prashanthi Roy /Pravina Ladva | L2: $42,228M | M2: 0.029 | N2: 1.0708 | O2: Yes | P2: CSC, Genpact, TCS | Q2: 2021 (They have multiple BPO, automation and analytics partner)
A3: Nationwide Insurance | B3: US | C3: Named | D3: Mohit | E3: Kirt Walker | F3: Mark Thresher | G3: Klaus Diem | H3: Sandra Rich | I3: Mark Berven | J3: James Fowler | L3: $49.3B | M3: 0.025 | N3: 0.94 | O3: Yes | P3: Cognizant, Genpact | Q3: Mid 2021, 2022
A4: American Modern | B4: US | C4: Named | D4: Sean | E4: Andreas Kleiner | F4: Rene Gobanya | G4: Trey Griffith | H4: Eric Hunzinger | I4: Paul Schneider | J4: Bill Gottsacker | K4: Kam Jha | L4: $2.5B | M4: 0.03 | N4: N/A | O4: Yes | P4: TCS | Q4: Just signed with us
A5: Everest Insurance | B5: US | C5: Named | D5: Sean | E5: Mike Karmilowicz | F5: Dana Lodge | G5: Bill Thygeson, CAO | H5: Patricia Mcmahon | I5: Mike Mulray | J5: Owen Williams | K5: Open | L5: $4B | M5: 0.04 | N5: 88.7 | O5: Yes | P5: None | Q5: 2023
A6: Axis | B6: US | C6: Named | D6: Sean | E6: Albert Benchimol | F6: Pete Vogt | G6: Ben Rubin | H6: Mike Baumel | I6: Rob Hartman | J6: Keith Schlosser | K6: Eric Gesick | L6: 6.9 | M6: 0.01 | N6: 107.3 | O6: Yes | P6: Genpact, Infy | Q6: 2022
A7: IAG | B7: Australia | C7: Strategic | D7: Vilas | E7: Peter Harmer | F7: Nick Hawkins | G7: David Watts | J7: Neil Morgan | L7: 12,135 ($m) | M7: 0.011 | N7: 1.23 | O7: Yes | P7: WNS | Q7: 44470
A8: Suncorp | B8: Australia | C8: Strategic | D8: Vilas | E8: Steve Johnston | F8: Jeremy Robson | G8: Fiona Thompson | I8: Paul Smeaton (Insurance) | J8: Adam Bennett | L8: 8119 ($m) | M8: 0.015 | N8: 0.96 | O8: Yes | P8: WNS, Genpact, Cognizant | Q8: 44191
A9: Allstate | B9: US | C9: Strategic | D9: Amit Gaba | E9: Tom Wilson | F9: Mario Rizzo | G9: Mark Prindiville | H9: Eric Brandt | I9: Glenn Shapiro | J9: Suren Gupta | L9: $34.8B | M9: 0.057 | N9: 85 | O9: Yes | P9: Genpact, Fractal | Q9: MSA is perpetual
A10: Kemper | B10: US | C10: Other | D10: Amit Gaba | E10: Joe Lacher | F10: Jim McKinney | G10: Max Mindak | H10: Kim Leggette | I10: Duane Sanders | J10: Charles Brooks | L10: $4B | M10: 0.3 | N10: 93 | O10: Yes | P10: Accenture | Q10: Key SOW renewal date Jan 1, 2021
A11: Travelers | B11: US | C11: Named | D11: Sean | E11: Alan Schnitzer | F11: Dan Frey | G11: Bruce Jones | H11: Nicolas Seminara | I11: Mojgan Lefebvre | J11: Mojgan Lefebvre | K11: Rick Schug | L11: $29B | M11: 0.05 | N11: 96.5 | O11: Yes | P11: CTS, WNS, Genpact | Q11: 2021
A12: Great American | B12: US | C12: Named | D12: Sean | E12: Carl Lindnor, Craig Lindnor | F12: Jeff Consolino | I12: Gary Gruber | J12: Chad Stewart | L12: $13B | M12: 0.02 | N12: 93.7
A13: Munich Re | B13: US | C13: Named | D13: Mohit | E13: Dave Brune | F13: Oliver J. Horbelt/Angela Homm | G13: Catherine Smith | H13: JannaLyn Allen | I13: Anita Kuchma | J13: Phil Roeper | L13: $60,433M | M13: 0.02 | N13: 1.01 | O13: Yes | P13: Wipro,Capgemini | Q13: Sep, 2022 (with Wipro) and 23rd July 2020 with Capgemini
A14: State Farm | B14: US | C14: Named | D14: Mohit | E14: Bruce Hull | F14: Connie Storey | G14: Cathy Wallace | H14: Terrence Ludwig | I14: Cleo Villaflores | J14: Ashley Pettit | L14: $42,137M | M14: 0 | N14: 0.987 | O14: No | P14: Wipro | Q14: NA
A15: Mapfre | B15: US | C15: Named | D15: Mohit | E15: Alexis Sanchez Geigel | F15: Francois Facon | G15: Dana Whiteley | H15: Christopher Matherly | I15: Scott Hammond | J15: Gregg Nickerson | L15: $6,398.6M | M15: 0.031 | N15: 0.976 | O15: Yes | P15: WNS | Q15: NA

Sheet Home
B1: P&C Solutions and Go-To-Market Strategy
K24: Version 1.5 | L24: Last Updated | N24: 44046

Sheet Go-To-Market Plan
B2: Home
B4: P&C Go-To-Market Business Development Plan
B6: Reset, Refresh and Re-imagine P&C business, pivoting to a solutions based, sustainable growth focused organization
B8: A. | C8: Critical success factors for EXL P&C
C9: Goal: Global Brand, Best in the Industry
C10: How: Global Market Share - ~20% CAGR; Growth Focus - $500M Annual Revenue; Industry Recognition -Thought Leader, Digital Disruptor
C11: Change needed: Focus on Industry Solutions, Customer Outcomes, Speed to Market, Augment with the Best Talent
C13: We are pivoting to be the Preferred Digital Transformation partner for the industry. EXL P&C a ‘solutions organization’ vs. a ‘services organization’
B15: B. | C15: What are clients telling us
C16: Clear appetite for digital solutions (vs. platforms) as a service (AI at the leading edge)
C17: Identify Problems and come with solutions…will buy solutions not people (People are only part of the solution – typically a combination of people and digital)
C18: Templatize transformation at base level…solve more end to end (Transformation benefit is table stakes)
C19: Price on solutions…vs. individual components (but need to be able to modularize the offerings as well)
C20: Develop transparent view from an end customer perspective, customer journeys…single view of customer (truly enable decisions with data and analytics)
C21: Lead the market; don’t chase it (we are often late to the party)
B23: C. | C23: Approach and Steps towards developing a solutions based go-to-market plan
C24: We believe there is a lot of great opportunities within the following layers as we cast a broad net and pivot towards solution based, sustainable growth focused organization-
C26: Tier 1: Strategic Accounts - expand to sell solutions vs. FTE; partner to co-build solutions with anchor clients; personalized CxO specific campaigns with solutions mapped to strategic priorities
C27: Tier 2: Named Accounts - research top 3-5 priorities, cross reference solution ideas with priorities; P&C solution owners to map with each account and Exec, personalized account based marketing
C28: Tier 3: Expand the net to include mid-level, regional, specialty, reinsurance carriers, brokers and smaller size firms, beyond the traditional big carriers. Research priorities, map solutions and GTM
C29: Tier 4: Target Competition logos - go after upcoming renewals (e.g. Project Ocean); research logos with performance dis-sat/evolving priorities (e.g.. Aon); pitch Digital and Data in BPO only clients etc.
C31: Step 1: Shortlist top-30 P&C firms across the globe (mix of Carriers, brokers, across above Tiers), add analysis on key metrics like NWP, Combined Ratio, Competition, Sourcing, Share of Wallet, Partner Network etc.
C32: Step 2: Map key CxOs across these top-30 firms
C33: Step 3: Research on top 3-5 priorities across the shortlisted firms
C34: Step 4: Cross-reference solution ideas with strategic priorities for solution build and logo prioritization
C35: Step 5: Allocate each logo and CxOs to P&C frontend team (AM, CE, Growth Leader, Sales) based on P&C solution teams
C36: Step 6: Map GTM ideas like ABM, Infographics, Webinars, Influencer Events, Case Studies and Webinars for Top-30 logos
C37: Step 7: Develop prioritization roadmap over next 12-18 months, with 30-60-90 day sprints
C38: Step 8: SFDC driven reviews and cadence
B40: D. | C40: Displacing competition and building for continuous, sustainable growth
C42: Proactively identifying white spaces across our capability set to develop a Build/Buy/Partner combination strategy around
C43: Insuretechs : few firms stand out to close our current capability gaps – Shift Technology, CapeAnalytics, Snapsheet, Datacubes etc. Analyzing from a list of 80 firms
C44: TPAs for onshore capabilities in response to market demand – e.g. Crawford Broadpsire, Gallagher Bassett, Segewick, York
C45: Competition analysis – to go after logos we don’t work with and assess partnerships / acquisitions that our competition has made
C46: Performing capability gap analysis : outside-in, inside-out
B48: E. | C48: Proactively developing ‘packaged solutions’ in response to outside-in industry problems, with an anchor client across each ‘solution’
B50: 1 | C50: FNOL as-as-service
B51: 2 | C51: Payments-as-a Service
B52: 3 | C52: Digitally Transforming Workers’ Compensation Claims
B53: 4 | C53: Digitally Transforming Commercial Underwriting
B54: 5 | C54: New Business Processing-as-a-Service
B55: 6 | C55: Endorsements-as-a-Service
B56: 7 | C56: Renewal Processing-as-a-Service
B57: 8 | C57: Receivables Management
B58: 9 | C58: FRAC Audit Analytics
B59: 10 | C59: FRAC Process Risk Assessment
C61: Each ‘packaged solution’ will be evaluated against the enterprise Solution Evaluation Criteria and will be designed to solve an industry problem, across the end-to-end value chain, with committed business and customer outcomes vs. traditional transactional SLAs. The solutions will be repeatable and have global applicability. Commercial construct will be linked to outcomes, moving away from the traditional FTE model. Cheap human labor model has long expired. Will require a change in thinking across the enterprise and willingness to take on more risk.
B66: F. | C66: Summary of Go-To-Market Strategy
B68: 1 | C68: Leverage Account Based Marketing : it is a market of one, we are creating personalized campaigns that are designed to resonate with each account.
B69: 2 | C69: Formalizing Demand Triggered Alliance Partnerships with key vendors that together, based on Demand function analysis, form an integrated solution focused on a specific set of business pains.
B70: 3 | C70: Working with our Market Development Partner in Beyond Codes to run specific campaigns whose team that once armed with some training and a script to fall back on, should be able to identify opportunities and help schedule calls, ultimately bringing our sales leaders into the cycle
B72: 4 | C72: Brand Building that has to continue through our Analyst and Advisor Relationships. We are not being brought into every deal that is taking place in the market, we need to figure out why, conduct the necessary education with these parties, and re-position ourselves accordingly so that we are top of mind with these firms

Sheet Top Insurers and Brokers
A1: Global List of Top Insurers & Brokers
A3: The following table comprises of Top Insurers and Brokers rated per industry standards. This list will be used to map Client Prioritization and Future GTM Strategies. This list includes non-EXL clients as well
A5: Home | B5: Source: | C5: http://www.ambest.com/review/displaychart.aspx?Record_Code=274586 | J5: https://www.insurancejournal.com/top-100-insurance-agencies/ | AI5: Inputs - Vishal Gupta | AK5: Inputs - CE
A6: Growth Leader | B6: Company/ Group | C6: CID | D6: Type | E6: NWP - 2019 | F6: % Change | G6: 2018 Rank | H6: 2019 Rank | I6: Geography | J6: Combined Ratio - 2019 | K6: Relationship Type | L6: CE | M6: CEO | N6: CFO | O6: CRO | P6: CCO | Q6: COO | R6: CIO/CTO | S6: CUO | T6: Outsource | U6: EXL Competitors | V6: Renewal Date | W6: InsureTech Partner 1 | X6: InsureTech Partner 2 | Y6: InsureTech Partner 3 | Z6: InsureTech Partner 4 | AA6: InsureTech Partner 5 | AB6: TPA Partner 1 | AC6: TPA Partner 2 | AD6: TPA Partner 3 | AE6: TPA Partner 4 | AF6: TPA Partner 5 | AG6: NWP-Range | AH6: Ranking Range | AI6: EXL Client | AJ6: 2020-Rev Budget | AK6: EXL's Share of Wallet | AL6: Competition Account | AM6: Competition's Share of Wallet | AN6: Relationship Maturity (Yrs) | AO6: Renewal Timeframe | AP6: Future TCV Potential | AQ6: Client Priority Rating
A7: Mohit | B7: State Farm Group | C7: 1 | D7: Carrier | E7: 65100455000 | F7: =-0.6/100 -> -0.006 | G7: 1 | H7: 1 | I7: US | J7: 98.7 | K7: Named | L7: Mohit | M7: Bruce Hull | N7: Connie Storey | O7: Cathy Wallace | P7: Terrence Ludwig | Q7: Cleo Villaflores | R7: Ashley Pettit | T7: Yes | U7: Wipro | W7: ITP1 | AG7: =IF(E7="","",IF(E7>='Reference Tab - Do not Delete'!$E$35,'Reference Tab - Do not Delete'!$D$35,IF(AND(E7>='Reference Tab - Do not Delete'!$E$36,E7<'Reference Tab - Do not Delete'!$E$35),'Reference Tab - Do not Delete'!$D$36,IF(AND(E7>='Reference Tab - Do not Delete'!$E$37,E7<'Reference Tab - Do not Delete'!$E$36),'Reference Tab - Do not Delete'!$D$37,IF(AND(E7>='Reference Tab - Do not Delete'!$E$38,E7<'Reference Tab - Do not Delete'!$E$37),'Reference Tab - Do not Delete'!$D$38,'Reference Tab - Do not Delete'!$D$39))))) -> Above $50B | AH7: =IF(H7="","DNA",IF(H7<=10,"Top 10",IF(AND(H7<=25,H7>10),"11 - 25",IF(AND(H7<=50,H7>25),"26 - 50","Above 50")))) -> Top 10 | AI7: =IF(AJ7>0,"Yes","") | AJ7: 0
B8: Berkshire Hathaway Ins | C8: 2 | D8: Carrier | E8: 53754763000 | F8: 0.079 | G8: 2 | H8: 2 | I8: US | W8: ITP2 | AG8: =IF(E8="","",IF(E8>='Reference Tab - Do not Delete'!$E$35,'Reference Tab - Do not Delete'!$D$35,IF(AND(E8>='Reference Tab - Do not Delete'!$E$36,E8<'Reference Tab - Do not Delete'!$E$35),'Reference Tab - Do not Delete'!$D$36,IF(AND(E8>='Reference Tab - Do not Delete'!$E$37,E8<'Reference Tab - Do not Delete'!$E$36),'Reference Tab - Do not Delete'!$D$37,IF(AND(E8>='Reference Tab - Do not Delete'!$E$38,E8<'Reference Tab - Do not Delete'!$E$37),'Reference Tab - Do not Delete'!$D$38,'Reference Tab - Do not Delete'!$D$39))))) -> Above $50B | AH8: =IF(H8="","DNA",IF(H8<=10,"Top 10",IF(AND(H8<=25,H8>10),"11 - 25",IF(AND(H8<=50,H8>25),"26 - 50","Above 50")))) -> Top 10 | AI8: =IF(AJ8>0,"Yes","") | AJ8: 0
B9: Progressive Ins Group | C9: 3 | D9: Carrier | E9: 37578689000 | F9: 0.152 | G9: 3 | H9: 3 | I9: US | W9: ITP3 | AG9: =IF(E9="","",IF(E9>='Reference Tab - Do not Delete'!$E$35,'Reference Tab - Do not Delete'!$D$35,IF(AND(E9>='Reference Tab - Do not Delete'!$E$36,E9<'Reference Tab - Do not Delete'!$E$35),'Reference Tab - Do not Delete'!$D$36,IF(AND(E9>='Reference Tab - Do not Delete'!$E$37,E9<'Reference Tab - Do not Delete'!$E$36),'Reference Tab - Do not Delete'!$D$37,IF(AND(E9>='Reference Tab - Do not Delete'!$E$38,E9<'Reference Tab - Do not Delete'!$E$37),'Reference Tab - Do not Delete'!$D$38,'Reference Tab - Do not Delete'!$D$39))))) -> $50B - $B | AH9: =IF(H9="","DNA",IF(H9<=10,"Top 10",IF(AND(H9<=25,H9>10),"11 - 25",IF(AND(H9<=50,H9>25),"26 - 50","Above 50")))) -> Top 10 | AI9: =IF(AJ9>0,"Yes","") -> Yes | AJ9: 2500
A10: Roopak | B10: Allstate Ins Group | C10: 4 | D10: Carrier | E10: 34038467000 | F10: 0.054 | G10: 4 | H10: 4 | I10: US | J10: 85 | K10: Strategic | L10: Amit Gaba | M10: Tom Wilson | N10: Mario Rizzo | O10: Mark Prindiville | P10: Eric Brandt | Q10: Glenn Shapiro | R10: Suren Gupta | T10: Yes | U10: Genpact, Fractal | V10: Perpetual MSA | W10: ITP2 | AG10: =IF(E10="","",IF(E10>='Reference Tab - Do not Delete'!$E$35,'Reference Tab - Do not Delete'!$D$35,IF(AND(E10>='Reference Tab - Do not Delete'!$E$36,E10<'Reference Tab - Do not Delete'!$E$35),'Reference Tab - Do not Delete'!$D$36,IF(AND(E10>='Reference Tab - Do not Delete'!$E$37,E10<'Reference Tab - Do not Delete'!$E$36),'Reference Tab - Do not Delete'!$D$37,IF(AND(E10>='Reference Tab - Do not Delete'!$E$38,E10<'Reference Tab - Do not Delete'!$E$37),'Reference Tab - Do not Delete'!$D$38,'Reference Tab - Do not Delete'!$D$39))))) -> $50B - $B | AH10: =IF(H10="","DNA",IF(H10<=10,"Top 10",IF(AND(H10<=25,H10>10),"11 - 25",IF(AND(H10<=50,H10>25),"26 - 50","Above 50")))) -> Top 10 | AI10: =IF(AJ10>0,"Yes","") -> Yes | AJ10: 9190553.4 | AK10: Medium | AL10: Yes
A11: Nikhil | B11: Liberty Mutual Ins Cos | C11: 5 | D11: Carrier | E11: 32268379000 | F11: 0.014 | G11: 5 | H11: 5 | I11: US | J11: 101.7 | K11: Named | L11: Kuldeep | M11: David H. Long | N11: Christopher Pierce | R11: James McGlennon | T11: Yes | U11: CTS | W11: ITP1 | AG11: =IF(E11="","",IF(E11>='Reference Tab - Do not Delete'!$E$35,'Reference Tab - Do not Delete'!$D$35,IF(AND(E11>='Reference Tab - Do not Delete'!$E$36,E11<'Reference Tab - Do not Delete'!$E$35),'Reference Tab - Do not Delete'!$D$36,IF(AND(E11>='Reference Tab - Do not Delete'!$E$37,E11<'Reference Tab - Do not Delete'!$E$36),'Reference Tab - Do not Delete'!$D$37,IF(AND(E11>='Reference Tab - Do not Delete'!$E$38,E11<'Reference Tab - Do not Delete'!$E$37),'Reference Tab - Do not Delete'!$D$38,'Reference Tab - Do not Delete'!$D$39))))) -> $50B - $B | AH11: =IF(H11="","DNA",IF(H11<=10,"Top 10",IF(AND(H11<=25,H11>10),"11 - 25",IF(AND(H11<=50,H11>25),"26 - 50","Above 50")))) -> Top 10 | AI11: =IF(AJ11>0,"Yes","") -> Yes | AJ11: 8246886.5 | AK11: Medium | AL11: Yes
A12: Sean | B12: Travelers Group | C12: 6 | D12: Carrier | E12: 27214083000 | F12: 0.055 | G12: 6 | H12: 6 | I12: US | J12: 96.5 | K12: Named | L12: Sean | M12: Alan Schnitzer | N12: Dan Frey | O12: Bruce Jones | P12: Nicolas Seminara | Q12: Mojgan Lefebvre | R12: Mojgan Lefebvre | S12: Rick Schug | T12: Yes | U12: CTS, WNS, Genpact | V12: 2021 | W12: ITP2 | AG12: =IF(E12="","",IF(E12>='Reference Tab - Do not Delete'!$E$35,'Reference Tab - Do not Delete'!$D$35,IF(AND(E12>='Reference Tab - Do not Delete'!$E$36,E12<'Reference Tab - Do not Delete'!$E$35),'Reference Tab - Do not Delete'!$D$36,IF(AND(E12>='Reference Tab - Do not Delete'!$E$37,E12<'Reference Tab - Do not Delete'!$E$36),'Reference Tab - Do not Delete'!$D$37,IF(AND(E12>='Reference Tab - Do not Delete'!$E$38,E12<'Reference Tab - Do not Delete'!$E$37),'Reference Tab - Do not Delete'!$D$38,'Reference Tab - Do not Delete'!$D$39))))) -> $50B - $B | AH12: =IF(H12="","DNA",IF(H12<=10,"Top 10",IF(AND(H12<=25,H12>10),"11 - 25",IF(AND(H12<=50,H12>25),"26 - 50","Above 50")))) -> Top 10 | AI12: =IF(AJ12>0,"Yes","") | AJ12: 0
A13: Sean | B13: USAA Group | C13: 7 | D13: Carrier | E13: 22981339000 | F13: 0.069 | G13: 7 | H13: 7 | I13: US | J13: 82.8 | K13: Named | L13: Sean | M13: Wayne Peacock | N13: Laura Bishop | O13: Torben Ostergaard | P13: Sean Burgess | R13: Michael Brady | T13: Yes | U13: TCS | W13: ITP3 | AG13: =IF(E13="","",IF(E13>='Reference Tab - Do not Delete'!$E$35,'Reference Tab - Do not Delete'!$D$35,IF(AND(E13>='Reference Tab - Do not Delete'!$E$36,E13<'Reference Tab - Do not Delete'!$E$35),'Reference Tab - Do not Delete'!$D$36,IF(AND(E13>='Reference Tab - Do not Delete'!$E$37,E13<'Reference Tab - Do not Delete'!$E$36),'Reference Tab - Do not Delete'!$D$37,IF(AND(E13>='Reference Tab - Do not Delete'!$E$38,E13<'Reference Tab - Do not Delete'!$E$37),'Reference Tab - Do not Delete'!$D$38,'Reference Tab - Do not Delete'!$D$39))))) -> $50B - $B | AH13: =IF(H13="","DNA",IF(H13<=10,"Top 10",IF(AND(H13<=25,H13>10),"11 - 25",IF(AND(H13<=50,H13>25),"26 - 50","Above 50")))) -> Top 10 | AI13: =IF(AJ13>0,"Yes","") -> Yes | AJ13: 3515776.7
B14: Chubb INA Group | C14: 8 | D14: Carrier | E14: 18249079000 | F14: -0.067 | G14: 8 | H14: 8 | I14: US | W14: ITP2 | AG14: =IF(E14="","",IF(E14>='Reference Tab - Do not Delete'!$E$35,'Reference Tab - Do not Delete'!$D$35,IF(AND(E14>='Reference Tab - Do not Delete'!$E$36,E14<'Reference Tab - Do not Delete'!$E$35),'Reference Tab - Do not Delete'!$D$36,IF(AND(E14>='Reference Tab - Do not Delete'!$E$37,E14<'Reference Tab - Do not Delete'!$E$36),'Reference Tab - Do not Delete'!$D$37,IF(AND(E14>='Reference Tab - Do not Delete'!$E$38,E14<'Reference Tab - Do not Delete'!$E$37),'Reference Tab - Do not Delete'!$D$38,'Reference Tab - Do not Delete'!$D$39))))) -> $50B - $B | AH14: =IF(H14="","DNA",IF(H14<=10,"Top 10",IF(AND(H14<=25,H14>10),"11 - 25",IF(AND(H14<=50,H14>25),"26 - 50","Above 50")))) -> Top 10 | AI14: =IF(AJ14>0,"Yes","") -> Yes | AJ14: 540548.98
A15: Mohit | B15: Nationwide Group | C15: 9 | D15: Carrier | E15: 17992806000 | F15: -0.008 | G15: 9 | H15: 9 | I15: US | J15: 94 | K15: Named | L15: Mohit | M15: Kirt Walker | N15: Mark Thresher | O15: Klaus Diem | P15: Sandra Rich | Q15: Mark Berven | R15: James Fowler | T15: Yes | U15: CTS, Genpact | V15: Mid 2021, 2022 | W15: ITP1 | AG15: =IF(E15="","",IF(E15>='Reference Tab - Do not Delete'!$E$35,'Reference Tab - Do not Delete'!$D$35,IF(AND(E15>='Reference Tab - Do not Delete'!$E$36,E15<'Reference Tab - Do not Delete'!$E$35),'Reference Tab - Do not Delete'!$D$36,IF(AND(E15>='Reference Tab - Do not Delete'!$E$37,E15<'Reference Tab - Do not Delete'!$E$36),'Reference Tab - Do not Delete'!$D$37,IF(AND(E15>='Reference Tab - Do not Delete'!$E$38,E15<'Reference Tab - Do not Delete'!$E$37),'Reference Tab - Do not Delete'!$D$38,'Reference Tab - Do not Delete'!$D$39))))) -> $50B - $B | AH15: =IF(H15="","DNA",IF(H15<=10,"Top 10",IF(AND(H15<=25,H15>10),"11 - 25",IF(AND(H15<=50,H15>25),"26 - 50","Above 50")))) -> Top 10 | AI15: =IF(AJ15>0,"Yes","") | AJ15: 0
B16: Amer Intl Group | C16: 10 | D16: Carrier | E16: 14825888000 | F16: 0.015 | G16: 10 | H16: 10 | I16: US | T16: Yes | U16: CTS | W16: ITP2 | AG16: =IF(E16="","",IF(E16>='Reference Tab - Do not Delete'!$E$35,'Reference Tab - Do not Delete'!$D$35,IF(AND(E16>='Reference Tab - Do not Delete'!$E$36,E16<'Reference Tab - Do not Delete'!$E$35),'Reference Tab - Do not Delete'!$D$36,IF(AND(E16>='Reference Tab - Do not Delete'!$E$37,E16<'Reference Tab - Do not Delete'!$E$36),'Reference Tab - Do not Delete'!$D$37,IF(AND(E16>='Reference Tab - Do not Delete'!$E$38,E16<'Reference Tab - Do not Delete'!$E$37),'Reference Tab - Do not Delete'!$D$38,'Reference Tab - Do not Delete'!$D$39))))) -> $50B - $B | AH16: =IF(H16="","DNA",IF(H16<=10,"Top 10",IF(AND(H16<=25,H16>10),"11 - 25",IF(AND(H16<=50,H16>25),"26 - 50","Above 50")))) -> Top 10 | AI16: =IF(AJ16>0,"Yes","") | AJ16: 0
A17: Sean | B17: Farmers Ins Group | C17: 11 | D17: Carrier | E17: 14483557000 | F17: 0.033 | G17: 11 | H17: 11 | I17: US | K17: Named | L17: Sean | M17: Jeff Dailey | N17: Scott Lindquist | P17: Rob Howard | R17: Paul Wilson | T17: Yes | W17: ITP3 | AG17: =IF(E17="","",IF(E17>='Reference Tab - Do not Delete'!$E$35,'Reference Tab - Do not Delete'!$D$35,IF(AND(E17>='Reference Tab - Do not Delete'!$E$36,E17<'Reference Tab - Do not Delete'!$E$35),'Reference Tab - Do not Delete'!$D$36,IF(AND(E17>='Reference Tab - Do not Delete'!$E$37,E17<'Reference Tab - Do not Delete'!$E$36),'Reference Tab - Do not Delete'!$D$37,IF(AND(E17>='Reference Tab - Do not Delete'!$E$38,E17<'Reference Tab - Do not Delete'!$E$37),'Reference Tab - Do not Delete'!$D$38,'Reference Tab - Do not Delete'!$D$39))))) -> $50B - $B | AH17: =IF(H17="","DNA",IF(H17<=10,"Top 10",IF(AND(H17<=25,H17>10),"11 - 25",IF(AND(H17<=50,H17>25),"26 - 50","Above 50")))) -> 11 - 25 | AI17: =IF(AJ17>0,"Yes","") -> Yes | AJ17: 3745787.8
A18: Saju | B18: Hartford Ins Group | C18: 12 | D18: Carrier | E18: 11871251000 | F18: 0.032 | G18: 12 | H18: 12 | I18: US | J18: 94 | K18: Strategic | L18: Kuldeep | M18: Chris Swift | N18: Beth Costello | O18: Robert Paiano | P18: John Kinney | Q18: Bill Bloom | R18: Bill Bloom | S18: Ross Fisher | T18: Yes | U18: CTS | V18: 45627 | W18: ITP2 | AG18: =IF(E18="","",IF(E18>='Reference Tab - Do not Delete'!$E$35,'Reference Tab - Do not Delete'!$D$35,IF(AND(E18>='Reference Tab - Do not Delete'!$E$36,E18<'Reference Tab - Do not Delete'!$E$35),'Reference Tab - Do not Delete'!$D$36,IF(AND(E18>='Reference Tab - Do not Delete'!$E$37,E18<'Reference Tab - Do not Delete'!$E$36),'Reference Tab - Do not Delete'!$D$37,IF(AND(E18>='Reference Tab - Do not Delete'!$E$38,E18<'Reference Tab - Do not Delete'!$E$37),'Reference Tab - Do not Delete'!$D$38,'Reference Tab - Do not Delete'!$D$39))))) -> $50B - $B | AH18: =IF(H18="","DNA",IF(H18<=10,"Top 10",IF(AND(H18<=25,H18>10),"11 - 25",IF(AND(H18<=50,H18>25),"26 - 50","Above 50")))) -> 11 - 25 | AI18: =IF(AJ18>0,"Yes","") -> Yes | AJ18: 18364859 | AK18: Medium | AL18: Yes
A19: Sean | B19: Amer Family Ins Group | C19: 13 | D19: Carrier | E19: 11841650000 | F19: 0.043 | G19: 13 | H19: 13 | I19: US | J19: 105.7 | K19: Named | L19: Sean | M19: Jack Charles Salzwedel | N19: Dan Kelly | O19: Joseph Gates | P19: Scott Little | R19: Kristen Kirkconnel | T19: Yes | W19: ITP3 | AG19: =IF(E19="","",IF(E19>='Reference Tab - Do not Delete'!$E$35,'Reference Tab - Do not Delete'!$D$35,IF(AND(E19>='Reference Tab - Do not Delete'!$E$36,E19<'Reference Tab - Do not Delete'!$E$35),'Reference Tab - Do not Delete'!$D$36,IF(AND(E19>='Reference Tab - Do not Delete'!$E$37,E19<'Reference Tab - Do not Delete'!$E$36),'Reference Tab - Do not Delete'!$D$37,IF(AND(E19>='Reference Tab - Do not Delete'!$E$38,E19<'Reference Tab - Do not Delete'!$E$37),'Reference Tab - Do not Delete'!$D$38,'Reference Tab - Do not Delete'!$D$39))))) -> $50B - $B | AH19: =IF(H19="","DNA",IF(H19<=10,"Top 10",IF(AND(H19<=25,H19>10),"11 - 25",IF(AND(H19<=50,H19>25),"26 - 50","Above 50")))) -> 11 - 25 | AI19: =IF(AJ19>0,"Yes","") -> Yes | AJ19: 7000
B20: Auto-Owners Ins Group | C20: 14 | D20: Carrier | E20: 8585830000 | F20: 0.074 | G20: 14 | H20: 14 | I20: US | AG20: =IF(E20="","",IF(E20>='Reference Tab - Do not Delete'!$E$35,'Reference Tab - Do not Delete'!$D$35,IF(AND(E20>='Reference Tab - Do not Delete'!$E$36,E20<'Reference Tab - Do not Delete'!$E$35),'Reference Tab - Do not Delete'!$D$36,IF(AND(E20>='Reference Tab - Do not Delete'!$E$37,E20<'Reference Tab - Do not Delete'!$E$36),'Reference Tab - Do not Delete'!$D$37,IF(AND(E20>='Reference Tab - Do not Delete'!$E$38,E20<'Reference Tab - Do not Delete'!$E$37),'Reference Tab - Do not Delete'!$D$38,'Reference Tab - Do not Delete'!$D$39))))) -> $50B - $B | AH20: =IF(H20="","DNA",IF(H20<=10,"Top 10",IF(AND(H20<=25,H20>10),"11 - 25",IF(AND(H20<=50,H20>25),"26 - 50","Above 50")))) -> 11 - 25 | AI20: =IF(AJ20>0,"Yes","") -> Yes | AJ20: 1000
B21: Fairfax Financial (USA) Group | C21: 15 | D21: Carrier | E21: 7632626000 | F21: 0.098 | G21: 15 | H21: 17 | I21: US | W21: ITP1 | AG21: =IF(E21="","",IF(E21>='Reference Tab - Do not Delete'!$E$35,'Reference Tab - Do not Delete'!$D$35,IF(AND(E21>='Reference Tab - Do not Delete'!$E$36,E21<'Reference Tab - Do not Delete'!$E$35),'Reference Tab - Do not Delete'!$D$36,IF(AND(E21>='Reference Tab - Do not Delete'!$E$37,E21<'Reference Tab - Do not Delete'!$E$36),'Reference Tab - Do not Delete'!$D$37,IF(AND(E21>='Reference Tab - Do not Delete'!$E$38,E21<'Reference Tab - Do not Delete'!$E$37),'Reference Tab - Do not Delete'!$D$38,'Reference Tab - Do not Delete'!$D$39))))) -> $50B - $B | AH21: =IF(H21="","DNA",IF(H21<=10,"Top 10",IF(AND(H21<=25,H21>10),"11 - 25",IF(AND(H21<=50,H21>25),"26 - 50","Above 50")))) -> 11 - 25 | AI21: =IF(AJ21>0,"Yes","") | AJ21: 0
B22: Erle Ins Group | C22: 16 | D22: Carrier | E22: 7478390000 | F22: 0.055 | G22: 16 | H22: 16 | I22: US | W22: ITP2 | AG22: =IF(E22="","",IF(E22>='Reference Tab - Do not Delete'!$E$35,'Reference Tab - Do not Delete'!$D$35,IF(AND(E22>='Reference Tab - Do not Delete'!$E$36,E22<'Reference Tab - Do not Delete'!$E$35),'Reference Tab - Do not Delete'!$D$36,IF(AND(E22>='Reference Tab - Do not Delete'!$E$37,E22<'Reference Tab - Do not Delete'!$E$36),'Reference Tab - Do not Delete'!$D$37,IF(AND(E22>='Reference Tab - Do not Delete'!$E$38,E22<'Reference Tab - Do not Delete'!$E$37),'Reference Tab - Do not Delete'!$D$38,'Reference Tab - Do not Delete'!$D$39))))) -> $50B - $B | AH22: =IF(H22="","DNA",IF(H22<=10,"Top 10",IF(AND(H22<=25,H22>10),"11 - 25",IF(AND(H22<=50,H22>25),"26 - 50","Above 50")))) -> 11 - 25 | AI22: =IF(AJ22>0,"Yes","") | AJ22: 0
B23: Tokio Marina US PC Group | C23: 17 | D23: Carrier | E23: 7083699000 | F23: 0.052 | G23: 17 | H23: 19 | I23: US | W23: ITP3 | AG23: =IF(E23="","",IF(E23>='Reference Tab - Do not Delete'!$E$35,'Reference Tab - Do not Delete'!$D$35,IF(AND(E23>='Reference Tab - Do not Delete'!$E$36,E23<'Reference Tab - Do not Delete'!$E$35),'Reference Tab - Do not Delete'!$D$36,IF(AND(E23>='Reference Tab - Do not Delete'!$E$37,E23<'Reference Tab - Do not Delete'!$E$36),'Reference Tab - Do not Delete'!$D$37,IF(AND(E23>='Reference Tab - Do not Delete'!$E$38,E23<'Reference Tab - Do not Delete'!$E$37),'Reference Tab - Do not Delete'!$D$38,'Reference Tab - Do not Delete'!$D$39))))) -> $50B - $B | AH23: =IF(H23="","DNA",IF(H23<=10,"Top 10",IF(AND(H23<=25,H23>10),"11 - 25",IF(AND(H23<=50,H23>25),"26 - 50","Above 50")))) -> 11 - 25 | AI23: =IF(AJ23>0,"Yes","") -> Yes | AJ23: 300
A24: Saju | B24: CNA Ins Cos | C24: 18 | D24: Carrier | E24: 6953530000 | F24: 0.059 | G24: 18 | H24: 20 | I24: US | J24: 94.8 | K24: Strategic | L24: Roopak | M24: Dino Robusto | N24: Al Miralles | P24: Daniel Franzetti | Q24: Kevin Leidwinger | R24: Michael Costonis | S24: Douglas M. Worman | T24: Yes | V24: 44562 | AG24: =IF(E24="","",IF(E24>='Reference Tab - Do not Delete'!$E$35,'Reference Tab - Do not Delete'!$D$35,IF(AND(E24>='Reference Tab - Do not Delete'!$E$36,E24<'Reference Tab - Do not Delete'!$E$35),'Reference Tab - Do not Delete'!$D$36,IF(AND(E24>='Reference Tab - Do not Delete'!$E$37,E24<'Reference Tab - Do not Delete'!$E$36),'Reference Tab - Do not Delete'!$D$37,IF(AND(E24>='Reference Tab - Do not Delete'!$E$38,E24<'Reference Tab - Do not Delete'!$E$37),'Reference Tab - Do not Delete'!$D$38,'Reference Tab - Do not Delete'!$D$39))))) -> $50B - $B | AH24: =IF(H24="","DNA",IF(H24<=10,"Top 10",IF(AND(H24<=25,H24>10),"11 - 25",IF(AND(H24<=50,H24>25),"26 - 50","Above 50")))) -> 11 - 25 | AI24: =IF(AJ24>0,"Yes","") -> Yes | AJ24: 11816240 | AK24: Medium | AL24: Yes
A25: Mohit | B25: Munich-Amer Hldg Corp Cos | C25: 19 | D25: Carrier | E25: 6639450000 | F25: -0.025 | G25: 19 | H25: 18 | I25: US | J25: 101 | K25: Named | L25: Mohit | M25: Dave Brune | N25: Oliver J. Horbelt/Angela Homm | O25: Catherine Smith | P25: JannaLyn Allen | Q25: Anita Kuchma | R25: Phil Roeper | T25: Yes | U25: Wipro,Capgemini | V25: Sep, 2022 (with Wipro) and 23rd July 2020 with Capgemini | W25: ITP1 | AG25: =IF(E25="","",IF(E25>='Reference Tab - Do not Delete'!$E$35,'Reference Tab - Do not Delete'!$D$35,IF(AND(E25>='Reference Tab - Do not Delete'!$E$36,E25<'Reference Tab - Do not Delete'!$E$35),'Reference Tab - Do not Delete'!$D$36,IF(AND(E25>='Reference Tab - Do not Delete'!$E$37,E25<'Reference Tab - Do not Delete'!$E$36),'Reference Tab - Do not Delete'!$D$37,IF(AND(E25>='Reference Tab - Do not Delete'!$E$38,E25<'Reference Tab - Do not Delete'!$E$37),'Reference Tab - Do not Delete'!$D$38,'Reference Tab - Do not Delete'!$D$39))))) -> $50B - $B | AH25: =IF(H25="","DNA",IF(H25<=10,"Top 10",IF(AND(H25<=25,H25>10),"11 - 25",IF(AND(H25<=50,H25>25),"26 - 50","Above 50")))) -> 11 - 25 | AI25: =IF(AJ25>0,"Yes","") | AJ25: 0
B26: W. R. Berkley Ins Group | C26: 20 | D26: Carrier | E26: 6131338000 | F26: 0.071 | G26: 20 | H26: 21 | I26: US | W26: ITP2 | AG26: =IF(E26="","",IF(E26>='Reference Tab - Do not Delete'!$E$35,'Reference Tab - Do not Delete'!$D$35,IF(AND(E26>='Reference Tab - Do not Delete'!$E$36,E26<'Reference Tab - Do not Delete'!$E$35),'Reference Tab - Do not Delete'!$D$36,IF(AND(E26>='Reference Tab - Do not Delete'!$E$37,E26<'Reference Tab - Do not Delete'!$E$36),'Reference Tab - Do not Delete'!$D$37,IF(AND(E26>='Reference Tab - Do not Delete'!$E$38,E26<'Reference Tab - Do not Delete'!$E$37),'Reference Tab - Do not Delete'!$D$38,'Reference Tab - Do not Delete'!$D$39))))) -> $50B - $B | AH26: =IF(H26="","DNA",IF(H26<=10,"Top 10",IF(AND(H26<=25,H26>10),"11 - 25",IF(AND(H26<=50,H26>25),"26 - 50","Above 50")))) -> 11 - 25 | AI26: =IF(AJ26>0,"Yes","") | AJ26: 0
A27: Sean | B27: Everest Re US Group | C27: 21 | D27: Carrier | E27: 5797634000 | F27: 0.148 | G27: 21 | H27: 22 | I27: US | J27: 88.7 | K27: Named | L27: Sean | M27: Mike Karmilowicz | N27: Dana Lodge | O27: Bill Thygeson, CAO | P27: Patricia Mcmahon | Q27: Mike Mulray | R27: Owen Williams | S27: Open | T27: Yes | U27: None | V27: 2023 | AG27: =IF(E27="","",IF(E27>='Reference Tab - Do not Delete'!$E$35,'Reference Tab - Do not Delete'!$D$35,IF(AND(E27>='Reference Tab - Do not Delete'!$E$36,E27<'Reference Tab - Do not Delete'!$E$35),'Reference Tab - Do not Delete'!$D$36,IF(AND(E27>='Reference Tab - Do not Delete'!$E$37,E27<'Reference Tab - Do not Delete'!$E$36),'Reference Tab - Do not Delete'!$D$37,IF(AND(E27>='Reference Tab - Do not Delete'!$E$38,E27<'Reference Tab - Do not Delete'!$E$37),'Reference Tab - Do not Delete'!$D$38,'Reference Tab - Do not Delete'!$D$39))))) -> $50B - $B | AH27: =IF(H27="","DNA",IF(H27<=10,"Top 10",IF(AND(H27<=25,H27>10),"11 - 25",IF(AND(H27<=50,H27>25),"26 - 50","Above 50")))) -> 11 - 25 | AI27: =IF(AJ27>0,"Yes","") -> Yes | AJ27: 1214372.9
B28: Cincinnati Ins Cos | C28: 22 | D28: Carrier | E28: 5379896000 | F28: 0.069 | G28: 22 | H28: 23 | I28: US | AG28: =IF(E28="","",IF(E28>='Reference Tab - Do not Delete'!$E$35,'Reference Tab - Do not Delete'!$D$35,IF(AND(E28>='Reference Tab - Do not Delete'!$E$36,E28<'Reference Tab - Do not Delete'!$E$35),'Reference Tab - Do not Delete'!$D$36,IF(AND(E28>='Reference Tab - Do not Delete'!$E$37,E28<'Reference Tab - Do not Delete'!$E$36),'Reference Tab - Do not Delete'!$D$37,IF(AND(E28>='Reference Tab - Do not Delete'!$E$38,E28<'Reference Tab - Do not Delete'!$E$37),'Reference Tab - Do not Delete'!$D$38,'Reference Tab - Do not Delete'!$D$39))))) -> $50B - $B | AH28: =IF(H28="","DNA",IF(H28<=10,"Top 10",IF(AND(H28<=25,H28>10),"11 - 25",IF(AND(H28<=50,H28>25),"26 - 50","Above 50")))) -> 11 - 25 | AI28: =IF(AJ28>0,"Yes","") | AJ28: 0
B29: Alleghany Corp Group | C29: 23 | D29: Carrier | E29: 5344634000 | F29: 0.145 | G29: 23 | H29: 24 | I29: US | W29: ITP1 | AG29: =IF(E29="","",IF(E29>='Reference Tab - Do not Delete'!$E$35,'Reference Tab - Do not Delete'!$D$35,IF(AND(E29>='Reference Tab - Do not Delete'!$E$36,E29<'Reference Tab - Do not Delete'!$E$35),'Reference Tab - Do not Delete'!$D$36,IF(AND(E29>='Reference Tab - Do not Delete'!$E$37,E29<'Reference Tab - Do not Delete'!$E$36),'Reference Tab - Do not Delete'!$D$37,IF(AND(E29>='Reference Tab - Do not Delete'!$E$38,E29<'Reference Tab - Do not Delete'!$E$37),'Reference Tab - Do not Delete'!$D$38,'Reference Tab - Do not Delete'!$D$39))))) -> $50B - $B | AH29: =IF(H29="","DNA",IF(H29<=10,"Top 10",IF(AND(H29<=25,H29>10),"11 - 25",IF(AND(H29<=50,H29>25),"26 - 50","Above 50")))) -> 11 - 25 | AI29: =IF(AJ29>0,"Yes","") | AJ29: 0
A30: Sean | B30: Great Amer P&C Ins Group | C30: 24 | D30: Carrier | E30: 4689656000 | F30: 0.079 | G30: 24 | H30: 26 | I30: US | J30: 93.7 | K30: Named | L30: Sean | M30: Carl Lindnor, Craig Lindnor | N30: Jeff Consolino | Q30: Gary Gruber | R30: Chad Stewart | T30: Yes | W30: ITP3 | AG30: =IF(E30="","",IF(E30>='Reference Tab - Do not Delete'!$E$35,'Reference Tab - Do not Delete'!$D$35,IF(AND(E30>='Reference Tab - Do not Delete'!$E$36,E30<'Reference Tab - Do not Delete'!$E$35),'Reference Tab - Do not Delete'!$D$36,IF(AND(E30>='Reference Tab - Do not Delete'!$E$37,E30<'Reference Tab - Do not Delete'!$E$36),'Reference Tab - Do not Delete'!$D$37,IF(AND(E30>='Reference Tab - Do not Delete'!$E$38,E30<'Reference Tab - Do not Delete'!$E$37),'Reference Tab - Do not Delete'!$D$38,'Reference Tab - Do not Delete'!$D$39))))) -> $50B - $B | AH30: =IF(H30="","DNA",IF(H30<=10,"Top 10",IF(AND(H30<=25,H30>10),"11 - 25",IF(AND(H30<=50,H30>25),"26 - 50","Above 50")))) -> 26 - 50 | AI30: =IF(AJ30>0,"Yes","") | AJ30: 0
A31: Saju | B31: Hanover Ins Group Prop & Cas Cos | C31: 25 | D31: Carrier | E31: 4580867000 | F31: 0.042 | G31: 25 | H31: 25 | I31: US | J31: 95.6 | K31: Strategic | L31: Aditya Chaturvedi | M31: John "Jack" Roche | N31: Jeff Farber | O31: Catherine Eska | P31: Mark Welzenbach | Q31: Gayle Falvey - CL Michele Streton - PL | R31: Mark Berthiaume | S31: Chip Hamann (Small Commercial) | T31: Yes | U31: CTS, NTT, PWC | V31: 44531 | AG31: =IF(E31="","",IF(E31>='Reference Tab - Do not Delete'!$E$35,'Reference Tab - Do not Delete'!$D$35,IF(AND(E31>='Reference Tab - Do not Delete'!$E$36,E31<'Reference Tab - Do not Delete'!$E$35),'Reference Tab - Do not Delete'!$D$36,IF(AND(E31>='Reference Tab - Do not Delete'!$E$37,E31<'Reference Tab - Do not Delete'!$E$36),'Reference Tab - Do not Delete'!$D$37,IF(AND(E31>='Reference Tab - Do not Delete'!$E$38,E31<'Reference Tab - Do not Delete'!$E$37),'Reference Tab - Do not Delete'!$D$38,'Reference Tab - Do not Delete'!$D$39))))) -> $50B - $B | AH31: =IF(H31="","DNA",IF(H31<=10,"Top 10",IF(AND(H31<=25,H31>10),"11 - 25",IF(AND(H31<=50,H31>25),"26 - 50","Above 50")))) -> 11 - 25 | AI31: =IF(AJ31>0,"Yes","") -> Yes | AJ31: 12214610 | AK31: Medium | AL31: Yes
B32: Auto Club Enterprises Ins Group | C32: 26 | D32: Carrier | E32: 4546591000 | F32: 0.053 | G32: 26 | H32: 27 | I32: US | AG32: =IF(E32="","",IF(E32>='Reference Tab - Do not Delete'!$E$35,'Reference Tab - Do not Delete'!$D$35,IF(AND(E32>='Reference Tab - Do not Delete'!$E$36,E32<'Reference Tab - Do not Delete'!$E$35),'Reference Tab - Do not Delete'!$D$36,IF(AND(E32>='Reference Tab - Do not Delete'!$E$37,E32<'Reference Tab - Do not Delete'!$E$36),'Reference Tab - Do not Delete'!$D$37,IF(AND(E32>='Reference Tab - Do not Delete'!$E$38,E32<'Reference Tab - Do not Delete'!$E$37),'Reference Tab - Do not Delete'!$D$38,'Reference Tab - Do not Delete'!$D$39))))) -> $50B - $B | AH32: =IF(H32="","DNA",IF(H32<=10,"Top 10",IF(AND(H32<=25,H32>10),"11 - 25",IF(AND(H32<=50,H32>25),"26 - 50","Above 50")))) -> 26 - 50 | AI32: =IF(AJ32>0,"Yes","") | AJ32: 0
B33: Allianz US PC Ins Companies | C33: 27 | D33: Carrier | E33: 4091021000 | F33: 0.536 | G33: 27 | H33: 40 | I33: US | W33: ITP1 | AG33: =IF(E33="","",IF(E33>='Reference Tab - Do not Delete'!$E$35,'Reference Tab - Do not Delete'!$D$35,IF(AND(E33>='Reference Tab - Do not Delete'!$E$36,E33<'Reference Tab - Do not Delete'!$E$35),'Reference Tab - Do not Delete'!$D$36,IF(AND(E33>='Reference Tab - Do not Delete'!$E$37,E33<'Reference Tab - Do not Delete'!$E$36),'Reference Tab - Do not Delete'!$D$37,IF(AND(E33>='Reference Tab - Do not Delete'!$E$38,E33<'Reference Tab - Do not Delete'!$E$37),'Reference Tab - Do not Delete'!$D$38,'Reference Tab - Do not Delete'!$D$39))))) -> $50B - $B | AH33: =IF(H33="","DNA",IF(H33<=10,"Top 10",IF(AND(H33<=25,H33>10),"11 - 25",IF(AND(H33<=50,H33>25),"26 - 50","Above 50")))) -> 26 - 50 | AI33: =IF(AJ33>0,"Yes","") | AJ33: 0
A34: Roopak | B34: Kemper PC Companies | C34: 28 | D34: Carrier | E34: 4042228000 | F34: 0.085 | G34: 28 | H34: 30 | I34: US | J34: 93 | K34: Named | L34: Amit Gaba | M34: Joe Lacher | N34: Jim McKinney | O34: Max Mindak | P34: Kim Leggette | Q34: Duane Sanders | R34: Charles Brooks | T34: Yes | U34: Accenture | V34: 44197 | W34: ITP2 | AG34: =IF(E34="","",IF(E34>='Reference Tab - Do not Delete'!$E$35,'Reference Tab - Do not Delete'!$D$35,IF(AND(E34>='Reference Tab - Do not Delete'!$E$36,E34<'Reference Tab - Do not Delete'!$E$35),'Reference Tab - Do not Delete'!$D$36,IF(AND(E34>='Reference Tab - Do not Delete'!$E$37,E34<'Reference Tab - Do not Delete'!$E$36),'Reference Tab - Do not Delete'!$D$37,IF(AND(E34>='Reference Tab - Do not Delete'!$E$38,E34<'Reference Tab - Do not Delete'!$E$37),'Reference Tab - Do not Delete'!$D$38,'Reference Tab - Do not Delete'!$D$39))))) -> $50B - $B | AH34: =IF(H34="","DNA",IF(H34<=10,"Top 10",IF(AND(H34<=25,H34>10),"11 - 25",IF(AND(H34<=50,H34>25),"26 - 50","Above 50")))) -> 26 - 50 | AI34: =IF(AJ34>0,"Yes","") -> Yes | AJ34: 2825296.4 | AK34: Medium | AL34: Yes
B35: CSAA Ins Group | C35: 29 | D35: Carrier | E35: 4031220000 | F35: 0.015 | G35: 29 | H35: 28 | I35: US | AG35: =IF(E35="","",IF(E35>='Reference Tab - Do not Delete'!$E$35,'Reference Tab - Do not Delete'!$D$35,IF(AND(E35>='Reference Tab - Do not Delete'!$E$36,E35<'Reference Tab - Do not Delete'!$E$35),'Reference Tab - Do not Delete'!$D$36,IF(AND(E35>='Reference Tab - Do not Delete'!$E$37,E35<'Reference Tab - Do not Delete'!$E$36),'Reference Tab - Do not Delete'!$D$37,IF(AND(E35>='Reference Tab - Do not Delete'!$E$38,E35<'Reference Tab - Do not Delete'!$E$37),'Reference Tab - Do not Delete'!$D$38,'Reference Tab - Do not Delete'!$D$39))))) -> $50B - $B | AH35: =IF(H35="","DNA",IF(H35<=10,"Top 10",IF(AND(H35<=25,H35>10),"11 - 25",IF(AND(H35<=50,H35>25),"26 - 50","Above 50")))) -> 26 - 50 | AI35: =IF(AJ35>0,"Yes","") | AJ35: 0
B36: FM Global Group | C36: 30 | D36: Carrier | E36: 4007616000 | F36: 0.104 | G36: 30 | H36: 32 | I36: US | AG36: =IF(E36="","",IF(E36>='Reference Tab - Do not Delete'!$E$35,'Reference Tab - Do not Delete'!$D$35,IF(AND(E36>='Reference Tab - Do not Delete'!$E$36,E36<'Reference Tab - Do not Delete'!$E$35),'Reference Tab - Do not Delete'!$D$36,IF(AND(E36>='Reference Tab - Do not Delete'!$E$37,E36<'Reference Tab - Do not Delete'!$E$36),'Reference Tab - Do not Delete'!$D$37,IF(AND(E36>='Reference Tab - Do not Delete'!$E$38,E36<'Reference Tab - Do not Delete'!$E$37),'Reference Tab - Do not Delete'!$D$38,'Reference Tab - Do not Delete'!$D$39))))) -> $50B - $B | AH36: =IF(H36="","DNA",IF(H36<=10,"Top 10",IF(AND(H36<=25,H36>10),"11 - 25",IF(AND(H36<=50,H36>25),"26 - 50","Above 50")))) -> 26 - 50 | AI36: =IF(AJ36>0,"Yes","") | AJ36: 0
B37: Markel Corp Group | C37: 31 | D37: Carrier | E37: 3809277000 | F37: 0.216 | G37: 31 | H37: 36 | I37: US | AG37: =IF(E37="","",IF(E37>='Reference Tab - Do not Delete'!$E$35,'Reference Tab - Do not Delete'!$D$35,IF(AND(E37>='Reference Tab - Do not Delete'!$E$36,E37<'Reference Tab - Do not Delete'!$E$35),'Reference Tab - Do not Delete'!$D$36,IF(AND(E37>='Reference Tab - Do not Delete'!$E$37,E37<'Reference Tab - Do not Delete'!$E$36),'Reference Tab - Do not Delete'!$D$37,IF(AND(E37>='Reference Tab - Do not Delete'!$E$38,E37<'Reference Tab - Do not Delete'!$E$37),'Reference Tab - Do not Delete'!$D$38,'Reference Tab - Do not Delete'!$D$39))))) -> $50B - $B | AH37: =IF(H37="","DNA",IF(H37<=10,"Top 10",IF(AND(H37<=25,H37>10),"11 - 25",IF(AND(H37<=50,H37>25),"26 - 50","Above 50")))) -> 26 - 50 | AI37: =IF(AJ37>0,"Yes","") | AJ37: 0
B38: MetLife Auto & Home Group | C38: 32 | D38: Carrier | E38: 3797476000 | F38: 0.02 | G38: 32 | H38: 31 | I38: US | W38: ITP1 | AG38: =IF(E38="","",IF(E38>='Reference Tab - Do not Delete'!$E$35,'Reference Tab - Do not Delete'!$D$35,IF(AND(E38>='Reference Tab - Do not Delete'!$E$36,E38<'Reference Tab - Do not Delete'!$E$35),'Reference Tab - Do not Delete'!$D$36,IF(AND(E38>='Reference Tab - Do not Delete'!$E$37,E38<'Reference Tab - Do not Delete'!$E$36),'Reference Tab - Do not Delete'!$D$37,IF(AND(E38>='Reference Tab - Do not Delete'!$E$38,E38<'Reference Tab - Do not Delete'!$E$37),'Reference Tab - Do not Delete'!$D$38,'Reference Tab - Do not Delete'!$D$39))))) -> $50B - $B | AH38: =IF(H38="","DNA",IF(H38<=10,"Top 10",IF(AND(H38<=25,H38>10),"11 - 25",IF(AND(H38<=50,H38>25),"26 - 50","Above 50")))) -> 26 - 50 | AI38: =IF(AJ38>0,"Yes","") -> Yes | AJ38: 2433250
B39: Mercury Gen Group | C39: 33 | D39: Carrier | E39: 3690508000 | F39: 0.067 | G39: 33 | H39: 34 | I39: US | W39: ITP3 | AG39: =IF(E39="","",IF(E39>='Reference Tab - Do not Delete'!$E$35,'Reference Tab - Do not Delete'!$D$35,IF(AND(E39>='Reference Tab - Do not Delete'!$E$36,E39<'Reference Tab - Do not Delete'!$E$35),'Reference Tab - Do not Delete'!$D$36,IF(AND(E39>='Reference Tab - Do not Delete'!$E$37,E39<'Reference Tab - Do not Delete'!$E$36),'Reference Tab - Do not Delete'!$D$37,IF(AND(E39>='Reference Tab - Do not Delete'!$E$38,E39<'Reference Tab - Do not Delete'!$E$37),'Reference Tab - Do not Delete'!$D$38,'Reference Tab - Do not Delete'!$D$39))))) -> $50B - $B | AH39: =IF(H39="","DNA",IF(H39<=10,"Top 10",IF(AND(H39<=25,H39>10),"11 - 25",IF(AND(H39<=50,H39>25),"26 - 50","Above 50")))) -> 26 - 50 | AI39: =IF(AJ39>0,"Yes","") | AJ39: 0
A40: Roopak | B40: Zurich Ins US PC Group | C40: 34 | D40: Carrier | E40: 3657532000 | F40: -0.067 | G40: 34 | H40: 29 | I40: US | J40: 96.4 | K40: Strategic | L40: Raish Malik | M40: Kathleen Savio | N40: Peter Hirs | O40: Colleen Zitt | P40: Paul Lavelle | Q40: Anurag Batta | R40: Mark Knipfer | S40: Brandin Fick | T40: Yes | U40: CTS, Genpact, Mphasis,Hinduja | V40: 44562 | AG40: =IF(E40="","",IF(E40>='Reference Tab - Do not Delete'!$E$35,'Reference Tab - Do not Delete'!$D$35,IF(AND(E40>='Reference Tab - Do not Delete'!$E$36,E40<'Reference Tab - Do not Delete'!$E$35),'Reference Tab - Do not Delete'!$D$36,IF(AND(E40>='Reference Tab - Do not Delete'!$E$37,E40<'Reference Tab - Do not Delete'!$E$36),'Reference Tab - Do not Delete'!$D$37,IF(AND(E40>='Reference Tab - Do not Delete'!$E$38,E40<'Reference Tab - Do not Delete'!$E$37),'Reference Tab - Do not Delete'!$D$38,'Reference Tab - Do not Delete'!$D$39))))) -> $50B - $B | AH40: =IF(H40="","DNA",IF(H40<=10,"Top 10",IF(AND(H40<=25,H40>10),"11 - 25",IF(AND(H40<=50,H40>25),"26 - 50","Above 50")))) -> 26 - 50 | AI40: =IF(AJ40>0,"Yes","") -> Yes | AJ40: 16435351 | AK40: Medium | AL40: Yes
A41: Roopak | B41: Assurant US PC Companies | C41: 35 | D41: Carrier | E41: 3000087000 | F41: -0.067 | G41: 35 | H41: 35 | I41: US | K41: Strategic | L41: Dushyant | AG41: =IF(E41="","",IF(E41>='Reference Tab - Do not Delete'!$E$35,'Reference Tab - Do not Delete'!$D$35,IF(AND(E41>='Reference Tab - Do not Delete'!$E$36,E41<'Reference Tab - Do not Delete'!$E$35),'Reference Tab - Do not Delete'!$D$36,IF(AND(E41>='Reference Tab - Do not Delete'!$E$37,E41<'Reference Tab - Do not Delete'!$E$36),'Reference Tab - Do not Delete'!$D$37,IF(AND(E41>='Reference Tab - Do not Delete'!$E$38,E41<'Reference Tab - Do not Delete'!$E$37),'Reference Tab - Do not Delete'!$D$38,'Reference Tab - Do not Delete'!$D$39))))) -> $50B - $B | AH41: =IF(H41="","DNA",IF(H41<=10,"Top 10",IF(AND(H41<=25,H41>10),"11 - 25",IF(AND(H41<=50,H41>25),"26 - 50","Above 50")))) -> 26 - 50 | AI41: =IF(AJ41>0,"Yes","") -> Yes | AJ41: 1064018.1
B42: QBE North America Ins Group | C42: 36 | D42: Carrier | E42: 2937088000 | F42: 0.048 | G42: 36 | H42: 38 | I42: US | T42: Yes | AG42: =IF(E42="","",IF(E42>='Reference Tab - Do not Delete'!$E$35,'Reference Tab - Do not Delete'!$D$35,IF(AND(E42>='Reference Tab - Do not Delete'!$E$36,E42<'Reference Tab - Do not Delete'!$E$35),'Reference Tab - Do not Delete'!$D$36,IF(AND(E42>='Reference Tab - Do not Delete'!$E$37,E42<'Reference Tab - Do not Delete'!$E$36),'Reference Tab - Do not Delete'!$D$37,IF(AND(E42>='Reference Tab - Do not Delete'!$E$38,E42<'Reference Tab - Do not Delete'!$E$37),'Reference Tab - Do not Delete'!$D$38,'Reference Tab - Do not Delete'!$D$39))))) -> $50B - $B | AH42: =IF(H42="","DNA",IF(H42<=10,"Top 10",IF(AND(H42<=25,H42>10),"11 - 25",IF(AND(H42<=50,H42>25),"26 - 50","Above 50")))) -> 26 - 50 | AI42: =IF(AJ42>0,"Yes","") -> Yes | AJ42: 585523.87
B43: Arch Ins Group | C43: 37 | D43: Carrier | E43: 2908209000 | F43: -0.002 | G43: 37 | H43: 37 | I43: US | AG43: =IF(E43="","",IF(E43>='Reference Tab - Do not Delete'!$E$35,'Reference Tab - Do not Delete'!$D$35,IF(AND(E43>='Reference Tab - Do not Delete'!$E$36,E43<'Reference Tab - Do not Delete'!$E$35),'Reference Tab - Do not Delete'!$D$36,IF(AND(E43>='Reference Tab - Do not Delete'!$E$37,E43<'Reference Tab - Do not Delete'!$E$36),'Reference Tab - Do not Delete'!$D$37,IF(AND(E43>='Reference Tab - Do not Delete'!$E$38,E43<'Reference Tab - Do not Delete'!$E$37),'Reference Tab - Do not Delete'!$D$38,'Reference Tab - Do not Delete'!$D$39))))) -> $50B - $B | AH43: =IF(H43="","DNA",IF(H43<=10,"Top 10",IF(AND(H43<=25,H43>10),"11 - 25",IF(AND(H43<=50,H43>25),"26 - 50","Above 50")))) -> 26 - 50 | AI43: =IF(AJ43>0,"Yes","") | AJ43: 0
B44: Selective Ins Group | C44: 38 | D44: Carrier | E44: 2679424000 | F44: 0.066 | G44: 38 | H44: 41 | I44: US | AG44: =IF(E44="","",IF(E44>='Reference Tab - Do not Delete'!$E$35,'Reference Tab - Do not Delete'!$D$35,IF(AND(E44>='Reference Tab - Do not Delete'!$E$36,E44<'Reference Tab - Do not Delete'!$E$35),'Reference Tab - Do not Delete'!$D$36,IF(AND(E44>='Reference Tab - Do not Delete'!$E$37,E44<'Reference Tab - Do not Delete'!$E$36),'Reference Tab - Do not Delete'!$D$37,IF(AND(E44>='Reference Tab - Do not Delete'!$E$38,E44<'Reference Tab - Do not Delete'!$E$37),'Reference Tab - Do not Delete'!$D$38,'Reference Tab - Do not Delete'!$D$39))))) -> $50B - $B | AH44: =IF(H44="","DNA",IF(H44<=10,"Top 10",IF(AND(H44<=25,H44>10),"11 - 25",IF(AND(H44<=50,H44>25),"26 - 50","Above 50")))) -> 26 - 50 | AI44: =IF(AJ44>0,"Yes","") | AJ44: 0
B45: Old Republic Ins Group | C45: 39 | D45: Carrier | E45: 2670167000 | F45: -0.01 | G45: 39 | H45: 39 | I45: US | AG45: =IF(E45="","",IF(E45>='Reference Tab - Do not Delete'!$E$35,'Reference Tab - Do not Delete'!$D$35,IF(AND(E45>='Reference Tab - Do not Delete'!$E$36,E45<'Reference Tab - Do not Delete'!$E$35),'Reference Tab - Do not Delete'!$D$36,IF(AND(E45>='Reference Tab - Do not Delete'!$E$37,E45<'Reference Tab - Do not Delete'!$E$36),'Reference Tab - Do not Delete'!$D$37,IF(AND(E45>='Reference Tab - Do not Delete'!$E$38,E45<'Reference Tab - Do not Delete'!$E$37),'Reference Tab - Do not Delete'!$D$38,'Reference Tab - Do not Delete'!$D$39))))) -> $50B - $B | AH45: =IF(H45="","DNA",IF(H45<=10,"Top 10",IF(AND(H45<=25,H45>10),"11 - 25",IF(AND(H45<=50,H45>25),"26 - 50","Above 50")))) -> 26 - 50 | AI45: =IF(AJ45>0,"Yes","") | AJ45: 0
B46: COUNTRY Financial PC Group | C46: 40 | D46: Carrier | E46: 2564827000 | F46: 0.069 | G46: 40 | H46: 44 | I46: US | AG46: =IF(E46="","",IF(E46>='Reference Tab - Do not Delete'!$E$35,'Reference Tab - Do not Delete'!$D$35,IF(AND(E46>='Reference Tab - Do not Delete'!$E$36,E46<'Reference Tab - Do not Delete'!$E$35),'Reference Tab - Do not Delete'!$D$36,IF(AND(E46>='Reference Tab - Do not Delete'!$E$37,E46<'Reference Tab - Do not Delete'!$E$36),'Reference Tab - Do not Delete'!$D$37,IF(AND(E46>='Reference Tab - Do not Delete'!$E$38,E46<'Reference Tab - Do not Delete'!$E$37),'Reference Tab - Do not Delete'!$D$38,'Reference Tab - Do not Delete'!$D$39))))) -> $50B - $B | AH46: =IF(H46="","DNA",IF(H46<=10,"Top 10",IF(AND(H46<=25,H46>10),"11 - 25",IF(AND(H46<=50,H46>25),"26 - 50","Above 50")))) -> 26 - 50 | AI46: =IF(AJ46>0,"Yes","") | AJ46: 0
B47: Natl Gen Companies | C47: 41 | D47: Carrier | E47: 2494927000 | F47: 0.113 | G47: 41 | H47: 50 | I47: US | AG47: =IF(E47="","",IF(E47>='Reference Tab - Do not Delete'!$E$35,'Reference Tab - Do not Delete'!$D$35,IF(AND(E47>='Reference Tab - Do not Delete'!$E$36,E47<'Reference Tab - Do not Delete'!$E$35),'Reference Tab - Do not Delete'!$D$36,IF(AND(E47>='Reference Tab - Do not Delete'!$E$37,E47<'Reference Tab - Do not Delete'!$E$36),'Reference Tab - Do not Delete'!$D$37,IF(AND(E47>='Reference Tab - Do not Delete'!$E$38,E47<'Reference Tab - Do not Delete'!$E$37),'Reference Tab - Do not Delete'!$D$38,'Reference Tab - Do not Delete'!$D$39))))) -> $50B - $B | AH47: =IF(H47="","DNA",IF(H47<=10,"Top 10",IF(AND(H47<=25,H47>10),"11 - 25",IF(AND(H47<=50,H47>25),"26 - 50","Above 50")))) -> 26 - 50 | AI47: =IF(AJ47>0,"Yes","") -> Yes | AJ47: 7500
B48: Auto Club Group | C48: 42 | D48: Carrier | E48: 2473773000 | F48: 0.03 | G48: 42 | H48: 43 | I48: US | AG48: =IF(E48="","",IF(E48>='Reference Tab - Do not Delete'!$E$35,'Reference Tab - Do not Delete'!$D$35,IF(AND(E48>='Reference Tab - Do not Delete'!$E$36,E48<'Reference Tab - Do not Delete'!$E$35),'Reference Tab - Do not Delete'!$D$36,IF(AND(E48>='Reference Tab - Do not Delete'!$E$37,E48<'Reference Tab - Do not Delete'!$E$36),'Reference Tab - Do not Delete'!$D$37,IF(AND(E48>='Reference Tab - Do not Delete'!$E$38,E48<'Reference Tab - Do not Delete'!$E$37),'Reference Tab - Do not Delete'!$D$38,'Reference Tab - Do not Delete'!$D$39))))) -> $50B - $B | AH48: =IF(H48="","DNA",IF(H48<=10,"Top 10",IF(AND(H48<=25,H48>10),"11 - 25",IF(AND(H48<=50,H48>25),"26 - 50","Above 50")))) -> 26 - 50 | AI48: =IF(AJ48>0,"Yes","") | AJ48: 0
B49: AXA U.S. Group | C49: 43 | D49: Carrier | E49: 2441804000 | F49: -0.303 | G49: 43 | H49: 33 | I49: US | AG49: =IF(E49="","",IF(E49>='Reference Tab - Do not Delete'!$E$35,'Reference Tab - Do not Delete'!$D$35,IF(AND(E49>='Reference Tab - Do not Delete'!$E$36,E49<'Reference Tab - Do not Delete'!$E$35),'Reference Tab - Do not Delete'!$D$36,IF(AND(E49>='Reference Tab - Do not Delete'!$E$37,E49<'Reference Tab - Do not Delete'!$E$36),'Reference Tab - Do not Delete'!$D$37,IF(AND(E49>='Reference Tab - Do not Delete'!$E$38,E49<'Reference Tab - Do not Delete'!$E$37),'Reference Tab - Do not Delete'!$D$38,'Reference Tab - Do not Delete'!$D$39))))) -> $50B - $B | AH49: =IF(H49="","DNA",IF(H49<=10,"Top 10",IF(AND(H49<=25,H49>10),"11 - 25",IF(AND(H49<=50,H49>25),"26 - 50","Above 50")))) -> 26 - 50 | AI49: =IF(AJ49>0,"Yes","") | AJ49: 0
B50: Sentry Ins Group | C50: 44 | D50: Carrier | E50: 2440418000 | F50: 0.067 | G50: 44 | H50: 47 | I50: US | AG50: =IF(E50="","",IF(E50>='Reference Tab - Do not Delete'!$E$35,'Reference Tab - Do not Delete'!$D$35,IF(AND(E50>='Reference Tab - Do not Delete'!$E$36,E50<'Reference Tab - Do not Delete'!$E$35),'Reference Tab - Do not Delete'!$D$36,IF(AND(E50>='Reference Tab - Do not Delete'!$E$37,E50<'Reference Tab - Do not Delete'!$E$36),'Reference Tab - Do not Delete'!$D$37,IF(AND(E50>='Reference Tab - Do not Delete'!$E$38,E50<'Reference Tab - Do not Delete'!$E$37),'Reference Tab - Do not Delete'!$D$38,'Reference Tab - Do not Delete'!$D$39))))) -> $50B - $B | AH50: =IF(H50="","DNA",IF(H50<=10,"Top 10",IF(AND(H50<=25,H50>10),"11 - 25",IF(AND(H50<=50,H50>25),"26 - 50","Above 50")))) -> 26 - 50 | AI50: =IF(AJ50>0,"Yes","") | AJ50: 0
B51: Amica Mutual Group | C51: 45 | D51: Carrier | E51: 2294966000 | F51: -0.033 | G51: 45 | H51: 45 | I51: US | AG51: =IF(E51="","",IF(E51>='Reference Tab - Do not Delete'!$E$35,'Reference Tab - Do not Delete'!$D$35,IF(AND(E51>='Reference Tab - Do not Delete'!$E$36,E51<'Reference Tab - Do not Delete'!$E$35),'Reference Tab - Do not Delete'!$D$36,IF(AND(E51>='Reference Tab - Do not Delete'!$E$37,E51<'Reference Tab - Do not Delete'!$E$36),'Reference Tab - Do not Delete'!$D$37,IF(AND(E51>='Reference Tab - Do not Delete'!$E$38,E51<'Reference Tab - Do not Delete'!$E$37),'Reference Tab - Do not Delete'!$D$38,'Reference Tab - Do not Delete'!$D$39))))) -> $50B - $B | AH51: =IF(H51="","DNA",IF(H51<=10,"Top 10",IF(AND(H51<=25,H51>10),"11 - 25",IF(AND(H51<=50,H51>25),"26 - 50","Above 50")))) -> 26 - 50 | AI51: =IF(AJ51>0,"Yes","") | AJ51: 0
B52: Sompo Hldgs US Group | C52: 46 | D52: Carrier | E52: 2264197000 | F52: -0.019 | G52: 46 | H52: 46 | I52: US | AG52: =IF(E52="","",IF(E52>='Reference Tab - Do not Delete'!$E$35,'Reference Tab - Do not Delete'!$D$35,IF(AND(E52>='Reference Tab - Do not Delete'!$E$36,E52<'Reference Tab - Do not Delete'!$E$35),'Reference Tab - Do not Delete'!$D$36,IF(AND(E52>='Reference Tab - Do not Delete'!$E$37,E52<'Reference Tab - Do not Delete'!$E$36),'Reference Tab - Do not Delete'!$D$37,IF(AND(E52>='Reference Tab - Do not Delete'!$E$38,E52<'Reference Tab - Do not Delete'!$E$37),'Reference Tab - Do not Delete'!$D$38,'Reference Tab - Do not Delete'!$D$39))))) -> $50B - $B | AH52: =IF(H52="","DNA",IF(H52<=10,"Top 10",IF(AND(H52<=25,H52>10),"11 - 25",IF(AND(H52<=50,H52>25),"26 - 50","Above 50")))) -> 26 - 50 | AI52: =IF(AJ52>0,"Yes","") | AJ52: 0
B53: PartnerRe US Group | C53: 47 | D53: Carrier | E53: 2142127000 | F53: 0.356 | G53: 47 | H53: 57 | I53: US | AG53: =IF(E53="","",IF(E53>='Reference Tab - Do not Delete'!$E$35,'Reference Tab - Do not Delete'!$D$35,IF(AND(E53>='Reference Tab - Do not Delete'!$E$36,E53<'Reference Tab - Do not Delete'!$E$35),'Reference Tab - Do not Delete'!$D$36,IF(AND(E53>='Reference Tab - Do not Delete'!$E$37,E53<'Reference Tab - Do not Delete'!$E$36),'Reference Tab - Do not Delete'!$D$37,IF(AND(E53>='Reference Tab - Do not Delete'!$E$38,E53<'Reference Tab - Do not Delete'!$E$37),'Reference Tab - Do not Delete'!$D$38,'Reference Tab - Do not Delete'!$D$39))))) -> $50B - $B | AH53: =IF(H53="","DNA",IF(H53<=10,"Top 10",IF(AND(H53<=25,H53>10),"11 - 25",IF(AND(H53<=50,H53>25),"26 - 50","Above 50")))) -> Above 50 | AI53: =IF(AJ53>0,"Yes","") | AJ53: 0
B54: AmTrust Group | C54: 48 | D54: Carrier | E54: 2083893000 | F54: -0.165 | G54: 46 | H54: 42 | I54: US | AG54: =IF(E54="","",IF(E54>='Reference Tab - Do not Delete'!$E$35,'Reference Tab - Do not Delete'!$D$35,IF(AND(E54>='Reference Tab - Do not Delete'!$E$36,E54<'Reference Tab - Do not Delete'!$E$35),'Reference Tab - Do not Delete'!$D$36,IF(AND(E54>='Reference Tab - Do not Delete'!$E$37,E54<'Reference Tab - Do not Delete'!$E$36),'Reference Tab - Do not Delete'!$D$37,IF(AND(E54>='Reference Tab - Do not Delete'!$E$38,E54<'Reference Tab - Do not Delete'!$E$37),'Reference Tab - Do not Delete'!$D$38,'Reference Tab - Do not Delete'!$D$39))))) -> $50B - $B | AH54: =IF(H54="","DNA",IF(H54<=10,"Top 10",IF(AND(H54<=25,H54>10),"11 - 25",IF(AND(H54<=50,H54>25),"26 - 50","Above 50")))) -> 26 - 50 | AI54: =IF(AJ54>0,"Yes","") -> Yes | AJ54: 14000
B55: State Auto Ins Cos | C55: 49 | D55: Carrier | E55: 2027918000 | F55: 0.089 | G55: 46 | H55: 54 | I55: US | AG55: =IF(E55="","",IF(E55>='Reference Tab - Do not Delete'!$E$35,'Reference Tab - Do not Delete'!$D$35,IF(AND(E55>='Reference Tab - Do not Delete'!$E$36,E55<'Reference Tab - Do not Delete'!$E$35),'Reference Tab - Do not Delete'!$D$36,IF(AND(E55>='Reference Tab - Do not Delete'!$E$37,E55<'Reference Tab - Do not Delete'!$E$36),'Reference Tab - Do not Delete'!$D$37,IF(AND(E55>='Reference Tab - Do not Delete'!$E$38,E55<'Reference Tab - Do not Delete'!$E$37),'Reference Tab - Do not Delete'!$D$38,'Reference Tab - Do not Delete'!$D$39))))) -> $50B - $B | AH55: =IF(H55="","DNA",IF(H55<=10,"Top 10",IF(AND(H55<=25,H55>10),"11 - 25",IF(AND(H55<=50,H55>25),"26 - 50","Above 50")))) -> Above 50 | AI55: =IF(AJ55>0,"Yes","") | AJ55: 0
A56: Mohit | B56: Swiss Reins Group | C56: 50 | D56: Carrier | E56: 2023929000 | F56: -0.722 | G56: 50 | H56: 15 | I56: US | J56: 107 | K56: Named | L56: Mohit | M56: J.Eric Smith | N56: Brian Rosenblum | O56: Stefanie Stratos | P56: Thomas Hyatte | Q56: Rich Agar | R56: Prashanthi Roy /Pravina Ladva | T56: Yes | U56: CSC, Genpact, TCS | V56: 2021 (They have multiple BPO, automation and analytics partner) | AG56: =IF(E56="","",IF(E56>='Reference Tab - Do not Delete'!$E$35,'Reference Tab - Do not Delete'!$D$35,IF(AND(E56>='Reference Tab - Do not Delete'!$E$36,E56<'Reference Tab - Do not Delete'!$E$35),'Reference Tab - Do not Delete'!$D$36,IF(AND(E56>='Reference Tab - Do not Delete'!$E$37,E56<'Reference Tab - Do not Delete'!$E$36),'Reference Tab - Do not Delete'!$D$37,IF(AND(E56>='Reference Tab - Do not Delete'!$E$38,E56<'Reference Tab - Do not Delete'!$E$37),'Reference Tab - Do not Delete'!$D$38,'Reference Tab - Do not Delete'!$D$39))))) -> $50B - $B | AH56: =IF(H56="","DNA",IF(H56<=10,"Top 10",IF(AND(H56<=25,H56>10),"11 - 25",IF(AND(H56<=50,H56>25),"26 - 50","Above 50")))) -> 11 - 25 | AI56: =IF(AJ56>0,"Yes","") -> Yes | AJ56: 600
B57: NJM Ins Group | C57: 51 | D57: Carrier | E57: 2006683000 | F57: 0.016 | G57: 51 | H57: 52 | I57: US | AG57: =IF(E57="","",IF(E57>='Reference Tab - Do not Delete'!$E$35,'Reference Tab - Do not Delete'!$D$35,IF(AND(E57>='Reference Tab - Do not Delete'!$E$36,E57<'Reference Tab - Do not Delete'!$E$35),'Reference Tab - Do not Delete'!$D$36,IF(AND(E57>='Reference Tab - Do not Delete'!$E$37,E57<'Reference Tab - Do not Delete'!$E$36),'Reference Tab - Do not Delete'!$D$37,IF(AND(E57>='Reference Tab - Do not Delete'!$E$38,E57<'Reference Tab - Do not Delete'!$E$37),'Reference Tab - Do not Delete'!$D$38,'Reference Tab - Do not Delete'!$D$39))))) -> $50B - $B | AH57: =IF(H57="","DNA",IF(H57<=10,"Top 10",IF(AND(H57<=25,H57>10),"11 - 25",IF(AND(H57<=50,H57>25),"26 - 50","Above 50")))) -> Above 50 | AI57: =IF(AJ57>0,"Yes","") | AJ57: 0
B58: State Ins Fund WC Fund | C58: 52 | D58: Carrier | E58: 1996372000 | F58: -0.115 | G58: 52 | H58: 49 | I58: US | AG58: =IF(E58="","",IF(E58>='Reference Tab - Do not Delete'!$E$35,'Reference Tab - Do not Delete'!$D$35,IF(AND(E58>='Reference Tab - Do not Delete'!$E$36,E58<'Reference Tab - Do not Delete'!$E$35),'Reference Tab - Do not Delete'!$D$36,IF(AND(E58>='Reference Tab - Do not Delete'!$E$37,E58<'Reference Tab - Do not Delete'!$E$36),'Reference Tab - Do not Delete'!$D$37,IF(AND(E58>='Reference Tab - Do not Delete'!$E$38,E58<'Reference Tab - Do not Delete'!$E$37),'Reference Tab - Do not Delete'!$D$38,'Reference Tab - Do not Delete'!$D$39))))) -> $50B - $B | AH58: =IF(H58="","DNA",IF(H58<=10,"Top 10",IF(AND(H58<=25,H58>10),"11 - 25",IF(AND(H58<=50,H58>25),"26 - 50","Above 50")))) -> 26 - 50 | AI58: =IF(AJ58>0,"Yes","") | AJ58: 0
A59: Sean | B59: AXIS US Operations | C59: 53 | D59: Carrier | E59: 1932319000 | F59: -0.148 | G59: 53 | H59: 48 | I59: US | J59: 107.3 | K59: Named | L59: Sean | M59: Albert Benchimol | N59: Pete Vogt | O59: Ben Rubin | P59: Mike Baumel | Q59: Rob Hartman | R59: Keith Schlosser | S59: Eric Gesick | T59: Yes | U59: Genpact, Infosys | V59: 2022 | AG59: =IF(E59="","",IF(E59>='Reference Tab - Do not Delete'!$E$35,'Reference Tab - Do not Delete'!$D$35,IF(AND(E59>='Reference Tab - Do not Delete'!$E$36,E59<'Reference Tab - Do not Delete'!$E$35),'Reference Tab - Do not Delete'!$D$36,IF(AND(E59>='Reference Tab - Do not Delete'!$E$37,E59<'Reference Tab - Do not Delete'!$E$36),'Reference Tab - Do not Delete'!$D$37,IF(AND(E59>='Reference Tab - Do not Delete'!$E$38,E59<'Reference Tab - Do not Delete'!$E$37),'Reference Tab - Do not Delete'!$D$38,'Reference Tab - Do not Delete'!$D$39))))) -> $50B - $B | AH59: =IF(H59="","DNA",IF(H59<=10,"Top 10",IF(AND(H59<=25,H59>10),"11 - 25",IF(AND(H59<=50,H59>25),"26 - 50","Above 50")))) -> 26 - 50 | AI59: =IF(AJ59>0,"Yes","") -> Yes | AJ59: 513322.32
B60: EMC lns Cos | C60: 54 | D60: Carrier | E60: 1910680000 | F60: 0.015 | G60: 54 | H60: 53 | I60: US | AG60: =IF(E60="","",IF(E60>='Reference Tab - Do not Delete'!$E$35,'Reference Tab - Do not Delete'!$D$35,IF(AND(E60>='Reference Tab - Do not Delete'!$E$36,E60<'Reference Tab - Do not Delete'!$E$35),'Reference Tab - Do not Delete'!$D$36,IF(AND(E60>='Reference Tab - Do not Delete'!$E$37,E60<'Reference Tab - Do not Delete'!$E$36),'Reference Tab - Do not Delete'!$D$37,IF(AND(E60>='Reference Tab - Do not Delete'!$E$38,E60<'Reference Tab - Do not Delete'!$E$37),'Reference Tab - Do not Delete'!$D$38,'Reference Tab - Do not Delete'!$D$39))))) -> $50B - $B | AH60: =IF(H60="","DNA",IF(H60<=10,"Top 10",IF(AND(H60<=25,H60>10),"11 - 25",IF(AND(H60<=50,H60>25),"26 - 50","Above 50")))) -> Above 50 | AI60: =IF(AJ60>0,"Yes","") | AJ60: 0
B61: Shelter Ins cos | C61: 55 | D61: Carrier | E61: 1907802000 | F61: 0.041 | G61: 55 | H61: 56 | I61: US | AG61: =IF(E61="","",IF(E61>='Reference Tab - Do not Delete'!$E$35,'Reference Tab - Do not Delete'!$D$35,IF(AND(E61>='Reference Tab - Do not Delete'!$E$36,E61<'Reference Tab - Do not Delete'!$E$35),'Reference Tab - Do not Delete'!$D$36,IF(AND(E61>='Reference Tab - Do not Delete'!$E$37,E61<'Reference Tab - Do not Delete'!$E$36),'Reference Tab - Do not Delete'!$D$37,IF(AND(E61>='Reference Tab - Do not Delete'!$E$38,E61<'Reference Tab - Do not Delete'!$E$37),'Reference Tab - Do not Delete'!$D$38,'Reference Tab - Do not Delete'!$D$39))))) -> $50B - $B | AH61: =IF(H61="","DNA",IF(H61<=10,"Top 10",IF(AND(H61<=25,H61>10),"11 - 25",IF(AND(H61<=50,H61>25),"26 - 50","Above 50")))) -> Above 50 | AI61: =IF(AJ61>0,"Yes","") | AJ61: 0
A62: Mohit | B62: MAPFRE North America Group | C62: 56 | D62: Carrier | E62: 1863845000 | F62: -0.162 | G62: 56 | H62: 51 | I62: US | J62: 97.6 | K62: Named | L62: Mohit | M62: Alexis Sanchez Geigel | N62: Francois Facon | O62: Dana Whiteley | P62: Christopher Matherly | Q62: Scott Hammond | R62: Gregg Nickerson | T62: Yes | U62: WNS | AG62: =IF(E62="","",IF(E62>='Reference Tab - Do not Delete'!$E$35,'Reference Tab - Do not Delete'!$D$35,IF(AND(E62>='Reference Tab - Do not Delete'!$E$36,E62<'Reference Tab - Do not Delete'!$E$35),'Reference Tab - Do not Delete'!$D$36,IF(AND(E62>='Reference Tab - Do not Delete'!$E$37,E62<'Reference Tab - Do not Delete'!$E$36),'Reference Tab - Do not Delete'!$D$37,IF(AND(E62>='Reference Tab - Do not Delete'!$E$38,E62<'Reference Tab - Do not Delete'!$E$37),'Reference Tab - Do not Delete'!$D$38,'Reference Tab - Do not Delete'!$D$39))))) -> $50B - $B | AH62: =IF(H62="","DNA",IF(H62<=10,"Top 10",IF(AND(H62<=25,H62>10),"11 - 25",IF(AND(H62<=50,H62>25),"26 - 50","Above 50")))) -> Above 50 | AI62: =IF(AJ62>0,"Yes","") | AJ62: 0
B63: SCOR US Group | C63: 57 | D63: Carrier | E63: 1848964000 | F63: 0.289 | G63: 57 | H63: 62 | I63: US | AG63: =IF(E63="","",IF(E63>='Reference Tab - Do not Delete'!$E$35,'Reference Tab - Do not Delete'!$D$35,IF(AND(E63>='Reference Tab - Do not Delete'!$E$36,E63<'Reference Tab - Do not Delete'!$E$35),'Reference Tab - Do not Delete'!$D$36,IF(AND(E63>='Reference Tab - Do not Delete'!$E$37,E63<'Reference Tab - Do not Delete'!$E$36),'Reference Tab - Do not Delete'!$D$37,IF(AND(E63>='Reference Tab - Do not Delete'!$E$38,E63<'Reference Tab - Do not Delete'!$E$37),'Reference Tab - Do not Delete'!$D$38,'Reference Tab - Do not Delete'!$D$39))))) -> $50B - $B | AH63: =IF(H63="","DNA",IF(H63<=10,"Top 10",IF(AND(H63<=25,H63>10),"11 - 25",IF(AND(H63<=50,H63>25),"26 - 50","Above 50")))) -> Above 50 | AI63: =IF(AJ63>0,"Yes","") | AJ63: 0
B64: Westfield Group | C64: 58 | D64: Carrier | E64: 1803649000 | F64: -0.017 | G64: 59 | H64: 55 | I64: US | AG64: =IF(E64="","",IF(E64>='Reference Tab - Do not Delete'!$E$35,'Reference Tab - Do not Delete'!$D$35,IF(AND(E64>='Reference Tab - Do not Delete'!$E$36,E64<'Reference Tab - Do not Delete'!$E$35),'Reference Tab - Do not Delete'!$D$36,IF(AND(E64>='Reference Tab - Do not Delete'!$E$37,E64<'Reference Tab - Do not Delete'!$E$36),'Reference Tab - Do not Delete'!$D$37,IF(AND(E64>='Reference Tab - Do not Delete'!$E$38,E64<'Reference Tab - Do not Delete'!$E$37),'Reference Tab - Do not Delete'!$D$38,'Reference Tab - Do not Delete'!$D$39))))) -> $50B - $B | AH64: =IF(H64="","DNA",IF(H64<=10,"Top 10",IF(AND(H64<=25,H64>10),"11 - 25",IF(AND(H64<=50,H64>25),"26 - 50","Above 50")))) -> Above 50 | AI64: =IF(AJ64>0,"Yes","") | AJ64: 0
B65: Federated Mutual Group | C65: 59 | D65: Carrier | E65: 1649373000 | F65: 0.115 | G65: 60 | H65: 60 | I65: US | AG65: =IF(E65="","",IF(E65>='Reference Tab - Do not Delete'!$E$35,'Reference Tab - Do not Delete'!$D$35,IF(AND(E65>='Reference Tab - Do not Delete'!$E$36,E65<'Reference Tab - Do not Delete'!$E$35),'Reference Tab - Do not Delete'!$D$36,IF(AND(E65>='Reference Tab - Do not Delete'!$E$37,E65<'Reference Tab - Do not Delete'!$E$36),'Reference Tab - Do not Delete'!$D$37,IF(AND(E65>='Reference Tab - Do not Delete'!$E$38,E65<'Reference Tab - Do not Delete'!$E$37),'Reference Tab - Do not Delete'!$D$38,'Reference Tab - Do not Delete'!$D$39))))) -> $50B - $B | AH65: =IF(H65="","DNA",IF(H65<=10,"Top 10",IF(AND(H65<=25,H65>10),"11 - 25",IF(AND(H65<=50,H65>25),"26 - 50","Above 50")))) -> Above 50 | AI65: =IF(AJ65>0,"Yes","") | AJ65: 0
B66: AF Group | C66: 60 | D66: Carrier | E66: 1617767000 | F66: 0.082 | G66: 61 | H66: 58 | I66: US | AG66: =IF(E66="","",IF(E66>='Reference Tab - Do not Delete'!$E$35,'Reference Tab - Do not Delete'!$D$35,IF(AND(E66>='Reference Tab - Do not Delete'!$E$36,E66<'Reference Tab - Do not Delete'!$E$35),'Reference Tab - Do not Delete'!$D$36,IF(AND(E66>='Reference Tab - Do not Delete'!$E$37,E66<'Reference Tab - Do not Delete'!$E$36),'Reference Tab - Do not Delete'!$D$37,IF(AND(E66>='Reference Tab - Do not Delete'!$E$38,E66<'Reference Tab - Do not Delete'!$E$37),'Reference Tab - Do not Delete'!$D$38,'Reference Tab - Do not Delete'!$D$39))))) -> $50B - $B | AH66: =IF(H66="","DNA",IF(H66<=10,"Top 10",IF(AND(H66<=25,H66>10),"11 - 25",IF(AND(H66<=50,H66>25),"26 - 50","Above 50")))) -> Above 50 | AI66: =IF(AJ66>0,"Yes","") | AJ66: 0
B67: Acuity, A Mutual Ins Co | C67: 61 | D67: Carrier | E67: 1582349000 | F67: 0.078 | G67: 62 | H67: 61 | I67: US | AG67: =IF(E67="","",IF(E67>='Reference Tab - Do not Delete'!$E$35,'Reference Tab - Do not Delete'!$D$35,IF(AND(E67>='Reference Tab - Do not Delete'!$E$36,E67<'Reference Tab - Do not Delete'!$E$35),'Reference Tab - Do not Delete'!$D$36,IF(AND(E67>='Reference Tab - Do not Delete'!$E$37,E67<'Reference Tab - Do not Delete'!$E$36),'Reference Tab - Do not Delete'!$D$37,IF(AND(E67>='Reference Tab - Do not Delete'!$E$38,E67<'Reference Tab - Do not Delete'!$E$37),'Reference Tab - Do not Delete'!$D$38,'Reference Tab - Do not Delete'!$D$39))))) -> $50B - $B | AH67: =IF(H67="","DNA",IF(H67<=10,"Top 10",IF(AND(H67<=25,H67>10),"11 - 25",IF(AND(H67<=50,H67>25),"26 - 50","Above 50")))) -> Above 50 | AI67: =IF(AJ67>0,"Yes","") | AJ67: 0
B68: Southern Farm Bureau Cas Group | C68: 62 | D68: Carrier | E68: 1509107000 | F68: 0.013 | G68: 63 | H68: 59 | I68: US | AG68: =IF(E68="","",IF(E68>='Reference Tab - Do not Delete'!$E$35,'Reference Tab - Do not Delete'!$D$35,IF(AND(E68>='Reference Tab - Do not Delete'!$E$36,E68<'Reference Tab - Do not Delete'!$E$35),'Reference Tab - Do not Delete'!$D$36,IF(AND(E68>='Reference Tab - Do not Delete'!$E$37,E68<'Reference Tab - Do not Delete'!$E$36),'Reference Tab - Do not Delete'!$D$37,IF(AND(E68>='Reference Tab - Do not Delete'!$E$38,E68<'Reference Tab - Do not Delete'!$E$37),'Reference Tab - Do not Delete'!$D$38,'Reference Tab - Do not Delete'!$D$39))))) -> $50B - $B | AH68: =IF(H68="","DNA",IF(H68<=10,"Top 10",IF(AND(H68<=25,H68>10),"11 - 25",IF(AND(H68<=50,H68>25),"26 - 50","Above 50")))) -> Above 50 | AI68: =IF(AJ68>0,"Yes","") | AJ68: 0
B69: Amer Natl Prop & Cas Group | C69: 63 | D69: Carrier | E69: 1430047000 | F69: 0.047 | G69: 84 | H69: 85 | I69: US | AG69: =IF(E69="","",IF(E69>='Reference Tab - Do not Delete'!$E$35,'Reference Tab - Do not Delete'!$D$35,IF(AND(E69>='Reference Tab - Do not Delete'!$E$36,E69<'Reference Tab - Do not Delete'!$E$35),'Reference Tab - Do not Delete'!$D$36,IF(AND(E69>='Reference Tab - Do not Delete'!$E$37,E69<'Reference Tab - Do not Delete'!$E$36),'Reference Tab - Do not Delete'!$D$37,IF(AND(E69>='Reference Tab - Do not Delete'!$E$38,E69<'Reference Tab - Do not Delete'!$E$37),'Reference Tab - Do not Delete'!$D$38,'Reference Tab - Do not Delete'!$D$39))))) -> $50B - $B | AH69: =IF(H69="","DNA",IF(H69<=10,"Top 10",IF(AND(H69<=25,H69>10),"11 - 25",IF(AND(H69<=50,H69>25),"26 - 50","Above 50")))) -> Above 50 | AI69: =IF(AJ69>0,"Yes","") | AJ69: 0
B70: Farm Bureau P&C Group | C70: 64 | D70: Carrier | E70: 1417693000 | F70: 0.023 | G70: 65 | H70: 63 | I70: US | AG70: =IF(E70="","",IF(E70>='Reference Tab - Do not Delete'!$E$35,'Reference Tab - Do not Delete'!$D$35,IF(AND(E70>='Reference Tab - Do not Delete'!$E$36,E70<'Reference Tab - Do not Delete'!$E$35),'Reference Tab - Do not Delete'!$D$36,IF(AND(E70>='Reference Tab - Do not Delete'!$E$37,E70<'Reference Tab - Do not Delete'!$E$36),'Reference Tab - Do not Delete'!$D$37,IF(AND(E70>='Reference Tab - Do not Delete'!$E$38,E70<'Reference Tab - Do not Delete'!$E$37),'Reference Tab - Do not Delete'!$D$38,'Reference Tab - Do not Delete'!$D$39))))) -> $50B - $B | AH70: =IF(H70="","DNA",IF(H70<=10,"Top 10",IF(AND(H70<=25,H70>10),"11 - 25",IF(AND(H70<=50,H70>25),"26 - 50","Above 50")))) -> Above 50 | AI70: =IF(AJ70>0,"Yes","") | AJ70: 0
B71: TN Farmers Ins Cos | C71: 65 | D71: Carrier | E71: 1413657000 | F71: 0.032 | G71: 66 | H71: 64 | I71: US | AG71: =IF(E71="","",IF(E71>='Reference Tab - Do not Delete'!$E$35,'Reference Tab - Do not Delete'!$D$35,IF(AND(E71>='Reference Tab - Do not Delete'!$E$36,E71<'Reference Tab - Do not Delete'!$E$35),'Reference Tab - Do not Delete'!$D$36,IF(AND(E71>='Reference Tab - Do not Delete'!$E$37,E71<'Reference Tab - Do not Delete'!$E$36),'Reference Tab - Do not Delete'!$D$37,IF(AND(E71>='Reference Tab - Do not Delete'!$E$38,E71<'Reference Tab - Do not Delete'!$E$37),'Reference Tab - Do not Delete'!$D$38,'Reference Tab - Do not Delete'!$D$39))))) -> $50B - $B | AH71: =IF(H71="","DNA",IF(H71<=10,"Top 10",IF(AND(H71<=25,H71>10),"11 - 25",IF(AND(H71<=50,H71>25),"26 - 50","Above 50")))) -> Above 50 | AI71: =IF(AJ71>0,"Yes","") | AJ71: 0
B72: Alfa Ins Group | C72: 66 | D72: Carrier | E72: 1326984000 | F72: -0.024 | G72: 67 | H72: 66 | I72: US | AG72: =IF(E72="","",IF(E72>='Reference Tab - Do not Delete'!$E$35,'Reference Tab - Do not Delete'!$D$35,IF(AND(E72>='Reference Tab - Do not Delete'!$E$36,E72<'Reference Tab - Do not Delete'!$E$35),'Reference Tab - Do not Delete'!$D$36,IF(AND(E72>='Reference Tab - Do not Delete'!$E$37,E72<'Reference Tab - Do not Delete'!$E$36),'Reference Tab - Do not Delete'!$D$37,IF(AND(E72>='Reference Tab - Do not Delete'!$E$38,E72<'Reference Tab - Do not Delete'!$E$37),'Reference Tab - Do not Delete'!$D$38,'Reference Tab - Do not Delete'!$D$39))))) -> $50B - $B | AH72: =IF(H72="","DNA",IF(H72<=10,"Top 10",IF(AND(H72<=25,H72>10),"11 - 25",IF(AND(H72<=50,H72>25),"26 - 50","Above 50")))) -> Above 50 | AI72: =IF(AJ72>0,"Yes","") | AJ72: 0
B73: West Bend Mutual Ins Co | C73: 67 | D73: Carrier | E73: 1275968000 | F73: 0.091 | G73: 68 | H73: 71 | I73: US | AG73: =IF(E73="","",IF(E73>='Reference Tab - Do not Delete'!$E$35,'Reference Tab - Do not Delete'!$D$35,IF(AND(E73>='Reference Tab - Do not Delete'!$E$36,E73<'Reference Tab - Do not Delete'!$E$35),'Reference Tab - Do not Delete'!$D$36,IF(AND(E73>='Reference Tab - Do not Delete'!$E$37,E73<'Reference Tab - Do not Delete'!$E$36),'Reference Tab - Do not Delete'!$D$37,IF(AND(E73>='Reference Tab - Do not Delete'!$E$38,E73<'Reference Tab - Do not Delete'!$E$37),'Reference Tab - Do not Delete'!$D$38,'Reference Tab - Do not Delete'!$D$39))))) -> $50B - $B | AH73: =IF(H73="","DNA",IF(H73<=10,"Top 10",IF(AND(H73<=25,H73>10),"11 - 25",IF(AND(H73<=50,H73>25),"26 - 50","Above 50")))) -> Above 50 | AI73: =IF(AJ73>0,"Yes","") | AJ73: 0
B74: Grange Ins Pool | C74: 68 | D74: Carrier | E74: 1274202000 | F74: 0.059 | G74: 69 | H74: 70 | I74: US | AG74: =IF(E74="","",IF(E74>='Reference Tab - Do not Delete'!$E$35,'Reference Tab - Do not Delete'!$D$35,IF(AND(E74>='Reference Tab - Do not Delete'!$E$36,E74<'Reference Tab - Do not Delete'!$E$35),'Reference Tab - Do not Delete'!$D$36,IF(AND(E74>='Reference Tab - Do not Delete'!$E$37,E74<'Reference Tab - Do not Delete'!$E$36),'Reference Tab - Do not Delete'!$D$37,IF(AND(E74>='Reference Tab - Do not Delete'!$E$38,E74<'Reference Tab - Do not Delete'!$E$37),'Reference Tab - Do not Delete'!$D$38,'Reference Tab - Do not Delete'!$D$39))))) -> $50B - $B | AH74: =IF(H74="","DNA",IF(H74<=10,"Top 10",IF(AND(H74<=25,H74>10),"11 - 25",IF(AND(H74<=50,H74>25),"26 - 50","Above 50")))) -> Above 50 | AI74: =IF(AJ74>0,"Yes","") | AJ74: 0
... B130: SAIF Corp | C130: 124 | D130: Carrier | E130: 508621000 | F130: -0.021 | G130: 125 | H130: 120 | I130: US | AG130: =IF(E130="","",IF(E130>='Reference Tab - Do not Delete'!$E$35,'Reference Tab - Do not Delete'!$D$35,IF(AND(E130>='Reference Tab - Do not Delete'!$E$36,E130<'Reference Tab - Do not Delete'!$E$35),'Reference Tab - Do not Delete'!$D$36,IF(AND(E130>='Reference Tab - Do not Delete'!$E$37,E130<'Reference Tab - Do not Delete'!$E$36),'Reference Tab - Do not Delete'!$D$37,IF(AND(E130>='Reference Tab - Do not Delete'!$E$38,E130<'Reference Tab - Do not Delete'!$E$37),'Reference Tab - Do not Delete'!$D$38,'Reference Tab - Do not Delete'!$D$39))))) -> $B - $500M | AH130: =IF(H130="","DNA",IF(H130<=10,"Top 10",IF(AND(H130<=25,H130>10),"11 - 25",IF(AND(H130<=50,H130>25),"26 - 50","Above 50")))) -> Above 50 | AI130: =IF(AJ130>0,"Yes","") | AJ130: 0
A131: Sean | B131: American Modern Ins Group | C131: 125 | D131: Carrier | E131: 2500000000 | F131: 0.03 | I131: US | K131: Named | L131: Sean | M131: Andreas Kleiner | N131: Rene Gobanya | O131: Trey Griffith | P131: Eric Hunzinger | Q131: Paul Schneider | R131: Bill Gottsacker | S131: Kam Jha | T131: Yes | U131: TCS | V131: Just signed with us | AG131: =IF(E131="","",IF(E131>='Reference Tab - Do not Delete'!$E$35,'Reference Tab - Do not Delete'!$D$35,IF(AND(E131>='Reference Tab - Do not Delete'!$E$36,E131<'Reference Tab - Do not Delete'!$E$35),'Reference Tab - Do not Delete'!$D$36,IF(AND(E131>='Reference Tab - Do not Delete'!$E$37,E131<'Reference Tab - Do not Delete'!$E$36),'Reference Tab - Do not Delete'!$D$37,IF(AND(E131>='Reference Tab - Do not Delete'!$E$38,E131<'Reference Tab - Do not Delete'!$E$37),'Reference Tab - Do not Delete'!$D$38,'Reference Tab - Do not Delete'!$D$39))))) -> $50B - $B | AH131: =IF(H131="","DNA",IF(H131<=10,"Top 10",IF(AND(H131<=25,H131>10),"11 - 25",IF(AND(H131<=50,H131>25),"26 - 50","Above 50")))) -> DNA | AI131: =IF(AJ131>0,"Yes","") | AJ131: 0
B132: HUB International Ltd. | C132: 126 | D132: Broker | E132: 1435434756 | G132: 1 | H132: 1 | I132: US | AG132: =IF(E132="","",IF(E132>='Reference Tab - Do not Delete'!$E$35,'Reference Tab - Do not Delete'!$D$35,IF(AND(E132>='Reference Tab - Do not Delete'!$E$36,E132<'Reference Tab - Do not Delete'!$E$35),'Reference Tab - Do not Delete'!$D$36,IF(AND(E132>='Reference Tab - Do not Delete'!$E$37,E132<'Reference Tab - Do not Delete'!$E$36),'Reference Tab - Do not Delete'!$D$37,IF(AND(E132>='Reference Tab - Do not Delete'!$E$38,E132<'Reference Tab - Do not Delete'!$E$37),'Reference Tab - Do not Delete'!$D$38,'Reference Tab - Do not Delete'!$D$39))))) -> $50B - $B | AH132: =IF(H132="","DNA",IF(H132<=10,"Top 10",IF(AND(H132<=25,H132>10),"11 - 25",IF(AND(H132<=50,H132>25),"26 - 50","Above 50")))) -> Top 10 | AI132: =IF(AJ132>0,"Yes","") | AJ132: 0
B133: Lockton Companies | C133: 127 | D133: Broker | E133: 1155316000 | G133: 2 | H133: 2 | I133: US | AG133: =IF(E133="","",IF(E133>='Reference Tab - Do not Delete'!$E$35,'Reference Tab - Do not Delete'!$D$35,IF(AND(E133>='Reference Tab - Do not Delete'!$E$36,E133<'Reference Tab - Do not Delete'!$E$35),'Reference Tab - Do not Delete'!$D$36,IF(AND(E133>='Reference Tab - Do not Delete'!$E$37,E133<'Reference Tab - Do not Delete'!$E$36),'Reference Tab - Do not Delete'!$D$37,IF(AND(E133>='Reference Tab - Do not Delete'!$E$38,E133<'Reference Tab - Do not Delete'!$E$37),'Reference Tab - Do not Delete'!$D$38,'Reference Tab - Do not Delete'!$D$39))))) -> $50B - $B | AH133: =IF(H133="","DNA",IF(H133<=10,"Top 10",IF(AND(H133<=25,H133>10),"11 - 25",IF(AND(H133<=50,H133>25),"26 - 50","Above 50")))) -> Top 10 | AI133: =IF(AJ133>0,"Yes","") | AJ133: 0
B134: USI Insurance Services | C134: 128 | D134: Broker | E134: 1087549902 | G134: 6 | H134: 3 | I134: US | AG134: =IF(E134="","",IF(E134>='Reference Tab - Do not Delete'!$E$35,'Reference Tab - Do not Delete'!$D$35,IF(AND(E134>='Reference Tab - Do not Delete'!$E$36,E134<'Reference Tab - Do not Delete'!$E$35),'Reference Tab - Do not Delete'!$D$36,IF(AND(E134>='Reference Tab - Do not Delete'!$E$37,E134<'Reference Tab - Do not Delete'!$E$36),'Reference Tab - Do not Delete'!$D$37,IF(AND(E134>='Reference Tab - Do not Delete'!$E$38,E134<'Reference Tab - Do not Delete'!$E$37),'Reference Tab - Do not Delete'!$D$38,'Reference Tab - Do not Delete'!$D$39))))) -> $50B - $B | AH134: =IF(H134="","DNA",IF(H134<=10,"Top 10",IF(AND(H134<=25,H134>10),"11 - 25",IF(AND(H134<=50,H134>25),"26 - 50","Above 50")))) -> Top 10 | AI134: =IF(AJ134>0,"Yes","") | AJ134: 0
B135: Alliant Insurance Services Inc. | C135: 129 | D135: Broker | E135: 1024784327 | G135: 3 | H135: 4 | I135: US | AG135: =IF(E135="","",IF(E135>='Reference Tab - Do not Delete'!$E$35,'Reference Tab - Do not Delete'!$D$35,IF(AND(E135>='Reference Tab - Do not Delete'!$E$36,E135<'Reference Tab - Do not Delete'!$E$35),'Reference Tab - Do not Delete'!$D$36,IF(AND(E135>='Reference Tab - Do not Delete'!$E$37,E135<'Reference Tab - Do not Delete'!$E$36),'Reference Tab - Do not Delete'!$D$37,IF(AND(E135>='Reference Tab - Do not Delete'!$E$38,E135<'Reference Tab - Do not Delete'!$E$37),'Reference Tab - Do not Delete'!$D$38,'Reference Tab - Do not Delete'!$D$39))))) -> $50B - $B | AH135: =IF(H135="","DNA",IF(H135<=10,"Top 10",IF(AND(H135<=25,H135>10),"11 - 25",IF(AND(H135<=50,H135>25),"26 - 50","Above 50")))) -> Top 10 | AI135: =IF(AJ135>0,"Yes","") | AJ135: 0
B136: AssuredPartners Inc. | C136: 130 | D136: Broker | E136: 981752255 | G136: 5 | H136: 5 | I136: US | AG136: =IF(E136="","",IF(E136>='Reference Tab - Do not Delete'!$E$35,'Reference Tab - Do not Delete'!$D$35,IF(AND(E136>='Reference Tab - Do not Delete'!$E$36,E136<'Reference Tab - Do not Delete'!$E$35),'Reference Tab - Do not Delete'!$D$36,IF(AND(E136>='Reference Tab - Do not Delete'!$E$37,E136<'Reference Tab - Do not Delete'!$E$36),'Reference Tab - Do not Delete'!$D$37,IF(AND(E136>='Reference Tab - Do not Delete'!$E$38,E136<'Reference Tab - Do not Delete'!$E$37),'Reference Tab - Do not Delete'!$D$38,'Reference Tab - Do not Delete'!$D$39))))) -> $B - $500M | AH136: =IF(H136="","DNA",IF(H136<=10,"Top 10",IF(AND(H136<=25,H136>10),"11 - 25",IF(AND(H136<=50,H136>25),"26 - 50","Above 50")))) -> Top 10 | AI136: =IF(AJ136>0,"Yes","") | AJ136: 0
B137: Acrisure LLC | C137: 131 | D137: Broker | E137: 942352957 | G137: 4 | H137: 6 | I137: US | AG137: =IF(E137="","",IF(E137>='Reference Tab - Do not Delete'!$E$35,'Reference Tab - Do not Delete'!$D$35,IF(AND(E137>='Reference Tab - Do not Delete'!$E$36,E137<'Reference Tab - Do not Delete'!$E$35),'Reference Tab - Do not Delete'!$D$36,IF(AND(E137>='Reference Tab - Do not Delete'!$E$37,E137<'Reference Tab - Do not Delete'!$E$36),'Reference Tab - Do not Delete'!$D$37,IF(AND(E137>='Reference Tab - Do not Delete'!$E$38,E137<'Reference Tab - Do not Delete'!$E$37),'Reference Tab - Do not Delete'!$D$38,'Reference Tab - Do not Delete'!$D$39))))) -> $B - $500M | AH137: =IF(H137="","DNA",IF(H137<=10,"Top 10",IF(AND(H137<=25,H137>10),"11 - 25",IF(AND(H137<=50,H137>25),"26 - 50","Above 50")))) -> Top 10 | AI137: =IF(AJ137>0,"Yes","") | AJ137: 0
B138: BroadStreet Partners Inc. | C138: 132 | D138: Broker | E138: 559589000 | G138: 8 | H138: 7 | I138: US | AG138: =IF(E138="","",IF(E138>='Reference Tab - Do not Delete'!$E$35,'Reference Tab - Do not Delete'!$D$35,IF(AND(E138>='Reference Tab - Do not Delete'!$E$36,E138<'Reference Tab - Do not Delete'!$E$35),'Reference Tab - Do not Delete'!$D$36,IF(AND(E138>='Reference Tab - Do not Delete'!$E$37,E138<'Reference Tab - Do not Delete'!$E$36),'Reference Tab - Do not Delete'!$D$37,IF(AND(E138>='Reference Tab - Do not Delete'!$E$38,E138<'Reference Tab - Do not Delete'!$E$37),'Reference Tab - Do not Delete'!$D$38,'Reference Tab - Do not Delete'!$D$39))))) -> $B - $500M | AH138: =IF(H138="","DNA",IF(H138<=10,"Top 10",IF(AND(H138<=25,H138>10),"11 - 25",IF(AND(H138<=50,H138>25),"26 - 50","Above 50")))) -> Top 10 | AI138: =IF(AJ138>0,"Yes","") | AJ138: 0
B139: Confie | C139: 133 | D139: Broker | E139: 515000000 | G139: 7 | H139: 8 | I139: US | AG139: =IF(E139="","",IF(E139>='Reference Tab - Do not Delete'!$E$35,'Reference Tab - Do not Delete'!$D$35,IF(AND(E139>='Reference Tab - Do not Delete'!$E$36,E139<'Reference Tab - Do not Delete'!$E$35),'Reference Tab - Do not Delete'!$D$36,IF(AND(E139>='Reference Tab - Do not Delete'!$E$37,E139<'Reference Tab - Do not Delete'!$E$36),'Reference Tab - Do not Delete'!$D$37,IF(AND(E139>='Reference Tab - Do not Delete'!$E$38,E139<'Reference Tab - Do not Delete'!$E$37),'Reference Tab - Do not Delete'!$D$38,'Reference Tab - Do not Delete'!$D$39))))) -> $B - $500M | AH139: =IF(H139="","DNA",IF(H139<=10,"Top 10",IF(AND(H139<=25,H139>10),"11 - 25",IF(AND(H139<=50,H139>25),"26 - 50","Above 50")))) -> Top 10 | AI139: =IF(AJ139>0,"Yes","") | AJ139: 0
B140: EPIC | C140: 134 | D140: Broker | E140: 461377714 | G140: 9 | H140: 9 | I140: US | AG140: =IF(E140="","",IF(E140>='Reference Tab - Do not Delete'!$E$35,'Reference Tab - Do not Delete'!$D$35,IF(AND(E140>='Reference Tab - Do not Delete'!$E$36,E140<'Reference Tab - Do not Delete'!$E$35),'Reference Tab - Do not Delete'!$D$36,IF(AND(E140>='Reference Tab - Do not Delete'!$E$37,E140<'Reference Tab - Do not Delete'!$E$36),'Reference Tab - Do not Delete'!$D$37,IF(AND(E140>='Reference Tab - Do not Delete'!$E$38,E140<'Reference Tab - Do not Delete'!$E$37),'Reference Tab - Do not Delete'!$D$38,'Reference Tab - Do not Delete'!$D$39))))) -> $500M - $M | AH140: =IF(H140="","DNA",IF(H140<=10,"Top 10",IF(AND(H140<=25,H140>10),"11 - 25",IF(AND(H140<=50,H140>25),"26 - 50","Above 50")))) -> Top 10 | AI140: =IF(AJ140>0,"Yes","") | AJ140: 0
B141: NFP | C141: 135 | D141: Broker | E141: 338500000 | G141: 10 | H141: 10 | I141: US | AG141: =IF(E141="","",IF(E141>='Reference Tab - Do not Delete'!$E$35,'Reference Tab - Do not Delete'!$D$35,IF(AND(E141>='Reference Tab - Do not Delete'!$E$36,E141<'Reference Tab - Do not Delete'!$E$35),'Reference Tab - Do not Delete'!$D$36,IF(AND(E141>='Reference Tab - Do not Delete'!$E$37,E141<'Reference Tab - Do not Delete'!$E$36),'Reference Tab - Do not Delete'!$D$37,IF(AND(E141>='Reference Tab - Do not Delete'!$E$38,E141<'Reference Tab - Do not Delete'!$E$37),'Reference Tab - Do not Delete'!$D$38,'Reference Tab - Do not Delete'!$D$39))))) -> $500M - $M | AH141: =IF(H141="","DNA",IF(H141<=10,"Top 10",IF(AND(H141<=25,H141>10),"11 - 25",IF(AND(H141<=50,H141>25),"26 - 50","Above 50")))) -> Top 10 | AI141: =IF(AJ141>0,"Yes","") | AJ141: 0
B142: Risk Strategies | C142: 136 | D142: Broker | E142: 290649571 | G142: 11 | H142: 11 | I142: US | AG142: =IF(E142="","",IF(E142>='Reference Tab - Do not Delete'!$E$35,'Reference Tab - Do not Delete'!$D$35,IF(AND(E142>='Reference Tab - Do not Delete'!$E$36,E142<'Reference Tab - Do not Delete'!$E$35),'Reference Tab - Do not Delete'!$D$36,IF(AND(E142>='Reference Tab - Do not Delete'!$E$37,E142<'Reference Tab - Do not Delete'!$E$36),'Reference Tab - Do not Delete'!$D$37,IF(AND(E142>='Reference Tab - Do not Delete'!$E$38,E142<'Reference Tab - Do not Delete'!$E$37),'Reference Tab - Do not Delete'!$D$38,'Reference Tab - Do not Delete'!$D$39))))) -> $500M - $M | AH142: =IF(H142="","DNA",IF(H142<=10,"Top 10",IF(AND(H142<=25,H142>10),"11 - 25",IF(AND(H142<=50,H142>25),"26 - 50","Above 50")))) -> 11 - 25 | AI142: =IF(AJ142>0,"Yes","") | AJ142: 0
B143: Leavitt Group | C143: 137 | D143: Broker | E143: 209445078 | G143: 14 | H143: 12 | I143: US | AG143: =IF(E143="","",IF(E143>='Reference Tab - Do not Delete'!$E$35,'Reference Tab - Do not Delete'!$D$35,IF(AND(E143>='Reference Tab - Do not Delete'!$E$36,E143<'Reference Tab - Do not Delete'!$E$35),'Reference Tab - Do not Delete'!$D$36,IF(AND(E143>='Reference Tab - Do not Delete'!$E$37,E143<'Reference Tab - Do not Delete'!$E$36),'Reference Tab - Do not Delete'!$D$37,IF(AND(E143>='Reference Tab - Do not Delete'!$E$38,E143<'Reference Tab - Do not Delete'!$E$37),'Reference Tab - Do not Delete'!$D$38,'Reference Tab - Do not Delete'!$D$39))))) -> $500M - $M | AH143: =IF(H143="","DNA",IF(H143<=10,"Top 10",IF(AND(H143<=25,H143>10),"11 - 25",IF(AND(H143<=50,H143>25),"26 - 50","Above 50")))) -> 11 - 25 | AI143: =IF(AJ143>0,"Yes","") | AJ143: 0
... B178: Parker, Smith & Feek Inc. | C178: 172 | D178: Broker | E178: 43744167 | G178: 41 | H178: 47 | I178: US | AG178: =IF(E178="","",IF(E178>='Reference Tab - Do not Delete'!$E$35,'Reference Tab - Do not Delete'!$D$35,IF(AND(E178>='Reference Tab - Do not Delete'!$E$36,E178<'Reference Tab - Do not Delete'!$E$35),'Reference Tab - Do not Delete'!$D$36,IF(AND(E178>='Reference Tab - Do not Delete'!$E$37,E178<'Reference Tab - Do not Delete'!$E$36),'Reference Tab - Do not Delete'!$D$37,IF(AND(E178>='Reference Tab - Do not Delete'!$E$38,E178<'Reference Tab - Do not Delete'!$E$37),'Reference Tab - Do not Delete'!$D$38,'Reference Tab - Do not Delete'!$D$39))))) -> $500M - $M | AH178: =IF(H178="","DNA",IF(H178<=10,"Top 10",IF(AND(H178<=25,H178>10),"11 - 25",IF(AND(H178<=50,H178>25),"26 - 50","Above 50")))) -> 26 - 50 | AI178: =IF(AJ178>0,"Yes","") | AJ178: 0
B179: Scott Insurance (James A. Scott and Son Inc.) | C179: 173 | D179: Broker | E179: 43579000 | G179: new | H179: 48 | I179: US | AG179: =IF(E179="","",IF(E179>='Reference Tab - Do not Delete'!$E$35,'Reference Tab - Do not Delete'!$D$35,IF(AND(E179>='Reference Tab - Do not Delete'!$E$36,E179<'Reference Tab - Do not Delete'!$E$35),'Reference Tab - Do not Delete'!$D$36,IF(AND(E179>='Reference Tab - Do not Delete'!$E$37,E179<'Reference Tab - Do not Delete'!$E$36),'Reference Tab - Do not Delete'!$D$37,IF(AND(E179>='Reference Tab - Do not Delete'!$E$38,E179<'Reference Tab - Do not Delete'!$E$37),'Reference Tab - Do not Delete'!$D$38,'Reference Tab - Do not Delete'!$D$39))))) -> $500M - $M | AH179: =IF(H179="","DNA",IF(H179<=10,"Top 10",IF(AND(H179<=25,H179>10),"11 - 25",IF(AND(H179<=50,H179>25),"26 - 50","Above 50")))) -> 26 - 50 | AI179: =IF(AJ179>0,"Yes","") | AJ179: 0
B180: Ansay & Associates | C180: 174 | D180: Broker | E180: 40986433 | G180: 63 | H180: 49 | I180: US | AG180: =IF(E180="","",IF(E180>='Reference Tab - Do not Delete'!$E$35,'Reference Tab - Do not Delete'!$D$35,IF(AND(E180>='Reference Tab - Do not Delete'!$E$36,E180<'Reference Tab - Do not Delete'!$E$35),'Reference Tab - Do not Delete'!$D$36,IF(AND(E180>='Reference Tab - Do not Delete'!$E$37,E180<'Reference Tab - Do not Delete'!$E$36),'Reference Tab - Do not Delete'!$D$37,IF(AND(E180>='Reference Tab - Do not Delete'!$E$38,E180<'Reference Tab - Do not Delete'!$E$37),'Reference Tab - Do not Delete'!$D$38,'Reference Tab - Do not Delete'!$D$39))))) -> $500M - $M | AH180: =IF(H180="","DNA",IF(H180<=10,"Top 10",IF(AND(H180<=25,H180>10),"11 - 25",IF(AND(H180<=50,H180>25),"26 - 50","Above 50")))) -> 26 - 50 | AI180: =IF(AJ180>0,"Yes","") | AJ180: 0
B181: Gowrie Group | C181: 175 | D181: Broker | E181: 40400000 | G181: 44 | H181: 50 | I181: US | AG181: =IF(E181="","",IF(E181>='Reference Tab - Do not Delete'!$E$35,'Reference Tab - Do not Delete'!$D$35,IF(AND(E181>='Reference Tab - Do not Delete'!$E$36,E181<'Reference Tab - Do not Delete'!$E$35),'Reference Tab - Do not Delete'!$D$36,IF(AND(E181>='Reference Tab - Do not Delete'!$E$37,E181<'Reference Tab - Do not Delete'!$E$36),'Reference Tab - Do not Delete'!$D$37,IF(AND(E181>='Reference Tab - Do not Delete'!$E$38,E181<'Reference Tab - Do not Delete'!$E$37),'Reference Tab - Do not Delete'!$D$38,'Reference Tab - Do not Delete'!$D$39))))) -> $500M - $M | AH181: =IF(H181="","DNA",IF(H181<=10,"Top 10",IF(AND(H181<=25,H181>10),"11 - 25",IF(AND(H181<=50,H181>25),"26 - 50","Above 50")))) -> 26 - 50 | AI181: =IF(AJ181>0,"Yes","") | AJ181: 0
B182: ABD Insurance and Financial Services | C182: 176 | D182: Broker | E182: 39200000 | G182: 59 | H182: 51 | I182: US | AG182: =IF(E182="","",IF(E182>='Reference Tab - Do not Delete'!$E$35,'Reference Tab - Do not Delete'!$D$35,IF(AND(E182>='Reference Tab - Do not Delete'!$E$36,E182<'Reference Tab - Do not Delete'!$E$35),'Reference Tab - Do not Delete'!$D$36,IF(AND(E182>='Reference Tab - Do not Delete'!$E$37,E182<'Reference Tab - Do not Delete'!$E$36),'Reference Tab - Do not Delete'!$D$37,IF(AND(E182>='Reference Tab - Do not Delete'!$E$38,E182<'Reference Tab - Do not Delete'!$E$37),'Reference Tab - Do not Delete'!$D$38,'Reference Tab - Do not Delete'!$D$39))))) -> $500M - $M | AH182: =IF(H182="","DNA",IF(H182<=10,"Top 10",IF(AND(H182<=25,H182>10),"11 - 25",IF(AND(H182<=50,H182>25),"26 - 50","Above 50")))) -> Above 50 | AI182: =IF(AJ182>0,"Yes","") | AJ182: 0
B183: Huntington Insurance | C183: 177 | D183: Broker | E183: 38406000 | G183: new | H183: 52 | I183: US | AG183: =IF(E183="","",IF(E183>='Reference Tab - Do not Delete'!$E$35,'Reference Tab - Do not Delete'!$D$35,IF(AND(E183>='Reference Tab - Do not Delete'!$E$36,E183<'Reference Tab - Do not Delete'!$E$35),'Reference Tab - Do not Delete'!$D$36,IF(AND(E183>='Reference Tab - Do not Delete'!$E$37,E183<'Reference Tab - Do not Delete'!$E$36),'Reference Tab - Do not Delete'!$D$37,IF(AND(E183>='Reference Tab - Do not Delete'!$E$38,E183<'Reference Tab - Do not Delete'!$E$37),'Reference Tab - Do not Delete'!$D$38,'Reference Tab - Do not Delete'!$D$39))))) -> $500M - $M | AH183: =IF(H183="","DNA",IF(H183<=10,"Top 10",IF(AND(H183<=25,H183>10),"11 - 25",IF(AND(H183<=50,H183>25),"26 - 50","Above 50")))) -> Above 50 | AI183: =IF(AJ183>0,"Yes","") | AJ183: 0
B184: The Mahoney Group | C184: 178 | D184: Broker | E184: 38329667 | G184: 53 | H184: 53 | I184: US | AG184: =IF(E184="","",IF(E184>='Reference Tab - Do not Delete'!$E$35,'Reference Tab - Do not Delete'!$D$35,IF(AND(E184>='Reference Tab - Do not Delete'!$E$36,E184<'Reference Tab - Do not Delete'!$E$35),'Reference Tab - Do not Delete'!$D$36,IF(AND(E184>='Reference Tab - Do not Delete'!$E$37,E184<'Reference Tab - Do not Delete'!$E$36),'Reference Tab - Do not Delete'!$D$37,IF(AND(E184>='Reference Tab - Do not Delete'!$E$38,E184<'Reference Tab - Do not Delete'!$E$37),'Reference Tab - Do not Delete'!$D$38,'Reference Tab - Do not Delete'!$D$39))))) -> $500M - $M | AH184: =IF(H184="","DNA",IF(H184<=10,"Top 10",IF(AND(H184<=25,H184>10),"11 - 25",IF(AND(H184<=50,H184>25),"26 - 50","Above 50")))) -> Above 50 | AI184: =IF(AJ184>0,"Yes","") | AJ184: 0
B185: Rose & Kiernan Inc. | C185: 179 | D185: Broker | E185: 38283740 | G185: new | H185: 54 | I185: US | AG185: =IF(E185="","",IF(E185>='Reference Tab - Do not Delete'!$E$35,'Reference Tab - Do not Delete'!$D$35,IF(AND(E185>='Reference Tab - Do not Delete'!$E$36,E185<'Reference Tab - Do not Delete'!$E$35),'Reference Tab - Do not Delete'!$D$36,IF(AND(E185>='Reference Tab - Do not Delete'!$E$37,E185<'Reference Tab - Do not Delete'!$E$36),'Reference Tab - Do not Delete'!$D$37,IF(AND(E185>='Reference Tab - Do not Delete'!$E$38,E185<'Reference Tab - Do not Delete'!$E$37),'Reference Tab - Do not Delete'!$D$38,'Reference Tab - Do not Delete'!$D$39))))) -> $500M - $M | AH185: =IF(H185="","DNA",IF(H185<=10,"Top 10",IF(AND(H185<=25,H185>10),"11 - 25",IF(AND(H185<=50,H185>25),"26 - 50","Above 50")))) -> Above 50 | AI185: =IF(AJ185>0,"Yes","") | AJ185: 0
B186: Premier Group Insurance | C186: 180 | D186: Broker | E186: 38151357 | G186: 62 | H186: 55 | I186: US | AG186: =IF(E186="","",IF(E186>='Reference Tab - Do not Delete'!$E$35,'Reference Tab - Do not Delete'!$D$35,IF(AND(E186>='Reference Tab - Do not Delete'!$E$36,E186<'Reference Tab - Do not Delete'!$E$35),'Reference Tab - Do not Delete'!$D$36,IF(AND(E186>='Reference Tab - Do not Delete'!$E$37,E186<'Reference Tab - Do not Delete'!$E$36),'Reference Tab - Do not Delete'!$D$37,IF(AND(E186>='Reference Tab - Do not Delete'!$E$38,E186<'Reference Tab - Do not Delete'!$E$37),'Reference Tab - Do not Delete'!$D$38,'Reference Tab - Do not Delete'!$D$39))))) -> $500M - $M | AH186: =IF(H186="","DNA",IF(H186<=10,"Top 10",IF(AND(H186<=25,H186>10),"11 - 25",IF(AND(H186<=50,H186>25),"26 - 50","Above 50")))) -> Above 50 | AI186: =IF(AJ186>0,"Yes","") | AJ186: 0
B187: Fisher Brown Bottrell Insurance Inc. | C187: 181 | D187: Broker | E187: 36224107 | G187: 46 | H187: 56 | I187: US | AG187: =IF(E187="","",IF(E187>='Reference Tab - Do not Delete'!$E$35,'Reference Tab - Do not Delete'!$D$35,IF(AND(E187>='Reference Tab - Do not Delete'!$E$36,E187<'Reference Tab - Do not Delete'!$E$35),'Reference Tab - Do not Delete'!$D$36,IF(AND(E187>='Reference Tab - Do not Delete'!$E$37,E187<'Reference Tab - Do not Delete'!$E$36),'Reference Tab - Do not Delete'!$D$37,IF(AND(E187>='Reference Tab - Do not Delete'!$E$38,E187<'Reference Tab - Do not Delete'!$E$37),'Reference Tab - Do not Delete'!$D$38,'Reference Tab - Do not Delete'!$D$39))))) -> $500M - $M | AH187: =IF(H187="","DNA",IF(H187<=10,"Top 10",IF(AND(H187<=25,H187>10),"11 - 25",IF(AND(H187<=50,H187>25),"26 - 50","Above 50")))) -> Above 50 | AI187: =IF(AJ187>0,"Yes","") | AJ187: 0
B188: Charles L. Crane Agency | C188: 182 | D188: Broker | E188: 36000000 | G188: 55 | H188: 57 | I188: US | AG188: =IF(E188="","",IF(E188>='Reference Tab - Do not Delete'!$E$35,'Reference Tab - Do not Delete'!$D$35,IF(AND(E188>='Reference Tab - Do not Delete'!$E$36,E188<'Reference Tab - Do not Delete'!$E$35),'Reference Tab - Do not Delete'!$D$36,IF(AND(E188>='Reference Tab - Do not Delete'!$E$37,E188<'Reference Tab - Do not Delete'!$E$36),'Reference Tab - Do not Delete'!$D$37,IF(AND(E188>='Reference Tab - Do not Delete'!$E$38,E188<'Reference Tab - Do not Delete'!$E$37),'Reference Tab - Do not Delete'!$D$38,'Reference Tab - Do not Delete'!$D$39))))) -> $500M - $M | AH188: =IF(H188="","DNA",IF(H188<=10,"Top 10",IF(AND(H188<=25,H188>10),"11 - 25",IF(AND(H188<=50,H188>25),"26 - 50","Above 50")))) -> Above 50 | AI188: =IF(AJ188>0,"Yes","") | AJ188: 0
B189: Robertson Ryan & Associates | C189: 183 | D189: Broker | E189: 35425000 | G189: 54 | H189: 58 | I189: US | AG189: =IF(E189="","",IF(E189>='Reference Tab - Do not Delete'!$E$35,'Reference Tab - Do not Delete'!$D$35,IF(AND(E189>='Reference Tab - Do not Delete'!$E$36,E189<'Reference Tab - Do not Delete'!$E$35),'Reference Tab - Do not Delete'!$D$36,IF(AND(E189>='Reference Tab - Do not Delete'!$E$37,E189<'Reference Tab - Do not Delete'!$E$36),'Reference Tab - Do not Delete'!$D$37,IF(AND(E189>='Reference Tab - Do not Delete'!$E$38,E189<'Reference Tab - Do not Delete'!$E$37),'Reference Tab - Do not Delete'!$D$38,'Reference Tab - Do not Delete'!$D$39))))) -> $500M - $M | AH189: =IF(H189="","DNA",IF(H189<=10,"Top 10",IF(AND(H189<=25,H189>10),"11 - 25",IF(AND(H189<=50,H189>25),"26 - 50","Above 50")))) -> Above 50 | AI189: =IF(AJ189>0,"Yes","") | AJ189: 0
B190: Rich & Cartmill Inc. | C190: 184 | D190: Broker | E190: 34827303 | G190: new | H190: 59 | I190: US | AG190: =IF(E190="","",IF(E190>='Reference Tab - Do not Delete'!$E$35,'Reference Tab - Do not Delete'!$D$35,IF(AND(E190>='Reference Tab - Do not Delete'!$E$36,E190<'Reference Tab - Do not Delete'!$E$35),'Reference Tab - Do not Delete'!$D$36,IF(AND(E190>='Reference Tab - Do not Delete'!$E$37,E190<'Reference Tab - Do not Delete'!$E$36),'Reference Tab - Do not Delete'!$D$37,IF(AND(E190>='Reference Tab - Do not Delete'!$E$38,E190<'Reference Tab - Do not Delete'!$E$37),'Reference Tab - Do not Delete'!$D$38,'Reference Tab - Do not Delete'!$D$39))))) -> $500M - $M | AH190: =IF(H190="","DNA",IF(H190<=10,"Top 10",IF(AND(H190<=25,H190>10),"11 - 25",IF(AND(H190<=50,H190>25),"26 - 50","Above 50")))) -> Above 50 | AI190: =IF(AJ190>0,"Yes","") | AJ190: 0
B191: Andreini & Company | C191: 185 | D191: Broker | E191: 34409442 | G191: 52 | H191: 60 | I191: US | AG191: =IF(E191="","",IF(E191>='Reference Tab - Do not Delete'!$E$35,'Reference Tab - Do not Delete'!$D$35,IF(AND(E191>='Reference Tab - Do not Delete'!$E$36,E191<'Reference Tab - Do not Delete'!$E$35),'Reference Tab - Do not Delete'!$D$36,IF(AND(E191>='Reference Tab - Do not Delete'!$E$37,E191<'Reference Tab - Do not Delete'!$E$36),'Reference Tab - Do not Delete'!$D$37,IF(AND(E191>='Reference Tab - Do not Delete'!$E$38,E191<'Reference Tab - Do not Delete'!$E$37),'Reference Tab - Do not Delete'!$D$38,'Reference Tab - Do not Delete'!$D$39))))) -> $500M - $M | AH191: =IF(H191="","DNA",IF(H191<=10,"Top 10",IF(AND(H191<=25,H191>10),"11 - 25",IF(AND(H191<=50,H191>25),"26 - 50","Above 50")))) -> Above 50 | AI191: =IF(AJ191>0,"Yes","") | AJ191: 0
...

Sheet Buyer Priorities
A1: Mapping Client Priorities - VOC to Solution
A2: The following table provides a consolidated view of all the Strategic Priorities for some of the Top Insurers and Brokers. These priorities (VOC) have been mapped to various EXL solution components to focus on future priorities
A5: Home | F5: VOC | I5: VOC Translation | J5: EXL Solution
A6: Client | B6: C-Level Designation | C6: C-Level Name | D6: Location | E6: EXL - CE | F6: VOC-Source | G6: Priority - Area | H6: Priority - Sub Area | I6: Opportunity | J6: Sign Off - Next Steps/ Delete | K6: EXL - Solution | L6: EXL - Solution Component | M6: Solution Life Cycle | T6: EXL - Solution
A7: Travelers Group | B7: CEO | C7: =IF(A7="","",INDEX('Top Insurers and Brokers'!$B$7:$AF$231,(VLOOKUP(A7,'Top Insurers and Brokers'!$B$7:$C$231,2,0)),VLOOKUP(B7,$AV$9:$AW$15,2,0))) -> Alan Schnitzer | D7: =IF(A7="","",VLOOKUP(A7,'Top Insurers and Brokers'!$B$7:$I$131,8,0)) -> US | E7: =IF(A7="","",VLOOKUP(A7,'Top Insurers and Brokers'!$B$7:$AB$131,11,0)) -> Sean | F7: Press Release | G7: Strong Top Line Performance | H7: Extending our advantage in risk expertise | M7: Not Initiated | T7: FNOL | W7: FNOL | X7: Omni Channel Intake
A8: Travelers Group | B8: CEO | C8: =IF(A8="","",INDEX('Top Insurers and Brokers'!$B$7:$AF$231,(VLOOKUP(A8,'Top Insurers and Brokers'!$B$7:$C$231,2,0)),VLOOKUP(B8,$AV$9:$AW$15,2,0))) -> Alan Schnitzer | D8: =IF(A8="","",VLOOKUP(A8,'Top Insurers and Brokers'!$B$7:$I$131,8,0)) -> US | E8: =IF(A8="","",VLOOKUP(A8,'Top Insurers and Brokers'!$B$7:$AB$131,11,0)) -> Sean | F8: Press Release | G8: Optimizing Operating Leverage | H8: Providing great experiences for our customers, agents and brokers and employees | M8: Not Initiated | T8: PaaS | W8: FNOL | X8: Automated Entry FNOL capability (Thin Human/Heavy Digital)
A9: Travelers Group | B9: CEO | C9: =IF(A9="","",INDEX('Top Insurers and Brokers'!$B$7:$AF$231,(VLOOKUP(A9,'Top Insurers and Brokers'!$B$7:$C$231,2,0)),VLOOKUP(B9,$AV$9:$AW$15,2,0))) -> Alan Schnitzer | D9: =IF(A9="","",VLOOKUP(A9,'Top Insurers and Brokers'!$B$7:$I$131,8,0)) -> US | E9: =IF(A9="","",VLOOKUP(A9,'Top Insurers and Brokers'!$B$7:$AB$131,11,0)) -> Sean | F9: Press Release | G9: Optimizing Operating Leverage | H9: Optimizing our productivity and efficiency | K9: FNOL | L9: Administrative Support and Services | M9: Not Initiated | T9: DT-WC | W9: FNOL | X9: Voice Center of Excellence (COE) | AV9: CEO | AW9: 12
A10: Travelers Group | B10: CEO | C10: =IF(A10="","",INDEX('Top Insurers and Brokers'!$B$7:$AF$231,(VLOOKUP(A10,'Top Insurers and Brokers'!$B$7:$C$231,2,0)),VLOOKUP(B10,$AV$9:$AW$15,2,0))) -> Alan Schnitzer | D10: =IF(A10="","",VLOOKUP(A10,'Top Insurers and Brokers'!$B$7:$I$131,8,0)) -> US | E10: =IF(A10="","",VLOOKUP(A10,'Top Insurers and Brokers'!$B$7:$AB$131,11,0)) -> Sean | F10: Press Release | G10: Growing Investment Portfolio | T10: NB-PaaS | W10: FNOL | X10: Predictive Analytics | AV10: CFO | AW10: 13
A11: Travelers Group | C11: =IF(A11="","",INDEX('Top Insurers and Brokers'!$B$7:$AF$231,(VLOOKUP(A11,'Top Insurers and Brokers'!$B$7:$C$231,2,0)),VLOOKUP(B11,$AV$9:$AW$15,2,0))) -> #N/A | D11: =IF(A11="","",VLOOKUP(A11,'Top Insurers and Brokers'!$B$7:$I$131,8,0)) -> US | E11: =IF(A11="","",VLOOKUP(A11,'Top Insurers and Brokers'!$B$7:$AB$131,11,0)) -> Sean | F11: RM-Meet | G11: Strong Top Line Performance | H11: Extending our advantage in risk expertise | K11: NB_PaaS | L11: Rating | M11: Not Initiated | T11: E-E2E | W11: FNOL | X11: Cloud Hosted | AV11: CRO | AW11: 14
A12: Travelers Group | C12: =IF(A12="","",INDEX('Top Insurers and Brokers'!$B$7:$AF$231,(VLOOKUP(A12,'Top Insurers and Brokers'!$B$7:$C$231,2,0)),VLOOKUP(B12,$AV$9:$AW$15,2,0))) -> #N/A | D12: =IF(A12="","",VLOOKUP(A12,'Top Insurers and Brokers'!$B$7:$I$131,8,0)) -> US | E12: =IF(A12="","",VLOOKUP(A12,'Top Insurers and Brokers'!$B$7:$AB$131,11,0)) -> Sean | F12: RM-Meet | G12: Strong Top Line Performance | H12: Extending our advantage in risk expertise | K12: NB_PaaS | L12: Analytics Insights and Reporting | M12: Not Initiated | T12: BIE | W12: FNOL | X12: Speech Analytics | AV12: CCO | AW12: 15
A13: Travelers Group | C13: =IF(A13="","",INDEX('Top Insurers and Brokers'!$B$7:$AF$231,(VLOOKUP(A13,'Top Insurers and Brokers'!$B$7:$C$231,2,0)),VLOOKUP(B13,$AV$9:$AW$15,2,0))) -> #N/A | D13: =IF(A13="","",VLOOKUP(A13,'Top Insurers and Brokers'!$B$7:$I$131,8,0)) -> US | E13: =IF(A13="","",VLOOKUP(A13,'Top Insurers and Brokers'!$B$7:$AB$131,11,0)) -> Sean | F13: RM-Meet | G13: Strong Top Line Performance | H13: Extending our advantage in risk expertise | K13: NB_PaaS | L13: Submission to Quote | M13: Not Initiated | T13: Int-Col | W13: PaaS | X13: Content Extraction | AV13: COO | AW13: 16
A14: Travelers Group | C14: =IF(A14="","",INDEX('Top Insurers and Brokers'!$B$7:$AF$231,(VLOOKUP(A14,'Top Insurers and Brokers'!$B$7:$C$231,2,0)),VLOOKUP(B14,$AV$9:$AW$15,2,0))) -> #N/A | D14: =IF(A14="","",VLOOKUP(A14,'Top Insurers and Brokers'!$B$7:$I$131,8,0)) -> US | E14: =IF(A14="","",VLOOKUP(A14,'Top Insurers and Brokers'!$B$7:$AB$131,11,0)) -> Sean | F14: RM-Meet | G14: Optimizing Operating Leverage | H14: Optimizing our productivity and efficiency | K14: E_E2E | L14: End to End Endorsement Processing | M14: Not Initiated | T14: Audit-ATC | W14: PaaS | X14: Payee Portal | AV14: CIO/CTO | AW14: 17
A15: Travelers Group | C15: =IF(A15="","",INDEX('Top Insurers and Brokers'!$B$7:$AF$231,(VLOOKUP(A15,'Top Insurers and Brokers'!$B$7:$C$231,2,0)),VLOOKUP(B15,$AV$9:$AW$15,2,0))) -> #N/A | D15: =IF(A15="","",VLOOKUP(A15,'Top Insurers and Brokers'!$B$7:$I$131,8,0)) -> US | E15: =IF(A15="","",VLOOKUP(A15,'Top Insurers and Brokers'!$B$7:$AB$131,11,0)) -> Sean | F15: RM-Meet | G15: Optimizing Operating Leverage | H15: Providing great experiences for our customers, agents and brokers and employees | K15: FNOL | L15: Omni Channel Intake | M15: Not Initiated | T15: PRA | W15: PaaS | X15: Transactional Servicing Features | AV15: CUO | AW15: 18
A16: Travelers Group | C16: =IF(A16="","",INDEX('Top Insurers and Brokers'!$B$7:$AF$231,(VLOOKUP(A16,'Top Insurers and Brokers'!$B$7:$C$231,2,0)),VLOOKUP(B16,$AV$9:$AW$15,2,0))) -> #N/A | D16: =IF(A16="","",VLOOKUP(A16,'Top Insurers and Brokers'!$B$7:$I$131,8,0)) -> US | E16: =IF(A16="","",VLOOKUP(A16,'Top Insurers and Brokers'!$B$7:$AB$131,11,0)) -> Sean | F16: RM-Meet | G16: Optimizing Operating Leverage | H16: Providing great experiences for our customers, agents and brokers and employees | K16: FNOL | L16: Automated Entry FNOL capability (Thin Human/Heavy Digital) | M16: Not Initiated | T16: Fin-Auto | W16: PaaS | X16: Administrative Support and Services
A17: Travelers Group | C17: =IF(A17="","",INDEX('Top Insurers and Brokers'!$B$7:$AF$231,(VLOOKUP(A17,'Top Insurers and Brokers'!$B$7:$C$231,2,0)),VLOOKUP(B17,$AV$9:$AW$15,2,0))) -> #N/A | D17: =IF(A17="","",VLOOKUP(A17,'Top Insurers and Brokers'!$B$7:$I$131,8,0)) -> US | E17: =IF(A17="","",VLOOKUP(A17,'Top Insurers and Brokers'!$B$7:$AB$131,11,0)) -> Sean | F17: RM-Meet | G17: Strong Top Line Performance | H17: Extending our advantage in risk expertise | K17: FNOL | L17: Predictive Analytics | M17: Not Initiated | T17: TrRFF | W17: DT-WC | X17: Medical Case Management Platform
A18: Travelers Group | C18: =IF(A18="","",INDEX('Top Insurers and Brokers'!$B$7:$AF$231,(VLOOKUP(A18,'Top Insurers and Brokers'!$B$7:$C$231,2,0)),VLOOKUP(B18,$AV$9:$AW$15,2,0))) -> #N/A | D18: =IF(A18="","",VLOOKUP(A18,'Top Insurers and Brokers'!$B$7:$I$131,8,0)) -> US | E18: =IF(A18="","",VLOOKUP(A18,'Top Insurers and Brokers'!$B$7:$AB$131,11,0)) -> Sean | F18: RM-Meet | G18: Optimizing Operating Leverage | H18: Providing great experiences for our customers, agents and brokers and employees | K18: FNOL | L18: Conversational IVR | M18: Not Initiated | W18: DT-WC | X18: Automated Entry Medical Record and Bill Management capability (Thin Human/Heavy Digital).
A19: Travelers Group | C19: =IF(A19="","",INDEX('Top Insurers and Brokers'!$B$7:$AF$231,(VLOOKUP(A19,'Top Insurers and Brokers'!$B$7:$C$231,2,0)),VLOOKUP(B19,$AV$9:$AW$15,2,0))) -> #N/A | D19: =IF(A19="","",VLOOKUP(A19,'Top Insurers and Brokers'!$B$7:$I$131,8,0)) -> US | E19: =IF(A19="","",VLOOKUP(A19,'Top Insurers and Brokers'!$B$7:$AB$131,11,0)) -> Sean | F19: RM-Meet | G19: Optimizing Operating Leverage | H19: Optimizing our productivity and efficiency | K19: Int_Col | L19: Analytics Led Risk Prioritization & Forecasting | M19: Not Initiated | W19: DT-WC | X19: End to End Utilization Review
A20: Travelers Group | C20: =IF(A20="","",INDEX('Top Insurers and Brokers'!$B$7:$AF$231,(VLOOKUP(A20,'Top Insurers and Brokers'!$B$7:$C$231,2,0)),VLOOKUP(B20,$AV$9:$AW$15,2,0))) -> #N/A | D20: =IF(A20="","",VLOOKUP(A20,'Top Insurers and Brokers'!$B$7:$I$131,8,0)) -> US | E20: =IF(A20="","",VLOOKUP(A20,'Top Insurers and Brokers'!$B$7:$AB$131,11,0)) -> Sean | F20: RM-Meet | G20: Optimizing Operating Leverage | H20: Optimizing our productivity and efficiency | K20: Int_Col | L20: Real Time Cash Application | M20: Not Initiated | W20: DT-WC | X20: Medical Bill Review Capability/Platform
A21: Allstate Ins Group | C21: =IF(A21="","",INDEX('Top Insurers and Brokers'!$B$7:$AF$231,(VLOOKUP(A21,'Top Insurers and Brokers'!$B$7:$C$231,2,0)),VLOOKUP(B21,$AV$9:$AW$15,2,0))) -> #N/A | D21: =IF(A21="","",VLOOKUP(A21,'Top Insurers and Brokers'!$B$7:$I$131,8,0)) -> US | E21: =IF(A21="","",VLOOKUP(A21,'Top Insurers and Brokers'!$B$7:$AB$131,11,0)) -> Amit Gaba | F21: Other | G21: Transformative Growth Plan | H21: Expand Customer Access | W21: DT-WC | X21: Predictive Analytics Models
A22: Allstate Ins Group | C22: =IF(A22="","",INDEX('Top Insurers and Brokers'!$B$7:$AF$231,(VLOOKUP(A22,'Top Insurers and Brokers'!$B$7:$C$231,2,0)),VLOOKUP(B22,$AV$9:$AW$15,2,0))) -> #N/A | D22: =IF(A22="","",VLOOKUP(A22,'Top Insurers and Brokers'!$B$7:$I$131,8,0)) -> US | E22: =IF(A22="","",VLOOKUP(A22,'Top Insurers and Brokers'!$B$7:$AB$131,11,0)) -> Amit Gaba | F22: Other | G22: Transformative Growth Plan | H22: Enhance Customer Value Proposition | W22: DT-WC | X22: STP Modeling and Automation (Medical Only Claims)
A23: Allstate Ins Group | C23: =IF(A23="","",INDEX('Top Insurers and Brokers'!$B$7:$AF$231,(VLOOKUP(A23,'Top Insurers and Brokers'!$B$7:$C$231,2,0)),VLOOKUP(B23,$AV$9:$AW$15,2,0))) -> #N/A | D23: =IF(A23="","",VLOOKUP(A23,'Top Insurers and Brokers'!$B$7:$I$131,8,0)) -> US | E23: =IF(A23="","",VLOOKUP(A23,'Top Insurers and Brokers'!$B$7:$AB$131,11,0)) -> Amit Gaba | F23: Other | G23: Transformative Growth Plan | H23: Invest in Marketing & Technology | W23: DT-WC | X23: Payment Integrity
A24: Allstate Ins Group | C24: =IF(A24="","",INDEX('Top Insurers and Brokers'!$B$7:$AF$231,(VLOOKUP(A24,'Top Insurers and Brokers'!$B$7:$C$231,2,0)),VLOOKUP(B24,$AV$9:$AW$15,2,0))) -> #N/A | D24: =IF(A24="","",VLOOKUP(A24,'Top Insurers and Brokers'!$B$7:$I$131,8,0)) -> US | E24: =IF(A24="","",VLOOKUP(A24,'Top Insurers and Brokers'!$B$7:$AB$131,11,0)) -> Amit Gaba | F24: Other | G24: Increase Market Share in P&C | H24: Grow exclusive Agencies and Direct Channels | W24: NB-PaaS | X24: Submission to Quote
A25: Allstate Ins Group | C25: =IF(A25="","",INDEX('Top Insurers and Brokers'!$B$7:$AF$231,(VLOOKUP(A25,'Top Insurers and Brokers'!$B$7:$C$231,2,0)),VLOOKUP(B25,$AV$9:$AW$15,2,0))) -> #N/A | D25: =IF(A25="","",VLOOKUP(A25,'Top Insurers and Brokers'!$B$7:$I$131,8,0)) -> US | E25: =IF(A25="","",VLOOKUP(A25,'Top Insurers and Brokers'!$B$7:$AB$131,11,0)) -> Amit Gaba | F25: Other | G25: Increase Market Share in P&C | H25: Leverage Best-in-Class Operational capabilities | W25: NB-PaaS | X25: Rating
A26: CNA Ins Cos | C26: =IF(A26="","",INDEX('Top Insurers and Brokers'!$B$7:$AF$231,(VLOOKUP(A26,'Top Insurers and Brokers'!$B$7:$C$231,2,0)),VLOOKUP(B26,$AV$9:$AW$15,2,0))) -> #N/A | D26: =IF(A26="","",VLOOKUP(A26,'Top Insurers and Brokers'!$B$7:$I$131,8,0)) -> US | E26: Rup Goswami | F26: Press Release | G26: Sustain a deep UW Culture | H26: Elevate employee execution - continuous training, performance management and governance to support the achievement of top quartile performance | W26: NB-PaaS | X26: Analytics Insights and Reporting
A27: CNA Ins Cos | C27: =IF(A27="","",INDEX('Top Insurers and Brokers'!$B$7:$AF$231,(VLOOKUP(A27,'Top Insurers and Brokers'!$B$7:$C$231,2,0)),VLOOKUP(B27,$AV$9:$AW$15,2,0))) -> #N/A | D27: =IF(A27="","",VLOOKUP(A27,'Top Insurers and Brokers'!$B$7:$I$131,8,0)) -> US | E27: Rup Goswami | F27: Press Release | G27: Optimizing distribution engagement | H27: Build effective alignment with distribution partners - product expertise, industry specialization and overall value proposition. | W27: =T10 -> NB-PaaS | X27: End to End Endorsement Processing
A28: CNA Ins Cos | C28: =IF(A28="","",INDEX('Top Insurers and Brokers'!$B$7:$AF$231,(VLOOKUP(A28,'Top Insurers and Brokers'!$B$7:$C$231,2,0)),VLOOKUP(B28,$AV$9:$AW$15,2,0))) -> #N/A | D28: =IF(A28="","",VLOOKUP(A28,'Top Insurers and Brokers'!$B$7:$I$131,8,0)) -> US | E28: Rup Goswami | F28: Press Release | G28: Attracting, developing and retaining top talent | H28: Invest in our people to create advantage and improve performance | W28: BIE | X28: Data Ingestion from Broker Platforms
A29: CNA Ins Cos | C29: =IF(A29="","",INDEX('Top Insurers and Brokers'!$B$7:$AF$231,(VLOOKUP(A29,'Top Insurers and Brokers'!$B$7:$C$231,2,0)),VLOOKUP(B29,$AV$9:$AW$15,2,0))) -> #N/A | D29: =IF(A29="","",VLOOKUP(A29,'Top Insurers and Brokers'!$B$7:$I$131,8,0)) -> US | E29: Rup Goswami | F29: Press Release | G29: Institutionalizing deep specialization | H29: Provide insurance solutions supported by value chains of technical expertise aligned around industry segments, products and exposures | W29: BIE | X29: Data Extraction Module
C30: =IF(A30="","",INDEX('Top Insurers and Brokers'!$B$7:$AF$231,(VLOOKUP(A30,'Top Insurers and Brokers'!$B$7:$C$231,2,0)),VLOOKUP(B30,$AV$9:$AW$15,2,0))) | D30: =IF(A30="","",VLOOKUP(A30,'Top Insurers and Brokers'!$B$7:$I$131,8,0)) | E30: =IF(A30="","",VLOOKUP(A30,'Top Insurers and Brokers'!$B$7:$AB$131,11,0)) | W30: BIE | X30: Value Add Services
C31: =IF(A31="","",INDEX('Top Insurers and Brokers'!$B$7:$AF$231,(VLOOKUP(A31,'Top Insurers and Brokers'!$B$7:$C$231,2,0)),VLOOKUP(B31,$AV$9:$AW$15,2,0))) | D31: =IF(A31="","",VLOOKUP(A31,'Top Insurers and Brokers'!$B$7:$I$131,8,0)) | E31: =IF(A31="","",VLOOKUP(A31,'Top Insurers and Brokers'!$B$7:$AB$131,11,0)) | W31: Int-Col | X31: Analytics Led Risk Prioritization & Forecasting
C32: =IF(A32="","",INDEX('Top Insurers and Brokers'!$B$7:$AF$231,(VLOOKUP(A32,'Top Insurers and Brokers'!$B$7:$C$231,2,0)),VLOOKUP(B32,$AV$9:$AW$15,2,0))) | D32: =IF(A32="","",VLOOKUP(A32,'Top Insurers and Brokers'!$B$7:$I$131,8,0)) | E32: =IF(A32="","",VLOOKUP(A32,'Top Insurers and Brokers'!$B$7:$AB$131,11,0)) | W32: Int-Col | X32: Automated Communications & Chasers
C33: =IF(A33="","",INDEX('Top Insurers and Brokers'!$B$7:$AF$231,(VLOOKUP(A33,'Top Insurers and Brokers'!$B$7:$C$231,2,0)),VLOOKUP(B33,$AV$9:$AW$15,2,0))) | D33: =IF(A33="","",VLOOKUP(A33,'Top Insurers and Brokers'!$B$7:$I$131,8,0)) | E33: =IF(A33="","",VLOOKUP(A33,'Top Insurers and Brokers'!$B$7:$AB$131,11,0)) | W33: Int-Col | X33: Real Time Cash Application
C34: =IF(A34="","",INDEX('Top Insurers and Brokers'!$B$7:$AF$231,(VLOOKUP(A34,'Top Insurers and Brokers'!$B$7:$C$231,2,0)),VLOOKUP(B34,$AV$9:$AW$15,2,0))) | D34: =IF(A34="","",VLOOKUP(A34,'Top Insurers and Brokers'!$B$7:$I$131,8,0)) | E34: =IF(A34="","",VLOOKUP(A34,'Top Insurers and Brokers'!$B$7:$AB$131,11,0)) | W34: Int-Col | X34: Comprehensive Data Reports and Dashboards
C35: =IF(A35="","",INDEX('Top Insurers and Brokers'!$B$7:$AF$231,(VLOOKUP(A35,'Top Insurers and Brokers'!$B$7:$C$231,2,0)),VLOOKUP(B35,$AV$9:$AW$15,2,0))) | D35: =IF(A35="","",VLOOKUP(A35,'Top Insurers and Brokers'!$B$7:$I$131,8,0)) | E35: =IF(A35="","",VLOOKUP(A35,'Top Insurers and Brokers'!$B$7:$AB$131,11,0)) | W35: Int-Col | X35: Other Receivables Areas
C36: =IF(A36="","",INDEX('Top Insurers and Brokers'!$B$7:$AF$231,(VLOOKUP(A36,'Top Insurers and Brokers'!$B$7:$C$231,2,0)),VLOOKUP(B36,$AV$9:$AW$15,2,0))) | D36: =IF(A36="","",VLOOKUP(A36,'Top Insurers and Brokers'!$B$7:$I$131,8,0)) | E36: =IF(A36="","",VLOOKUP(A36,'Top Insurers and Brokers'!$B$7:$AB$131,11,0)) | W36: Audit-ATC | X36: Audit Analytics Center of Excellence (COE)
C37: =IF(A37="","",INDEX('Top Insurers and Brokers'!$B$7:$AF$231,(VLOOKUP(A37,'Top Insurers and Brokers'!$B$7:$C$231,2,0)),VLOOKUP(B37,$AV$9:$AW$15,2,0))) | D37: =IF(A37="","",VLOOKUP(A37,'Top Insurers and Brokers'!$B$7:$I$131,8,0)) | E37: =IF(A37="","",VLOOKUP(A37,'Top Insurers and Brokers'!$B$7:$AB$131,11,0)) | W37: Audit-ATC | X37: Dashboard/Customer Report Development
C38: =IF(A38="","",INDEX('Top Insurers and Brokers'!$B$7:$AF$231,(VLOOKUP(A38,'Top Insurers and Brokers'!$B$7:$C$231,2,0)),VLOOKUP(B38,$AV$9:$AW$15,2,0))) | D38: =IF(A38="","",VLOOKUP(A38,'Top Insurers and Brokers'!$B$7:$I$131,8,0)) | E38: =IF(A38="","",VLOOKUP(A38,'Top Insurers and Brokers'!$B$7:$AB$131,11,0)) | W38: Audit-ATC | X38: Audit Bot Development and Maintenance
C39: =IF(A39="","",INDEX('Top Insurers and Brokers'!$B$7:$AF$231,(VLOOKUP(A39,'Top Insurers and Brokers'!$B$7:$C$231,2,0)),VLOOKUP(B39,$AV$9:$AW$15,2,0))) | D39: =IF(A39="","",VLOOKUP(A39,'Top Insurers and Brokers'!$B$7:$I$131,8,0)) | E39: =IF(A39="","",VLOOKUP(A39,'Top Insurers and Brokers'!$B$7:$AB$131,11,0)) | W39: PRA | X39: COE Delivery Structure
C40: =IF(A40="","",INDEX('Top Insurers and Brokers'!$B$7:$AF$231,(VLOOKUP(A40,'Top Insurers and Brokers'!$B$7:$C$231,2,0)),VLOOKUP(B40,$AV$9:$AW$15,2,0))) | D40: =IF(A40="","",VLOOKUP(A40,'Top Insurers and Brokers'!$B$7:$I$131,8,0)) | E40: =IF(A40="","",VLOOKUP(A40,'Top Insurers and Brokers'!$B$7:$AB$131,11,0)) | W40: PRA | X40: Automation/Robotics
C41: =IF(A41="","",INDEX('Top Insurers and Brokers'!$B$7:$AF$231,(VLOOKUP(A41,'Top Insurers and Brokers'!$B$7:$C$231,2,0)),VLOOKUP(B41,$AV$9:$AW$15,2,0))) | D41: =IF(A41="","",VLOOKUP(A41,'Top Insurers and Brokers'!$B$7:$I$131,8,0)) | E41: =IF(A41="","",VLOOKUP(A41,'Top Insurers and Brokers'!$B$7:$AB$131,11,0)) | W41: PRA | X41: Analytics & Reporting
... C43: =IF(A43="","",INDEX('Top Insurers and Brokers'!$B$7:$AF$231,(VLOOKUP(A43,'Top Insurers and Brokers'!$B$7:$C$231,2,0)),VLOOKUP(B43,$AV$9:$AW$15,2,0))) | D43: =IF(A43="","",VLOOKUP(A43,'Top Insurers and Brokers'!$B$7:$I$131,8,0)) | E43: =IF(A43="","",VLOOKUP(A43,'Top Insurers and Brokers'!$B$7:$AB$131,11,0)) | W43: PRA | X43: Dual Shore
C44: =IF(A44="","",INDEX('Top Insurers and Brokers'!$B$7:$AF$231,(VLOOKUP(A44,'Top Insurers and Brokers'!$B$7:$C$231,2,0)),VLOOKUP(B44,$AV$9:$AW$15,2,0))) | D44: =IF(A44="","",VLOOKUP(A44,'Top Insurers and Brokers'!$B$7:$I$131,8,0)) | E44: =IF(A44="","",VLOOKUP(A44,'Top Insurers and Brokers'!$B$7:$AB$131,11,0)) | W44: =T16 -> Fin-Auto | X44: RPA
C45: =IF(A45="","",INDEX('Top Insurers and Brokers'!$B$7:$AF$231,(VLOOKUP(A45,'Top Insurers and Brokers'!$B$7:$C$231,2,0)),VLOOKUP(B45,$AV$9:$AW$15,2,0))) | D45: =IF(A45="","",VLOOKUP(A45,'Top Insurers and Brokers'!$B$7:$I$131,8,0)) | E45: =IF(A45="","",VLOOKUP(A45,'Top Insurers and Brokers'!$B$7:$AB$131,11,0)) | W45: =T17 -> TrRFF | X45: Finance Blueprint
C46: =IF(A46="","",INDEX('Top Insurers and Brokers'!$B$7:$AF$231,(VLOOKUP(A46,'Top Insurers and Brokers'!$B$7:$C$231,2,0)),VLOOKUP(B46,$AV$9:$AW$15,2,0))) | D46: =IF(A46="","",VLOOKUP(A46,'Top Insurers and Brokers'!$B$7:$I$131,8,0)) | E46: =IF(A46="","",VLOOKUP(A46,'Top Insurers and Brokers'!$B$7:$AB$131,11,0))
C47: =IF(A47="","",INDEX('Top Insurers and Brokers'!$B$7:$AF$231,(VLOOKUP(A47,'Top Insurers and Brokers'!$B$7:$C$231,2,0)),VLOOKUP(B47,$AV$9:$AW$15,2,0))) | D47: =IF(A47="","",VLOOKUP(A47,'Top Insurers and Brokers'!$B$7:$I$131,8,0)) | E47: =IF(A47="","",VLOOKUP(A47,'Top Insurers and Brokers'!$B$7:$AB$131,11,0))
C48: =IF(A48="","",INDEX('Top Insurers and Brokers'!$B$7:$AF$231,(VLOOKUP(A48,'Top Insurers and Brokers'!$B$7:$C$231,2,0)),VLOOKUP(B48,$AV$9:$AW$15,2,0))) | D48: =IF(A48="","",VLOOKUP(A48,'Top Insurers and Brokers'!$B$7:$I$131,8,0)) | E48: =IF(A48="","",VLOOKUP(A48,'Top Insurers and Brokers'!$B$7:$AB$131,11,0))
C49: =IF(A49="","",INDEX('Top Insurers and Brokers'!$B$7:$AF$231,(VLOOKUP(A49,'Top Insurers and Brokers'!$B$7:$C$231,2,0)),VLOOKUP(B49,$AV$9:$AW$15,2,0))) | D49: =IF(A49="","",VLOOKUP(A49,'Top Insurers and Brokers'!$B$7:$I$131,8,0)) | E49: =IF(A49="","",VLOOKUP(A49,'Top Insurers and Brokers'!$B$7:$AB$131,11,0))
C50: =IF(A50="","",INDEX('Top Insurers and Brokers'!$B$7:$AF$231,(VLOOKUP(A50,'Top Insurers and Brokers'!$B$7:$C$231,2,0)),VLOOKUP(B50,$AV$9:$AW$15,2,0))) | D50: =IF(A50="","",VLOOKUP(A50,'Top Insurers and Brokers'!$B$7:$I$131,8,0)) | E50: =IF(A50="","",VLOOKUP(A50,'Top Insurers and Brokers'!$B$7:$AB$131,11,0))
C51: =IF(A51="","",INDEX('Top Insurers and Brokers'!$B$7:$AF$231,(VLOOKUP(A51,'Top Insurers and Brokers'!$B$7:$C$231,2,0)),VLOOKUP(B51,$AV$9:$AW$15,2,0))) | D51: =IF(A51="","",VLOOKUP(A51,'Top Insurers and Brokers'!$B$7:$I$131,8,0)) | E51: =IF(A51="","",VLOOKUP(A51,'Top Insurers and Brokers'!$B$7:$AB$131,11,0))
C52: =IF(A52="","",INDEX('Top Insurers and Brokers'!$B$7:$AF$231,(VLOOKUP(A52,'Top Insurers and Brokers'!$B$7:$C$231,2,0)),VLOOKUP(B52,$AV$9:$AW$15,2,0))) | D52: =IF(A52="","",VLOOKUP(A52,'Top Insurers and Brokers'!$B$7:$I$131,8,0)) | E52: =IF(A52="","",VLOOKUP(A52,'Top Insurers and Brokers'!$B$7:$AB$131,11,0))
C53: =IF(A53="","",INDEX('Top Insurers and Brokers'!$B$7:$AF$231,(VLOOKUP(A53,'Top Insurers and Brokers'!$B$7:$C$231,2,0)),VLOOKUP(B53,$AV$9:$AW$15,2,0))) | D53: =IF(A53="","",VLOOKUP(A53,'Top Insurers and Brokers'!$B$7:$I$131,8,0)) | E53: =IF(A53="","",VLOOKUP(A53,'Top Insurers and Brokers'!$B$7:$AB$131,11,0))
C54: =IF(A54="","",INDEX('Top Insurers and Brokers'!$B$7:$AF$231,(VLOOKUP(A54,'Top Insurers and Brokers'!$B$7:$C$231,2,0)),VLOOKUP(B54,$AV$9:$AW$15,2,0))) | D54: =IF(A54="","",VLOOKUP(A54,'Top Insurers and Brokers'!$B$7:$I$131,8,0)) | E54: =IF(A54="","",VLOOKUP(A54,'Top Insurers and Brokers'!$B$7:$AB$131,11,0))
C55: =IF(A55="","",INDEX('Top Insurers and Brokers'!$B$7:$AF$231,(VLOOKUP(A55,'Top Insurers and Brokers'!$B$7:$C$231,2,0)),VLOOKUP(B55,$AV$9:$AW$15,2,0))) | D55: =IF(A55="","",VLOOKUP(A55,'Top Insurers and Brokers'!$B$7:$I$131,8,0)) | E55: =IF(A55="","",VLOOKUP(A55,'Top Insurers and Brokers'!$B$7:$AB$131,11,0))
C56: =IF(A56="","",INDEX('Top Insurers and Brokers'!$B$7:$AF$231,(VLOOKUP(A56,'Top Insurers and Brokers'!$B$7:$C$231,2,0)),VLOOKUP(B56,$AV$9:$AW$15,2,0))) | D56: =IF(A56="","",VLOOKUP(A56,'Top Insurers and Brokers'!$B$7:$I$131,8,0)) | E56: =IF(A56="","",VLOOKUP(A56,'Top Insurers and Brokers'!$B$7:$AB$131,11,0))
C57: =IF(A57="","",INDEX('Top Insurers and Brokers'!$B$7:$AF$231,(VLOOKUP(A57,'Top Insurers and Brokers'!$B$7:$C$231,2,0)),VLOOKUP(B57,$AV$9:$AW$15,2,0))) | D57: =IF(A57="","",VLOOKUP(A57,'Top Insurers and Brokers'!$B$7:$I$131,8,0)) | E57: =IF(A57="","",VLOOKUP(A57,'Top Insurers and Brokers'!$B$7:$AB$131,11,0))
... C108: =IF(A108="","",INDEX('Top Insurers and Brokers'!$B$7:$AF$231,(VLOOKUP(A108,'Top Insurers and Brokers'!$B$7:$C$231,2,0)),VLOOKUP(B108,$AV$9:$AW$15,2,0))) | D108: =IF(A108="","",VLOOKUP(A108,'Top Insurers and Brokers'!$B$7:$I$131,8,0)) | E108: =IF(A108="","",VLOOKUP(A108,'Top Insurers and Brokers'!$B$7:$AB$131,11,0))
C109: =IF(A109="","",INDEX('Top Insurers and Brokers'!$B$7:$AF$131,(VLOOKUP(A109,'Top Insurers and Brokers'!$B$7:$C$131,2,0)),VLOOKUP(B109,$AV$9:$AW$15,2,0))) | D109: =IF(A109="","",VLOOKUP(A109,'Top Insurers and Brokers'!$B$7:$I$131,8,0)) | E109: =IF(A109="","",VLOOKUP(A109,'Top Insurers and Brokers'!$B$7:$AB$131,11,0))

Sheet Competitor Analysis
A1: Competitor Analysis
A2: This active document tracks the range of services by each client area currently being provided by EXL's competitors alogn with the potential FTE span as an opportunity area for EXL
A3: Home
A4: S No | B4: GROUP NAME | C4: Type | D4: Strategic / Named | E4: EXL Contact | F4: Service Provider | G4: Contract Renewal | H4: Claims | I4: UW | J4: Premium Audit | K4: F&A | L4: Platform | M4: FTEs | N4: Comments (Processes etc.) | Q4: Existing EXL Client | S4: < 6 Months
A5: 1 | B5: Hanover Insurance Group Inc. | C5: Public | D5: Strategic | F5: Corvel | H5: Y | M5: NA | N5: Medical Bill Review (WC Claims) - now being rolled off | S5: 1 Year
A6: 2 | B6: Liberty Mutual | C6: Mutual | D6: Named | F6: CTS | H6: Y | M6: 100 | N6: Clinical Operations - Bill review and Utilization review | S6: 2 Year
A7: 3 | B7: Liberty Mutual | F7: CTS | I7: Y | M7: 200 | N7: Policy Admin - Endorsement, Policy Servicing , underwriting | S7: 3 Year
A8: 4 | B8: Travelers Companies Inc. | C8: Public | D8: Named Backup | F8: CTS | G8: < 6 Months | H8: Y | I8: Y | M8: 450 | N8: Personal Insurance, Commercial Insurnace - From new business to claims settlement
A9: 5 | B9: Travelers Companies Inc. | F9: CTS | G9: < 6 Months | H9: Y | M9: 100 | N9: Bill Review and Utilization Review
A10: 6 | B10: Travelers Companies Inc. | F10: CTS | G10: < 6 Months | I10: Y | M10: 200 | N10: Policy Admin- Endorsement, Policy Servicing , underwriting
A11: 7 | B11: Travelers Companies Inc. | F11: CTS | G11: < 6 Months | H11: Y | M11: 100 | N11: Group Benefit Claims
A12: 8 | B12: Travelers Companies Inc. | F12: CTS | G12: < 6 Months | K12: Y | M12: 150 | N12: Contact Center - Direct billing, Agency calls, provider call, 3rd party calls, financial calls
A13: 9 | B13: One Call Care Management (OCCM) | F13: CTS | K13: Y | M13: 180 | N13: Client is a mediator between various healthcare providers, patient and Insurance company. They manage end to end work right from Intake to invoice processing. Intake, AP, AR, Customer Service
A14: 10 | B14: One Call Care Management (OCCM) | F14: CTS | H14: Y | M14: 1000 | N14: Provider credentialling, Claim packaging, Transprt and language, Medical equipment
A15: 11 | B15: Nationwide Mutual Group | C15: Mutual | D15: Named | F15: CTS | I15: Y | M15: 200 | N15: Policy Admin - Endorsement, Policy Servicing , underwriting
A16: 12 | B16: American International Group | C16: Public | D16: Strategic | F16: CTS | I16: Y | K16: Y | M16: 760 | N16: Policy Admin, Policy Maintenance, AP, AR (minus collection)
A17: 13 | B17: American International Group | F17: CTS | K17: Y | M17: 100 | N17: Collections
A18: 14 | B18: Hartford Financial Services | C18: Public | D18: Strategic | F18: CTS | H18: Y | I18: Y | M18: 350 | N18: They manage end to end work right from new business to claims settlement
A19: 15 | B19: Hartford Financial Services | F19: CTS | H19: Y | M19: 117 | N19: Group Benefit claim
A20: 16 | B20: Hartford Financial Services | F20: CTS | M20: 50 | N20: Consumer EDM
A21: 17 | B21: Hartford Financial Services | F21: CTS | K21: Y | M21: 163 | N21: FinOps
A22: 18 | B22: Zurich Insurance Group | C22: Public | D22: Strategic | F22: CTS | H22: Y | M22: 100 | N22: Medical Bill Review - Medwise
A23: 19 | B23: Hanover Insurance Group Inc. | C23: Public | D23: Strategic | F23: CTS | H23: Y | L23: Y | M23: NA | N23: System Integrator for Guidewire and RPA service provider
A24: 20 | B24: Utica National Insurance Group | C24: Private/Mutual | F24: CTS
A25: 21 | B25: TRYG (Nordics) | F25: CTS
A26: 22 | B26: Optum | F26: CTS
A27: 23 | B27: Zurich NA | F27: CTS | H27: Y
A28: 24 | B28: Nationwide | F28: CTS
A29: 25 | B29: Mitchell Insurance | F29: CTS
A30: 26 | B30: CCC Information Services | F30: CTS
A31: 27 | B31: Utica National Insurance Group | F31: CTS
A32: 28 | B32: Hartford | F32: CTS
A33: 29 | B33: Allstate Corp. | C33: Public | D33: Strategic | F33: Genpact
A34: 30 | B34: Liberty Mutual | F34: Genpact
A35: 31 | B35: RSA Group UK | F35: Genpact
A36: 32 | B36: BUPA UK | F36: Genpact
A37: 33 | B37: Allstate Corp. | F37: Genpact
A38: 34 | B38: Aspen | F38: Genpact
A39: 35 | B39: Travelers Companies Inc. | F39: Genpact | I39: Y | M39: 60 | N39: Policy Maintenance
A40: 36 | B40: Travelers Companies Inc. | F40: Genpact | H40: Y | M40: 50 | N40: Claims
A41: 37 | B41: Travelers Companies Inc. | F41: Genpact | K41: Y | M41: 100 | N41: Invoicing
A42: 38 | B42: Swiss Re Ltd. | C42: Public | F42: Genpact | I42: Y | M42: 100 | N42: Undewritng Support Policy Admin
A43: 39 | B43: Swiss Re Ltd. | F43: Genpact | I43: Y | M43: 250 | N43: Policy Maintenance
A44: 40 | B44: Genworth Financial Inc. | C44: Public | F44: Genpact | I44: Y | M44: 240 | N44: Underwriting Support POlicy Admin
A45: 41 | B45: Genworth Financial Inc. | C45: Public | F45: Genpact | H45: Y | M45: 60 | N45: Claims
A46: 42 | B46: AON | F46: Genpact | I46: Y | M46: 40 | N46: Underwriting Support CSU
A47: 43 | B47: AON | F47: Genpact | I47: Y | M47: 100 | N47: Underwriting Support Invoicing
A48: 44 | B48: AON | F48: Genpact | I48: Y | M48: 150 | N48: Underwriting Support DPU
A49: 45 | B49: AON | F49: Genpact | I49: Y | M49: 100 | N49: Underwriting Support Policy Admin
A50: 46 | B50: AON (Netherlands) | F50: Genpact | I50: Y | M50: 100 | N50: Underwriting Support Policy Admin
A51: 47 | B51: Root Insurance | F51: Genpact | H51: Y | N51: https://www.genpact.com/about-us/media/press-releases/2019-root-insurance-partners-with-genpact-to-transform-the-auto-insurance-industry
A52: 48 | B52: Hanover Insurance Group Inc. | C52: Public | D52: Strategic | F52: Insurity | I52: Y | L52: Y | M52: NA | N52: Insurity Platform for UW processes
A53: 49 | B53: Hanover Insurance Group Inc. | C53: Public | D53: Strategic | F53: Medata | H53: Y | M53: TBD | N53: Medical Bill Review (WC Claims)
A54: 50 | B54: Hanover Insurance Group Inc. | C54: Public | D54: Strategic | F54: NTT | H54: Y | I54: Y | J54: Y | K54: Y | L54: Y | M54: NA | N54: Technology Infra and Maintenance
A55: 51 | B55: Hiscox US | F55: Sutherland
A56: 52 | B56: Hanover Insurance Group Inc. | C56: Public | D56: Strategic | F56: TBD | I56: Y | L56: Y | M56: NA | N56: New System Integrator for insurity to be announced
A57: 53 | B57: State Farm Mutual Automobile Ins. | C57: Mutual | D57: Named | F57: TCS
A58: 54 | B58: Progressive Corp. | C58: Public | D58: Named | F58: TCS
A59: 55 | B59: American International Group | C59: Public | F59: Cognizant (F&A - Collections), TCS (Analytics - Data / IT) | G59: 1 Year | H59: N | I59: N | J59: Y | K59: Y | L59: Y | M59: 50 | N59: EXL does Billing, Premium Adjustement and Collections. Collections process for us is on contingency (not FTE based), AIG has its own captive for domain BPO and analytics. TCS does work on the Technical side of Analytics (from the IT side)
A60: 56 | B60: Aviva | F60: TCS
A61: 57 | B61: AXA | F61: TCS
A62: 58 | B62: ING Group | F62: TCS
A63: 59 | B63: Tryg | F63: TCS
A64: 60 | B64: Hiscox UK (5 FTE’s) | F64: WNS
A65: 61 | B65: Travelers Companies Inc. | F65: WNS
A66: 62 | B66: AmTrust Financial Services | C66: Public | D66: Named Backup | F66: WNS
A67: 63 | B67: QBE Insurance Group Ltd. | C67: Public | D67: Named | F67: WNS | N67: BPO / Analytics - $40 MM TCV
A68: 64 | B68: IAG NZ | F68: WNS | I68: Y | M68: 110 | N68: Rating (Broker Business), Policy Servicing
A69: 65 | B69: IAG NZ | F69: WNS | H69: Y | M69: 135 | N69: Payments & closure, Claims Lodgement(FNOL), Filing, Recoveries
A70: 66 | B70: IAG NZ | F70: WNS | I70: Y | M70: 30 | N70: Bank Insurance Rating
A71: 67 | B71: IAH Australia | F71: WNS | I71: Y | M71: 50 | N71: Rating, Policy Servicing
A72: 68 | B72: MARSH Broker | F72: WNS
A73: 69 | B73: Sun Corp | F73: WNS
A74: 70 | B74: Aviva | F74: WNS | N74: $640 MM TCV BPO Insurance Services Other ITO (Hosting, Email, Security, Disaster Recovery), F&A, Insurance Services, Analytics,
A75: 71 | B75: Canopious | F75: WNS
A76: 72 | B76: Marsh | F76: WNS

Sheet Dashboard
B1: P&C Strategy & Solution Dashboard
B3: This page provides one view of all the Top Insurers & Brokers, their priorities mapped to EXL's solution elements along with Gap assessment vs. Build-Buy-Partner options
B5: Home
B6: Shortlisting Clients | K6: Summary of VOC to EXL Solution | Q6: Capability - Gap Analysis

Sheet Top Clients Shortlist
C1: Home | D1: Top Insurers and Brokers
D3: The following table provides a wholsitic view of the top Global Insurers and Brokers along with their Top Executives and Financial standing to arrive at a Prioritzation to identify EXL's future strategies and Key Customers.
A5: Bucket | B5: # | C5: Client | D5: Geography | E5: Strategic/Named | F5: Growth Leader | G5: Client Exec | H5: CEO | I5: CFO | J5: CRO | K5: CCO | L5: COO | M5: CIO/CTO | N5: CUO | O5: GWP | P5: Growth % | Q5: Combined Ratio (2019) | R5: Do they outsource today | S5: Competitors | T5: Renewal Date | U5: Known partnership with InsureTech | V5: EXL Solutions Go-To-Market Mapping | W5: EXL Client | X5: 2020-Rev Budget | Y5: EXL's Share of Wallet | Z5: Competition Account | AA5: Competition's Share of Wallet | AB5: Relationship Maturity (Yrs) | AC5: Renewal Timeframe | AD5: Future TCV Potential | AE5: Client Priority Rating
A6: Drive Solutions across existing and new clients that leverages our combined strengths | B6: 1 | C6: QBE | D6: Australia | E6: Strategic | F6: Vilas | G6: Vilas | H6: Vivek Bhatia | I6: Chris Killourhy | J6: Jonathan Groves | K6: Jon Fox | M6: Mark Gay/ Fiona Hayes-St Clair | O6: 3920 ($m) | P6: 0.03 | Q6: 90 | R6: Yes | S6: Accenture, Delloitte, KPMG
B7: 2 | C7: C-N-A | D7: US | E7: Strategic | F7: Saju | G7: Roopak Chadha | H7: Dino Robusto | I7: Al Miralles | K7: Daniel Franzetti | L7: Kevin Leidwinger | M7: Michael Costonis | N7: Douglas M. Worman | O7: $7.7B | P7: 0.07 | Q7: 94.8 | R7: Yes | T7: 44562
A8: Drive more adoption of Analytics | B8: 3 | C8: Liberty Mutual | D8: US | E8: Strategic | F8: Nikhil | G8: Kuldeep | H8: David H. Long | I8: Christopher Pierce | M8: James McGlennon | O8: $39.8B | P8: 0.018 | Q8: 101.7 | R8: Yes | S8: Genpact, Cognizant, TCS | T8: 45078 | AE8: 11
A9: Drive more adoption of Analytics | B9: 4 | C9: Zurich | D9: US | E9: Strategic | F9: Roopak | G9: Raish Malik | H9: Kathleen Savio | I9: Peter Hirs | J9: Colleen Zitt | K9: Paul Lavelle | L9: Anurag Batta | M9: Mark Knipfer | N9: Brandin Fick | O9: $34.1B | P9: 0.061 | Q9: 96.4 | R9: Yes | S9: Cognizant, Genpact, Mphasis,Hinduja | T9: 44562
A10: Drive more adoption of Analytics | B10: 5 | C10: Hartford | D10: US | E10: Strategic | F10: Saju | G10: Kuldeep | H10: Kuldeep Singh | I10: Chris Swift | J10: Beth Costello | K10: Robert Paiano | L10: John Kinney | M10: Bill Bloom | N10: Bill Bloom | O10: Ross Fisher | P10: $17B | Q10: 94 CL(97.7), PL(95) | R10: Yes | S10: CTS | T10: 45627
A11: Drive more adoption of Analytics | B11: 6 | C11: Hanover | D11: US | E11: Strategic | F11: Saju | G11: Aditya Chaturvedi | H11: John "Jack" Roche | I11: Jeff Farber | J11: Catherine Eska | K11: Mark Welzenbach | L11: Gayle Falvey - CL Michele Streton - PL | M11: Mark Berthiaume | N11: Chip Hamann (Small Commercial) | O11: $4,581.7 M (NWP) | P11: 0.045 | Q11: 95.6 | R11: Yes | S11: CTS, NTT, PWC | T11: 44531
A12: Accelerate decision making in existing new pursuits | B12: 7 | C12: Allstate | D12: US | E12: Strategic | F12: Amit Gaba | G12: Amit Gaba | H12: Tom Wilson | I12: Mario Rizzo | J12: Mark Prindiville | K12: Eric Brandt | L12: Glenn Shapiro | M12: Suren Gupta | O12: $34.8B | P12: 0.057 | Q12: 85 | R12: Yes | S12: Genpact, Fractal | T12: MSA is perpetual
A13: Accelerate decision making in existing new pursuits | B13: 8 | C13: Kemper | D13: US | E13: Other | F13: Amit Gaba | G13: Amit Gaba | H13: Joe Lacher | I13: Jim McKinney | J13: Max Mindak | K13: Kim Leggette | L13: Duane Sanders | M13: Charles Brooks | O13: $4B | P13: 30%+ | Q13: 93 | R13: Yes | S13: Accenture | T13: Key SOW renewal date Jan 1, 2021
A14: Accelerate decision making in existing new pursuits | B14: 9 | C14: IAG | D14: Australia | E14: Strategic | F14: Vilas | G14: Vilas | H14: Peter Harmer | I14: Nick Hawkins | J14: David Watts | M14: Neil Morgan | O14: 12,135 ($m) | P14: 0.011 | Q14: 123 | R14: Yes | S14: WNS | T14: 44470
A15: Accelerate decision making in existing new pursuits | B15: 10 | C15: Suncorp | D15: Australia | E15: Strategic | F15: Vilas | G15: Viilas | H15: Steve Johnston | I15: Jeremy Robson | J15: Fiona Thompson | L15: Paul Smeaton (Insurance) | M15: Adam Bennett | O15: 8119 ($m) | P15: 0.015 | Q15: 96 | R15: Yes | S15: WNS, Genpact, Cognizant | T15: 44191
A16: Accelerate decision making in existing new pursuits | B16: 11 | C16: Assurant | D16: US | E16: Strategic | F16: Roopak | G16: Dushyant
A17: Drive Solutions across existing and new clients that leverages our combined strengths | B17: 12 | C17: Esure Insurance Holdings | D17: UK/Europe | E17: Named | F17: Mohit | H17: David McMillan | I17: Steve Long | J17: Darren Boland | K17: Graham Hughes | L17: David Pitt | M17: Graham Bolton
A18: Drive Solutions across existing and new clients that leverages our combined strengths | B18: 13 | C18: Swiss Re | D18: US | E18: Named | F18: Mohit | G18: Mohit | H18: J.Eric Smith | I18: Brian Rosenblum | J18: Stefanie Stratos | K18: Thomas Hyatte | L18: Rich Agar | M18: Prashanthi Roy /Pravina Ladva | O18: $42,228M | P18: 0.029 | Q18: 107 | R18: Yes | S18: CSC, Genpact, TCS | T18: 2021 (They have multiple BPO, automation and analytics partner)
A19: Accelerate decision making in existing new pursuits | B19: 14 | C19: Nationwide Insurance | D19: US | E19: Named | F19: Mohit | G19: Mohit | H19: Kirt Walker | I19: Mark Thresher | J19: Klaus Diem | K19: Sandra Rich | L19: Mark Berven | M19: James Fowler | O19: $49.3B | P19: 0.025 | Q19: 94 | R19: Yes | S19: Cognizant, Genpact | T19: Mid 2021, 2022
A20: Accelerate decision making in existing new pursuits | B20: 15 | C20: American Modern | D20: US | E20: Named | F20: Sean | G20: Sean | H20: Andreas Kleiner | I20: Rene Gobanya | J20: Trey Griffith | K20: Eric Hunzinger | L20: Paul Schneider | M20: Bill Gottsacker | N20: Kam Jha | O20: $2.5B | P20: 0.03 | Q20: N/A | R20: Yes | S20: TCS | T20: Just signed with us
A21: Accelerate decision making in existing new pursuits | B21: 16 | C21: Everest Insurance | D21: US | E21: Named | F21: Sean | G21: Sean | H21: Mike Karmilowicz | I21: Dana Lodge | J21: Bill Thygeson, CAO | K21: Patricia Mcmahon | L21: Mike Mulray | M21: Owen Williams | N21: Open | O21: $4B | P21: 0.04 | Q21: 88.7 | R21: Yes | S21: None | T21: 2023
A22: Accelerate decision making in existing new pursuits | B22: 17 | C22: Axis | D22: US | E22: Named | F22: Sean | G22: Sean | H22: Albert Benchimol | I22: Pete Vogt | J22: Ben Rubin | K22: Mike Baumel | L22: Rob Hartman | M22: Keith Schlosser | N22: Eric Gesick | O22: 6.9 | P22: 0.01 | Q22: 107.3 | R22: Yes | S22: Genpact, Infy | T22: 2022
A23: Acceleration of ramps / Deacceleration of ramp downs | B23: 18 | C23: Aon | D23: UK/Europe | E23: Named | F23: Mohit | G23: Wayne Reed | H23: Greg Case | I23: Christa Davies | J23: Paul Henmueller | L23: John Bruno | M23: Rajeev Khanna | P23: 0.019
A24: Accelerate decision making in existing new pursuits | B24: 19 | C24: Marsh | D24: UK/Europe | E24: Named | F24: Mohit | G24: Wayne Reed | H24: Dan Glaser | I24: Mark McGivney | J24: Diane Rosen | K24: Srivatsan Sridharan | L24: Levee Brooks | M24: Scott Gilbert | P24: 0.04 | R24: Yes | S24: WNS,CTS
A25: Accelerate decision making in existing new pursuits | B25: 20 | C25: Aviva | D25: UK/Europe | E25: Strategic | F25: Nick | G25: Nick | H25: Amanda Blanc | I25: Mark Windsor | J25: Jan – Hendrik Erasmus | L25: Nick Amin | O25: £31.2bn | P25: 0.09 | Q25: 97.5 | R25: Yes | S25: WNS incumbent | T25: Competitive process running: EXL, Genpact, TCS, WNS - submission Sept, decision for BAFO with 2 suppliers end October
A26: Acceleration of ramps / Deacceleration of ramp downs | B26: 21 | C26: Travelers | D26: US | E26: Named | F26: Sean | G26: Sean | H26: Alan Schnitzer | I26: Dan Frey | J26: Bruce Jones | K26: Nicolas Seminara | L26: Mojgan Lefebvre | M26: Mojgan Lefebvre | N26: Rick Schug | O26: $29B | P26: 0.05 | Q26: 96.5 | R26: Yes | S26: CTS, WNS, Genpact | T26: 2021 | AE26: 12
A27: Acceleration of ramps / Deacceleration of ramp downs | B27: 22 | C27: Great American | D27: US | E27: Named | F27: Sean | G27: Sean | H27: Carl Lindnor, Craig Lindnor | I27: Jeff Consolino | L27: Gary Gruber | M27: Chad Stewart | O27: $13B | P27: 0.02 | Q27: 93.7
A28: Acceleration of ramps / Deacceleration of ramp downs | B28: 23 | C28: Farmers | D28: US | E28: Named | F28: Sean | G28: Sean | H28: Jeff Dailey | I28: Scott Lindquist | K28: Rob Howard | M28: Paul Wilson
A29: Acceleration of ramps / Deacceleration of ramp downs | B29: 24 | C29: USAA | D29: US | E29: Named | F29: Sean | G29: Sean | H29: Wayne Peacock | I29: Laura Bishop | J29: Torben Ostergaard | K29: Sean Burgess | M29: Michael Brady | O29: $20B | Q29: 82.8 | R29: Yes | S29: TCS
A30: Drive Solutions across existing and new clients that leverages our combined strengths | B30: 25 | C30: American Family | D30: US | E30: Named | F30: Sean | G30: Sean | H30: Jack Charles Salzwedel | I30: Dan Kelly | J30: Joseph Gates | K30: Scott Little | M30: Kristen Kirkconnel | O30: $23B | Q30: 105.7 | R30: No | AE30: 10
A31: Drive more adoption of Analytics | B31: 26 | C31: Munich Re | D31: US | E31: Named | F31: Mohit | G31: Mohit | H31: Dave Brune | I31: Oliver J. Horbelt/Angela Homm | J31: Catherine Smith | K31: JannaLyn Allen | L31: Anita Kuchma | M31: Phil Roeper | O31: $60,433M | P31: 0.02 | Q31: 101 | R31: Yes | S31: Wipro,Capgemini | T31: Sep, 2022 (with Wipro) and 23rd July 2020 with Capgemini
A32: Acceleration of ramps / Deacceleration of ramp downs | B32: 27 | C32: State Farm | D32: US | E32: Named | F32: Mohit | G32: Mohit | H32: Bruce Hull | I32: Connie Storey | J32: Cathy Wallace | K32: Terrence Ludwig | L32: Cleo Villaflores | M32: Ashley Pettit | O32: $42,137M | P32: 0 | Q32: 98.7 | R32: No | S32: Wipro | T32: NA
A33: Acceleration of ramps / Deacceleration of ramp downs | B33: 28 | C33: Mapfre | D33: US | E33: Named | F33: Mohit | G33: Mohit | H33: Alexis Sanchez Geigel | I33: Francois Facon | J33: Dana Whiteley | K33: Christopher Matherly | L33: Scott Hammond | M33: Gregg Nickerson | O33: $6,398.6M | P33: 0.031 | Q33: 97.6 | R33: Yes | S33: WNS | T33: NA

Sheet Partnerships and Alliances
A1: Partnership & Alliances
A3: Potential Partnership and Alliances mapped to EXL solution elements (based on internal research). Extensive assessment needs to be conducted to qualify and validate commercial viability for each solution and partner/ alliance
A5: Home
C6: Function/Capability | D6: Providers | E6: 2020 EXL Assessment | G6: Low
C7: Advanced Analytics | D7: BlockClaim (Sprout.ai) | E7: Low | G7: Medium
D8: Cape Analytic | E8: Low | G8: High
D9: Clara | E9: Medium
D10: concirrus | E10: Medium
D11: Gradient | E11: High
D12: Shift Technology | E12: High | G12: Internal Parameters used for Evaluation
C13: Big Data | D13: otonomo | E13: Low | G13: 1 | H13: Vertical
D14: Quantemplate | E14: High | G14: 2 | H14: Business Lines Supported
D15: Zesty AI | E15: Medium | G15: 3 | H15: Products Supported
C16: Claim Processing | D16: Crawford/ Broadspire | E16: Low | G16: 4 | H16: Digital Disruption Level
D17: ESIS | E17: Low | G17: 5 | H17: Industry Utility
D18: Gallagher Bassett (Everest Group (Skand) published a 2020 State of the TPA industry report. Must be purchased to review. ($5000) ) | E18: High | G18: 6 | H18: Product
D19: Sedgewick | E19: High | G19: 7 | H19: Market
C20: Contact Center | D20: Actec | E20: Medium | G20: 8 | H20: EXL Investment Potential
D21: AnsaFone | E21: Low | G21: 9 | H21: Functional Capability
C22: Content Extraction | D22: Chisel.ai | E22: High | G22: 10 | H22: Solution Applicability
D23: DataCubes (Now Convr) | E23: Low
D24: Groundspeed | E24: High
D25: Hyperscience | E25: Medium
D26: KORE | E26: High
D27: omni:us | E27: Medium
D28: Sumyag Data Sciences | E28: Medium
C29: Digital Exchange | D29: Bold Penguin | E29: Medium
D30: Goji (UK Company) | E30: Low
D31: handdii (Australian Company) | E31: Low
D32: IVANS Insurance Solutions | E32: Low
D33: Westhill | E33: Low
C34: Digital Insurer | D34: acko (India) | E34: Low
D35: Cake | E35: Low
D36: Cove (New Zealand) | E36: Low
D37: digit (India) | E37: Low
D38: FloodFlash | E38: Low
D39: Hippo | E39: Low
D40: Slice | E40: Medium
C41: eSignatures and Document Collection | D41: Lightico | E41: Medium
C42: Estimating Software | D42: Flyreel | E42: Medium
D43: Hover | E43: Medium
D44: Matterport | E44: Medium
D45: Plnar | E45: Medium
D46: Snapsheet | E46: Medium
D47: Tractable | E47: Medium
C48: FNOL | D48: Gerber NCS | E48: Medium
D49: NetClaim | E49: High
D50: Safelite | E50: High
C51: Medical Mgmt Supplier | D51: EK Health (Woman owned business. Need to find out if service all 50 dates. Specialize in CA.) | E51: Medium
D52: Mitchell/Genex | E52: Medium
D53: Strataware | E53: High
C54: Payment Platform | D54: ACI Worldwide | E54: Medium
D55: Commerce Bank | E55: High
D56: Fiserv | E56: Medium
D57: Ingo Money | E57: Medium
D58: Invenger | E58: Medium
D59: One Inc | E59: High
D60: Vpay | E60: Medium
C61: Policy Admin System | D61: BriteCore | E61: Low
D62: Setoo | E62: Low
D63: Sure | E63: High
C64: Risk Assessment | D64: RiskAPP | E64: Medium
D65: Riskgenius | E65: Low
D66: TensorFlight | E66: Medium
C67: Telematics | D67: Jooycar | E67: Low
D68: TrakGlobalGroup | E68: Low
C69: Telemedicine Platform | D69: American Well | E69: Medium
C70: Grand Total

Sheet Capability Gap Assessment 
B1: Capability Gap Assessment
B3: The following table maps various P&C opportunity areas to identified solution elements. The study also maps the solution elements to potential gaps where EXL will have to bridge the deficiency in capability through possible external channels - Partnership, Alliances or Acquisition.
B5: Home
A6: # | B6: Area | C6: Solutions | D6: Solution Components | E6: Solution Features | F6: EXL Capability | G6: Challenges we are trying to solve | H6: Capability Gap Description | I6: Partnership Required | L6: Competition Capability | P6: Benchmarks | Q6: Business Outcomes
I7: InsureTech | J7: TPA | K7: Other | L7: Genpact | M7: WNS | N7: TCS | O7: Cognizant | P7: Metrics that Matter
A8: 1 | B8: Claim | C8: FNOL-as-a- Service | D8: Omni Channel Intake | E8: Provides a channel agnostic claim reporting solution for customers (broker and insured) | F8: Medium | G8: -Brokers and Insureds want the choice of reporting channels (Mobile, Web, Email, Fax, Phone) and expect a carrier to provide them with all options -Carriers and customers desire FNOL set up (claim # assignment) and adjuster assignment as quickly as possible in order to ensure timely investigation, evaluation reserving and resolution. Anything more than 4 hours is often perceived as too long leading to adverse impacts on the claim and the customer experience. -An FNOL contains a number of data points which are important to capture quickly and accurately so they can be immediately used to predict claim outcomes, properly reserve, report losses to underwriting, price risks and manage aggregate loss costs. -Significant effort and cost is needed to convert unstructured, semi-structured and structured documents, embedded files, notes, ACORD forms, scans, images etc...) to useable formats. -Customers often complain of insufficient transparency into the claim assignment process. They do not receive timely notification of the claim number nor the adjuster ID leading to unnecessary phone calls and emails and ultimately poor customer satisfaction. . -Customers and regulators require data privacy and security for all PHI, PII information shared when reporting a loss. | H8: Capability exists. 1. Full scale multi-channel implementation has not been done with any client to date 2. Mobile interface and reporting does not exist today | I8: Y | J8: N | K8: N | P8: TAT Non Voice - 95% assigned within 2 hours (most stringent) AHT - not always measured. HIG Measures and standard is 4.30. (Typical AHT across commercial lines is 10 - 20min) Quality - 88% - 95% DPU and DPO (typical is 90 - 95% DPU) %Reassignments Complaint Ratio Voice ASA - 70 - 80 % answered within 20 - 25 sec industry might reflect higher) Abandonment Rate - 2%-7% | Q8: -Reduce claim costs - ALAE and ULAE -Streamline and simplify the process -Improve accuracy of assignment -Provide early warning flags for fraud, litigation etc. reducing indemnity and legal cost -Improve customer experience -Simplify pricing - price per FNOL - allows for surge capacity and flexibility transferring burden to supplier
D9: Automated Entry FNOL capability (Thin Human/Heavy Digital) | E9: Provides front end capability to ingest all types of FNOL documents across all lines of business (Commercial and Personal) from all channels (except Voice). App needs to extract data/content and auto populate carrier claim systems (Guidewire, Duck Creek etc..) | F9: Low | H9: 1. Robust and functioning extraction capability 2. A functioning bolt on FNOL interface that could work with various Claims platforms like Guidewire and Duck Creek | I9: Y | J9: N | K9: Y
D10: Voice Center of Excellence (COE) | E10: Provides insured/broker with the ability to report claims via phone in a workflow enabled call flow using dynamic scripts, triage and adjuster assignment. Claims Inquiry and Provider Help lines may also be part of the module. | F10: Medium | H10: Offshore Voice FNOL capability exists with entry into client platforms. Gap: 1. Front end (Cloud Based) Dynamically scripted FNOL tool to capture loss information to reduce AHT and improve CX 2. No onshore competitive capability | I10: Y | J10: Y | K10: Y
D11: Acknowledgement Notice Automation | E11: Provides immediate notice to insured and broker that the claim has been received and a claim number assigned | F11: High | H11: None | I11: N | J11: N | K11: N
D12: Reports and Dashboards | E12: Provides ability to capture and report real time on TAT, Volume by LOB, Volume by Channel, Quality etc..) | F12: High | H12: None | I12: N | J12: N | K12: N
D13: Predictive Analytics | E13: Provides early indicator flags (Fraud, Litigation, Recovery, Total Loss) to improve assignment, investigation cues, improved cycle time, decision support | F13: High | H13: Capability exists. 1. Predictive Analytics have not been applied at FNOL but have been applied further downstream. Decision whether to build or buy and which parts to build. | I13: Y | J13: N | K13: N
D14: Cloud Hosted | E14: Provides ability to host data in the cloud while protecting security and data privacy | F14: Medium | H14: -EXL needs a partner with experience in client/customer sensitive data hosting on cloud compliant with regulations (AWS) | I14: N | J14: N | K14: Y
D15: Conversational IVR | E15: Provides for reduced FNOL Call AHT, improved call routing ability to answer basic claim inquiry calls | F15: High | H15: None | I15: N | J15: N | K15: N
D16: Speech Analytics | E16: Fraud propensity, Customer Experience analytics, call flow/script optimization | F16: High | H16: We already have a partnership with Verint? | I16: N | J16: N | K16: N
A17: 2 | B17: Claim | C17: Payment-as-a Service | D17: Content Extraction | E17: Intelligent data extraction from bills/invoices sent via paper/email/fax to enable automated entry and into payment systems | F17: Low | G17: -Insurers make a significant number of claims payments annually. It’s an expensive process — not just in terms of the physical costs of printing, paper, and postage, but human beings are needed to answer questions, manage accounting, and oversee reconciliation. It’s a very non-strategic backroom process. '-Today’s claimants expect fast, transparent claims payments with the ability to choose the payment mechanism — including newer mechanisms such as Venmo or Zelle. '-Vendor recipients want a method that makes it simple and efficient for them to process and reconcile as well. -Claims payment recipients expect much more flexibility in how their payment is handled and transparency in the process history. -Individuals expect to be able to choose how they want to receive their money — whether by check, debit card, ACH, Venmo, or other mechanisms. -Businesses don’t want to be overwhelmed with multiple payments on individual transactions; they want taxes and liens to be handled appropriately; and they also want self-service capabilities to track and reconcile payments. -An increasing number of insurers are questioning the overall costs of handling payments. Rather than modifying their software systems in order to provide new capabilities, they’re deciding to outsource the entire process. | H17: 1. Robust and functioning extraction capability 2. A functioning bolt on interface that could work with various systems | I17: Y | J17: N | K17: Y
D18: Payee Portal | E18: A payee portal allows the payee to easily handle their payment processes online. Those intended for an individual usually allow the payee to set up their payment preference, add or manage accounts for payment deposits, and view real time status of payments. | F18: Low | H18: 1. EXL does not have a portal, tool, platform or bolt on solution today that could work with client ERP and claim systems | I18: Y | J18: N | K18: Y
D19: Transactional Servicing Features | E19: Provides automated Payment Methods, Payment Transactions, EOB Remittance, Payee Types,Workflow,Party Types, Fraud Management & Controls | F19: Medium | H19: The people capability to execute these transactions exists today and there are automated features which do exist 1. A holistic, integrated solution with payment processing vendors (E.g. VISA) does not exist | I19: Y | J19: N | K19: Y
D20: Customer Service | E20: Payment-as-a-Service providers typically provide the frontline customer service to the payee, answering questions about the timing or amount of the payment, processing individual transactions such as stop payments, or providing support for changing payment preferences or accounts. | F20: High | H20: None | I20: N | J20: N | K20: N
D21: Administrative Support and Services | E21: The solution needs to provide for a number of administrative services. '-Account Funding - Some vendors can use the insurers’ own bank accounts. -Escheatment - PaaS providers can handle the escheatment processes for each state as needed. -Marketing Services - MostPaaS providers include some support for marketing (insurer branded cards, drive demand for paper-free payments, marketing messages within payee portal) -Reporting Data - real time data or regular data files that aggregate data across all payment channels for easy reconciliation -Reconciliation Tools -Administrative Portal - provides the insurer with access to data and admin tools (access to scheduled reports, recon tools, admin access to add insurer users and manage permissions, search, manage and view real time status of each payment, stop pay/voids/reissue -Payment Integrity | F21: Medium | H21: The people capability to execute these transactions exists today and there are automated features which do exist 1. An Admin portal does not exist | I21: Y | J21: N | K21: Y
A22: 3 | B22: Claim | C22: Digitally Transforming Workers’ Compensation Claims Optimizing Medical and Disability Management | D22: Medical Case Management Platform | E22: AI Powered platform to manage medical case assignment, co-ordinate appointments (Physicians, Diagnostics etc.) and order services (Therapy, testing, Medical Supplies, transportation etc.) | F22: Low | G22: -The economic slowdown over the last several years has put pressure on both growth and profitability. There has been a significant shift in the split between medical costs and indemnity costs on a claim. -Variations and inconsistencies in state WC laws and reporting requirements increase cost and decrease efficiency. -Carriers need to create holistic treatment and medical management programs to deal effectively with the physical, emotional and psychological aspects of pain. -Opportunity to reduce claim lifecycle and expedite claim payments - medical and indemnity -Opportunity to manage return to work more effectively and reduce claim cost -Opportunity to reduce medical payment fraud, waste and abuse -Opportunity to reduce penalties as this continues to be a pain point for most WC insurers. -Opportunity to improve communication between the injured worker, employer and carrier -Opportunity to improve/optimize cost management and disability management programs using data and analytics -Reduce costs associated with UR and Medical Bill Review programs -Streamline and digitize ingestion and intake of medical documents and bills Potential Covid Impacts on WC - There could be an increase in the # of compensable claims arising in frontline, Covid related situations. However, this could be offset by a decrease in WC claims due to the increased # of employees WFH - Carriers may see a decrease in the # of PT sessions that are deemed to be not immediately critical (likely only a short term effect) - In economic downturns, workers may forgo filing claims for minor injuries to maintain active employment leading to a temporary downward pressure on claim frequency -Will medical costs go up as Covid related injuries require extensive medical/hospital care? -Will death claims see an increase? -What happens to nurse case management? - IME's may be delayed along with other types of medical care - Will claims, therefore, stay open longer and thereby increase indemnity and medical costs - Court systems have been closed - and will continue to be closed - creating backlogs and delays - will this also cause claims to be open longer and therefore drive up costs? -Tighter investigations in Covid cases are required to prevent fraud and prove compensability -Leverage telemedicine as a way to injured workers' to keep appointments while social distancing (not allowed in all states but there has been some easing of restrictions) - So far, actuarial estimates about the potential cost of Covid have been all over the map - 2 of the largest rating agencies aren't even guessing how much covid-19 might cost in permanent disability benefits - despite evidence that the virus causes long lasting ill health effects - State governors and regulators are changing WC laws on the fly - it is continually evolving - making it difficult for a carrier to predict loss severity, reserve adequacy, rates etc. | H22: -Platform or bolt-on solution that could work with multiple client and medical provider systems for case management, appointment co-ordination and ordering services | I22: Y | J22: N | K22: Y | P22: Penalties - <2% of indemnity spend Quality - 98% TBD | Q22: -Reduce medical spend by X -Reduce overpayments, duplicate payments, penalties and interest -Reduce Return to Work days and ultimate indemnity spend -Reduce claim leakage leveraging analytics models like fraud propensity, litigation propensity, return to work potential -Improve policyholder/Injured worker experience and customer satisfaction - Improve experience mods - Lower premiums
D23: Automated Entry Medical Record and Bill Management capability (Thin Human/Heavy Digital). | E23: Provides front end capability to ingest all medical records and bills from all channels. App needs to ingest data, extract data/content, auto populate carrier systems and feed data to Bill Review platforms, Bill Payment systems and Medical Summarization tools. | F23: Low | H23: 1. Robust and functioning extraction capability 2. A functioning bolt on FNOL interface that could work with various Claims platforms like Guidewire and Duck Creek | I23: Y | J23: N | K23: Y
D24: Medical Record Summarization | E24: Leverage EXLs MedConnection tool to intake, tag, catalogue and summarize medical records and create a comprehensive medical summary for adjusters and attorneys | F24: High | H24: None | I24: N | J24: N | K24: N
D25: End to End Utilization Review | E25: Provide full service Utilization Review capability beyond existing USRN & PHRN capability Typically need a Physician Peer Review network | F25: Medium | H25: Nurse expertise in UR exists at EXL if able to work in client UR platforms and tools and leverage benchmarks and state guidelines 1. Gap is in having our own UR platform/tool/licenses (i.e.; Strata, Mitchell) 2. Lack of access to Physician Peer Review Network | I25: N | J25: Y | K25: Y
D26: Medical Bill Review Capability/Platform | E26: Bill review platform integrated with claim systems populated with all ICD-9 codes, treatment protocols, benchmarks etc.… Access to PPO Networks | F26: Low | H26: -MBR capability exists if able to work in client platform. 1. Gap is lack of MBR platform with PPO networks, RX programs, benchmarks | I26: N | J26: Y | K26: Y
D27: Predictive Analytics Models | E27: RTW Modeling (prediction of MO, LT, Catastrophic Injuries and RTW/MMI days), Severity Modeling, Nurse Triage (Nurse Intervention Success, Nurse Performance), Litigation Propensity, Indemnity Spend Analytics, RX Analytics (target high risk meds which harm RTW efforts - guide appropriate utilization), PPO Outcomes (Inside Network/Outside Network), Physician Peer Review Performance, Fraud Analytics, WFH Injury Models, Vendor Outcome Models, Early Intervention/Chronic Pain Analysis, AI Tools to identify potentially difficult or complex claims | F27: High | H27: -NA | I27: N | J27: N | K27: N
D28: STP Modeling and Automation (Medical Only Claims) | E28: Model the appropriate threshold for STP of medical only claims and process without human touch. | F28: Medium | H28: STP capability does not exist | I28: Y | J28: N | K28: Y
D29: Payment Integrity | E29: Leverage payment integrity identification and collection capabilities in HC and/or SCIO to recover leakage in medical payments. | F29: High | H29: None | I29: N | J29: N | K29: N
D30: Subrogation | E30: Leverage subrogation capabilities to highlight claims with high Subro potential early in the case and pursue accordingly. | F30: High | H30: None | I30: N | J30: N | K30: N
A31: 4 | B31: UW | C31: New Business Processing-as-a-Service | D31: Submission to Quote - | E31: Enable already redesigned New Business Model office with analytics and digital solution to further improve Speed to Market and reduce cost | F31: High | G31: 1. Improving speed to market - It takes 48-72 hours to share a quote 2. Reducing Cost of Quote Generation - Multiple touches across the shared service and underwriting organization to present a quote 3. Prioritizing and writing profitable business 4. Increasing Quote to Bind Ratio The above issues are largely driven by: a) Limited availability of proven digital capabilities that can cater to non standard and complex market segments b) Limited integration of Analytics models in New Business risk selection and application prioritization workflow c) Heavy reliance on Underwriter's experience and change management issues d) Limited use of upfront data enrichment techniques e) Data entry heavy transactions | H31: 1. Data extraction from Acord, email and supplementary documents 2. APIs to communicate with top 5 agency systems 3. Digital packet with a summary of losses, risk exposure basis social-media research, financial performance summary, Aerial imagery etc. | I31: Y | J31: N | K31: N | Q31: 1. Improving speed to market (WHY) - Inability to gain business insights driven by analytics - Inability to process Omni channel intake - Lack of digital solutions - High degree of missing information resulting in back and forth - Risk selection and submission prioritization - Multiple touches across the organization resulting slower turn around 2. Reducing cost of quote generation (WHY) - Multiple touches across the shared service and underwriting organization to present a quote - Need to digitize the process - Prioritize what to quote versus quoting everything 3. Prioritizing and writing profitable business 4. Increasing Quote to Bind Ratio (WHY) - Improve broker and customer experience - Approval rates by broker - Broker/Agency benchmarking - which broker is more suitable - Commissions management
D32: Rating | E32: Automated data entry for quote creation Identify segments/risk profiles to increase quick rating (Quick Rate Process) | F32: Low | H32: 1. Data Augmentation through use of third party dataset/secondary data source 2. Integration modules that work with top 2 policy admin systems | I32: Y | J32: N | K32: N
D33: Issuance | E33: Automated Issuance Automated communication for binders Binder generation, DEC package | F33: High
D34: Analytics Insights and Reporting | E34: Provides ability to capture and report real time on TAT, Volume by LOB, Volume by Channel, Quality etc..) Provide ability to predict quote conversion rate etc. | F34: Medium | H34: While EXL has a deep analytics expertise but there are no ready to deploy solutions for submission prioritization, risk assessment and selection etc | I34: Y | J34: N | K34: N
A35: 5 | B35: UW | C35: Endorsements End to End Solution | D35: End to End Endorsement Processing | E35: Digital Endorsement solution services end to end value chain from intake of requests to issuance of policies without human intervention. - Straight Through Processing of simple endorsement requests -ability to ingest data from any channel -Early identification of missing information -Data intelligence to improve self service functionality -Ability to prioritize based on VOC | F35: High | G35: Endorsements requests for various market segment are inconsistent and not standard hindering the ability to get a good understanding of endorsement volumes, types etc. and adding complexity to processing. Insurers are looking to reduce unwanted endorsements 1.Unstructured & Unstandardized Requests resulting in inability to get business insights into types of endorsements and reasons driving the endorsements (quality, broker behavior etc.) 2. Need to support Omni channels for endorsements 3. Need to centralize endorsement processing across various market segments 4. Lower adoption of Brokers to self service portals | H35: 1. Data extraction from Acord, email and supplementary documents | I35: Y | J35: N | K35: N | Q35: Reducing cost of endorsements - Reducing preventable (Non value add) endorsements Improved Broker experience (NPS Score improvement) Reportable data and ability to gain business insights from the data
D36: Exception Handling | E36: Process endorsements manually for exception cases leveraging experienced insurance workforce | F36: Low
D37: Reporting and Analytics | E37: -Ability to report on endorsement volumes -Provide business insights into core reasons for endorsements to enable addressing the root causes -Identify broker behavior issues Reduce endorsement volume through repeat request reduction, upstream optimization -Send proactive alerts and communication for endorsement (as an example) | F37: Medium
A38: 7 | B38: UW | C38: Broker Intake Engine | D38: Data Ingestion from Broker Platforms | E38: - Comparative Rater - Ability for brokers to send the requests to "EXL Broker Services" - Federation model - Standardize intake for insurers | F38: Low | G38: Multiple submission Delayed quote generation time Administration overhead due to non standard requests to insurers | H38: 1. No existing experience - AON experience can be the blue print 2. A commercial insurance exchange that connects customers, agents, and carriers to match the right quote in record time | I38: Y | J38: N | K38: N | Q38: Reduction in administration overhead Better customer experience Faster Quote to customer
D39: Data Extraction Module | E39: -Data intake from multiple sources | F39: Low | H39: 3. Data extraction from Acord, email and supplementary documents | I39: Y | J39: N | K39: N
D40: Value Add Services | E40: - Pre-identification of missing information - Risk propensity model - Lead prioritization - Commission forecast | F40: Low | H40: While EXL has a deep analytics expertise but there are no ready to deploy solutions for submission prioritization, risk assessment and selection etc | I40: Y | J40: N | K40: N
A41: 8 | B41: F & A | C41: Intelligent Collections | D41: Analytics Led Risk Prioritization & Forecasting | E41: -Dynamic risk scoring based on industry level macro variables, historical account performance and external factors as applicable -Automated prioritization of activities based on customer type, collection, risk, balance and location -Standardized dispute resolution with standard routing, escalation and approval processes -Data from banks, external remittance data, electronic data from customers, or any other supporting data used to improve auto-match% and better cash forecasting | F41: High | G41: Analytics driven Human + Digital Collections: As the lockdowns impact household income and company revenues insurers are either starting to see or anticipating the following: 1. Higher Expected Default: Adverse impact across customer industries – adversely impacting company’s cash position 2. Erratic pandemic behavior: Overestimated risk scores, impacted UW deaccessioning and lower forecasting accuracy 3. Non-standardized highly manual processes: Need to design experience with focus on the right outcomes EXL will help insurers get more cash in faster by using specialized analytics, automated communications and leveraging specialized targeted collections strategies, in addition to quicker matching and resolution of cash balances. | H41: Low capability in off-the shelf digital solutions | P41: Daily Sales Outstanding Collectability Rate Installment Plans Promise to Pay | Q41: Better Cash Management - Focused Collections and Customer Service Effort on cases with very high probability of default to improve DSOs Improved speed of dispute resolution & billing rectification - better customer outcomes Better staffing & planning of Receivables Management operations Better capture of customer behavior & industry behavior data at billing / dispute and collections stage for better front end deaccessioning Improved UW Deaccessioning
D42: Automated Communications & Chasers | E42: '-Automated reminders pre due date based on inherent risk; Automated chasers post due date based on ageing | F42: Low
D43: Real Time Cash Application | E43: Real time cash application integrated with collections, dispute resolution and self service portal | F43: Medium
D44: Comprehensive Data Reports and Dashboards | E44: -Stringent Credit Risk Management - automated credit reviews and customer score cards 'Reporting engine – Collections Dashboard, AR aging report, On Account and Misapplied Cash | F44: High
D45: Other Receivables Areas | E45: Analytics driven Post Billing activities: Run AR reports from the system (by product / broker / location) and run Analytics engines to determine likelihood of default for more targeted focus. Enhance outreach and connect with Insured / broker by confirm in invoice receipt by the right contact at the client / broker and share any information required. | F45: High
E46: Intelligent pro-active dispute resolution and automated reminder Pre-Due: Identify cases with high propensity for disputes and escalate and help resolve disputes (revisions/credit/other). Automated reminders at various stages and confirmation of the scheduled payment date (Promise to Pay) | F46: High
E47: Intelligent Reporting and Tracking: Consistently and proactively move the invoice to the payments stages, effectively collect and proactively escalate, send Overdue statement if payment not received as per “Promise to Pay”, loop in brokers and account managers (as needed) in collections email | F47: High
E48: Dispute Resolution: Create and follow dynamic follow escalation matrix to resolve the dispute with client / broker, create processes for quick and efficient dispute resolution, Intelligent solution to capture resolutions and post resolution, confirm schedule payment date on disputed invoices | F48: High
E49: Reporting - Create Single Versions of Truth: Optimize system reports as “version of truth” for all collections reporting and follow-up; Report, track and benchmark DSO, Overdue AR, disputes, bad-debts and other KPI’s; Quantify the $’s to be collected on a time scale | F49: High
E50: Additional Value Add: Create customized ‘risk’ segments leveraging multiple criterion like balance/tenure, likelihood-to-pay, tenure, time to payment and other models. Assign these collections risk scores and portfolio risk ranking to prioritize collections and minimize loss. Proactive feedback loop for credit team to better manage credit risk. Leverage customer intel across product lines (behavior patterns, terms, contracts, shutouts, etc.) to give clients better understanding of customer shifts | F50: High
A51: 9 | B51: F & A | C51: Audit Analytics | D51: Audit Analytics Center of Excellence (COE) | E51: - Audit Analytics opportunity identification - Design of Analytics Strategy and Pilot Program - Audit Analytics assessment – Current State Assessment & Future State Design | F51: Medium | G51: Remote working has increased the possibility of financial impact to Insurers due to malicious acts and inadvertent errors. | H51: Low capability in off-the shelf digital solutions | Q51: - Increased risk coverage - Insight in real time/ right time - Effective risk mitigation - Efficiency gains
D52: Dashboard/Customer Report Development | F52: Medium
D53: Audit Bot Development and Maintenance | E53: Tester Bots, Data Extraction Bots, Recon Cots etc. | F53: Medium
B54: F & A | C54: Process Risk Assessment | D54: COE Delivery Structure | E54: As part of this offering EXL proposes to perform a health-check of - Process, risk, controls and organizational taxonomy - Process flows, risks, controls - Risk and Controls Matrix - Review testing methodology and guidelines - Develop Test Scripts for key controls - Perform test-of-one - Evaluate design effectiveness of key control(s) - Report on the status of controls tested, its effectiveness and open gaps | F54: High | G54: - Incomplete and inaccurate system data - Spikes in the level of effort - Inconsistent controls and testing documentation - Regular surprises, especially at year-end - Issue Management - Lack of early warning mechanism - Late identification of exceptions - Little time left to remediate at year end - Testing not aligned to evolving risks - Challenging project management – a lot of key stakeholders '- | Q54: ~35-40% reduction in cost of compliance Increased assurance through automated testing of entire population as opposed to sample testing Early identification of deficiencies for remediation prior to year end Standardized controls testing documentation resulting in increased external audit reliance Reduced manual effort – automation of select SOX compliance activities and underlying processes
D55: Automation/Robotics | E55: -Advanced automation and robotics interventions directed at select SOX compliance tasks and underlying processes | F55: High
D56: Analytics & Reporting | E56: -Insightful and granular analysis of data to identify high risk areas and detect potential exceptions early | F56: High
D57: Leading Practices | E57: -Implement risk based testing methodologies and work-paper documentation standards for increased external audit reliance | F57: High
D58: Dual Shore | E58: -Large pool of SOX auditors, data scientists and automation SMEs both onshore and offshore | F58: High
A59: 10 | B59: F & A | C59: Finance Automation | D59: RPA | E59: RPA is a key driver being discussed with most clients to drive efficiency and plan capacity. EXL will implement Robotics and Intelligent Automation solutions for core Finance processes such as Balance Sheet Reconciliations and Manual Journal Entries and transactional Finance processes such as Account payables and receivables, to help clients drive better outcomes. | F59: High | G59: -Lockdowns have led to an acceleration in the speed of automation being implemented across clients to drive operations resiliency and improve efficiency. Clients are looking at partners to come up with ready and implementable solutions for automation. | Q59: Operational Resiliency - automated processed provide natural BCP in cases where FTEs are unable to continue delivery due to circumstances Cost Efficiency: Given that the cost of operating a BOT is a fraction of a human FTE - automation can help drive significant cost efficiencies across the board Better process management Improved customer experience
B60: F & A | C60: Transformation Roadmap for Finance Function | D60: Finance Blueprint | E60: EXL will conduct Finance functions diagnostic to identify process transformation and expense management opportunities, estimate benefits, build a business case, and develop an implementation roadmap. | F60: High | G60: -Cost and efficiency pressures are driving most CFOs to urgently look to assess their functions and develop end-to-end transformation and cost reduction solutions. | Q60: Optimal end-state vision for the Finance organization Detailed business case with projected benefits and cost / risks Prioritized implementations road-map
A69: 11

Sheet Build-Buy-Partner Analysis
B1: Home | C1: Build-Buy-Partner Analysis
B2: Summary of InsureTech/TPA Preliminary Analysis
B4: Reviewed 2019 InsureTech study of 80 InsureTech to determine how many, if any, should carry over to the 2020 analysis. Only 1, Shift Technology, stayed High in both years
B5: - Created a comprehensive list of 75+ top InsureTech/TPA/Service Providers using secondary research
B6: - Studied an additional 62 InsureTech/TPA and Other firms to determine applicability to our identified solutions
B7: - 41 InsureTech/TPAs have been rated as Medium/High purely based on their applicability to a solution
B8: - A second level of research was done to shortlist the InsureTech' s that best address white spaces and augments our chosen solutions. Basic criteria was applied to determine "Best Fit" for a given solution.
B9: - Preliminary assessment taken as to whether EXL could/should potentially Buy/Partner or Build the Solution component .Of the 39 solution components, we have the capability to build 18 solutions in-house, partnering for 16 components and build or partner for 5
B11: Table A : Summary of Service Providers that best fit our solutions
G12: Potential Partnership and Alliance Candidates | J12: Potential to Build | M12: Further research required
B13: Solution Name | C13: Solution Component | D13: Gap Description | E13: Evaluation Criteria | F13: Supplier Applicability | G13: InsureTech | H13: TPA | I13: Other | J13: Y/N | K13: Comments | M13: Develop evaluation criterion
B14: Solution 1 FNOL | C14: Omni Channel Intake | D14: 1. Full scale multi-channel implementation has not been done with any client to date 2. Mobile interface and reporting does not exist today | E14: Market Line of Business Functional Capability Applies to Solution | F14: Gradient/NetClaim Crawford/Broadspire Actec AnsaFone Lightico Safelite KORE Gallagher Bassett Omni.us Shift Technology | G14: KORE | H14: Gallagher Bassett | I14: Safelite | J14: Y | K14: KORE: Digital Assistant
C15: Automated Entry FNOL capability (Thin Human/Heavy Digital) | D15: 1. Robust and functioning extraction capability 2. A functioning bolt on FNOL interface that could work with various Claims platforms like Guidewire and Duck Creek | G15: Omni.US | I15: Gallagher Bassett | K15: Omni.us - content extraction and decision support
C16: Voice Center of Excellence (COE) | D16: 1. Front end (Cloud Based) Dynamically scripted FNOL tool to capture loss information to reduce AHT and improve CX 2. No onshore competitive capability | G16: Gradient/ NetClaim KORE | H16: Crawford/ Broadspire | I16: Safelite Actec AnsaFone
C17: Predictive Analytics | D17: Predictive Analytics have not been applied at FNOL but have been applied further downstream. Decision whether to build or buy and which parts to build. | G17: Gradient/ NetClaim Shift Technology | J17: Y
C18: Cloud Hosted | D18: EXL needs a partner with experience in client/customer sensitive data hosting on cloud compliant with regulations (AWS) | I18: AWS
C19: Speech Analytics | D19: Do we already have a partnership with Verint? | I19: Verint | J19: Y
B20: Solution 2 Payment As a Service | C20: Content Extraction | D20: 1. Robust and functioning extraction capability 2. A functioning bolt on interface that could work with various systems | E20: Payment Services from Celent Payment As a Service paper | F20: ACI Worldwide Commerce Bank Fiserv Ingo Money Invenger Vpay One Inc | J20: Y | K20: Leverage Enterprise Solution
C21: Payee Portal | D21: EXL does not have a portal, tool, platform or bolt on solution today that could work with client ERP and claim systems | I21: One Inc Commerce Bank Avenger Vpay | K21: One Inc is the leader according to Celent
C22: Transactional Servicing Features | D22: A holistic, integrated solution with payment processing vendors (E.g. VISA) does not exist
C23: Administrative Support and Services | D23: An Admin portal does not exist
B24: Solution 3 Digitally Transforming Worker's Compensation Claims while Optimizing Medical Management | C24: Medical Case Management Platform | D24: Platform or bolt-on solution that could work with multiple client and medical provider systems for case management, appointment co-ordination and ordering services | E24: Market, LOB, Functional Capability | F24: American Well - telemedicine Clara Gallagher Bassett ESIS EK Health Strataware Mitchell | H24: Gallagher Bassett | I24: Mitchell EK Health | K24: American Well: telemedicine
C25: Automated Entry Medical Record and Bill Management capability (Thin Human/Heavy Digital). | D25: 1. Robust and functioning extraction capability 2. A functioning bolt on FNOL interface that could work with various Claims platforms like Guidewire and Duck Creek | J25: Y | K25: Leverage Enterprise Solution
C26: End to End Utilization Review | D26: ` | H26: Gallagher Bassett | I26: Strataware Mitchell/Genex EK Health
C27: Medical Bill Review Capability/Platform | D27: Lack of MBR platform with PPO networks, RX programs, benchmarks | I27: Strataware Mitchell EK Health
C28: Predictive Analytics Models | D28: EXL analytics models exist but are not stitched and packaged in a solution oriented way Does not happen at the time of FNOL | G28: Clara | J28: Y | K28: Clara: Claim Analytics
C29: STP Modeling and Automation (Medical Only Claims) | D29: STP capability does not exist | J29: Y
C30: Payment Integrity | D30: None | K30: Need to meet with HC team
B31: Solution 4 New Business Processing-as-a-Service | C31: Submission to Quote | D31: 1. Data extraction from Acord, email and supplementary documents 2. APIs to communicate with top 5 agency systems 3. Digital packet with a summary of losses, risk exposure basis social-media research, financial performance summary, Aerial imagery etc. | E31: Market Line of Business Functional Capability Applies to Solution | F31: Zesty AI Hyperscience Quantemplate concirrus TensorFlight Flyreel Groundspeed Chisel.ai Sumyag Data Sciences RiskAPP KORE Bold Penguin Lightico | G31: Hyperscience Quantemplate Concirrus TensorFlight Flyreel Groundspeed Chisel.ai Sumyag Data Sciences KORE Bold Penguin Lightico
C32: Rating | D32: 1. Data Augmentation through use of third party dataset/secondary data source 2. Integration modules that work with top 2 policy admin systems
C33: Analytics Insights and Reporting | D33: 1. While EXL has a deep analytics expertise but there are no ready to deploy solutions for submission prioritization, risk assessment and selection etc. | G33: RiskAPP Concirrus Flyreel | J33: Y
B34: Solution 5 Endorsements End to End Solution | C34: End to End Endorsement Processing | D34: 1. Data extraction from Acord, email and supplementary documents | E34: AI/NLP/NLU based data Extraction | F34: Hyperscience Flyreel Chisel.ai Sumyag Data Sciences KORE Lightico RiskAPP | G34: Hyperscience Flyreel Chisel.ai Sumyag Data Sciences KORE Lightico RiskAPP
B35: Solution 6 Broker Intake Engine | C35: Data Ingestion from Broker Platforms | D35: 1. No existing experience - AON experience can be the blue print 2. A commercial insurance exchange that connects customers, agents, and carriers to match the right quote in record time | E35: Extraction and Digital Data Exchange | F35: Bold Penguin concirrus Lightico Hyperscience; Groundspeed Chisel.ai KORE | G35: Bold Penguin concirrus Lightico
C36: Data Extraction Module | D36: 1. Data extraction from Acord, email and supplementary documents | G36: Hyperscience; Groundspeed Chisel.ai KORE
C37: Value Add Services | D37: 1. While EXL has a deep analytics expertise but there are no ready to deploy solutions for submission prioritization, risk assessment and selection etc. | J37: Y
B38: Solution 7 Intelligent Collections | C38: Analytics Led Risk Prioritization & Forecasting | J38: Y
C39: Automated Communications & Chasers | D39: Low capability in off-the shelf digital solutions | J39: Y
C40: Real Time Cash Application | D40: Low capability in off-the shelf digital solutions | J40: Y
C41: Comprehensive Data Reports and Dashboards | J41: Y
C42: Other Receivables Areas | J42: Y
B43: Solution 8 Audit Analytics | C43: Audit Analytics Center of Excellence (COE) | D43: Low capability in off-the shelf digital solutions | J43: Y
C44: Dashboard/Customer Report Development | J44: Y
C45: Audit Bot Development and Maintenance | J45: Y
B46: Solution 9 Process Risk Assessment | C46: COE Delivery Structure | J46: Y
C47: Automation/Robotics | J47: Y
C48: Analytics & Reporting | J48: Y
C49: Leading Practices | J49: Y
C50: Dual Shore | J50: Y
B51: Solution 10 Finance Automation | C51: RPA | J51: Y
B52: Solution 11 Transformation Roadmap for Finance Function | C52: Finance Blueprint
B55: Table B: Preliminary rating based on functional capability for all service providers
C57: Count of Providers | D57: Column Labels
C58: Row Labels | D58: High | E58: Low | F58: Medium
C59: Advanced Analytics | D59: 2 | E59: 2 | F59: 2
C60: BlockClaim (Sprout.ai) | E60: 1
C61: Cape Analytic | E61: 1
C62: Clara | F62: 1
C63: concirrus | F63: 1
C64: Gradient | D64: 1
C65: Shift Technology | D65: 1
C66: Big Data | D66: 1 | E66: 1 | F66: 2
C67: otonomo | E67: 1
C68: Quantemplate | D68: 1
C69: Zesty AI | F69: 2
C70: Claim Processing | D70: 2 | E70: 2
C71: Crawford/ Broadspire | E71: 1
C72: ESIS | E72: 1
C73: Gallagher Bassett (Everest Group (Skand) published a 2020 State of the TPA industry report. Must be purchased to review. ($5000) ) | D73: 1
C74: Sedgewick | D74: 1
C75: Contact Center | E75: 1 | F75: 1
C76: Actec | F76: 1
C77: AnsaFone | E77: 1
C78: Content Extraction | D78: 3 | E78: 1 | F78: 3
C79: Chisel.ai | D79: 1
C80: DataCubes (Now Convr) | E80: 1
C81: Groundspeed | D81: 1
C82: Hyperscience | F82: 1
C83: KORE | D83: 1
C84: omni:us | F84: 1
C85: Sumyag Data Sciences | F85: 1
C86: Digital Exchange | E86: 4 | F86: 1
C87: Bold Penguin | F87: 1
C88: Goji (UK Company) | E88: 1
C89: handdii (Australian Company) | E89: 1
C90: IVANS Insurance Solutions | E90: 1
C91: Westhill | E91: 1
C92: Digital Insurer | E92: 6 | F92: 1
C93: acko (India) | E93: 1
C94: Cake | E94: 1
C95: Cove (New Zealand) | E95: 1
C96: digit (India) | E96: 1
C97: FloodFlash | E97: 1
C98: Hippo | E98: 1
C99: Slice | F99: 1
C100: eSignatures and Document Collection | F100: 1
C101: Lightico | F101: 1
C102: Estimating Software | F102: 6
C103: Flyreel | F103: 1
C104: Hover | F104: 1
C105: Matterport | F105: 1
...

Sheet Collated Collaterals List
A1: Collated Collaterals
A4: Home
A5: Type1 | B5: Type | C5: Group | D5: Topic | E5: URL | F5: Author
A6: Infographics | B6: Infographic | C6: Insurance | D6: SA Infographic | E6: https://www.exlservice.com/our-service-and-support-operations-in-south-africa | F6: Mohit Manchanda | Wayne Reed | Nick Lamb
B7: Infographic | C7: Insurance | D7: Philippines Infographic | E7: https://www.exlservice.com/sales-and-support-services-for-insurance-organizations-in-philippines | F7: Mohit Manchanda | Wayne Reed | Nick Lamb
B8: Infographic | C8: Insurance | D8: Policy Processing and Broker Service Offerings | E8: https://www.exlservice.com/policy-processing-and-broker-service-offerings-covid-19-and-beyond | F8: Sean Patrick Allen | Roopak Chadha | Kathleen Welday
B9: Infographic | C9: COVID and insurance | D9: Policy Processing and Broker Service Offerings: COVID-19 and Beyond | E9: https://www.exlservice.com/policy-processing-and-broker-service-offerings-covid-19-and-beyond | F9: Content Team
B10: Infographic | C10: Claims | D10: SUBROSOURCE® | E10: https://www.exlservice.com/subrosource-infographic | F10: Content Team
B11: Infographic | C11: GDPR | D11: Global Privacy Risk Monitoring Framework | E11: https://www.exlservice.com/global-privacy-risk-monitoring-framework | F11: Mohit Manchanda | Prakhar Agarwal
B12: Infographic | C12: Digital | D12: Digital Intake for Insurance | E12: https://www.exlservice.com/digital-intake-for-insurance | F12: Ahson Pai | Keith Johnson
B13: Infographic | C13: Insurance | D13: Insurance Transformation Blueprint | E13: https://info1.exlservice.com/hubfs/EXL-IG-Insurance-Transformation-Blueprint.pdf?hsLang=no | F13: Rohan Regis
B14: Infographic | C14: Insurance | D14: London Market Modernization | E14: ENABLING INSURANCE BUSINESSES IN LONDON MARKET TO ACHIEVE MODERNISATION THROUGH AUTOMATION & ANALYTICS | F14: Rohan Regis
B15: Infographic | C15: Insurance | D15: Post Merger Integration | E15: https://www.exlservice.com/postmerger-integration-for-insurers-to-unlock-desired-value | F15: Rohan Regis
B16: Infographic | C16: Analytics | D16: Fraud Detection & Investigation Management | E16: https://www.exlservice.com/fraud-detection-and-investigation-management | F16: Kshitij Jain
A17: White Paper | B17: White Paper | C17: Insurance | D17: Delivering Next Generation Claims Operating Model For General Insurers | E17: https://www.exlservice.com/delivering-next-generation-claims-operating-model-for-general-insurers | F17: Rohan Regis | Vikas Kapoor | Rahul Singh
B18: White Paper | C18: Insurance | D18: Strategic Review To Drive Reduction In Expense Ratio For Commercial Insurers | E18: https://www.exlservice.com/strategic-review-to-drive-reduction-in-expense-ratio-for-commercial-insurers | F18: Rohan Regis | Mohit Manchanda | Sidhartha Sinha | Sumeet Shetty
B19: White Paper | C19: COVID and insurance | D19: Adaptive Framework to Manage Risk During COVID-19 | E19: https://www.exlservice.com/adaptive-framework-to-manage-risk-during-covid-19 | F19: Raghav Jaggi | Vikrant Saraswat
B20: White Paper | C20: Insurance | D20: Five Levels of Digital Disruption in Insurance | E20: https://www.exlservice.com/five-levels-of-digital-disruption-in-insurance | F20: Vikas Bhalla | Sumit Taneja
B21: White Paper | C21: Insurance | D21: Why Insurance Companies Should Re-evaluate Operations in a Digital World | E21: https://www.exlservice.com/why-insurance-companies-should-reevaluate-operations-in-a-digital-world | F21: Vishal Arora
B22: White Paper | C22: Insurance | D22: The Times, They are A-Changing- The insurance industry's business model disruption | E22: https://www.exlservice.com/the-times-they-are-achanging | F22: Content Team
B23: White paper | C23: Insurance | D23: Business Impact Assessment due to COVID-19: Remediation Actions and Updates | E23: https://www.exlservice.com/business-impact-assessment-due-to-covid-19-remediation-actions-and-updates | F23: Roopak Chadha | Mohit Manchanda | Rohan Regis
B24: White paper | C24: Insurance | D24: Decouple and Digitize the Leave Claims Process to Address the COVID-19 Surge | E24: https://www.exlservice.com/decouple-and-digitize-the-leave-claims-process-to-address-the-covid-19-surge | F24: Gaurav Singh | Sumit Taneja | Andy Logani
B25: White paper | C25: Insurance | D25: Reacting to Realities of COVID-19 and Adjusting to the New Normal | E25: https://www.exlservice.com/reacting-to-realities-of-covid-19-and-adjusting-to-the-new-normal | F25: Sagar Mehta
B26: White paper | C26: Insurance | D26: How Insurance Companies can Adapt to the New Normal | E26: https://www.exlservice.com/how-insurance-companies-can-adapt-to-the-new-normal | F26: Rohan Regis | Vikas Kapoor |Mainak Bhowmik
B27: White Paper | C27: COVID and insurance/CLAIMS | D27: Decouple and Digitize the Leave Claims Process to Address the COVID-19 Surge | E27: https://www.exlservice.com/decouple-and-digitize-the-leave-claims-process-to-address-the-covid-19-surge | F27: Munish Mahajan
B28: White paper | C28: Claims | D28: New era of P&C claim management | E28: https://www.exlservice.com/a-new-era-of-pc-claims-management | F28: Content Team
B29: White paper | C29: Claims | D29: Improving legal team effectiveness | E29: https://www.exlservice.com/improving-legal-team-effectiveness-with-digitized-litigated-claims-information | F29: Adolfo Canovi
... B47: White Paper | C47: Analytics | D47: Motor Insurance - How to acquire and retain customers in post COVID19 world | E47: https://www.exlservice.com/motor-insurance-post-covid-19-world | F47: Swarnava Ghosh | Aditya

Sheet Reference Tab - Do not Delete
A1: Home
A2: Solutions | B2: A21:A31
A3: FNOL | B3: B21:B26
A4: PaaS | B4: C21:C24
A5: DT-WC | B5: D21:D27
A6: NB-PaaS | B6: E21:E23
A7: E-E2E | B7: F21:F21
A8: BIE | B8: G21:G23
A9: Int-Col | B9: H21:H25
A10: Audit-ATC | B10: I21:I23
A11: PRA | B11: J21:J25
A12: Fin-Auto | B12: K21:K21
A13: TrRFF | B13: L21:L21
A20: Solutions | B20: FNOL | C20: PaaS | D20: DT_WC | E20: NB_PaaS | F20: E_E2E | G20: BIE | H20: Int_Col | I20: Audit_ATC | J20: PRA | K20: Fin_Auto | L20: TrRFF
A21: FNOL | B21: Omni Channel Intake | C21: Content Extraction | D21: Medical Case Management Platform | E21: Submission to Quote | F21: End to End Endorsement Processing | G21: Data Ingestion from Broker Platforms | H21: Analytics Led Risk Prioritization & Forecasting | I21: Audit Analytics Center of Excellence (COE) | J21: COE Delivery Structure | K21: RPA | L21: Finance Blueprint
A22: PaaS | B22: Automated Entry FNOL capability (Thin Human/Heavy Digital) | C22: Payee Portal | D22: Automated Entry Medical Record and Bill Management capability (Thin Human/Heavy Digital). | E22: Rating | G22: Data Extraction Module | H22: Automated Comunications & Chasers | I22: Dashboard/Customer Report Development | J22: Automation/Robotics
A23: DT-WC | B23: Voice Center of Excellence (COE) | C23: Transactional Servicing Features | D23: End to End Utilization Review | E23: Analytics Insights and Reporting | G23: Value Add Services | H23: Real Time Cash Application | I23: Audit Bot Development and Maintenance | J23: Analytics & Reporting
A24: NB-PaaS | B24: Predictive Analytics | C24: Administrative Support and Services | D24: Medical Bill Review Capability/Platform | H24: Comprehansive Data Reports and Dashboards | J24: Leading Practices
A25: E-E2E | B25: Cloud Hosted | D25: Predictive Analytics Models | H25: Other Receivables Areas | J25: Dual Shore
A26: BIE | B26: Speech Analytics | D26: STP Modeling and Automation (Medical Only Claims)
A27: Int-Col | B27: Conversational IVR | D27: Payment Integrity
A28: Audit-ATC
A29: PRA
A30: Fin-Auto
A31: TrRFF
A34: VOC-Source | B34: Sign Off - Next Steps | C34: Life Cycle | D34: NWP Range
A35: Press Release | B35: Pending | C35: Not Initiated | D35: Above $50B | E35: 50000000000
A36: Exec-Meet | B36: Completed - SOW Signed | C36: Due Diligence | D36: $50B - $B | E36: 1000000000
A37: RM-Meet | B37: Completed - SOW Pending | C37: Planning | D37: $B - $500M | E37: 500000000
A38: SOW/MSA | B38: POC Required | C38: Analysis | D38: $500M - $M | E38: 1000000
A39: Informal-Meet | B39: Rejected | C39: Design | D39: Below $M
A40: Other | B40: Partner directly with InsureTech | C40: Implementation
C41: Testing & Integration
C42: Maintenance

Sheet Consolidated Solutions
A1: # | B1: Problem Statement | C1: Offering | D1: Modules | E1: Outcomes | F1: Metrics and Benchmarks | G1: Buying Center | H1: Client Appetite / Feedback Feedback received from clients to be updated here | I1: Market Appetite | J1: Existing Capability in market (are there any existing similar products in the market?). Describe. | K1: EXL Capabilities | N1: Speed to Market | O1: Next Steps
K2: Area | L2: L/M/H | M2: Details
A3: 1 | B3: The first step in the Claim process is FNOL and it is one of the most important. It is often the first interaction a policyholder has with their insurance carrier and it represents a Moment of Truth for the carrier. Service is what an insurance company sells and an efficient, timely, painless process to report new losses is core to every insurance carrier and claim department. FNOL represents X (TBD)% of overall claim cost on an annual basis and is a multi-billion dollar industry expenditure. -Brokers and Insureds want the choice of reporting channels (Mobile, Web, Email, Fax, Phone) and expect a carrier to provide them with all options -Carriers and customers desire FNOL set up (claim # assignment) and adjuster assignment as quickly as possible in order to ensure timely investigation, evaluation reserving and resolution. Anything more than 4 hours is often perceived as too long leading to adverse impacts on the claim and the customer experience. -An FNOL contains a number of data points which are important to capture quickly and accurately so they can be immediately used to predict claim outcomes, properly reserve, report losses to underwriting, price risks and manage aggregate loss costs. -Significant effort and cost is needed to convert unstructured, semi-structured and structured documents, embedded files, notes, ACORD forms, scans, images etc...) to useable formats. -Customers often complain of insufficient transparency into the claim assignment process. They do not receive timely notification of the claim number nor the adjuster ID leading to unnecessary phone calls and emails and ultimately poor customer satisfaction. . -Customers and regulators require data privacy and security for all PHI, PII information shared when reporting a loss. | C3: FNOL "As a Service" | D3: 1. Omni Channel Intake - provides a channel agnostic claim reporting solution for customers (broker and insured) | E3: -Reduce claim costs - ALAE and ULAE -Streamline and simplify the process -Improve accuracy of assignment -Provide early warning flags for fraud, litigation etc. reducing indemnity and legal cost -Improve customer experience -Simplify pricing - price per FNOL - allows for surge capacity and flexibility transferring burden to supplier | F3: TAT Non Voice - 95% assigned within 2 hours (most stringent) AHT - not always measured. HIG Measures and standard is 4.30. (Typical AHT across commercial lines is 10 - 20min) Quality - 88% - 95% DPU and DPO (typical is 90 - 95% DPU) %Reassignments Complaint Ratio Voice ASA - 70 - 80 % answered within 20 - 25 sec industry might reflect higher) Abandonment Rate - 2%-7% | G3: Chief Claim Officer | H3: Allstate, Assurant CNA Hanover HIG Liberty Mutual | I3: High | J3: More research needed here No one has tied the whole solution together. We are creating a one stop shop with the ability to provide data loops | K3: Operational | L3: High | M3: Moderate footprint in FNOL both voice and non-voice across personal and commercial insurance | N3: Medium We can package and put Value Prop together quickly. Building and stitching the modules together will take more time. | O3: 1. Vet the solution concept and components with existing clients 2. If prioritized, begin to build the Packaged Solution collateral including the Value Prop included
D4: 2. Automated Entry FNOL capability (Thin Human/Heavy Digital)- provides front end capability to ingest all types of FNOL documents across all lines of business (Commercial and Personal) from all channels (except Voice). App needs to extract data/content and auto populate carrier claim systems (Guidewire, Duck Creek etc..)
D5: 3. Voice Center of Excellence (COE) - provides insured/broker with the ability to report claims via phone in a workflow enabled call flow using dynamic scripts, triage and adjuster assignment. Claims Inquiry and Provider Help lines may also be part of the module. | K5: Platform | L5: Medium | M5: EXL's platforms services team does have an FNOL platform with the right components We also have the ability to partner with companies like Sapiens which would increase speed to market
D6: 4. Acknowledgement Notice with Claim number - provides immediate notice to insured and broker that the claim has been received and a claim number assigned
D7: 5. Reports and Dashboards - provides ability to capture and report real time on TAT, Volume by LOB, Volume by Channel, Quality etc..) | K7: Analytics | L7: High | M7: EXL has experience in several analytics interventions applied for existing BPO as well as consulting/Analytics clients
D8: 6. Predictive Analytics - Early Indicator Flags (Fraud, Litigation, Recovery, Total Loss) - provides early indicator flags for accurate assignment, investigation cues and improved cycle time
